Workbook

Sheet Início
B1: 🏠 Início | D1: 📊 Painel Geral | G1: 👤 Painel Pessoal | I1: 💼 Painel Negócio | K1: ⚙ Config
B2: PESSOAL | D2: 📝 Lançamentos | G2: 💳 Orçamento | I2: 📅 Resumo anual | K2: 🎯 Metas
B3: NEGÓCIO | D3: 📝 Lançamentos | F3: 🤝 Clientes | H3: 💰 Recebimentos | J3: 🧾 Impostos | L3: 📈 Fluxo de Caixa
B5: Finanças em Dia — Autônomo & MEI
B6: Controle financeiro pessoal + negócio • Excel e Google Sheets
B7: Bem-vindo(a)! Esta planilha organiza suas finanças do jeito mais simples: você só LANÇA os valores e todo o resto — resumos, gráficos, alertas e metas — é calculado automaticamente. Aqui, vida pessoal e negócio ficam separados, com controle de clientes, recebimentos, impostos (DAS do MEI) e fluxo de caixa.
B9: 🚀 COMECE EM 5 MINUTOS
B10: 1 | C10: Em ⚙ Config: confira o ANO, escreva seu nome/negócio e renomeie as categorias, se quiser.
B11: 2 | C11: Em 💳 Orçamento Pessoal e 🎯 Metas: informe quanto pretende gastar e quais objetivos quer alcançar.
B12: 3 | C12: Em 🧾 Impostos: escolha seu regime (MEI, Simples ou outro) e confira o valor do DAS.
B13: 4 | C13: Cadastre seus 🤝 Clientes e registre cada cobrança em 💰 Recebimentos (com vencimento e data de pagamento).
B14: 5 | C14: No dia a dia: lance gastos em 📝 Lançamentos (pessoal e negócio). Depois é só abrir os 📊 Painéis!
B16: 🗺 MAPA DA PLANILHA — clique no botão para navegar
B17: 📊 Painel Geral | E17: Visão consolidada: caixa pessoal + negócio, resultado mensal e cobertura do custo de vida.
B18: 👤 Painel Pessoal | E18: Entradas, saídas, saldo, taxa de poupança, categorias, metas e alertas da vida pessoal.
B19: 💼 Painel Negócio | E19: Receita, despesas, lucro, top clientes, cobranças em atraso e limite do MEI.
B20: 📝 Lanç. Pessoal | E20: Registro de entradas e saídas pessoais (tipo automático pela categoria).
B21: 💳 Orçamento Pessoal | E21: Planejado × realizado por categoria, com barras de progresso e alertas.
B22: 📅 Resumo Pessoal | E22: Quadro anual mês a mês por categoria, com mapa de calor.
B23: 🎯 Metas | E23: Objetivos de economia, aporte mensal necessário e reserva de emergência.
B24: 📝 Lanç. Negócio | E24: Despesas e receitas avulsas do negócio (separadas das pessoais).
B25: 🤝 Clientes | E25: Cadastro de clientes com faturamento, recebido, a receber e inadimplência.
B26: 💰 Recebimentos | E26: Cobranças emitidas: vencimento, data de pagamento e status automático.
B27: 🧾 Impostos | E27: DAS do MEI (ou % do Simples), vencimentos, pagamentos e limite anual.
B28: 📈 Fluxo de Caixa | E28: Caixa do negócio mês a mês: realizado e projetado, com saldo acumulado.
B29: ⚙ Config | E29: Ano, nome, categorias, formas de pagamento e metas gerais.
B31: 🎨 LEGENDA DE CORES
B32: Você preenche | D32: Fórmula (automático) | F32: Positivo / bom | H32: Atenção | J32: Negativo / alerta | L32: Informação
B34: 💡 DICAS IMPORTANTES
B35: • Google Sheets: envie o arquivo .xlsx para o Google Drive e abra com o Google Planilhas (ou Arquivo ▸ Importar). Os menus, gráficos, listas suspensas e cores funcionam igualmente.
B36: • Digite sempre valores POSITIVOS. Se a categoria for de entrada, o valor soma; se for de saída, subtrai — o tipo é automático.
B37: • Retirada do negócio: lance a saída 'Pró-labore / Retirada' em Lanç. Negócio e a entrada 'Pró-labore' em Lanç. Pessoal. Receitas de clientes: lance só em Recebimentos (não duplique).
B38: • Para começar um novo ano: salve uma cópia do arquivo, apague os lançamentos (colunas amarelas) e mude o ano em Config.
B39: • Não insira/apague linhas dentro das tabelas de fórmulas. Para ver mais lançamentos, use os filtros do cabeçalho; há espaço para 1500 linhas.
B40: • Cada aba tem botões de navegação no topo. Se algo parecer estranho, confira a faixa de VERIFICAÇÃO no topo de Lançamentos.
B41: • Os valores do DAS/MEI e o limite anual são parâmetros editáveis na aba Impostos — confira sempre a legislação vigente no Portal do Simples Nacional. Esta planilha organiza, mas não substitui um contador.
B43: Planilha educativa de organização financeira. Valores e exemplos são fictícios.

Sheet Painel Geral
B1: 🏠 Início | D1: 📊 Painel Geral | G1: 👤 Painel Pessoal | I1: 💼 Painel Negócio | K1: ⚙ Config
B2: PESSOAL | D2: 📝 Lançamentos | G2: 💳 Orçamento | I2: 📅 Resumo anual | K2: 🎯 Metas
B3: NEGÓCIO | D3: 📝 Lançamentos | F3: 🤝 Clientes | H3: 💰 Recebimentos | J3: 🧾 Impostos | L3: 📈 Fluxo de Caixa
B5: ="📊 Painel Geral — "&'Config'!$C$10 -> 📊 Painel Geral — Meu Controle Financeiro
B6: Visão consolidada: vida pessoal + negócio. O negócio sustenta o seu custo de vida?
B7: 📅 Mês de análise | D7: Setembro | G7: Ano de referência | I7: ='Config'!$C$8 -> 2026 | J7: ← escolha o mês; a aba Config guarda ano e metas
B9: SALDO PESSOAL ACUMULADO | D9: CAIXA DO NEGÓCIO | F9: CAIXA TOTAL | H9: RESULTADO PESSOAL (MÊS) | J9: LUCRO DO NEGÓCIO (MÊS) | L9: PRÓ-LABORE ÷ GASTOS PESSOAIS
B10: =INDEX('Resumo Pessoal'!$C$38:$N$38,'Dados'!$C$41) -> 3592.59 | D10: =INDEX('Fluxo de Caixa'!$C$29:$N$29,'Dados'!$C$41) -> 4182.18 | F10: =INDEX('Resumo Pessoal'!$C$38:$N$38,'Dados'!$C$41)+INDEX('Fluxo de Caixa'!$C$29:$N$29,'Dados'!$C$41) -> 7774.77 | H10: =INDEX('Dados'!$C$115:$N$115,'Dados'!$C$41) -> 560.05 | J10: =INDEX('Dados'!$C$110:$N$110,'Dados'!$C$41) -> 4710.68 | L10: =IF(INDEX('Dados'!$C$117:$N$117,'Dados'!$C$41)=0,0,INDEX('Dados'!$C$116:$N$116,'Dados'!$C$41)/INDEX('Dados'!$C$117:$N$117,'Dados'!$C$41)) -> 1.1270174
B11: pessoal, no fim do mês | D11: =IF('Dados'!$C$41<='Dados'!$C$10,"realizado","projetado") -> realizado | F11: pessoal + negócio | H11: entradas − saídas pessoais | J11: receita − despesas − impostos | L11: cobertura do custo de vida
B45: 🔔 ALERTAS E INSIGHTS
B46: ='Impostos'!$H$13 -> ✓ Dentro do limite anual do MEI.
B47: =IF(SUM('Recebimentos'!$L$11:$L$1010)=0,"✓ Nenhuma cobrança em atraso.","⚠ Você tem R$ "&FIXED(SUM('Recebimentos'!$L$11:$L$1010),2)&" em cobranças atrasadas — veja a aba Recebimentos.") -> ⚠ Você tem R$ 4,430.00 em cobranças atrasadas — veja a aba Recebimentos.
B48: =IF('Dados'!$C$42=99,"✓ O caixa do negócio permanece positivo no ano (incluindo a projeção).","⚠ O caixa do negócio projetado fica negativo a partir de "&INDEX('Config'!$K$8:$K$19,'Dados'!$C$42)&".") -> ✓ O caixa do negócio permanece positivo no ano (incluindo a projeção).
B49: =IF(INDEX('Dados'!$C$117:$N$117,'Dados'!$C$41)=0,"ℹ Registre os gastos pessoais do mês para medir a cobertura do custo de vida.",IF(IF(INDEX('Dados'!$C$117:$N$117,'Dados'!$C$41)=0,0,INDEX('Dados'!$C$116:$N$116,'Dados'!$C$41)/INDEX('Dados'!$C$117:$N$117,'Dados'!$C$41))>=1,"✓ O pró-labore do mês cobre "&TEXT(IF(INDEX('Dados'!$C$117:$N$117,'Dados'!$C$41)=0,0,INDEX('Dados'!$C$116:$N$116,'Dados'!$C$41)/INDEX('Dados'!$C$117:$N$117,'Dados'!$C$41)),"0%")&" dos seus gastos pessoais.","⚠ O pró-labore cobre só "&TEXT(IF(INDEX('Dados'!$C$117:$N$117,'Dados'!$C$41)=0,0,INDEX('Dados'!$C$116:$N$116,'Dados'!$C$41)/INDEX('Dados'!$C$117:$N$117,'Dados'!$C$41)),"0%")&" dos gastos pessoais do mês — o restante saiu de reservas.")) -> ✓ O pró-labore do mês cobre 113% dos seus gastos pessoais.

Sheet Painel Pessoal
B1: 🏠 Início | D1: 📊 Painel Geral | G1: 👤 Painel Pessoal | I1: 💼 Painel Negócio | K1: ⚙ Config
B2: PESSOAL | D2: 📝 Lançamentos | G2: 💳 Orçamento | I2: 📅 Resumo anual | K2: 🎯 Metas
B3: NEGÓCIO | D3: 📝 Lançamentos | F3: 🤝 Clientes | H3: 💰 Recebimentos | J3: 🧾 Impostos | L3: 📈 Fluxo de Caixa
B5: ="👤 Painel Pessoal — "&'Config'!$C$10 -> 👤 Painel Pessoal — Meu Controle Financeiro
B6: Escolha o mês no menu suspenso: cartões, gráficos e alertas se atualizam sozinhos.
B7: 📅 Mês de análise | D7: Setembro | G7: Ano de referência | I7: ='Config'!$C$8 -> 2026 | J7: ← o ano e a meta de poupança ficam na aba Config
B9: ENTRADAS DO MÊS | D9: SAÍDAS DO MÊS | F9: SALDO DO MÊS | H9: TAXA DE POUPANÇA | J9: SALDO ACUMULADO | L9: MAIOR GASTO DO MÊS
B10: =INDEX('Resumo Pessoal'!$C$18:$N$18,'Dados'!$C$8) -> 4552.89 | D10: =INDEX('Resumo Pessoal'!$C$36:$N$36,'Dados'!$C$8) -> 3992.84 | F10: =INDEX('Resumo Pessoal'!$C$18:$N$18,'Dados'!$C$8)-INDEX('Resumo Pessoal'!$C$36:$N$36,'Dados'!$C$8) -> 560.05 | H10: =IF(INDEX('Resumo Pessoal'!$C$18:$N$18,'Dados'!$C$8)=0,0,INDEX('Resumo Pessoal'!$C$39:$N$39,'Dados'!$C$8)) -> 0.25479421 | J10: =INDEX('Resumo Pessoal'!$C$38:$N$38,'Dados'!$C$8) -> 3592.59 | L10: ='Dados'!$J$18 -> Moradia
B11: =IF('Dados'!$C$8=1,"—",IF(INDEX('Resumo Pessoal'!$C$18:$N$18,'Dados'!$C$8-1)=0,"—",IF(INDEX('Resumo Pessoal'!$C$18:$N$18,'Dados'!$C$8)>=INDEX('Resumo Pessoal'!$C$18:$N$18,'Dados'!$C$8-1),"▲ ","▼ ")&TEXT(ABS(INDEX('Resumo Pessoal'!$C$18:$N$18,'Dados'!$C$8)/INDEX('Resumo Pessoal'!$C$18:$N$18,'Dados'!$C$8-1)-1),"0%")&" vs mês anterior")) -> ▲ 0% vs mês anterior | D11: =IF('Dados'!$C$8=1,"—",IF(INDEX('Resumo Pessoal'!$C$36:$N$36,'Dados'!$C$8-1)=0,"—",IF(INDEX('Resumo Pessoal'!$C$36:$N$36,'Dados'!$C$8)>=INDEX('Resumo Pessoal'!$C$36:$N$36,'Dados'!$C$8-1),"▲ ","▼ ")&TEXT(ABS(INDEX('Resumo Pessoal'!$C$36:$N$36,'Dados'!$C$8)/INDEX('Resumo Pessoal'!$C$36:$N$36,'Dados'!$C$8-1)-1),"0%")&" vs mês anterior")) -> ▼ 14% vs mês anterior | F11: =IF(INDEX('Resumo Pessoal'!$C$18:$N$18,'Dados'!$C$8)-INDEX('Resumo Pessoal'!$C$36:$N$36,'Dados'!$C$8)>=0,"Sobrou dinheiro ✓","Gastou mais do que ganhou") -> Sobrou dinheiro ✓ | H11: ="Meta: "&TEXT('Config'!$C$11,"0%") -> Meta: 20% | J11: no ano, até o mês escolhido | L11: ='Dados'!$K$18 -> 1100
B45: 🎯 METAS DE ECONOMIA
B46: Meta | E46: Guardado | G46: Valor alvo | I46: % | J46: Progresso | M46: Situação
B47: =IF('Metas'!$B$8="","",'Metas'!$B$8) -> Reserva de emergência | E47: =IF('Metas'!$B$8="","",'Metas'!$G$8) -> 8700 | G47: =IF('Metas'!$B$8="","",'Metas'!$C$8) -> 24000 | I47: =IF('Metas'!$H$8="","",'Metas'!$H$8) -> 0.3625 | J47: =IF('Metas'!$I$8="","",'Metas'!$I$8) -> ███████ | M47: =IF('Metas'!$B$8="","",'Metas'!$M$8) -> ● No prazo
B48: =IF('Metas'!$B$9="","",'Metas'!$B$9) -> Reserva para impostos | E48: =IF('Metas'!$B$9="","",'Metas'!$G$9) -> 1350 | G48: =IF('Metas'!$B$9="","",'Metas'!$C$9) -> 4000 | I48: =IF('Metas'!$H$9="","",'Metas'!$H$9) -> 0.3375 | J48: =IF('Metas'!$I$9="","",'Metas'!$I$9) -> ███████ | M48: =IF('Metas'!$B$9="","",'Metas'!$M$9) -> ● No prazo
B49: =IF('Metas'!$B$10="","",'Metas'!$B$10) -> Viagem de férias | E49: =IF('Metas'!$B$10="","",'Metas'!$G$10) -> 1400 | G49: =IF('Metas'!$B$10="","",'Metas'!$C$10) -> 6000 | I49: =IF('Metas'!$H$10="","",'Metas'!$H$10) -> 0.23333333 | J49: =IF('Metas'!$I$10="","",'Metas'!$I$10) -> █████ | M49: =IF('Metas'!$B$10="","",'Metas'!$M$10) -> ● No prazo
B50: =IF('Metas'!$B$11="","",'Metas'!$B$11) | E50: =IF('Metas'!$B$11="","",'Metas'!$G$11) | G50: =IF('Metas'!$B$11="","",'Metas'!$C$11) | I50: =IF('Metas'!$H$11="","",'Metas'!$H$11) | J50: =IF('Metas'!$I$11="","",'Metas'!$I$11) | M50: =IF('Metas'!$B$11="","",'Metas'!$M$11)
B51: =IF('Metas'!$B$12="","",'Metas'!$B$12) | E51: =IF('Metas'!$B$12="","",'Metas'!$G$12) | G51: =IF('Metas'!$B$12="","",'Metas'!$C$12) | I51: =IF('Metas'!$H$12="","",'Metas'!$H$12) | J51: =IF('Metas'!$I$12="","",'Metas'!$I$12) | M51: =IF('Metas'!$B$12="","",'Metas'!$M$12)
B53: Veja todas as metas e o simulador de aportes na aba Metas.
B54: 🔔 ALERTAS E INSIGHTS DO MÊS
B55: =IF(AND(INDEX('Resumo Pessoal'!$C$18:$N$18,'Dados'!$C$8)=0,INDEX('Resumo Pessoal'!$C$36:$N$36,'Dados'!$C$8)=0),"ℹ Ainda não há lançamentos neste mês.",IF((INDEX('Resumo Pessoal'!$C$18:$N$18,'Dados'!$C$8)-INDEX('Resumo Pessoal'!$C$36:$N$36,'Dados'!$C$8))<0,"⚠ Você gastou R$ "&FIXED(-(INDEX('Resumo Pessoal'!$C$18:$N$18,'Dados'!$C$8)-INDEX('Resumo Pessoal'!$C$36:$N$36,'Dados'!$C$8)),2)&" a mais do que ganhou neste mês.","✓ Mês no azul: sobraram R$ "&FIXED((INDEX('Resumo Pessoal'!$C$18:$N$18,'Dados'!$C$8)-INDEX('Resumo Pessoal'!$C$36:$N$36,'Dados'!$C$8)),2)&" depois de todas as saídas.")) -> ✓ Mês no azul: sobraram R$ 560.05 depois de todas as saídas.
B56: =IF('Orçamento Pessoal'!$C$28=0,"ℹ Defina o orçamento por categoria na aba Orçamento para receber alertas de gastos.",IF('Dados'!$C$13=0,"✓ Nenhuma categoria acima do orçamento neste mês.","⚠ "&'Dados'!$C$13&" categoria(s) acima do orçamento planejado — veja a aba Orçamento.")) -> ⚠ 2 categoria(s) acima do orçamento planejado — veja a aba Orçamento.
B57: =IF(INDEX('Resumo Pessoal'!$C$18:$N$18,'Dados'!$C$8)=0,"ℹ Registre suas entradas do mês para calcular a taxa de poupança.",IF(INDEX('Resumo Pessoal'!$C$39:$N$39,'Dados'!$C$8)>='Config'!$C$11,"✓ Meta de poupança atingida: "&TEXT(INDEX('Resumo Pessoal'!$C$39:$N$39,'Dados'!$C$8),"0%")&" (meta "&TEXT('Config'!$C$11,"0%")&").","⚠ Taxa de poupança de "&TEXT(INDEX('Resumo Pessoal'!$C$39:$N$39,'Dados'!$C$8),"0%")&", abaixo da meta de "&TEXT('Config'!$C$11,"0%")&".")) -> ✓ Meta de poupança atingida: 25% (meta 20%).

Sheet Painel Negócio
B1: 🏠 Início | D1: 📊 Painel Geral | G1: 👤 Painel Pessoal | I1: 💼 Painel Negócio | K1: ⚙ Config
B2: PESSOAL | D2: 📝 Lançamentos | G2: 💳 Orçamento | I2: 📅 Resumo anual | K2: 🎯 Metas
B3: NEGÓCIO | D3: 📝 Lançamentos | F3: 🤝 Clientes | H3: 💰 Recebimentos | J3: 🧾 Impostos | L3: 📈 Fluxo de Caixa
B5: ="💼 Painel Negócio — "&'Config'!$C$13 -> 💼 Painel Negócio — Estúdio Exemplo
B6: Receita, despesas, lucro, clientes, cobranças em atraso e limite do MEI — tudo do mês escolhido.
B7: 📅 Mês de análise | D7: Setembro | G7: Ano de referência | I7: ='Config'!$C$8 -> 2026 | J7: ← escolha o mês; os valores só aparecem até o mês de referência (hoje)
B9: RECEITA DO MÊS | D9: DESPESAS + IMPOSTOS | F9: LUCRO DE CAIXA | H9: A RECEBER (EM ABERTO) | J9: LIMITE DO MEI USADO | L9: IMPOSTO DO MÊS (DAS)
B10: =INDEX('Dados'!$C$108:$N$108,'Dados'!$C$40) -> 6266.84 | D10: =INDEX('Dados'!$C$109:$N$109,'Dados'!$C$40) -> 1556.16 | F10: =INDEX('Dados'!$C$110:$N$110,'Dados'!$C$40) -> 4710.68 | H10: =SUM('Recebimentos'!$K$11:$K$1010) -> 6730 | J10: =IF('Impostos'!$E$8<>"MEI","n/a",'Impostos'!$L$10) -> 0.69763691 | L10: =INDEX('Impostos'!$D$23:$D$34,'Dados'!$C$40) -> 86.05
B11: =IF('Dados'!$C$40=1,"—",IF(INDEX('Dados'!$C$108:$N$108,'Dados'!$C$40-1)=0,"—",IF(INDEX('Dados'!$C$108:$N$108,'Dados'!$C$40)>=INDEX('Dados'!$C$108:$N$108,'Dados'!$C$40-1),"▲ ","▼ ")&TEXT(ABS(INDEX('Dados'!$C$108:$N$108,'Dados'!$C$40)/INDEX('Dados'!$C$108:$N$108,'Dados'!$C$40-1)-1),"0%")&" vs mês anterior")) -> ▼ 14% vs mês anterior | D11: =IF('Dados'!$C$40=1,"—",IF(INDEX('Dados'!$C$109:$N$109,'Dados'!$C$40-1)=0,"—",IF(INDEX('Dados'!$C$109:$N$109,'Dados'!$C$40)>=INDEX('Dados'!$C$109:$N$109,'Dados'!$C$40-1),"▲ ","▼ ")&TEXT(ABS(INDEX('Dados'!$C$109:$N$109,'Dados'!$C$40)/INDEX('Dados'!$C$109:$N$109,'Dados'!$C$40-1)-1),"0%")&" vs mês anterior")) -> ▲ 2% vs mês anterior | F11: =IF(INDEX('Dados'!$C$108:$N$108,'Dados'!$C$40)=0,"—","Margem de "&TEXT(INDEX('Dados'!$C$110:$N$110,'Dados'!$C$40)/INDEX('Dados'!$C$108:$N$108,'Dados'!$C$40),"0%")) -> Margem de 75% | H11: =SUM('Recebimentos'!$L$11:$L$1010) -> 4430 | J11: =IF('Impostos'!$E$8<>"MEI","regime sem limite MEI","Projeção: "&TEXT('Impostos'!$L$12,"0%")&" do limite") -> Projeção: 93% do limite | L11: =INDEX('Impostos'!$I$23:$I$34,'Dados'!$C$40) -> A pagar
B45: ⏰ COBRANÇAS EM ATRASO (as 5 mais antigas)
B46: Cliente | E46: Descrição | I46: Vencimento | K46: Dias | L46: Valor
B47: =IF('Dados'!$I$100>0,'Dados'!$J$100,IF('Dados'!$I$100=0,"✓ Nenhuma cobrança em atraso","")) -> Café do Centro | E47: ='Dados'!$K$100 -> Reimpressão de materiais | I47: ='Dados'!$L$100 -> 46261 | K47: ='Dados'!$M$100 -> 34 | L47: ='Dados'!$N$100 -> 480
B48: =IF('Dados'!$I$101>0,'Dados'!$J$101,"") -> Studio Aurora | E48: ='Dados'!$K$101 -> Gestão de redes sociais – 09/2026 | I48: ='Dados'!$L$101 -> 46278 | K48: ='Dados'!$M$101 -> 17 | L48: ='Dados'!$N$101 -> 1800
B49: =IF('Dados'!$I$102>0,'Dados'!$J$102,"") -> Clínica Vida Plena | E49: ='Dados'!$K$102 -> Pacote de conteúdo mensal – 09/2026 | I49: ='Dados'!$L$102 -> 46280 | K49: ='Dados'!$M$102 -> 15 | L49: ='Dados'!$N$102 -> 1500
B50: =IF('Dados'!$I$103>0,'Dados'!$J$103,"") -> Padaria Dois Irmãos | E50: ='Dados'!$K$103 -> Materiais e cardápio – 09/2026 | I50: ='Dados'!$L$103 -> 46283 | K50: ='Dados'!$M$103 -> 12 | L50: ='Dados'!$N$103 -> 650
B51: =IF('Dados'!$I$104>0,'Dados'!$J$104,"") | E51: ='Dados'!$K$104 | I51: ='Dados'!$L$104 | K51: ='Dados'!$M$104 | L51: ='Dados'!$N$104
B53: 🔔 ALERTAS E INSIGHTS
B54: ='Impostos'!$H$13 -> ✓ Dentro do limite anual do MEI.
B55: =IF('Clientes'!$B$40="","ℹ Registre recebimentos para analisar a concentração de clientes.",'Clientes'!$B$40) -> ✓ Receita bem distribuída entre clientes (maior cliente: 26%).
B56: =IF('Dados'!$C$42=99,"✓ O caixa do negócio não fica negativo em nenhum mês do ano (incluindo a projeção).","⚠ O caixa projetado fica negativo a partir de "&INDEX('Config'!$K$8:$K$19,'Dados'!$C$42)&". Antecipe recebimentos ou reduza despesas.") -> ✓ O caixa do negócio não fica negativo em nenhum mês do ano (incluindo a projeção).

Sheet Lanç. Pessoal
B1: 🏠 Início | D1: 📊 Painel Geral | E1: 👤 Painel Pessoal | G1: 💼 Painel Negócio | I1: ⚙ Config
B2: PESSOAL | D2: 📝 Lançamentos | E2: 💳 Orçamento | G2: 📅 Resumo anual | I2: 🎯 Metas
B3: NEGÓCIO | C3: 📝 Lançamentos | D3: 🤝 Clientes | E3: 💰 Recebimentos | G3: 🧾 Impostos | I3: 📈 Fluxo de Caixa
B5: 📝 Lançamentos pessoais
B6: Preencha as colunas amarelas. Valor sempre positivo; o Tipo (Entrada/Saída) é automático pela categoria.
B7: ENTRADAS NO ANO | D7: SAÍDAS NO ANO | E7: SALDO DO ANO | G7: VERIFICAÇÃO AUTOMÁTICA
B8: =SUMIFS('Lanç. Pessoal'!$F$11:$F$1510,'Lanç. Pessoal'!$G$11:$G$1510,"Entrada",'Lanç. Pessoal'!$B$11:$B$1510,">="&DATE('Config'!$C$8,1,1),'Lanç. Pessoal'!$B$11:$B$1510,"<"&DATE('Config'!$C$8+1,1,1)) -> 41725.12 | D8: =SUMIFS('Lanç. Pessoal'!$F$11:$F$1510,'Lanç. Pessoal'!$G$11:$G$1510,"Saída",'Lanç. Pessoal'!$B$11:$B$1510,">="&DATE('Config'!$C$8,1,1),'Lanç. Pessoal'!$B$11:$B$1510,"<"&DATE('Config'!$C$8+1,1,1)) -> 40632.53 | E8: =B8-D8 -> 1092.59 | G8: =IF(SUMPRODUCT(('Lanç. Pessoal'!$F$11:$F$1510>0)*('Lanç. Pessoal'!$D$11:$D$1510=""))>0,"⚠ "&SUMPRODUCT(('Lanç. Pessoal'!$F$11:$F$1510>0)*('Lanç. Pessoal'!$D$11:$D$1510=""))&" lançamento(s) sem categoria — não entram nos painéis",IF(COUNTIF('Lanç. Pessoal'!$G$11:$G$1510,"Verificar")>0,"⚠ "&COUNTIF('Lanç. Pessoal'!$G$11:$G$1510,"Verificar")&" lançamento(s) com categoria inválida (coluna Tipo = Verificar)",IF((COUNT('Lanç. Pessoal'!$F$11:$F$1510)-COUNTIFS('Lanç. Pessoal'!$B$11:$B$1510,">="&DATE('Config'!$C$8,1,1),'Lanç. Pessoal'!$B$11:$B$1510,"<"&DATE('Config'!$C$8+1,1,1),'Lanç. Pessoal'!$F$11:$F$1510,">0"))>0,"⚠ "&(COUNT('Lanç. Pessoal'!$F$11:$F$1510)-COUNTIFS('Lanç. Pessoal'!$B$11:$B$1510,">="&DATE('Config'!$C$8,1,1),'Lanç. Pessoal'!$B$11:$B$1510,"<"&DATE('Config'!$C$8+1,1,1),'Lanç. Pessoal'!$F$11:$F$1510,">0"))&" lançamento(s) sem data ou fora de "&'Config'!$C$8&" — não entram nos painéis","✓ Tudo certo: "&COUNT('Lanç. Pessoal'!$F$11:$F$1510)&" lançamento(s) registrados"))) -> ✓ Tudo certo: 321 lançamento(s) registrados
B10: Data | C10: Descrição | D10: Categoria | E10: Forma de pagamento | F10: Valor (R$) | G10: Tipo | H10: Meta (opcional) | I10: Observação
B11: 46025 | C11: Academia | D11: Cuidados pessoais | E11: Débito automático | F11: 119.9 | G11: =IF($D11="","",IF(COUNTIF('Config'!$E$8:$E$15,$D11)>0,"Entrada",IF(COUNTIF('Config'!$G$8:$G$23,$D11)>0,"Saída","Verificar"))) -> Saída
B12: 46025 | C12: Supermercado | D12: Alimentação | E12: Cartão de crédito | F12: 178.02 | G12: =IF($D12="","",IF(COUNTIF('Config'!$E$8:$E$15,$D12)>0,"Entrada",IF(COUNTIF('Config'!$G$8:$G$23,$D12)>0,"Saída","Verificar"))) -> Saída
B13: 46026 | C13: Combustível | D13: Transporte | E13: Cartão de crédito | F13: 194.3 | G13: =IF($D13="","",IF(COUNTIF('Config'!$E$8:$E$15,$D13)>0,"Entrada",IF(COUNTIF('Config'!$G$8:$G$23,$D13)>0,"Saída","Verificar"))) -> Saída
B14: 46027 | C14: Pró-labore do mês | D14: Pró-labore / Retirada do negócio | E14: Transferência | F14: 4500 | G14: =IF($D14="","",IF(COUNTIF('Config'!$E$8:$E$15,$D14)>0,"Entrada",IF(COUNTIF('Config'!$G$8:$G$23,$D14)>0,"Saída","Verificar"))) -> Entrada
B15: 46028 | C15: Aporte reserva de emergência | D15: Reserva e Metas | E15: Pix | F15: 300 | G15: =IF($D15="","",IF(COUNTIF('Config'!$E$8:$E$15,$D15)>0,"Entrada",IF(COUNTIF('Config'!$G$8:$G$23,$D15)>0,"Saída","Verificar"))) -> Saída | H15: Reserva de emergência
B16: 46028 | C16: Aporte reserva para impostos | D16: Reserva e Metas | E16: Pix | F16: 150 | G16: =IF($D16="","",IF(COUNTIF('Config'!$E$8:$E$15,$D16)>0,"Entrada",IF(COUNTIF('Config'!$G$8:$G$23,$D16)>0,"Saída","Verificar"))) -> Saída | H16: Reserva para impostos
B17: 46028 | C17: Armazenamento na nuvem | D17: Assinaturas | E17: Cartão de crédito | F17: 9.9 | G17: =IF($D17="","",IF(COUNTIF('Config'!$E$8:$E$15,$D17)>0,"Entrada",IF(COUNTIF('Config'!$G$8:$G$23,$D17)>0,"Saída","Verificar"))) -> Saída
B18: 46028 | C18: Netflix | D18: Assinaturas | E18: Cartão de crédito | F18: 55.9 | G18: =IF($D18="","",IF(COUNTIF('Config'!$E$8:$E$15,$D18)>0,"Entrada",IF(COUNTIF('Config'!$G$8:$G$23,$D18)>0,"Saída","Verificar"))) -> Saída
B19: 46028 | C19: Padaria / hortifruti | D19: Alimentação | E19: Pix | F19: 31.96 | G19: =IF($D19="","",IF(COUNTIF('Config'!$E$8:$E$15,$D19)>0,"Entrada",IF(COUNTIF('Config'!$G$8:$G$23,$D19)>0,"Saída","Verificar"))) -> Saída
B20: 46028 | C20: Spotify | D20: Assinaturas | E20: Cartão de crédito | F20: 21.9 | G20: =IF($D20="","",IF(COUNTIF('Config'!$E$8:$E$15,$D20)>0,"Entrada",IF(COUNTIF('Config'!$G$8:$G$23,$D20)>0,"Saída","Verificar"))) -> Saída
B21: 46029 | C21: App de transporte | D21: Transporte | E21: Cartão de crédito | F21: 32.68 | G21: =IF($D21="","",IF(COUNTIF('Config'!$E$8:$E$15,$D21)>0,"Entrada",IF(COUNTIF('Config'!$G$8:$G$23,$D21)>0,"Saída","Verificar"))) -> Saída
B22: 46030 | C22: Internet fibra | D22: Contas da casa | E22: Débito automático | F22: 119.9 | G22: =IF($D22="","",IF(COUNTIF('Config'!$E$8:$E$15,$D22)>0,"Entrada",IF(COUNTIF('Config'!$G$8:$G$23,$D22)>0,"Saída","Verificar"))) -> Saída
B23: 46030 | C23: Restaurante / bar | D23: Lazer | E23: Cartão de crédito | F23: 54.68 | G23: =IF($D23="","",IF(COUNTIF('Config'!$E$8:$E$15,$D23)>0,"Entrada",IF(COUNTIF('Config'!$G$8:$G$23,$D23)>0,"Saída","Verificar"))) -> Saída
B24: 46031 | C24: Delivery | D24: Alimentação | E24: Cartão de débito | F24: 63.39 | G24: =IF($D24="","",IF(COUNTIF('Config'!$E$8:$E$15,$D24)>0,"Entrada",IF(COUNTIF('Config'!$G$8:$G$23,$D24)>0,"Saída","Verificar"))) -> Saída
B25: 46032 | C25: Aluguel | D25: Moradia | E25: Boleto | F25: 950 | G25: =IF($D25="","",IF(COUNTIF('Config'!$E$8:$E$15,$D25)>0,"Entrada",IF(COUNTIF('Config'!$G$8:$G$23,$D25)>0,"Saída","Verificar"))) -> Saída
B26: 46032 | C26: Condomínio | D26: Moradia | E26: Boleto | F26: 150 | G26: =IF($D26="","",IF(COUNTIF('Config'!$E$8:$E$15,$D26)>0,"Entrada",IF(COUNTIF('Config'!$G$8:$G$23,$D26)>0,"Saída","Verificar"))) -> Saída
B27: 46032 | C27: Plano de saúde | D27: Saúde | E27: Débito automático | F27: 180 | G27: =IF($D27="","",IF(COUNTIF('Config'!$E$8:$E$15,$D27)>0,"Entrada",IF(COUNTIF('Config'!$G$8:$G$23,$D27)>0,"Saída","Verificar"))) -> Saída
B28: 46032 | C28: Supermercado | D28: Alimentação | E28: Cartão de crédito | F28: 163.56 | G28: =IF($D28="","",IF(COUNTIF('Config'!$E$8:$E$15,$D28)>0,"Entrada",IF(COUNTIF('Config'!$G$8:$G$23,$D28)>0,"Saída","Verificar"))) -> Saída
... B47: 46058 | C47: Pró-labore do mês | D47: Pró-labore / Retirada do negócio | E47: Transferência | F47: 4500 | G47: =IF($D47="","",IF(COUNTIF('Config'!$E$8:$E$15,$D47)>0,"Entrada",IF(COUNTIF('Config'!$G$8:$G$23,$D47)>0,"Saída","Verificar"))) -> Entrada
B48: 46059 | C48: Aporte reserva de emergência | D48: Reserva e Metas | E48: Pix | F48: 300 | G48: =IF($D48="","",IF(COUNTIF('Config'!$E$8:$E$15,$D48)>0,"Entrada",IF(COUNTIF('Config'!$G$8:$G$23,$D48)>0,"Saída","Verificar"))) -> Saída | H48: Reserva de emergência
B49: 46059 | C49: Aporte reserva para impostos | D49: Reserva e Metas | E49: Pix | F49: 150 | G49: =IF($D49="","",IF(COUNTIF('Config'!$E$8:$E$15,$D49)>0,"Entrada",IF(COUNTIF('Config'!$G$8:$G$23,$D49)>0,"Saída","Verificar"))) -> Saída | H49: Reserva para impostos
B50: 46059 | C50: Armazenamento na nuvem | D50: Assinaturas | E50: Cartão de crédito | F50: 9.9 | G50: =IF($D50="","",IF(COUNTIF('Config'!$E$8:$E$15,$D50)>0,"Entrada",IF(COUNTIF('Config'!$G$8:$G$23,$D50)>0,"Saída","Verificar"))) -> Saída
B51: 46059 | C51: Netflix | D51: Assinaturas | E51: Cartão de crédito | F51: 55.9 | G51: =IF($D51="","",IF(COUNTIF('Config'!$E$8:$E$15,$D51)>0,"Entrada",IF(COUNTIF('Config'!$G$8:$G$23,$D51)>0,"Saída","Verificar"))) -> Saída
B52: 46059 | C52: Padaria / hortifruti | D52: Alimentação | E52: Pix | F52: 35.75 | G52: =IF($D52="","",IF(COUNTIF('Config'!$E$8:$E$15,$D52)>0,"Entrada",IF(COUNTIF('Config'!$G$8:$G$23,$D52)>0,"Saída","Verificar"))) -> Saída
B53: 46059 | C53: Spotify | D53: Assinaturas | E53: Cartão de crédito | F53: 21.9 | G53: =IF($D53="","",IF(COUNTIF('Config'!$E$8:$E$15,$D53)>0,"Entrada",IF(COUNTIF('Config'!$G$8:$G$23,$D53)>0,"Saída","Verificar"))) -> Saída
B54: 46060 | C54: App de transporte | D54: Transporte | E54: Cartão de crédito | F54: 25.76 | G54: =IF($D54="","",IF(COUNTIF('Config'!$E$8:$E$15,$D54)>0,"Entrada",IF(COUNTIF('Config'!$G$8:$G$23,$D54)>0,"Saída","Verificar"))) -> Saída
B55: 46061 | C55: Internet fibra | D55: Contas da casa | E55: Débito automático | F55: 119.9 | G55: =IF($D55="","",IF(COUNTIF('Config'!$E$8:$E$15,$D55)>0,"Entrada",IF(COUNTIF('Config'!$G$8:$G$23,$D55)>0,"Saída","Verificar"))) -> Saída
B56: 46061 | C56: Restaurante / bar | D56: Lazer | E56: Cartão de crédito | F56: 86.79 | G56: =IF($D56="","",IF(COUNTIF('Config'!$E$8:$E$15,$D56)>0,"Entrada",IF(COUNTIF('Config'!$G$8:$G$23,$D56)>0,"Saída","Verificar"))) -> Saída
B57: 46062 | C57: Delivery | D57: Alimentação | E57: Cartão de débito | F57: 66.74 | G57: =IF($D57="","",IF(COUNTIF('Config'!$E$8:$E$15,$D57)>0,"Entrada",IF(COUNTIF('Config'!$G$8:$G$23,$D57)>0,"Saída","Verificar"))) -> Saída
B58: 46063 | C58: Aluguel | D58: Moradia | E58: Boleto | F58: 950 | G58: =IF($D58="","",IF(COUNTIF('Config'!$E$8:$E$15,$D58)>0,"Entrada",IF(COUNTIF('Config'!$G$8:$G$23,$D58)>0,"Saída","Verificar"))) -> Saída
B59: 46063 | C59: Condomínio | D59: Moradia | E59: Boleto | F59: 150 | G59: =IF($D59="","",IF(COUNTIF('Config'!$E$8:$E$15,$D59)>0,"Entrada",IF(COUNTIF('Config'!$G$8:$G$23,$D59)>0,"Saída","Verificar"))) -> Saída
B60: 46063 | C60: Plano de saúde | D60: Saúde | E60: Débito automático | F60: 180 | G60: =IF($D60="","",IF(COUNTIF('Config'!$E$8:$E$15,$D60)>0,"Entrada",IF(COUNTIF('Config'!$G$8:$G$23,$D60)>0,"Saída","Verificar"))) -> Saída
B61: 46063 | C61: Supermercado | D61: Alimentação | E61: Cartão de crédito | F61: 136.4 | G61: =IF($D61="","",IF(COUNTIF('Config'!$E$8:$E$15,$D61)>0,"Entrada",IF(COUNTIF('Config'!$G$8:$G$23,$D61)>0,"Saída","Verificar"))) -> Saída
... B83: 46086 | C83: Pró-labore do mês | D83: Pró-labore / Retirada do negócio | E83: Transferência | F83: 4500 | G83: =IF($D83="","",IF(COUNTIF('Config'!$E$8:$E$15,$D83)>0,"Entrada",IF(COUNTIF('Config'!$G$8:$G$23,$D83)>0,"Saída","Verificar"))) -> Entrada
B84: 46087 | C84: Aporte reserva de emergência | D84: Reserva e Metas | E84: Pix | F84: 300 | G84: =IF($D84="","",IF(COUNTIF('Config'!$E$8:$E$15,$D84)>0,"Entrada",IF(COUNTIF('Config'!$G$8:$G$23,$D84)>0,"Saída","Verificar"))) -> Saída | H84: Reserva de emergência
B85: 46087 | C85: Aporte reserva para impostos | D85: Reserva e Metas | E85: Pix | F85: 150 | G85: =IF($D85="","",IF(COUNTIF('Config'!$E$8:$E$15,$D85)>0,"Entrada",IF(COUNTIF('Config'!$G$8:$G$23,$D85)>0,"Saída","Verificar"))) -> Saída | H85: Reserva para impostos
B86: 46087 | C86: Armazenamento na nuvem | D86: Assinaturas | E86: Cartão de crédito | F86: 9.9 | G86: =IF($D86="","",IF(COUNTIF('Config'!$E$8:$E$15,$D86)>0,"Entrada",IF(COUNTIF('Config'!$G$8:$G$23,$D86)>0,"Saída","Verificar"))) -> Saída
B87: 46087 | C87: Netflix | D87: Assinaturas | E87: Cartão de crédito | F87: 55.9 | G87: =IF($D87="","",IF(COUNTIF('Config'!$E$8:$E$15,$D87)>0,"Entrada",IF(COUNTIF('Config'!$G$8:$G$23,$D87)>0,"Saída","Verificar"))) -> Saída
B88: 46087 | C88: Padaria / hortifruti | D88: Alimentação | E88: Pix | F88: 51.57 | G88: =IF($D88="","",IF(COUNTIF('Config'!$E$8:$E$15,$D88)>0,"Entrada",IF(COUNTIF('Config'!$G$8:$G$23,$D88)>0,"Saída","Verificar"))) -> Saída
B89: 46087 | C89: Spotify | D89: Assinaturas | E89: Cartão de crédito | F89: 21.9 | G89: =IF($D89="","",IF(COUNTIF('Config'!$E$8:$E$15,$D89)>0,"Entrada",IF(COUNTIF('Config'!$G$8:$G$23,$D89)>0,"Saída","Verificar"))) -> Saída
B90: 46088 | C90: App de transporte | D90: Transporte | E90: Cartão de crédito | F90: 28.28 | G90: =IF($D90="","",IF(COUNTIF('Config'!$E$8:$E$15,$D90)>0,"Entrada",IF(COUNTIF('Config'!$G$8:$G$23,$D90)>0,"Saída","Verificar"))) -> Saída
B91: 46089 | C91: Internet fibra | D91: Contas da casa | E91: Débito automático | F91: 119.9 | G91: =IF($D91="","",IF(COUNTIF('Config'!$E$8:$E$15,$D91)>0,"Entrada",IF(COUNTIF('Config'!$G$8:$G$23,$D91)>0,"Saída","Verificar"))) -> Saída
B92: 46089 | C92: Restaurante / bar | D92: Lazer | E92: Cartão de crédito | F92: 73.24 | G92: =IF($D92="","",IF(COUNTIF('Config'!$E$8:$E$15,$D92)>0,"Entrada",IF(COUNTIF('Config'!$G$8:$G$23,$D92)>0,"Saída","Verificar"))) -> Saída
B93: 46090 | C93: Delivery | D93: Alimentação | E93: Cartão de débito | F93: 54.9 | G93: =IF($D93="","",IF(COUNTIF('Config'!$E$8:$E$15,$D93)>0,"Entrada",IF(COUNTIF('Config'!$G$8:$G$23,$D93)>0,"Saída","Verificar"))) -> Saída
B94: 46091 | C94: Aluguel | D94: Moradia | E94: Boleto | F94: 950 | G94: =IF($D94="","",IF(COUNTIF('Config'!$E$8:$E$15,$D94)>0,"Entrada",IF(COUNTIF('Config'!$G$8:$G$23,$D94)>0,"Saída","Verificar"))) -> Saída
B95: 46091 | C95: Condomínio | D95: Moradia | E95: Boleto | F95: 150 | G95: =IF($D95="","",IF(COUNTIF('Config'!$E$8:$E$15,$D95)>0,"Entrada",IF(COUNTIF('Config'!$G$8:$G$23,$D95)>0,"Saída","Verificar"))) -> Saída
B96: 46091 | C96: Plano de saúde | D96: Saúde | E96: Débito automático | F96: 180 | G96: =IF($D96="","",IF(COUNTIF('Config'!$E$8:$E$15,$D96)>0,"Entrada",IF(COUNTIF('Config'!$G$8:$G$23,$D96)>0,"Saída","Verificar"))) -> Saída
B97: 46091 | C97: Supermercado | D97: Alimentação | E97: Cartão de crédito | F97: 204.27 | G97: =IF($D97="","",IF(COUNTIF('Config'!$E$8:$E$15,$D97)>0,"Entrada",IF(COUNTIF('Config'!$G$8:$G$23,$D97)>0,"Saída","Verificar"))) -> Saída
... B118: 46117 | C118: Pró-labore do mês | D118: Pró-labore / Retirada do negócio | E118: Transferência | F118: 4500 | G118: =IF($D118="","",IF(COUNTIF('Config'!$E$8:$E$15,$D118)>0,"Entrada",IF(COUNTIF('Config'!$G$8:$G$23,$D118)>0,"Saída","Verificar"))) -> Entrada
B119: 46118 | C119: Aporte reserva de emergência | D119: Reserva e Metas | E119: Pix | F119: 300 | G119: =IF($D119="","",IF(COUNTIF('Config'!$E$8:$E$15,$D119)>0,"Entrada",IF(COUNTIF('Config'!$G$8:$G$23,$D119)>0,"Saída","Verificar"))) -> Saída | H119: Reserva de emergência
B120: 46118 | C120: Aporte reserva para impostos | D120: Reserva e Metas | E120: Pix | F120: 150 | G120: =IF($D120="","",IF(COUNTIF('Config'!$E$8:$E$15,$D120)>0,"Entrada",IF(COUNTIF('Config'!$G$8:$G$23,$D120)>0,"Saída","Verificar"))) -> Saída | H120: Reserva para impostos
B121: 46118 | C121: Aporte viagem | D121: Reserva e Metas | E121: Pix | F121: 150 | G121: =IF($D121="","",IF(COUNTIF('Config'!$E$8:$E$15,$D121)>0,"Entrada",IF(COUNTIF('Config'!$G$8:$G$23,$D121)>0,"Saída","Verificar"))) -> Saída | H121: Viagem de férias
B122: 46118 | C122: Armazenamento na nuvem | D122: Assinaturas | E122: Cartão de crédito | F122: 9.9 | G122: =IF($D122="","",IF(COUNTIF('Config'!$E$8:$E$15,$D122)>0,"Entrada",IF(COUNTIF('Config'!$G$8:$G$23,$D122)>0,"Saída","Verificar"))) -> Saída
B123: 46118 | C123: Netflix | D123: Assinaturas | E123: Cartão de crédito | F123: 55.9 | G123: =IF($D123="","",IF(COUNTIF('Config'!$E$8:$E$15,$D123)>0,"Entrada",IF(COUNTIF('Config'!$G$8:$G$23,$D123)>0,"Saída","Verificar"))) -> Saída
B124: 46118 | C124: Padaria / hortifruti | D124: Alimentação | E124: Pix | F124: 49.24 | G124: =IF($D124="","",IF(COUNTIF('Config'!$E$8:$E$15,$D124)>0,"Entrada",IF(COUNTIF('Config'!$G$8:$G$23,$D124)>0,"Saída","Verificar"))) -> Saída
B125: 46118 | C125: Spotify | D125: Assinaturas | E125: Cartão de crédito | F125: 21.9 | G125: =IF($D125="","",IF(COUNTIF('Config'!$E$8:$E$15,$D125)>0,"Entrada",IF(COUNTIF('Config'!$G$8:$G$23,$D125)>0,"Saída","Verificar"))) -> Saída
B126: 46119 | C126: App de transporte | D126: Transporte | E126: Cartão de crédito | F126: 36.48 | G126: =IF($D126="","",IF(COUNTIF('Config'!$E$8:$E$15,$D126)>0,"Entrada",IF(COUNTIF('Config'!$G$8:$G$23,$D126)>0,"Saída","Verificar"))) -> Saída
B127: 46120 | C127: Internet fibra | D127: Contas da casa | E127: Débito automático | F127: 119.9 | G127: =IF($D127="","",IF(COUNTIF('Config'!$E$8:$E$15,$D127)>0,"Entrada",IF(COUNTIF('Config'!$G$8:$G$23,$D127)>0,"Saída","Verificar"))) -> Saída
B128: 46120 | C128: Restaurante / bar | D128: Lazer | E128: Cartão de crédito | F128: 90.37 | G128: =IF($D128="","",IF(COUNTIF('Config'!$E$8:$E$15,$D128)>0,"Entrada",IF(COUNTIF('Config'!$G$8:$G$23,$D128)>0,"Saída","Verificar"))) -> Saída
B129: 46121 | C129: Delivery | D129: Alimentação | E129: Cartão de débito | F129: 51.22 | G129: =IF($D129="","",IF(COUNTIF('Config'!$E$8:$E$15,$D129)>0,"Entrada",IF(COUNTIF('Config'!$G$8:$G$23,$D129)>0,"Saída","Verificar"))) -> Saída
B130: 46122 | C130: Aluguel | D130: Moradia | E130: Boleto | F130: 950 | G130: =IF($D130="","",IF(COUNTIF('Config'!$E$8:$E$15,$D130)>0,"Entrada",IF(COUNTIF('Config'!$G$8:$G$23,$D130)>0,"Saída","Verificar"))) -> Saída
B131: 46122 | C131: Condomínio | D131: Moradia | E131: Boleto | F131: 150 | G131: =IF($D131="","",IF(COUNTIF('Config'!$E$8:$E$15,$D131)>0,"Entrada",IF(COUNTIF('Config'!$G$8:$G$23,$D131)>0,"Saída","Verificar"))) -> Saída
B132: 46122 | C132: Plano de saúde | D132: Saúde | E132: Débito automático | F132: 180 | G132: =IF($D132="","",IF(COUNTIF('Config'!$E$8:$E$15,$D132)>0,"Entrada",IF(COUNTIF('Config'!$G$8:$G$23,$D132)>0,"Saída","Verificar"))) -> Saída
B133: 46122 | C133: Supermercado | D133: Alimentação | E133: Cartão de crédito | F133: 185.05 | G133: =IF($D133="","",IF(COUNTIF('Config'!$E$8:$E$15,$D133)>0,"Entrada",IF(COUNTIF('Config'!$G$8:$G$23,$D133)>0,"Saída","Verificar"))) -> Saída
... B153: 46147 | C153: Pró-labore do mês | D153: Pró-labore / Retirada do negócio | E153: Transferência | F153: 4500 | G153: =IF($D153="","",IF(COUNTIF('Config'!$E$8:$E$15,$D153)>0,"Entrada",IF(COUNTIF('Config'!$G$8:$G$23,$D153)>0,"Saída","Verificar"))) -> Entrada
B154: 46148 | C154: Aporte reserva de emergência | D154: Reserva e Metas | E154: Pix | F154: 300 | G154: =IF($D154="","",IF(COUNTIF('Config'!$E$8:$E$15,$D154)>0,"Entrada",IF(COUNTIF('Config'!$G$8:$G$23,$D154)>0,"Saída","Verificar"))) -> Saída | H154: Reserva de emergência
B155: 46148 | C155: Aporte reserva para impostos | D155: Reserva e Metas | E155: Pix | F155: 150 | G155: =IF($D155="","",IF(COUNTIF('Config'!$E$8:$E$15,$D155)>0,"Entrada",IF(COUNTIF('Config'!$G$8:$G$23,$D155)>0,"Saída","Verificar"))) -> Saída | H155: Reserva para impostos
B156: 46148 | C156: Aporte viagem | D156: Reserva e Metas | E156: Pix | F156: 150 | G156: =IF($D156="","",IF(COUNTIF('Config'!$E$8:$E$15,$D156)>0,"Entrada",IF(COUNTIF('Config'!$G$8:$G$23,$D156)>0,"Saída","Verificar"))) -> Saída | H156: Viagem de férias
B157: 46148 | C157: Armazenamento na nuvem | D157: Assinaturas | E157: Cartão de crédito | F157: 9.9 | G157: =IF($D157="","",IF(COUNTIF('Config'!$E$8:$E$15,$D157)>0,"Entrada",IF(COUNTIF('Config'!$G$8:$G$23,$D157)>0,"Saída","Verificar"))) -> Saída
B158: 46148 | C158: Netflix | D158: Assinaturas | E158: Cartão de crédito | F158: 55.9 | G158: =IF($D158="","",IF(COUNTIF('Config'!$E$8:$E$15,$D158)>0,"Entrada",IF(COUNTIF('Config'!$G$8:$G$23,$D158)>0,"Saída","Verificar"))) -> Saída
B159: 46148 | C159: Padaria / hortifruti | D159: Alimentação | E159: Pix | F159: 31.74 | G159: =IF($D159="","",IF(COUNTIF('Config'!$E$8:$E$15,$D159)>0,"Entrada",IF(COUNTIF('Config'!$G$8:$G$23,$D159)>0,"Saída","Verificar"))) -> Saída
B160: 46148 | C160: Spotify | D160: Assinaturas | E160: Cartão de crédito | F160: 21.9 | G160: =IF($D160="","",IF(COUNTIF('Config'!$E$8:$E$15,$D160)>0,"Entrada",IF(COUNTIF('Config'!$G$8:$G$23,$D160)>0,"Saída","Verificar"))) -> Saída
B161: 46149 | C161: App de transporte | D161: Transporte | E161: Cartão de crédito | F161: 23.63 | G161: =IF($D161="","",IF(COUNTIF('Config'!$E$8:$E$15,$D161)>0,"Entrada",IF(COUNTIF('Config'!$G$8:$G$23,$D161)>0,"Saída","Verificar"))) -> Saída
B162: 46150 | C162: Internet fibra | D162: Contas da casa | E162: Débito automático | F162: 119.9 | G162: =IF($D162="","",IF(COUNTIF('Config'!$E$8:$E$15,$D162)>0,"Entrada",IF(COUNTIF('Config'!$G$8:$G$23,$D162)>0,"Saída","Verificar"))) -> Saída
B163: 46150 | C163: Presente Dia das Mães | D163: Presentes e doações | E163: Cartão de crédito | F163: 155 | G163: =IF($D163="","",IF(COUNTIF('Config'!$E$8:$E$15,$D163)>0,"Entrada",IF(COUNTIF('Config'!$G$8:$G$23,$D163)>0,"Saída","Verificar"))) -> Saída
B164: 46150 | C164: Restaurante / bar | D164: Lazer | E164: Cartão de crédito | F164: 89.53 | G164: =IF($D164="","",IF(COUNTIF('Config'!$E$8:$E$15,$D164)>0,"Entrada",IF(COUNTIF('Config'!$G$8:$G$23,$D164)>0,"Saída","Verificar"))) -> Saída
B165: 46151 | C165: Delivery | D165: Alimentação | E165: Cartão de débito | F165: 43.44 | G165: =IF($D165="","",IF(COUNTIF('Config'!$E$8:$E$15,$D165)>0,"Entrada",IF(COUNTIF('Config'!$G$8:$G$23,$D165)>0,"Saída","Verificar"))) -> Saída
B166: 46152 | C166: Aluguel | D166: Moradia | E166: Boleto | F166: 950 | G166: =IF($D166="","",IF(COUNTIF('Config'!$E$8:$E$15,$D166)>0,"Entrada",IF(COUNTIF('Config'!$G$8:$G$23,$D166)>0,"Saída","Verificar"))) -> Saída
B167: 46152 | C167: Condomínio | D167: Moradia | E167: Boleto | F167: 150 | G167: =IF($D167="","",IF(COUNTIF('Config'!$E$8:$E$15,$D167)>0,"Entrada",IF(COUNTIF('Config'!$G$8:$G$23,$D167)>0,"Saída","Verificar"))) -> Saída
B168: 46152 | C168: Plano de saúde | D168: Saúde | E168: Débito automático | F168: 180 | G168: =IF($D168="","",IF(COUNTIF('Config'!$E$8:$E$15,$D168)>0,"Entrada",IF(COUNTIF('Config'!$G$8:$G$23,$D168)>0,"Saída","Verificar"))) -> Saída
... B191: 46178 | C191: Pró-labore do mês | D191: Pró-labore / Retirada do negócio | E191: Transferência | F191: 4500 | G191: =IF($D191="","",IF(COUNTIF('Config'!$E$8:$E$15,$D191)>0,"Entrada",IF(COUNTIF('Config'!$G$8:$G$23,$D191)>0,"Saída","Verificar"))) -> Entrada
B192: 46179 | C192: Aporte reserva de emergência | D192: Reserva e Metas | E192: Pix | F192: 300 | G192: =IF($D192="","",IF(COUNTIF('Config'!$E$8:$E$15,$D192)>0,"Entrada",IF(COUNTIF('Config'!$G$8:$G$23,$D192)>0,"Saída","Verificar"))) -> Saída | H192: Reserva de emergência
B193: 46179 | C193: Aporte reserva para impostos | D193: Reserva e Metas | E193: Pix | F193: 150 | G193: =IF($D193="","",IF(COUNTIF('Config'!$E$8:$E$15,$D193)>0,"Entrada",IF(COUNTIF('Config'!$G$8:$G$23,$D193)>0,"Saída","Verificar"))) -> Saída | H193: Reserva para impostos
B194: 46179 | C194: Aporte viagem | D194: Reserva e Metas | E194: Pix | F194: 150 | G194: =IF($D194="","",IF(COUNTIF('Config'!$E$8:$E$15,$D194)>0,"Entrada",IF(COUNTIF('Config'!$G$8:$G$23,$D194)>0,"Saída","Verificar"))) -> Saída | H194: Viagem de férias
B195: 46179 | C195: Armazenamento na nuvem | D195: Assinaturas | E195: Cartão de crédito | F195: 9.9 | G195: =IF($D195="","",IF(COUNTIF('Config'!$E$8:$E$15,$D195)>0,"Entrada",IF(COUNTIF('Config'!$G$8:$G$23,$D195)>0,"Saída","Verificar"))) -> Saída
B196: 46179 | C196: Netflix | D196: Assinaturas | E196: Cartão de crédito | F196: 55.9 | G196: =IF($D196="","",IF(COUNTIF('Config'!$E$8:$E$15,$D196)>0,"Entrada",IF(COUNTIF('Config'!$G$8:$G$23,$D196)>0,"Saída","Verificar"))) -> Saída
B197: 46179 | C197: Padaria / hortifruti | D197: Alimentação | E197: Pix | F197: 29.18 | G197: =IF($D197="","",IF(COUNTIF('Config'!$E$8:$E$15,$D197)>0,"Entrada",IF(COUNTIF('Config'!$G$8:$G$23,$D197)>0,"Saída","Verificar"))) -> Saída
B198: 46179 | C198: Spotify | D198: Assinaturas | E198: Cartão de crédito | F198: 21.9 | G198: =IF($D198="","",IF(COUNTIF('Config'!$E$8:$E$15,$D198)>0,"Entrada",IF(COUNTIF('Config'!$G$8:$G$23,$D198)>0,"Saída","Verificar"))) -> Saída
B199: 46180 | C199: App de transporte | D199: Transporte | E199: Cartão de crédito | F199: 38.72 | G199: =IF($D199="","",IF(COUNTIF('Config'!$E$8:$E$15,$D199)>0,"Entrada",IF(COUNTIF('Config'!$G$8:$G$23,$D199)>0,"Saída","Verificar"))) -> Saída
B200: 46181 | C200: Internet fibra | D200: Contas da casa | E200: Débito automático | F200: 119.9 | G200: =IF($D200="","",IF(COUNTIF('Config'!$E$8:$E$15,$D200)>0,"Entrada",IF(COUNTIF('Config'!$G$8:$G$23,$D200)>0,"Saída","Verificar"))) -> Saída
B201: 46181 | C201: Restaurante / bar | D201: Lazer | E201: Cartão de crédito | F201: 83.82 | G201: =IF($D201="","",IF(COUNTIF('Config'!$E$8:$E$15,$D201)>0,"Entrada",IF(COUNTIF('Config'!$G$8:$G$23,$D201)>0,"Saída","Verificar"))) -> Saída
B202: 46182 | C202: Delivery | D202: Alimentação | E202: Cartão de débito | F202: 40.81 | G202: =IF($D202="","",IF(COUNTIF('Config'!$E$8:$E$15,$D202)>0,"Entrada",IF(COUNTIF('Config'!$G$8:$G$23,$D202)>0,"Saída","Verificar"))) -> Saída
...

Sheet Orçamento Pessoal
B1: 🏠 Início | C1: 📊 Painel Geral | E1: 👤 Painel Pessoal | G1: 💼 Painel Negócio | H1: ⚙ Config
B2: PESSOAL | C2: 📝 Lançamentos | E2: 💳 Orçamento | G2: 📅 Resumo anual | H2: 🎯 Metas
B3: NEGÓCIO | C3: 📝 Lançamentos | D3: 🤝 Clientes | E3: 💰 Recebimentos | G3: 🧾 Impostos | H3: 📈 Fluxo de Caixa
B5: 💳 Orçamento mensal — planejado × realizado
B6: Defina quanto pretende gastar em cada categoria. O 'realizado' vem dos lançamentos do mês escolhido.
B7: 📅 Mês de análise: | C7: Setembro | D7: ← escolha o mês no menu suspenso. Os valores planejados (amarelo) valem para todos os meses.
B9: Categoria | C9: Planejado (mês) | D9: Realizado | E9: Diferença | F9: % usado | G9: Progresso | H9: Situação
B10: Renda do mês (entradas) | C10: 4500 | D10: =INDEX('Resumo Pessoal'!$C$18:$N$18,'Dados'!$C$9) -> 4552.89 | E10: =D10-C10 -> 52.89 | F10: =IF(C10>0,D10/C10,"") -> 1.0117533 | G10: =IF(F10="","",REPT("█",MIN(22,ROUND(F10*20,0)))) -> ████████████████████ | H10: =IF(C10=0,"—",IF(D10>=C10,"✓ Meta batida",IF(D10>=C10*0.8,"⚠ Quase lá","✖ Abaixo"))) -> ✓ Meta batida
B11: DESPESAS POR CATEGORIA
B12: =IF('Config'!$G$8="","",'Config'!$G$8) -> Moradia | C12: 1100 | D12: =IF(B12="",0,INDEX('Resumo Pessoal'!$C$20:$N$20,'Dados'!$C$9)) -> 1100 | E12: =C12-D12 -> 0 | F12: =IF(C12>0,D12/C12,"") -> 1 | G12: =IF(F12="","",REPT("█",MIN(22,ROUND(F12*20,0)))) -> ████████████████████ | H12: =IF(C12=0,IF(D12>0,"Sem orçamento","—"),IF(D12>C12,"✖ Estourou",IF(D12>=C12*0.8,"⚠ Atenção","✓ OK"))) -> ⚠ Atenção
B13: =IF('Config'!$G$9="","",'Config'!$G$9) -> Contas da casa | C13: 360 | D13: =IF(B13="",0,INDEX('Resumo Pessoal'!$C$21:$N$21,'Dados'!$C$9)) -> 289.91 | E13: =C13-D13 -> 70.09 | F13: =IF(C13>0,D13/C13,"") -> 0.80530556 | G13: =IF(F13="","",REPT("█",MIN(22,ROUND(F13*20,0)))) -> ████████████████ | H13: =IF(C13=0,IF(D13>0,"Sem orçamento","—"),IF(D13>C13,"✖ Estourou",IF(D13>=C13*0.8,"⚠ Atenção","✓ OK"))) -> ⚠ Atenção
B14: =IF('Config'!$G$10="","",'Config'!$G$10) -> Alimentação | C14: 650 | D14: =IF(B14="",0,INDEX('Resumo Pessoal'!$C$22:$N$22,'Dados'!$C$9)) -> 627.27 | E14: =C14-D14 -> 22.73 | F14: =IF(C14>0,D14/C14,"") -> 0.96503077 | G14: =IF(F14="","",REPT("█",MIN(22,ROUND(F14*20,0)))) -> ███████████████████ | H14: =IF(C14=0,IF(D14>0,"Sem orçamento","—"),IF(D14>C14,"✖ Estourou",IF(D14>=C14*0.8,"⚠ Atenção","✓ OK"))) -> ⚠ Atenção
B15: =IF('Config'!$G$11="","",'Config'!$G$11) -> Transporte | C15: 420 | D15: =IF(B15="",0,INDEX('Resumo Pessoal'!$C$23:$N$23,'Dados'!$C$9)) -> 264.51 | E15: =C15-D15 -> 155.49 | F15: =IF(C15>0,D15/C15,"") -> 0.62978571 | G15: =IF(F15="","",REPT("█",MIN(22,ROUND(F15*20,0)))) -> █████████████ | H15: =IF(C15=0,IF(D15>0,"Sem orçamento","—"),IF(D15>C15,"✖ Estourou",IF(D15>=C15*0.8,"⚠ Atenção","✓ OK"))) -> ✓ OK
B16: =IF('Config'!$G$12="","",'Config'!$G$12) -> Saúde | C16: 250 | D16: =IF(B16="",0,INDEX('Resumo Pessoal'!$C$24:$N$24,'Dados'!$C$9)) -> 255.85 | E16: =C16-D16 -> -5.85 | F16: =IF(C16>0,D16/C16,"") -> 1.0234 | G16: =IF(F16="","",REPT("█",MIN(22,ROUND(F16*20,0)))) -> ████████████████████ | H16: =IF(C16=0,IF(D16>0,"Sem orçamento","—"),IF(D16>C16,"✖ Estourou",IF(D16>=C16*0.8,"⚠ Atenção","✓ OK"))) -> ✖ Estourou
B17: =IF('Config'!$G$13="","",'Config'!$G$13) -> Educação | C17: 150 | D17: =IF(B17="",0,INDEX('Resumo Pessoal'!$C$25:$N$25,'Dados'!$C$9)) -> 149 | E17: =C17-D17 -> 1 | F17: =IF(C17>0,D17/C17,"") -> 0.99333333 | G17: =IF(F17="","",REPT("█",MIN(22,ROUND(F17*20,0)))) -> ████████████████████ | H17: =IF(C17=0,IF(D17>0,"Sem orçamento","—"),IF(D17>C17,"✖ Estourou",IF(D17>=C17*0.8,"⚠ Atenção","✓ OK"))) -> ⚠ Atenção
B18: =IF('Config'!$G$14="","",'Config'!$G$14) -> Lazer | C18: 250 | D18: =IF(B18="",0,INDEX('Resumo Pessoal'!$C$26:$N$26,'Dados'!$C$9)) -> 201.67 | E18: =C18-D18 -> 48.33 | F18: =IF(C18>0,D18/C18,"") -> 0.80668 | G18: =IF(F18="","",REPT("█",MIN(22,ROUND(F18*20,0)))) -> ████████████████ | H18: =IF(C18=0,IF(D18>0,"Sem orçamento","—"),IF(D18>C18,"✖ Estourou",IF(D18>=C18*0.8,"⚠ Atenção","✓ OK"))) -> ⚠ Atenção
B19: =IF('Config'!$G$15="","",'Config'!$G$15) -> Vestuário | C19: 100 | D19: =IF(B19="",0,INDEX('Resumo Pessoal'!$C$27:$N$27,'Dados'!$C$9)) -> 138.36 | E19: =C19-D19 -> -38.36 | F19: =IF(C19>0,D19/C19,"") -> 1.3836 | G19: =IF(F19="","",REPT("█",MIN(22,ROUND(F19*20,0)))) -> ██████████████████████ | H19: =IF(C19=0,IF(D19>0,"Sem orçamento","—"),IF(D19>C19,"✖ Estourou",IF(D19>=C19*0.8,"⚠ Atenção","✓ OK"))) -> ✖ Estourou
B20: =IF('Config'!$G$16="","",'Config'!$G$16) -> Assinaturas | C20: 90 | D20: =IF(B20="",0,INDEX('Resumo Pessoal'!$C$28:$N$28,'Dados'!$C$9)) -> 87.7 | E20: =C20-D20 -> 2.3 | F20: =IF(C20>0,D20/C20,"") -> 0.97444444 | G20: =IF(F20="","",REPT("█",MIN(22,ROUND(F20*20,0)))) -> ███████████████████ | H20: =IF(C20=0,IF(D20>0,"Sem orçamento","—"),IF(D20>C20,"✖ Estourou",IF(D20>=C20*0.8,"⚠ Atenção","✓ OK"))) -> ⚠ Atenção
B21: =IF('Config'!$G$17="","",'Config'!$G$17) -> Cuidados pessoais | C21: 200 | D21: =IF(B21="",0,INDEX('Resumo Pessoal'!$C$29:$N$29,'Dados'!$C$9)) -> 175.11 | E21: =C21-D21 -> 24.89 | F21: =IF(C21>0,D21/C21,"") -> 0.87555 | G21: =IF(F21="","",REPT("█",MIN(22,ROUND(F21*20,0)))) -> ██████████████████ | H21: =IF(C21=0,IF(D21>0,"Sem orçamento","—"),IF(D21>C21,"✖ Estourou",IF(D21>=C21*0.8,"⚠ Atenção","✓ OK"))) -> ⚠ Atenção
B22: =IF('Config'!$G$18="","",'Config'!$G$18) -> Pets | C22: 0 | D22: =IF(B22="",0,INDEX('Resumo Pessoal'!$C$30:$N$30,'Dados'!$C$9)) -> 0 | E22: =C22-D22 -> 0 | F22: =IF(C22>0,D22/C22,"") | G22: =IF(F22="","",REPT("█",MIN(22,ROUND(F22*20,0)))) | H22: =IF(C22=0,IF(D22>0,"Sem orçamento","—"),IF(D22>C22,"✖ Estourou",IF(D22>=C22*0.8,"⚠ Atenção","✓ OK"))) -> —
B23: =IF('Config'!$G$19="","",'Config'!$G$19) -> Presentes e doações | C23: 80 | D23: =IF(B23="",0,INDEX('Resumo Pessoal'!$C$31:$N$31,'Dados'!$C$9)) -> 50 | E23: =C23-D23 -> 30 | F23: =IF(C23>0,D23/C23,"") -> 0.625 | G23: =IF(F23="","",REPT("█",MIN(22,ROUND(F23*20,0)))) -> █████████████ | H23: =IF(C23=0,IF(D23>0,"Sem orçamento","—"),IF(D23>C23,"✖ Estourou",IF(D23>=C23*0.8,"⚠ Atenção","✓ OK"))) -> ✓ OK
B24: =IF('Config'!$G$20="","",'Config'!$G$20) -> Dívidas e financiamentos | C24: 0 | D24: =IF(B24="",0,INDEX('Resumo Pessoal'!$C$32:$N$32,'Dados'!$C$9)) -> 0 | E24: =C24-D24 -> 0 | F24: =IF(C24>0,D24/C24,"") | G24: =IF(F24="","",REPT("█",MIN(22,ROUND(F24*20,0)))) | H24: =IF(C24=0,IF(D24>0,"Sem orçamento","—"),IF(D24>C24,"✖ Estourou",IF(D24>=C24*0.8,"⚠ Atenção","✓ OK"))) -> —
B25: =IF('Config'!$G$21="","",'Config'!$G$21) -> Reserva e Metas | C25: 600 | D25: =IF(B25="",0,INDEX('Resumo Pessoal'!$C$33:$N$33,'Dados'!$C$9)) -> 600 | E25: =D25-C25 -> 0 | F25: =IF(C25>0,D25/C25,"") -> 1 | G25: =IF(F25="","",REPT("█",MIN(22,ROUND(F25*20,0)))) -> ████████████████████ | H25: =IF(C25=0,"—",IF(D25>=C25,"✓ Meta batida",IF(D25>=C25*0.8,"⚠ Quase lá","✖ Abaixo"))) -> ✓ Meta batida
B26: =IF('Config'!$G$22="","",'Config'!$G$22) -> Impostos pessoais | C26: 80 | D26: =IF(B26="",0,INDEX('Resumo Pessoal'!$C$34:$N$34,'Dados'!$C$9)) -> 0 | E26: =C26-D26 -> 80 | F26: =IF(C26>0,D26/C26,"") -> 0 | G26: =IF(F26="","",REPT("█",MIN(22,ROUND(F26*20,0)))) | H26: =IF(C26=0,IF(D26>0,"Sem orçamento","—"),IF(D26>C26,"✖ Estourou",IF(D26>=C26*0.8,"⚠ Atenção","✓ OK"))) -> ✓ OK
B27: =IF('Config'!$G$23="","",'Config'!$G$23) -> Outros | C27: 80 | D27: =IF(B27="",0,INDEX('Resumo Pessoal'!$C$35:$N$35,'Dados'!$C$9)) -> 53.46 | E27: =C27-D27 -> 26.54 | F27: =IF(C27>0,D27/C27,"") -> 0.66825 | G27: =IF(F27="","",REPT("█",MIN(22,ROUND(F27*20,0)))) -> █████████████ | H27: =IF(C27=0,IF(D27>0,"Sem orçamento","—"),IF(D27>C27,"✖ Estourou",IF(D27>=C27*0.8,"⚠ Atenção","✓ OK"))) -> ✓ OK
B28: TOTAL DAS DESPESAS | C28: =SUM(C12:C27) -> 4410 | D28: =SUM(D12:D27) -> 3992.84 | E28: =C28-D28 -> 417.16 | F28: =IF(C28>0,D28/C28,"") -> 0.9054059 | G28: =IF(F28="","",REPT("█",MIN(22,ROUND(F28*20,0)))) -> ██████████████████ | H28: =IF(C28=0,"—",IF(D28>C28,"✖ Estourou",IF(D28>=C28*0.8,"⚠ Atenção","✓ OK"))) -> ⚠ Atenção
B29: SALDO (renda − despesas) | C29: =C10-C28 -> 90 | D29: =D10-D28 -> 560.05 | E29: =D29-C29 -> 470.05

Sheet Resumo Pessoal
B1: 🏠 Início | D1: 📊 Painel Geral | G1: 👤 Painel Pessoal | K1: 💼 Painel Negócio | O1: ⚙ Config
B2: PESSOAL | D2: 📝 Lançamentos | G2: 💳 Orçamento | K2: 📅 Resumo anual | O2: 🎯 Metas
B3: NEGÓCIO | C3: 📝 Lançamentos | F3: 🤝 Clientes | I3: 💰 Recebimentos | L3: 🧾 Impostos | O3: 📈 Fluxo de Caixa
B5: 📅 Resumo anual — entradas e saídas por mês
B6: Totalizado automaticamente a partir da aba de lançamentos. Cores destacam saldos positivos e negativos.
C7: =DATE('Config'!$C$8,1,1) -> 46023 | D7: =DATE('Config'!$C$8,2,1) -> 46054 | E7: =DATE('Config'!$C$8,3,1) -> 46082 | F7: =DATE('Config'!$C$8,4,1) -> 46113 | G7: =DATE('Config'!$C$8,5,1) -> 46143 | H7: =DATE('Config'!$C$8,6,1) -> 46174 | I7: =DATE('Config'!$C$8,7,1) -> 46204 | J7: =DATE('Config'!$C$8,8,1) -> 46235 | K7: =DATE('Config'!$C$8,9,1) -> 46266 | L7: =DATE('Config'!$C$8,10,1) -> 46296 | M7: =DATE('Config'!$C$8,11,1) -> 46327 | N7: =DATE('Config'!$C$8,12,1) -> 46357
B8: Categoria | C8: =INDEX('Config'!$L$8:$L$19,1) -> Jan | D8: =INDEX('Config'!$L$8:$L$19,2) -> Fev | E8: =INDEX('Config'!$L$8:$L$19,3) -> Mar | F8: =INDEX('Config'!$L$8:$L$19,4) -> Abr | G8: =INDEX('Config'!$L$8:$L$19,5) -> Mai | H8: =INDEX('Config'!$L$8:$L$19,6) -> Jun | I8: =INDEX('Config'!$L$8:$L$19,7) -> Jul | J8: =INDEX('Config'!$L$8:$L$19,8) -> Ago | K8: =INDEX('Config'!$L$8:$L$19,9) -> Set | L8: =INDEX('Config'!$L$8:$L$19,10) -> Out | M8: =INDEX('Config'!$L$8:$L$19,11) -> Nov | N8: =INDEX('Config'!$L$8:$L$19,12) -> Dez | O8: Total | P8: Média/mês | Q8: % das saídas
B9: ▲ ENTRADAS
B10: =IF('Config'!$E$8="","",'Config'!$E$8) -> Pró-labore / Retirada do negócio | C10: =IF($B10="",0,SUMIFS('Lanç. Pessoal'!$F$11:$F$1510,'Lanç. Pessoal'!$D$11:$D$1510,$B10,'Lanç. Pessoal'!$B$11:$B$1510,">="&C$7,'Lanç. Pessoal'!$B$11:$B$1510,"<"&EDATE(C$7,1))) -> 4500 | D10: =IF($B10="",0,SUMIFS('Lanç. Pessoal'!$F$11:$F$1510,'Lanç. Pessoal'!$D$11:$D$1510,$B10,'Lanç. Pessoal'!$B$11:$B$1510,">="&D$7,'Lanç. Pessoal'!$B$11:$B$1510,"<"&EDATE(D$7,1))) -> 4500 | E10: =IF($B10="",0,SUMIFS('Lanç. Pessoal'!$F$11:$F$1510,'Lanç. Pessoal'!$D$11:$D$1510,$B10,'Lanç. Pessoal'!$B$11:$B$1510,">="&E$7,'Lanç. Pessoal'!$B$11:$B$1510,"<"&EDATE(E$7,1))) -> 4500 | F10: =IF($B10="",0,SUMIFS('Lanç. Pessoal'!$F$11:$F$1510,'Lanç. Pessoal'!$D$11:$D$1510,$B10,'Lanç. Pessoal'!$B$11:$B$1510,">="&F$7,'Lanç. Pessoal'!$B$11:$B$1510,"<"&EDATE(F$7,1))) -> 4500 | G10: =IF($B10="",0,SUMIFS('Lanç. Pessoal'!$F$11:$F$1510,'Lanç. Pessoal'!$D$11:$D$1510,$B10,'Lanç. Pessoal'!$B$11:$B$1510,">="&G$7,'Lanç. Pessoal'!$B$11:$B$1510,"<"&EDATE(G$7,1))) -> 4500 | H10: =IF($B10="",0,SUMIFS('Lanç. Pessoal'!$F$11:$F$1510,'Lanç. Pessoal'!$D$11:$D$1510,$B10,'Lanç. Pessoal'!$B$11:$B$1510,">="&H$7,'Lanç. Pessoal'!$B$11:$B$1510,"<"&EDATE(H$7,1))) -> 4500 | I10: =IF($B10="",0,SUMIFS('Lanç. Pessoal'!$F$11:$F$1510,'Lanç. Pessoal'!$D$11:$D$1510,$B10,'Lanç. Pessoal'!$B$11:$B$1510,">="&I$7,'Lanç. Pessoal'!$B$11:$B$1510,"<"&EDATE(I$7,1))) -> 4500 | J10: =IF($B10="",0,SUMIFS('Lanç. Pessoal'!$F$11:$F$1510,'Lanç. Pessoal'!$D$11:$D$1510,$B10,'Lanç. Pessoal'!$B$11:$B$1510,">="&J$7,'Lanç. Pessoal'!$B$11:$B$1510,"<"&EDATE(J$7,1))) -> 4500 | ... N10: =IF($B10="",0,SUMIFS('Lanç. Pessoal'!$F$11:$F$1510,'Lanç. Pessoal'!$D$11:$D$1510,$B10,'Lanç. Pessoal'!$B$11:$B$1510,">="&N$7,'Lanç. Pessoal'!$B$11:$B$1510,"<"&EDATE(N$7,1))) -> 0 | O10: =SUM(C10:N10) -> 40500 | P10: =IFERROR(O10/'Dados'!$C$11,0) -> 4500
B11: =IF('Config'!$E$9="","",'Config'!$E$9) -> Salário / Renda fixa | C11: =IF($B11="",0,SUMIFS('Lanç. Pessoal'!$F$11:$F$1510,'Lanç. Pessoal'!$D$11:$D$1510,$B11,'Lanç. Pessoal'!$B$11:$B$1510,">="&C$7,'Lanç. Pessoal'!$B$11:$B$1510,"<"&EDATE(C$7,1))) -> 0 | D11: =IF($B11="",0,SUMIFS('Lanç. Pessoal'!$F$11:$F$1510,'Lanç. Pessoal'!$D$11:$D$1510,$B11,'Lanç. Pessoal'!$B$11:$B$1510,">="&D$7,'Lanç. Pessoal'!$B$11:$B$1510,"<"&EDATE(D$7,1))) -> 0 | E11: =IF($B11="",0,SUMIFS('Lanç. Pessoal'!$F$11:$F$1510,'Lanç. Pessoal'!$D$11:$D$1510,$B11,'Lanç. Pessoal'!$B$11:$B$1510,">="&E$7,'Lanç. Pessoal'!$B$11:$B$1510,"<"&EDATE(E$7,1))) -> 0 | F11: =IF($B11="",0,SUMIFS('Lanç. Pessoal'!$F$11:$F$1510,'Lanç. Pessoal'!$D$11:$D$1510,$B11,'Lanç. Pessoal'!$B$11:$B$1510,">="&F$7,'Lanç. Pessoal'!$B$11:$B$1510,"<"&EDATE(F$7,1))) -> 0 | G11: =IF($B11="",0,SUMIFS('Lanç. Pessoal'!$F$11:$F$1510,'Lanç. Pessoal'!$D$11:$D$1510,$B11,'Lanç. Pessoal'!$B$11:$B$1510,">="&G$7,'Lanç. Pessoal'!$B$11:$B$1510,"<"&EDATE(G$7,1))) -> 0 | H11: =IF($B11="",0,SUMIFS('Lanç. Pessoal'!$F$11:$F$1510,'Lanç. Pessoal'!$D$11:$D$1510,$B11,'Lanç. Pessoal'!$B$11:$B$1510,">="&H$7,'Lanç. Pessoal'!$B$11:$B$1510,"<"&EDATE(H$7,1))) -> 0 | I11: =IF($B11="",0,SUMIFS('Lanç. Pessoal'!$F$11:$F$1510,'Lanç. Pessoal'!$D$11:$D$1510,$B11,'Lanç. Pessoal'!$B$11:$B$1510,">="&I$7,'Lanç. Pessoal'!$B$11:$B$1510,"<"&EDATE(I$7,1))) -> 0 | J11: =IF($B11="",0,SUMIFS('Lanç. Pessoal'!$F$11:$F$1510,'Lanç. Pessoal'!$D$11:$D$1510,$B11,'Lanç. Pessoal'!$B$11:$B$1510,">="&J$7,'Lanç. Pessoal'!$B$11:$B$1510,"<"&EDATE(J$7,1))) -> 0 | ... N11: =IF($B11="",0,SUMIFS('Lanç. Pessoal'!$F$11:$F$1510,'Lanç. Pessoal'!$D$11:$D$1510,$B11,'Lanç. Pessoal'!$B$11:$B$1510,">="&N$7,'Lanç. Pessoal'!$B$11:$B$1510,"<"&EDATE(N$7,1))) -> 0 | O11: =SUM(C11:N11) -> 0 | P11: =IFERROR(O11/'Dados'!$C$11,0) -> 0
B12: =IF('Config'!$E$10="","",'Config'!$E$10) -> Renda extra | C12: =IF($B12="",0,SUMIFS('Lanç. Pessoal'!$F$11:$F$1510,'Lanç. Pessoal'!$D$11:$D$1510,$B12,'Lanç. Pessoal'!$B$11:$B$1510,">="&C$7,'Lanç. Pessoal'!$B$11:$B$1510,"<"&EDATE(C$7,1))) -> 0 | D12: =IF($B12="",0,SUMIFS('Lanç. Pessoal'!$F$11:$F$1510,'Lanç. Pessoal'!$D$11:$D$1510,$B12,'Lanç. Pessoal'!$B$11:$B$1510,">="&D$7,'Lanç. Pessoal'!$B$11:$B$1510,"<"&EDATE(D$7,1))) -> 0 | E12: =IF($B12="",0,SUMIFS('Lanç. Pessoal'!$F$11:$F$1510,'Lanç. Pessoal'!$D$11:$D$1510,$B12,'Lanç. Pessoal'!$B$11:$B$1510,">="&E$7,'Lanç. Pessoal'!$B$11:$B$1510,"<"&EDATE(E$7,1))) -> 0 | F12: =IF($B12="",0,SUMIFS('Lanç. Pessoal'!$F$11:$F$1510,'Lanç. Pessoal'!$D$11:$D$1510,$B12,'Lanç. Pessoal'!$B$11:$B$1510,">="&F$7,'Lanç. Pessoal'!$B$11:$B$1510,"<"&EDATE(F$7,1))) -> 0 | G12: =IF($B12="",0,SUMIFS('Lanç. Pessoal'!$F$11:$F$1510,'Lanç. Pessoal'!$D$11:$D$1510,$B12,'Lanç. Pessoal'!$B$11:$B$1510,">="&G$7,'Lanç. Pessoal'!$B$11:$B$1510,"<"&EDATE(G$7,1))) -> 0 | H12: =IF($B12="",0,SUMIFS('Lanç. Pessoal'!$F$11:$F$1510,'Lanç. Pessoal'!$D$11:$D$1510,$B12,'Lanç. Pessoal'!$B$11:$B$1510,">="&H$7,'Lanç. Pessoal'!$B$11:$B$1510,"<"&EDATE(H$7,1))) -> 0 | I12: =IF($B12="",0,SUMIFS('Lanç. Pessoal'!$F$11:$F$1510,'Lanç. Pessoal'!$D$11:$D$1510,$B12,'Lanç. Pessoal'!$B$11:$B$1510,">="&I$7,'Lanç. Pessoal'!$B$11:$B$1510,"<"&EDATE(I$7,1))) -> 0 | J12: =IF($B12="",0,SUMIFS('Lanç. Pessoal'!$F$11:$F$1510,'Lanç. Pessoal'!$D$11:$D$1510,$B12,'Lanç. Pessoal'!$B$11:$B$1510,">="&J$7,'Lanç. Pessoal'!$B$11:$B$1510,"<"&EDATE(J$7,1))) -> 0 | ... N12: =IF($B12="",0,SUMIFS('Lanç. Pessoal'!$F$11:$F$1510,'Lanç. Pessoal'!$D$11:$D$1510,$B12,'Lanç. Pessoal'!$B$11:$B$1510,">="&N$7,'Lanç. Pessoal'!$B$11:$B$1510,"<"&EDATE(N$7,1))) -> 0 | O12: =SUM(C12:N12) -> 0 | P12: =IFERROR(O12/'Dados'!$C$11,0) -> 0
B13: =IF('Config'!$E$11="","",'Config'!$E$11) -> Rendimentos de investimentos | C13: =IF($B13="",0,SUMIFS('Lanç. Pessoal'!$F$11:$F$1510,'Lanç. Pessoal'!$D$11:$D$1510,$B13,'Lanç. Pessoal'!$B$11:$B$1510,">="&C$7,'Lanç. Pessoal'!$B$11:$B$1510,"<"&EDATE(C$7,1))) -> 46.63 | D13: =IF($B13="",0,SUMIFS('Lanç. Pessoal'!$F$11:$F$1510,'Lanç. Pessoal'!$D$11:$D$1510,$B13,'Lanç. Pessoal'!$B$11:$B$1510,">="&D$7,'Lanç. Pessoal'!$B$11:$B$1510,"<"&EDATE(D$7,1))) -> 50.78 | E13: =IF($B13="",0,SUMIFS('Lanç. Pessoal'!$F$11:$F$1510,'Lanç. Pessoal'!$D$11:$D$1510,$B13,'Lanç. Pessoal'!$B$11:$B$1510,">="&E$7,'Lanç. Pessoal'!$B$11:$B$1510,"<"&EDATE(E$7,1))) -> 58.6 | F13: =IF($B13="",0,SUMIFS('Lanç. Pessoal'!$F$11:$F$1510,'Lanç. Pessoal'!$D$11:$D$1510,$B13,'Lanç. Pessoal'!$B$11:$B$1510,">="&F$7,'Lanç. Pessoal'!$B$11:$B$1510,"<"&EDATE(F$7,1))) -> 69.41 | G13: =IF($B13="",0,SUMIFS('Lanç. Pessoal'!$F$11:$F$1510,'Lanç. Pessoal'!$D$11:$D$1510,$B13,'Lanç. Pessoal'!$B$11:$B$1510,">="&G$7,'Lanç. Pessoal'!$B$11:$B$1510,"<"&EDATE(G$7,1))) -> 53.22 | H13: =IF($B13="",0,SUMIFS('Lanç. Pessoal'!$F$11:$F$1510,'Lanç. Pessoal'!$D$11:$D$1510,$B13,'Lanç. Pessoal'!$B$11:$B$1510,">="&H$7,'Lanç. Pessoal'!$B$11:$B$1510,"<"&EDATE(H$7,1))) -> 41.87 | I13: =IF($B13="",0,SUMIFS('Lanç. Pessoal'!$F$11:$F$1510,'Lanç. Pessoal'!$D$11:$D$1510,$B13,'Lanç. Pessoal'!$B$11:$B$1510,">="&I$7,'Lanç. Pessoal'!$B$11:$B$1510,"<"&EDATE(I$7,1))) -> 60.59 | J13: =IF($B13="",0,SUMIFS('Lanç. Pessoal'!$F$11:$F$1510,'Lanç. Pessoal'!$D$11:$D$1510,$B13,'Lanç. Pessoal'!$B$11:$B$1510,">="&J$7,'Lanç. Pessoal'!$B$11:$B$1510,"<"&EDATE(J$7,1))) -> 44.92 | ... N13: =IF($B13="",0,SUMIFS('Lanç. Pessoal'!$F$11:$F$1510,'Lanç. Pessoal'!$D$11:$D$1510,$B13,'Lanç. Pessoal'!$B$11:$B$1510,">="&N$7,'Lanç. Pessoal'!$B$11:$B$1510,"<"&EDATE(N$7,1))) -> 0 | O13: =SUM(C13:N13) -> 478.91 | P13: =IFERROR(O13/'Dados'!$C$11,0) -> 53.212222
B14: =IF('Config'!$E$12="","",'Config'!$E$12) -> Reembolsos | C14: =IF($B14="",0,SUMIFS('Lanç. Pessoal'!$F$11:$F$1510,'Lanç. Pessoal'!$D$11:$D$1510,$B14,'Lanç. Pessoal'!$B$11:$B$1510,">="&C$7,'Lanç. Pessoal'!$B$11:$B$1510,"<"&EDATE(C$7,1))) -> 0 | D14: =IF($B14="",0,SUMIFS('Lanç. Pessoal'!$F$11:$F$1510,'Lanç. Pessoal'!$D$11:$D$1510,$B14,'Lanç. Pessoal'!$B$11:$B$1510,">="&D$7,'Lanç. Pessoal'!$B$11:$B$1510,"<"&EDATE(D$7,1))) -> 0 | E14: =IF($B14="",0,SUMIFS('Lanç. Pessoal'!$F$11:$F$1510,'Lanç. Pessoal'!$D$11:$D$1510,$B14,'Lanç. Pessoal'!$B$11:$B$1510,">="&E$7,'Lanç. Pessoal'!$B$11:$B$1510,"<"&EDATE(E$7,1))) -> 386.08 | F14: =IF($B14="",0,SUMIFS('Lanç. Pessoal'!$F$11:$F$1510,'Lanç. Pessoal'!$D$11:$D$1510,$B14,'Lanç. Pessoal'!$B$11:$B$1510,">="&F$7,'Lanç. Pessoal'!$B$11:$B$1510,"<"&EDATE(F$7,1))) -> 0 | G14: =IF($B14="",0,SUMIFS('Lanç. Pessoal'!$F$11:$F$1510,'Lanç. Pessoal'!$D$11:$D$1510,$B14,'Lanç. Pessoal'!$B$11:$B$1510,">="&G$7,'Lanç. Pessoal'!$B$11:$B$1510,"<"&EDATE(G$7,1))) -> 0 | H14: =IF($B14="",0,SUMIFS('Lanç. Pessoal'!$F$11:$F$1510,'Lanç. Pessoal'!$D$11:$D$1510,$B14,'Lanç. Pessoal'!$B$11:$B$1510,">="&H$7,'Lanç. Pessoal'!$B$11:$B$1510,"<"&EDATE(H$7,1))) -> 360.13 | I14: =IF($B14="",0,SUMIFS('Lanç. Pessoal'!$F$11:$F$1510,'Lanç. Pessoal'!$D$11:$D$1510,$B14,'Lanç. Pessoal'!$B$11:$B$1510,">="&I$7,'Lanç. Pessoal'!$B$11:$B$1510,"<"&EDATE(I$7,1))) -> 0 | J14: =IF($B14="",0,SUMIFS('Lanç. Pessoal'!$F$11:$F$1510,'Lanç. Pessoal'!$D$11:$D$1510,$B14,'Lanç. Pessoal'!$B$11:$B$1510,">="&J$7,'Lanç. Pessoal'!$B$11:$B$1510,"<"&EDATE(J$7,1))) -> 0 | ... N14: =IF($B14="",0,SUMIFS('Lanç. Pessoal'!$F$11:$F$1510,'Lanç. Pessoal'!$D$11:$D$1510,$B14,'Lanç. Pessoal'!$B$11:$B$1510,">="&N$7,'Lanç. Pessoal'!$B$11:$B$1510,"<"&EDATE(N$7,1))) -> 0 | O14: =SUM(C14:N14) -> 746.21 | P14: =IFERROR(O14/'Dados'!$C$11,0) -> 82.912222
B15: =IF('Config'!$E$13="","",'Config'!$E$13) -> Aluguéis recebidos | C15: =IF($B15="",0,SUMIFS('Lanç. Pessoal'!$F$11:$F$1510,'Lanç. Pessoal'!$D$11:$D$1510,$B15,'Lanç. Pessoal'!$B$11:$B$1510,">="&C$7,'Lanç. Pessoal'!$B$11:$B$1510,"<"&EDATE(C$7,1))) -> 0 | D15: =IF($B15="",0,SUMIFS('Lanç. Pessoal'!$F$11:$F$1510,'Lanç. Pessoal'!$D$11:$D$1510,$B15,'Lanç. Pessoal'!$B$11:$B$1510,">="&D$7,'Lanç. Pessoal'!$B$11:$B$1510,"<"&EDATE(D$7,1))) -> 0 | E15: =IF($B15="",0,SUMIFS('Lanç. Pessoal'!$F$11:$F$1510,'Lanç. Pessoal'!$D$11:$D$1510,$B15,'Lanç. Pessoal'!$B$11:$B$1510,">="&E$7,'Lanç. Pessoal'!$B$11:$B$1510,"<"&EDATE(E$7,1))) -> 0 | F15: =IF($B15="",0,SUMIFS('Lanç. Pessoal'!$F$11:$F$1510,'Lanç. Pessoal'!$D$11:$D$1510,$B15,'Lanç. Pessoal'!$B$11:$B$1510,">="&F$7,'Lanç. Pessoal'!$B$11:$B$1510,"<"&EDATE(F$7,1))) -> 0 | G15: =IF($B15="",0,SUMIFS('Lanç. Pessoal'!$F$11:$F$1510,'Lanç. Pessoal'!$D$11:$D$1510,$B15,'Lanç. Pessoal'!$B$11:$B$1510,">="&G$7,'Lanç. Pessoal'!$B$11:$B$1510,"<"&EDATE(G$7,1))) -> 0 | H15: =IF($B15="",0,SUMIFS('Lanç. Pessoal'!$F$11:$F$1510,'Lanç. Pessoal'!$D$11:$D$1510,$B15,'Lanç. Pessoal'!$B$11:$B$1510,">="&H$7,'Lanç. Pessoal'!$B$11:$B$1510,"<"&EDATE(H$7,1))) -> 0 | I15: =IF($B15="",0,SUMIFS('Lanç. Pessoal'!$F$11:$F$1510,'Lanç. Pessoal'!$D$11:$D$1510,$B15,'Lanç. Pessoal'!$B$11:$B$1510,">="&I$7,'Lanç. Pessoal'!$B$11:$B$1510,"<"&EDATE(I$7,1))) -> 0 | J15: =IF($B15="",0,SUMIFS('Lanç. Pessoal'!$F$11:$F$1510,'Lanç. Pessoal'!$D$11:$D$1510,$B15,'Lanç. Pessoal'!$B$11:$B$1510,">="&J$7,'Lanç. Pessoal'!$B$11:$B$1510,"<"&EDATE(J$7,1))) -> 0 | ... N15: =IF($B15="",0,SUMIFS('Lanç. Pessoal'!$F$11:$F$1510,'Lanç. Pessoal'!$D$11:$D$1510,$B15,'Lanç. Pessoal'!$B$11:$B$1510,">="&N$7,'Lanç. Pessoal'!$B$11:$B$1510,"<"&EDATE(N$7,1))) -> 0 | O15: =SUM(C15:N15) -> 0 | P15: =IFERROR(O15/'Dados'!$C$11,0) -> 0
B16: =IF('Config'!$E$14="","",'Config'!$E$14) -> Presentes recebidos | C16: =IF($B16="",0,SUMIFS('Lanç. Pessoal'!$F$11:$F$1510,'Lanç. Pessoal'!$D$11:$D$1510,$B16,'Lanç. Pessoal'!$B$11:$B$1510,">="&C$7,'Lanç. Pessoal'!$B$11:$B$1510,"<"&EDATE(C$7,1))) -> 0 | D16: =IF($B16="",0,SUMIFS('Lanç. Pessoal'!$F$11:$F$1510,'Lanç. Pessoal'!$D$11:$D$1510,$B16,'Lanç. Pessoal'!$B$11:$B$1510,">="&D$7,'Lanç. Pessoal'!$B$11:$B$1510,"<"&EDATE(D$7,1))) -> 0 | E16: =IF($B16="",0,SUMIFS('Lanç. Pessoal'!$F$11:$F$1510,'Lanç. Pessoal'!$D$11:$D$1510,$B16,'Lanç. Pessoal'!$B$11:$B$1510,">="&E$7,'Lanç. Pessoal'!$B$11:$B$1510,"<"&EDATE(E$7,1))) -> 0 | F16: =IF($B16="",0,SUMIFS('Lanç. Pessoal'!$F$11:$F$1510,'Lanç. Pessoal'!$D$11:$D$1510,$B16,'Lanç. Pessoal'!$B$11:$B$1510,">="&F$7,'Lanç. Pessoal'!$B$11:$B$1510,"<"&EDATE(F$7,1))) -> 0 | G16: =IF($B16="",0,SUMIFS('Lanç. Pessoal'!$F$11:$F$1510,'Lanç. Pessoal'!$D$11:$D$1510,$B16,'Lanç. Pessoal'!$B$11:$B$1510,">="&G$7,'Lanç. Pessoal'!$B$11:$B$1510,"<"&EDATE(G$7,1))) -> 0 | H16: =IF($B16="",0,SUMIFS('Lanç. Pessoal'!$F$11:$F$1510,'Lanç. Pessoal'!$D$11:$D$1510,$B16,'Lanç. Pessoal'!$B$11:$B$1510,">="&H$7,'Lanç. Pessoal'!$B$11:$B$1510,"<"&EDATE(H$7,1))) -> 0 | I16: =IF($B16="",0,SUMIFS('Lanç. Pessoal'!$F$11:$F$1510,'Lanç. Pessoal'!$D$11:$D$1510,$B16,'Lanç. Pessoal'!$B$11:$B$1510,">="&I$7,'Lanç. Pessoal'!$B$11:$B$1510,"<"&EDATE(I$7,1))) -> 0 | J16: =IF($B16="",0,SUMIFS('Lanç. Pessoal'!$F$11:$F$1510,'Lanç. Pessoal'!$D$11:$D$1510,$B16,'Lanç. Pessoal'!$B$11:$B$1510,">="&J$7,'Lanç. Pessoal'!$B$11:$B$1510,"<"&EDATE(J$7,1))) -> 0 | ... N16: =IF($B16="",0,SUMIFS('Lanç. Pessoal'!$F$11:$F$1510,'Lanç. Pessoal'!$D$11:$D$1510,$B16,'Lanç. Pessoal'!$B$11:$B$1510,">="&N$7,'Lanç. Pessoal'!$B$11:$B$1510,"<"&EDATE(N$7,1))) -> 0 | O16: =SUM(C16:N16) -> 0 | P16: =IFERROR(O16/'Dados'!$C$11,0) -> 0
B17: =IF('Config'!$E$15="","",'Config'!$E$15) -> Outras entradas | C17: =IF($B17="",0,SUMIFS('Lanç. Pessoal'!$F$11:$F$1510,'Lanç. Pessoal'!$D$11:$D$1510,$B17,'Lanç. Pessoal'!$B$11:$B$1510,">="&C$7,'Lanç. Pessoal'!$B$11:$B$1510,"<"&EDATE(C$7,1))) -> 0 | D17: =IF($B17="",0,SUMIFS('Lanç. Pessoal'!$F$11:$F$1510,'Lanç. Pessoal'!$D$11:$D$1510,$B17,'Lanç. Pessoal'!$B$11:$B$1510,">="&D$7,'Lanç. Pessoal'!$B$11:$B$1510,"<"&EDATE(D$7,1))) -> 0 | E17: =IF($B17="",0,SUMIFS('Lanç. Pessoal'!$F$11:$F$1510,'Lanç. Pessoal'!$D$11:$D$1510,$B17,'Lanç. Pessoal'!$B$11:$B$1510,">="&E$7,'Lanç. Pessoal'!$B$11:$B$1510,"<"&EDATE(E$7,1))) -> 0 | F17: =IF($B17="",0,SUMIFS('Lanç. Pessoal'!$F$11:$F$1510,'Lanç. Pessoal'!$D$11:$D$1510,$B17,'Lanç. Pessoal'!$B$11:$B$1510,">="&F$7,'Lanç. Pessoal'!$B$11:$B$1510,"<"&EDATE(F$7,1))) -> 0 | G17: =IF($B17="",0,SUMIFS('Lanç. Pessoal'!$F$11:$F$1510,'Lanç. Pessoal'!$D$11:$D$1510,$B17,'Lanç. Pessoal'!$B$11:$B$1510,">="&G$7,'Lanç. Pessoal'!$B$11:$B$1510,"<"&EDATE(G$7,1))) -> 0 | H17: =IF($B17="",0,SUMIFS('Lanç. Pessoal'!$F$11:$F$1510,'Lanç. Pessoal'!$D$11:$D$1510,$B17,'Lanç. Pessoal'!$B$11:$B$1510,">="&H$7,'Lanç. Pessoal'!$B$11:$B$1510,"<"&EDATE(H$7,1))) -> 0 | I17: =IF($B17="",0,SUMIFS('Lanç. Pessoal'!$F$11:$F$1510,'Lanç. Pessoal'!$D$11:$D$1510,$B17,'Lanç. Pessoal'!$B$11:$B$1510,">="&I$7,'Lanç. Pessoal'!$B$11:$B$1510,"<"&EDATE(I$7,1))) -> 0 | J17: =IF($B17="",0,SUMIFS('Lanç. Pessoal'!$F$11:$F$1510,'Lanç. Pessoal'!$D$11:$D$1510,$B17,'Lanç. Pessoal'!$B$11:$B$1510,">="&J$7,'Lanç. Pessoal'!$B$11:$B$1510,"<"&EDATE(J$7,1))) -> 0 | ... N17: =IF($B17="",0,SUMIFS('Lanç. Pessoal'!$F$11:$F$1510,'Lanç. Pessoal'!$D$11:$D$1510,$B17,'Lanç. Pessoal'!$B$11:$B$1510,">="&N$7,'Lanç. Pessoal'!$B$11:$B$1510,"<"&EDATE(N$7,1))) -> 0 | O17: =SUM(C17:N17) -> 0 | P17: =IFERROR(O17/'Dados'!$C$11,0) -> 0
B18: Total de entradas | C18: =SUM(C10:C17) -> 4546.63 | D18: =SUM(D10:D17) -> 4550.78 | E18: =SUM(E10:E17) -> 4944.68 | F18: =SUM(F10:F17) -> 4569.41 | G18: =SUM(G10:G17) -> 4553.22 | H18: =SUM(H10:H17) -> 4902 | I18: =SUM(I10:I17) -> 4560.59 | J18: =SUM(J10:J17) -> 4544.92 | ... P18: =SUM(P10:P17) -> 4636.1244
B19: ▼ SAÍDAS
B20: =IF('Config'!$G$8="","",'Config'!$G$8) -> Moradia | C20: =IF($B20="",0,SUMIFS('Lanç. Pessoal'!$F$11:$F$1510,'Lanç. Pessoal'!$D$11:$D$1510,$B20,'Lanç. Pessoal'!$B$11:$B$1510,">="&C$7,'Lanç. Pessoal'!$B$11:$B$1510,"<"&EDATE(C$7,1))) -> 1100 | D20: =IF($B20="",0,SUMIFS('Lanç. Pessoal'!$F$11:$F$1510,'Lanç. Pessoal'!$D$11:$D$1510,$B20,'Lanç. Pessoal'!$B$11:$B$1510,">="&D$7,'Lanç. Pessoal'!$B$11:$B$1510,"<"&EDATE(D$7,1))) -> 1100 | E20: =IF($B20="",0,SUMIFS('Lanç. Pessoal'!$F$11:$F$1510,'Lanç. Pessoal'!$D$11:$D$1510,$B20,'Lanç. Pessoal'!$B$11:$B$1510,">="&E$7,'Lanç. Pessoal'!$B$11:$B$1510,"<"&EDATE(E$7,1))) -> 1100 | F20: =IF($B20="",0,SUMIFS('Lanç. Pessoal'!$F$11:$F$1510,'Lanç. Pessoal'!$D$11:$D$1510,$B20,'Lanç. Pessoal'!$B$11:$B$1510,">="&F$7,'Lanç. Pessoal'!$B$11:$B$1510,"<"&EDATE(F$7,1))) -> 1100 | G20: =IF($B20="",0,SUMIFS('Lanç. Pessoal'!$F$11:$F$1510,'Lanç. Pessoal'!$D$11:$D$1510,$B20,'Lanç. Pessoal'!$B$11:$B$1510,">="&G$7,'Lanç. Pessoal'!$B$11:$B$1510,"<"&EDATE(G$7,1))) -> 1100 | H20: =IF($B20="",0,SUMIFS('Lanç. Pessoal'!$F$11:$F$1510,'Lanç. Pessoal'!$D$11:$D$1510,$B20,'Lanç. Pessoal'!$B$11:$B$1510,">="&H$7,'Lanç. Pessoal'!$B$11:$B$1510,"<"&EDATE(H$7,1))) -> 1100 | I20: =IF($B20="",0,SUMIFS('Lanç. Pessoal'!$F$11:$F$1510,'Lanç. Pessoal'!$D$11:$D$1510,$B20,'Lanç. Pessoal'!$B$11:$B$1510,">="&I$7,'Lanç. Pessoal'!$B$11:$B$1510,"<"&EDATE(I$7,1))) -> 1100 | J20: =IF($B20="",0,SUMIFS('Lanç. Pessoal'!$F$11:$F$1510,'Lanç. Pessoal'!$D$11:$D$1510,$B20,'Lanç. Pessoal'!$B$11:$B$1510,">="&J$7,'Lanç. Pessoal'!$B$11:$B$1510,"<"&EDATE(J$7,1))) -> 1100 | ... N20: =IF($B20="",0,SUMIFS('Lanç. Pessoal'!$F$11:$F$1510,'Lanç. Pessoal'!$D$11:$D$1510,$B20,'Lanç. Pessoal'!$B$11:$B$1510,">="&N$7,'Lanç. Pessoal'!$B$11:$B$1510,"<"&EDATE(N$7,1))) -> 0 | O20: =SUM(C20:N20) -> 9900 | P20: =IFERROR(O20/'Dados'!$C$11,0) -> 1100 | Q20: =IFERROR(O20/$O$36,0) -> 0.24364715
B21: =IF('Config'!$G$9="","",'Config'!$G$9) -> Contas da casa | C21: =IF($B21="",0,SUMIFS('Lanç. Pessoal'!$F$11:$F$1510,'Lanç. Pessoal'!$D$11:$D$1510,$B21,'Lanç. Pessoal'!$B$11:$B$1510,">="&C$7,'Lanç. Pessoal'!$B$11:$B$1510,"<"&EDATE(C$7,1))) -> 334.23 | D21: =IF($B21="",0,SUMIFS('Lanç. Pessoal'!$F$11:$F$1510,'Lanç. Pessoal'!$D$11:$D$1510,$B21,'Lanç. Pessoal'!$B$11:$B$1510,">="&D$7,'Lanç. Pessoal'!$B$11:$B$1510,"<"&EDATE(D$7,1))) -> 396.48 | E21: =IF($B21="",0,SUMIFS('Lanç. Pessoal'!$F$11:$F$1510,'Lanç. Pessoal'!$D$11:$D$1510,$B21,'Lanç. Pessoal'!$B$11:$B$1510,">="&E$7,'Lanç. Pessoal'!$B$11:$B$1510,"<"&EDATE(E$7,1))) -> 346.44 | F21: =IF($B21="",0,SUMIFS('Lanç. Pessoal'!$F$11:$F$1510,'Lanç. Pessoal'!$D$11:$D$1510,$B21,'Lanç. Pessoal'!$B$11:$B$1510,">="&F$7,'Lanç. Pessoal'!$B$11:$B$1510,"<"&EDATE(F$7,1))) -> 340.42 | G21: =IF($B21="",0,SUMIFS('Lanç. Pessoal'!$F$11:$F$1510,'Lanç. Pessoal'!$D$11:$D$1510,$B21,'Lanç. Pessoal'!$B$11:$B$1510,">="&G$7,'Lanç. Pessoal'!$B$11:$B$1510,"<"&EDATE(G$7,1))) -> 458.67 | H21: =IF($B21="",0,SUMIFS('Lanç. Pessoal'!$F$11:$F$1510,'Lanç. Pessoal'!$D$11:$D$1510,$B21,'Lanç. Pessoal'!$B$11:$B$1510,">="&H$7,'Lanç. Pessoal'!$B$11:$B$1510,"<"&EDATE(H$7,1))) -> 358.42 | I21: =IF($B21="",0,SUMIFS('Lanç. Pessoal'!$F$11:$F$1510,'Lanç. Pessoal'!$D$11:$D$1510,$B21,'Lanç. Pessoal'!$B$11:$B$1510,">="&I$7,'Lanç. Pessoal'!$B$11:$B$1510,"<"&EDATE(I$7,1))) -> 296.98 | J21: =IF($B21="",0,SUMIFS('Lanç. Pessoal'!$F$11:$F$1510,'Lanç. Pessoal'!$D$11:$D$1510,$B21,'Lanç. Pessoal'!$B$11:$B$1510,">="&J$7,'Lanç. Pessoal'!$B$11:$B$1510,"<"&EDATE(J$7,1))) -> 419.01 | ... N21: =IF($B21="",0,SUMIFS('Lanç. Pessoal'!$F$11:$F$1510,'Lanç. Pessoal'!$D$11:$D$1510,$B21,'Lanç. Pessoal'!$B$11:$B$1510,">="&N$7,'Lanç. Pessoal'!$B$11:$B$1510,"<"&EDATE(N$7,1))) -> 0 | O21: =SUM(C21:N21) -> 3240.56 | P21: =IFERROR(O21/'Dados'!$C$11,0) -> 360.06222 | Q21: =IFERROR(O21/$O$36,0) -> 0.079752848
B22: =IF('Config'!$G$10="","",'Config'!$G$10) -> Alimentação | C22: =IF($B22="",0,SUMIFS('Lanç. Pessoal'!$F$11:$F$1510,'Lanç. Pessoal'!$D$11:$D$1510,$B22,'Lanç. Pessoal'!$B$11:$B$1510,">="&C$7,'Lanç. Pessoal'!$B$11:$B$1510,"<"&EDATE(C$7,1))) -> 695.87 | D22: =IF($B22="",0,SUMIFS('Lanç. Pessoal'!$F$11:$F$1510,'Lanç. Pessoal'!$D$11:$D$1510,$B22,'Lanç. Pessoal'!$B$11:$B$1510,">="&D$7,'Lanç. Pessoal'!$B$11:$B$1510,"<"&EDATE(D$7,1))) -> 637.86 | E22: =IF($B22="",0,SUMIFS('Lanç. Pessoal'!$F$11:$F$1510,'Lanç. Pessoal'!$D$11:$D$1510,$B22,'Lanç. Pessoal'!$B$11:$B$1510,">="&E$7,'Lanç. Pessoal'!$B$11:$B$1510,"<"&EDATE(E$7,1))) -> 800.28 | F22: =IF($B22="",0,SUMIFS('Lanç. Pessoal'!$F$11:$F$1510,'Lanç. Pessoal'!$D$11:$D$1510,$B22,'Lanç. Pessoal'!$B$11:$B$1510,">="&F$7,'Lanç. Pessoal'!$B$11:$B$1510,"<"&EDATE(F$7,1))) -> 713.43 | G22: =IF($B22="",0,SUMIFS('Lanç. Pessoal'!$F$11:$F$1510,'Lanç. Pessoal'!$D$11:$D$1510,$B22,'Lanç. Pessoal'!$B$11:$B$1510,">="&G$7,'Lanç. Pessoal'!$B$11:$B$1510,"<"&EDATE(G$7,1))) -> 611.9 | H22: =IF($B22="",0,SUMIFS('Lanç. Pessoal'!$F$11:$F$1510,'Lanç. Pessoal'!$D$11:$D$1510,$B22,'Lanç. Pessoal'!$B$11:$B$1510,">="&H$7,'Lanç. Pessoal'!$B$11:$B$1510,"<"&EDATE(H$7,1))) -> 688.54 | I22: =IF($B22="",0,SUMIFS('Lanç. Pessoal'!$F$11:$F$1510,'Lanç. Pessoal'!$D$11:$D$1510,$B22,'Lanç. Pessoal'!$B$11:$B$1510,">="&I$7,'Lanç. Pessoal'!$B$11:$B$1510,"<"&EDATE(I$7,1))) -> 667.96 | J22: =IF($B22="",0,SUMIFS('Lanç. Pessoal'!$F$11:$F$1510,'Lanç. Pessoal'!$D$11:$D$1510,$B22,'Lanç. Pessoal'!$B$11:$B$1510,">="&J$7,'Lanç. Pessoal'!$B$11:$B$1510,"<"&EDATE(J$7,1))) -> 717.97 | ... N22: =IF($B22="",0,SUMIFS('Lanç. Pessoal'!$F$11:$F$1510,'Lanç. Pessoal'!$D$11:$D$1510,$B22,'Lanç. Pessoal'!$B$11:$B$1510,">="&N$7,'Lanç. Pessoal'!$B$11:$B$1510,"<"&EDATE(N$7,1))) -> 0 | O22: =SUM(C22:N22) -> 6161.08 | P22: =IFERROR(O22/'Dados'!$C$11,0) -> 684.56444 | Q22: =IFERROR(O22/$O$36,0) -> 0.15162925
B23: =IF('Config'!$G$11="","",'Config'!$G$11) -> Transporte | C23: =IF($B23="",0,SUMIFS('Lanç. Pessoal'!$F$11:$F$1510,'Lanç. Pessoal'!$D$11:$D$1510,$B23,'Lanç. Pessoal'!$B$11:$B$1510,">="&C$7,'Lanç. Pessoal'!$B$11:$B$1510,"<"&EDATE(C$7,1))) -> 287.17 | D23: =IF($B23="",0,SUMIFS('Lanç. Pessoal'!$F$11:$F$1510,'Lanç. Pessoal'!$D$11:$D$1510,$B23,'Lanç. Pessoal'!$B$11:$B$1510,">="&D$7,'Lanç. Pessoal'!$B$11:$B$1510,"<"&EDATE(D$7,1))) -> 267.73 | E23: =IF($B23="",0,SUMIFS('Lanç. Pessoal'!$F$11:$F$1510,'Lanç. Pessoal'!$D$11:$D$1510,$B23,'Lanç. Pessoal'!$B$11:$B$1510,">="&E$7,'Lanç. Pessoal'!$B$11:$B$1510,"<"&EDATE(E$7,1))) -> 285.21 | F23: =IF($B23="",0,SUMIFS('Lanç. Pessoal'!$F$11:$F$1510,'Lanç. Pessoal'!$D$11:$D$1510,$B23,'Lanç. Pessoal'!$B$11:$B$1510,">="&F$7,'Lanç. Pessoal'!$B$11:$B$1510,"<"&EDATE(F$7,1))) -> 989.03 | G23: =IF($B23="",0,SUMIFS('Lanç. Pessoal'!$F$11:$F$1510,'Lanç. Pessoal'!$D$11:$D$1510,$B23,'Lanç. Pessoal'!$B$11:$B$1510,">="&G$7,'Lanç. Pessoal'!$B$11:$B$1510,"<"&EDATE(G$7,1))) -> 267.33 | H23: =IF($B23="",0,SUMIFS('Lanç. Pessoal'!$F$11:$F$1510,'Lanç. Pessoal'!$D$11:$D$1510,$B23,'Lanç. Pessoal'!$B$11:$B$1510,">="&H$7,'Lanç. Pessoal'!$B$11:$B$1510,"<"&EDATE(H$7,1))) -> 276.74 | I23: =IF($B23="",0,SUMIFS('Lanç. Pessoal'!$F$11:$F$1510,'Lanç. Pessoal'!$D$11:$D$1510,$B23,'Lanç. Pessoal'!$B$11:$B$1510,">="&I$7,'Lanç. Pessoal'!$B$11:$B$1510,"<"&EDATE(I$7,1))) -> 287.7 | J23: =IF($B23="",0,SUMIFS('Lanç. Pessoal'!$F$11:$F$1510,'Lanç. Pessoal'!$D$11:$D$1510,$B23,'Lanç. Pessoal'!$B$11:$B$1510,">="&J$7,'Lanç. Pessoal'!$B$11:$B$1510,"<"&EDATE(J$7,1))) -> 729.29 | ... N23: =IF($B23="",0,SUMIFS('Lanç. Pessoal'!$F$11:$F$1510,'Lanç. Pessoal'!$D$11:$D$1510,$B23,'Lanç. Pessoal'!$B$11:$B$1510,">="&N$7,'Lanç. Pessoal'!$B$11:$B$1510,"<"&EDATE(N$7,1))) -> 0 | O23: =SUM(C23:N23) -> 3654.71 | P23: =IFERROR(O23/'Dados'!$C$11,0) -> 406.07889 | Q23: =IFERROR(O23/$O$36,0) -> 0.089945421
B24: =IF('Config'!$G$12="","",'Config'!$G$12) -> Saúde | C24: =IF($B24="",0,SUMIFS('Lanç. Pessoal'!$F$11:$F$1510,'Lanç. Pessoal'!$D$11:$D$1510,$B24,'Lanç. Pessoal'!$B$11:$B$1510,">="&C$7,'Lanç. Pessoal'!$B$11:$B$1510,"<"&EDATE(C$7,1))) -> 224.74 | D24: =IF($B24="",0,SUMIFS('Lanç. Pessoal'!$F$11:$F$1510,'Lanç. Pessoal'!$D$11:$D$1510,$B24,'Lanç. Pessoal'!$B$11:$B$1510,">="&D$7,'Lanç. Pessoal'!$B$11:$B$1510,"<"&EDATE(D$7,1))) -> 250.34 | E24: =IF($B24="",0,SUMIFS('Lanç. Pessoal'!$F$11:$F$1510,'Lanç. Pessoal'!$D$11:$D$1510,$B24,'Lanç. Pessoal'!$B$11:$B$1510,">="&E$7,'Lanç. Pessoal'!$B$11:$B$1510,"<"&EDATE(E$7,1))) -> 491.19 | F24: =IF($B24="",0,SUMIFS('Lanç. Pessoal'!$F$11:$F$1510,'Lanç. Pessoal'!$D$11:$D$1510,$B24,'Lanç. Pessoal'!$B$11:$B$1510,">="&F$7,'Lanç. Pessoal'!$B$11:$B$1510,"<"&EDATE(F$7,1))) -> 255.08 | G24: =IF($B24="",0,SUMIFS('Lanç. Pessoal'!$F$11:$F$1510,'Lanç. Pessoal'!$D$11:$D$1510,$B24,'Lanç. Pessoal'!$B$11:$B$1510,">="&G$7,'Lanç. Pessoal'!$B$11:$B$1510,"<"&EDATE(G$7,1))) -> 212.59 | H24: =IF($B24="",0,SUMIFS('Lanç. Pessoal'!$F$11:$F$1510,'Lanç. Pessoal'!$D$11:$D$1510,$B24,'Lanç. Pessoal'!$B$11:$B$1510,">="&H$7,'Lanç. Pessoal'!$B$11:$B$1510,"<"&EDATE(H$7,1))) -> 258.08 | I24: =IF($B24="",0,SUMIFS('Lanç. Pessoal'!$F$11:$F$1510,'Lanç. Pessoal'!$D$11:$D$1510,$B24,'Lanç. Pessoal'!$B$11:$B$1510,">="&I$7,'Lanç. Pessoal'!$B$11:$B$1510,"<"&EDATE(I$7,1))) -> 491.7 | J24: =IF($B24="",0,SUMIFS('Lanç. Pessoal'!$F$11:$F$1510,'Lanç. Pessoal'!$D$11:$D$1510,$B24,'Lanç. Pessoal'!$B$11:$B$1510,">="&J$7,'Lanç. Pessoal'!$B$11:$B$1510,"<"&EDATE(J$7,1))) -> 221.77 | ... N24: =IF($B24="",0,SUMIFS('Lanç. Pessoal'!$F$11:$F$1510,'Lanç. Pessoal'!$D$11:$D$1510,$B24,'Lanç. Pessoal'!$B$11:$B$1510,">="&N$7,'Lanç. Pessoal'!$B$11:$B$1510,"<"&EDATE(N$7,1))) -> 0 | O24: =SUM(C24:N24) -> 2661.34 | P24: =IFERROR(O24/'Dados'!$C$11,0) -> 295.70444 | Q24: =IFERROR(O24/$O$36,0) -> 0.065497767
B25: =IF('Config'!$G$13="","",'Config'!$G$13) -> Educação | C25: =IF($B25="",0,SUMIFS('Lanç. Pessoal'!$F$11:$F$1510,'Lanç. Pessoal'!$D$11:$D$1510,$B25,'Lanç. Pessoal'!$B$11:$B$1510,">="&C$7,'Lanç. Pessoal'!$B$11:$B$1510,"<"&EDATE(C$7,1))) -> 149 | D25: =IF($B25="",0,SUMIFS('Lanç. Pessoal'!$F$11:$F$1510,'Lanç. Pessoal'!$D$11:$D$1510,$B25,'Lanç. Pessoal'!$B$11:$B$1510,">="&D$7,'Lanç. Pessoal'!$B$11:$B$1510,"<"&EDATE(D$7,1))) -> 149 | E25: =IF($B25="",0,SUMIFS('Lanç. Pessoal'!$F$11:$F$1510,'Lanç. Pessoal'!$D$11:$D$1510,$B25,'Lanç. Pessoal'!$B$11:$B$1510,">="&E$7,'Lanç. Pessoal'!$B$11:$B$1510,"<"&EDATE(E$7,1))) -> 149 | F25: =IF($B25="",0,SUMIFS('Lanç. Pessoal'!$F$11:$F$1510,'Lanç. Pessoal'!$D$11:$D$1510,$B25,'Lanç. Pessoal'!$B$11:$B$1510,">="&F$7,'Lanç. Pessoal'!$B$11:$B$1510,"<"&EDATE(F$7,1))) -> 149 | G25: =IF($B25="",0,SUMIFS('Lanç. Pessoal'!$F$11:$F$1510,'Lanç. Pessoal'!$D$11:$D$1510,$B25,'Lanç. Pessoal'!$B$11:$B$1510,">="&G$7,'Lanç. Pessoal'!$B$11:$B$1510,"<"&EDATE(G$7,1))) -> 149 | H25: =IF($B25="",0,SUMIFS('Lanç. Pessoal'!$F$11:$F$1510,'Lanç. Pessoal'!$D$11:$D$1510,$B25,'Lanç. Pessoal'!$B$11:$B$1510,">="&H$7,'Lanç. Pessoal'!$B$11:$B$1510,"<"&EDATE(H$7,1))) -> 149 | I25: =IF($B25="",0,SUMIFS('Lanç. Pessoal'!$F$11:$F$1510,'Lanç. Pessoal'!$D$11:$D$1510,$B25,'Lanç. Pessoal'!$B$11:$B$1510,">="&I$7,'Lanç. Pessoal'!$B$11:$B$1510,"<"&EDATE(I$7,1))) -> 149 | J25: =IF($B25="",0,SUMIFS('Lanç. Pessoal'!$F$11:$F$1510,'Lanç. Pessoal'!$D$11:$D$1510,$B25,'Lanç. Pessoal'!$B$11:$B$1510,">="&J$7,'Lanç. Pessoal'!$B$11:$B$1510,"<"&EDATE(J$7,1))) -> 149 | ... N25: =IF($B25="",0,SUMIFS('Lanç. Pessoal'!$F$11:$F$1510,'Lanç. Pessoal'!$D$11:$D$1510,$B25,'Lanç. Pessoal'!$B$11:$B$1510,">="&N$7,'Lanç. Pessoal'!$B$11:$B$1510,"<"&EDATE(N$7,1))) -> 0 | O25: =SUM(C25:N25) -> 1341 | P25: =IFERROR(O25/'Dados'!$C$11,0) -> 149 | Q25: =IFERROR(O25/$O$36,0) -> 0.033003114
B26: =IF('Config'!$G$14="","",'Config'!$G$14) -> Lazer | C26: =IF($B26="",0,SUMIFS('Lanç. Pessoal'!$F$11:$F$1510,'Lanç. Pessoal'!$D$11:$D$1510,$B26,'Lanç. Pessoal'!$B$11:$B$1510,">="&C$7,'Lanç. Pessoal'!$B$11:$B$1510,"<"&EDATE(C$7,1))) -> 202.65 | D26: =IF($B26="",0,SUMIFS('Lanç. Pessoal'!$F$11:$F$1510,'Lanç. Pessoal'!$D$11:$D$1510,$B26,'Lanç. Pessoal'!$B$11:$B$1510,">="&D$7,'Lanç. Pessoal'!$B$11:$B$1510,"<"&EDATE(D$7,1))) -> 240.29 | E26: =IF($B26="",0,SUMIFS('Lanç. Pessoal'!$F$11:$F$1510,'Lanç. Pessoal'!$D$11:$D$1510,$B26,'Lanç. Pessoal'!$B$11:$B$1510,">="&E$7,'Lanç. Pessoal'!$B$11:$B$1510,"<"&EDATE(E$7,1))) -> 193.13 | F26: =IF($B26="",0,SUMIFS('Lanç. Pessoal'!$F$11:$F$1510,'Lanç. Pessoal'!$D$11:$D$1510,$B26,'Lanç. Pessoal'!$B$11:$B$1510,">="&F$7,'Lanç. Pessoal'!$B$11:$B$1510,"<"&EDATE(F$7,1))) -> 253.76 | G26: =IF($B26="",0,SUMIFS('Lanç. Pessoal'!$F$11:$F$1510,'Lanç. Pessoal'!$D$11:$D$1510,$B26,'Lanç. Pessoal'!$B$11:$B$1510,">="&G$7,'Lanç. Pessoal'!$B$11:$B$1510,"<"&EDATE(G$7,1))) -> 555.74 | H26: =IF($B26="",0,SUMIFS('Lanç. Pessoal'!$F$11:$F$1510,'Lanç. Pessoal'!$D$11:$D$1510,$B26,'Lanç. Pessoal'!$B$11:$B$1510,">="&H$7,'Lanç. Pessoal'!$B$11:$B$1510,"<"&EDATE(H$7,1))) -> 208.85 | I26: =IF($B26="",0,SUMIFS('Lanç. Pessoal'!$F$11:$F$1510,'Lanç. Pessoal'!$D$11:$D$1510,$B26,'Lanç. Pessoal'!$B$11:$B$1510,">="&I$7,'Lanç. Pessoal'!$B$11:$B$1510,"<"&EDATE(I$7,1))) -> 1474.33 | J26: =IF($B26="",0,SUMIFS('Lanç. Pessoal'!$F$11:$F$1510,'Lanç. Pessoal'!$D$11:$D$1510,$B26,'Lanç. Pessoal'!$B$11:$B$1510,">="&J$7,'Lanç. Pessoal'!$B$11:$B$1510,"<"&EDATE(J$7,1))) -> 193.23 | ... N26: =IF($B26="",0,SUMIFS('Lanç. Pessoal'!$F$11:$F$1510,'Lanç. Pessoal'!$D$11:$D$1510,$B26,'Lanç. Pessoal'!$B$11:$B$1510,">="&N$7,'Lanç. Pessoal'!$B$11:$B$1510,"<"&EDATE(N$7,1))) -> 0 | O26: =SUM(C26:N26) -> 3523.65 | P26: =IFERROR(O26/'Dados'!$C$11,0) -> 391.51667 | Q26: =IFERROR(O26/$O$36,0) -> 0.086719926
B27: =IF('Config'!$G$15="","",'Config'!$G$15) -> Vestuário | C27: =IF($B27="",0,SUMIFS('Lanç. Pessoal'!$F$11:$F$1510,'Lanç. Pessoal'!$D$11:$D$1510,$B27,'Lanç. Pessoal'!$B$11:$B$1510,">="&C$7,'Lanç. Pessoal'!$B$11:$B$1510,"<"&EDATE(C$7,1))) -> 0 | D27: =IF($B27="",0,SUMIFS('Lanç. Pessoal'!$F$11:$F$1510,'Lanç. Pessoal'!$D$11:$D$1510,$B27,'Lanç. Pessoal'!$B$11:$B$1510,">="&D$7,'Lanç. Pessoal'!$B$11:$B$1510,"<"&EDATE(D$7,1))) -> 190.65 | E27: =IF($B27="",0,SUMIFS('Lanç. Pessoal'!$F$11:$F$1510,'Lanç. Pessoal'!$D$11:$D$1510,$B27,'Lanç. Pessoal'!$B$11:$B$1510,">="&E$7,'Lanç. Pessoal'!$B$11:$B$1510,"<"&EDATE(E$7,1))) -> 0 | F27: =IF($B27="",0,SUMIFS('Lanç. Pessoal'!$F$11:$F$1510,'Lanç. Pessoal'!$D$11:$D$1510,$B27,'Lanç. Pessoal'!$B$11:$B$1510,">="&F$7,'Lanç. Pessoal'!$B$11:$B$1510,"<"&EDATE(F$7,1))) -> 0 | G27: =IF($B27="",0,SUMIFS('Lanç. Pessoal'!$F$11:$F$1510,'Lanç. Pessoal'!$D$11:$D$1510,$B27,'Lanç. Pessoal'!$B$11:$B$1510,">="&G$7,'Lanç. Pessoal'!$B$11:$B$1510,"<"&EDATE(G$7,1))) -> 166.23 | H27: =IF($B27="",0,SUMIFS('Lanç. Pessoal'!$F$11:$F$1510,'Lanç. Pessoal'!$D$11:$D$1510,$B27,'Lanç. Pessoal'!$B$11:$B$1510,">="&H$7,'Lanç. Pessoal'!$B$11:$B$1510,"<"&EDATE(H$7,1))) -> 0 | I27: =IF($B27="",0,SUMIFS('Lanç. Pessoal'!$F$11:$F$1510,'Lanç. Pessoal'!$D$11:$D$1510,$B27,'Lanç. Pessoal'!$B$11:$B$1510,">="&I$7,'Lanç. Pessoal'!$B$11:$B$1510,"<"&EDATE(I$7,1))) -> 201.36 | J27: =IF($B27="",0,SUMIFS('Lanç. Pessoal'!$F$11:$F$1510,'Lanç. Pessoal'!$D$11:$D$1510,$B27,'Lanç. Pessoal'!$B$11:$B$1510,">="&J$7,'Lanç. Pessoal'!$B$11:$B$1510,"<"&EDATE(J$7,1))) -> 0 | ... N27: =IF($B27="",0,SUMIFS('Lanç. Pessoal'!$F$11:$F$1510,'Lanç. Pessoal'!$D$11:$D$1510,$B27,'Lanç. Pessoal'!$B$11:$B$1510,">="&N$7,'Lanç. Pessoal'!$B$11:$B$1510,"<"&EDATE(N$7,1))) -> 0 | O27: =SUM(C27:N27) -> 696.6 | P27: =IFERROR(O27/'Dados'!$C$11,0) -> 77.4 | Q27: =IFERROR(O27/$O$36,0) -> 0.017143899
B28: =IF('Config'!$G$16="","",'Config'!$G$16) -> Assinaturas | C28: =IF($B28="",0,SUMIFS('Lanç. Pessoal'!$F$11:$F$1510,'Lanç. Pessoal'!$D$11:$D$1510,$B28,'Lanç. Pessoal'!$B$11:$B$1510,">="&C$7,'Lanç. Pessoal'!$B$11:$B$1510,"<"&EDATE(C$7,1))) -> 87.7 | D28: =IF($B28="",0,SUMIFS('Lanç. Pessoal'!$F$11:$F$1510,'Lanç. Pessoal'!$D$11:$D$1510,$B28,'Lanç. Pessoal'!$B$11:$B$1510,">="&D$7,'Lanç. Pessoal'!$B$11:$B$1510,"<"&EDATE(D$7,1))) -> 87.7 | E28: =IF($B28="",0,SUMIFS('Lanç. Pessoal'!$F$11:$F$1510,'Lanç. Pessoal'!$D$11:$D$1510,$B28,'Lanç. Pessoal'!$B$11:$B$1510,">="&E$7,'Lanç. Pessoal'!$B$11:$B$1510,"<"&EDATE(E$7,1))) -> 87.7 | F28: =IF($B28="",0,SUMIFS('Lanç. Pessoal'!$F$11:$F$1510,'Lanç. Pessoal'!$D$11:$D$1510,$B28,'Lanç. Pessoal'!$B$11:$B$1510,">="&F$7,'Lanç. Pessoal'!$B$11:$B$1510,"<"&EDATE(F$7,1))) -> 87.7 | G28: =IF($B28="",0,SUMIFS('Lanç. Pessoal'!$F$11:$F$1510,'Lanç. Pessoal'!$D$11:$D$1510,$B28,'Lanç. Pessoal'!$B$11:$B$1510,">="&G$7,'Lanç. Pessoal'!$B$11:$B$1510,"<"&EDATE(G$7,1))) -> 87.7 | H28: =IF($B28="",0,SUMIFS('Lanç. Pessoal'!$F$11:$F$1510,'Lanç. Pessoal'!$D$11:$D$1510,$B28,'Lanç. Pessoal'!$B$11:$B$1510,">="&H$7,'Lanç. Pessoal'!$B$11:$B$1510,"<"&EDATE(H$7,1))) -> 87.7 | I28: =IF($B28="",0,SUMIFS('Lanç. Pessoal'!$F$11:$F$1510,'Lanç. Pessoal'!$D$11:$D$1510,$B28,'Lanç. Pessoal'!$B$11:$B$1510,">="&I$7,'Lanç. Pessoal'!$B$11:$B$1510,"<"&EDATE(I$7,1))) -> 87.7 | J28: =IF($B28="",0,SUMIFS('Lanç. Pessoal'!$F$11:$F$1510,'Lanç. Pessoal'!$D$11:$D$1510,$B28,'Lanç. Pessoal'!$B$11:$B$1510,">="&J$7,'Lanç. Pessoal'!$B$11:$B$1510,"<"&EDATE(J$7,1))) -> 87.7 | ... N28: =IF($B28="",0,SUMIFS('Lanç. Pessoal'!$F$11:$F$1510,'Lanç. Pessoal'!$D$11:$D$1510,$B28,'Lanç. Pessoal'!$B$11:$B$1510,">="&N$7,'Lanç. Pessoal'!$B$11:$B$1510,"<"&EDATE(N$7,1))) -> 0 | O28: =SUM(C28:N28) -> 789.3 | P28: =IFERROR(O28/'Dados'!$C$11,0) -> 87.7 | Q28: =IFERROR(O28/$O$36,0) -> 0.019425323
B29: =IF('Config'!$G$17="","",'Config'!$G$17) -> Cuidados pessoais | C29: =IF($B29="",0,SUMIFS('Lanç. Pessoal'!$F$11:$F$1510,'Lanç. Pessoal'!$D$11:$D$1510,$B29,'Lanç. Pessoal'!$B$11:$B$1510,">="&C$7,'Lanç. Pessoal'!$B$11:$B$1510,"<"&EDATE(C$7,1))) -> 199.75 | D29: =IF($B29="",0,SUMIFS('Lanç. Pessoal'!$F$11:$F$1510,'Lanç. Pessoal'!$D$11:$D$1510,$B29,'Lanç. Pessoal'!$B$11:$B$1510,">="&D$7,'Lanç. Pessoal'!$B$11:$B$1510,"<"&EDATE(D$7,1))) -> 181.44 | E29: =IF($B29="",0,SUMIFS('Lanç. Pessoal'!$F$11:$F$1510,'Lanç. Pessoal'!$D$11:$D$1510,$B29,'Lanç. Pessoal'!$B$11:$B$1510,">="&E$7,'Lanç. Pessoal'!$B$11:$B$1510,"<"&EDATE(E$7,1))) -> 199.91 | F29: =IF($B29="",0,SUMIFS('Lanç. Pessoal'!$F$11:$F$1510,'Lanç. Pessoal'!$D$11:$D$1510,$B29,'Lanç. Pessoal'!$B$11:$B$1510,">="&F$7,'Lanç. Pessoal'!$B$11:$B$1510,"<"&EDATE(F$7,1))) -> 186.28 | G29: =IF($B29="",0,SUMIFS('Lanç. Pessoal'!$F$11:$F$1510,'Lanç. Pessoal'!$D$11:$D$1510,$B29,'Lanç. Pessoal'!$B$11:$B$1510,">="&G$7,'Lanç. Pessoal'!$B$11:$B$1510,"<"&EDATE(G$7,1))) -> 183.09 | H29: =IF($B29="",0,SUMIFS('Lanç. Pessoal'!$F$11:$F$1510,'Lanç. Pessoal'!$D$11:$D$1510,$B29,'Lanç. Pessoal'!$B$11:$B$1510,">="&H$7,'Lanç. Pessoal'!$B$11:$B$1510,"<"&EDATE(H$7,1))) -> 205.77 | I29: =IF($B29="",0,SUMIFS('Lanç. Pessoal'!$F$11:$F$1510,'Lanç. Pessoal'!$D$11:$D$1510,$B29,'Lanç. Pessoal'!$B$11:$B$1510,">="&I$7,'Lanç. Pessoal'!$B$11:$B$1510,"<"&EDATE(I$7,1))) -> 183.83 | J29: =IF($B29="",0,SUMIFS('Lanç. Pessoal'!$F$11:$F$1510,'Lanç. Pessoal'!$D$11:$D$1510,$B29,'Lanç. Pessoal'!$B$11:$B$1510,">="&J$7,'Lanç. Pessoal'!$B$11:$B$1510,"<"&EDATE(J$7,1))) -> 173.44 | ... N29: =IF($B29="",0,SUMIFS('Lanç. Pessoal'!$F$11:$F$1510,'Lanç. Pessoal'!$D$11:$D$1510,$B29,'Lanç. Pessoal'!$B$11:$B$1510,">="&N$7,'Lanç. Pessoal'!$B$11:$B$1510,"<"&EDATE(N$7,1))) -> 0 | O29: =SUM(C29:N29) -> 1688.62 | P29: =IFERROR(O29/'Dados'!$C$11,0) -> 187.62444 | Q29: =IFERROR(O29/$O$36,0) -> 0.041558328
B30: =IF('Config'!$G$18="","",'Config'!$G$18) -> Pets | C30: =IF($B30="",0,SUMIFS('Lanç. Pessoal'!$F$11:$F$1510,'Lanç. Pessoal'!$D$11:$D$1510,$B30,'Lanç. Pessoal'!$B$11:$B$1510,">="&C$7,'Lanç. Pessoal'!$B$11:$B$1510,"<"&EDATE(C$7,1))) -> 0 | D30: =IF($B30="",0,SUMIFS('Lanç. Pessoal'!$F$11:$F$1510,'Lanç. Pessoal'!$D$11:$D$1510,$B30,'Lanç. Pessoal'!$B$11:$B$1510,">="&D$7,'Lanç. Pessoal'!$B$11:$B$1510,"<"&EDATE(D$7,1))) -> 0 | E30: =IF($B30="",0,SUMIFS('Lanç. Pessoal'!$F$11:$F$1510,'Lanç. Pessoal'!$D$11:$D$1510,$B30,'Lanç. Pessoal'!$B$11:$B$1510,">="&E$7,'Lanç. Pessoal'!$B$11:$B$1510,"<"&EDATE(E$7,1))) -> 0 | F30: =IF($B30="",0,SUMIFS('Lanç. Pessoal'!$F$11:$F$1510,'Lanç. Pessoal'!$D$11:$D$1510,$B30,'Lanç. Pessoal'!$B$11:$B$1510,">="&F$7,'Lanç. Pessoal'!$B$11:$B$1510,"<"&EDATE(F$7,1))) -> 0 | G30: =IF($B30="",0,SUMIFS('Lanç. Pessoal'!$F$11:$F$1510,'Lanç. Pessoal'!$D$11:$D$1510,$B30,'Lanç. Pessoal'!$B$11:$B$1510,">="&G$7,'Lanç. Pessoal'!$B$11:$B$1510,"<"&EDATE(G$7,1))) -> 0 | H30: =IF($B30="",0,SUMIFS('Lanç. Pessoal'!$F$11:$F$1510,'Lanç. Pessoal'!$D$11:$D$1510,$B30,'Lanç. Pessoal'!$B$11:$B$1510,">="&H$7,'Lanç. Pessoal'!$B$11:$B$1510,"<"&EDATE(H$7,1))) -> 0 | I30: =IF($B30="",0,SUMIFS('Lanç. Pessoal'!$F$11:$F$1510,'Lanç. Pessoal'!$D$11:$D$1510,$B30,'Lanç. Pessoal'!$B$11:$B$1510,">="&I$7,'Lanç. Pessoal'!$B$11:$B$1510,"<"&EDATE(I$7,1))) -> 0 | J30: =IF($B30="",0,SUMIFS('Lanç. Pessoal'!$F$11:$F$1510,'Lanç. Pessoal'!$D$11:$D$1510,$B30,'Lanç. Pessoal'!$B$11:$B$1510,">="&J$7,'Lanç. Pessoal'!$B$11:$B$1510,"<"&EDATE(J$7,1))) -> 0 | ... N30: =IF($B30="",0,SUMIFS('Lanç. Pessoal'!$F$11:$F$1510,'Lanç. Pessoal'!$D$11:$D$1510,$B30,'Lanç. Pessoal'!$B$11:$B$1510,">="&N$7,'Lanç. Pessoal'!$B$11:$B$1510,"<"&EDATE(N$7,1))) -> 0 | O30: =SUM(C30:N30) -> 0 | P30: =IFERROR(O30/'Dados'!$C$11,0) -> 0 | Q30: =IFERROR(O30/$O$36,0) -> 0
B31: =IF('Config'!$G$19="","",'Config'!$G$19) -> Presentes e doações | C31: =IF($B31="",0,SUMIFS('Lanç. Pessoal'!$F$11:$F$1510,'Lanç. Pessoal'!$D$11:$D$1510,$B31,'Lanç. Pessoal'!$B$11:$B$1510,">="&C$7,'Lanç. Pessoal'!$B$11:$B$1510,"<"&EDATE(C$7,1))) -> 50 | D31: =IF($B31="",0,SUMIFS('Lanç. Pessoal'!$F$11:$F$1510,'Lanç. Pessoal'!$D$11:$D$1510,$B31,'Lanç. Pessoal'!$B$11:$B$1510,">="&D$7,'Lanç. Pessoal'!$B$11:$B$1510,"<"&EDATE(D$7,1))) -> 50 | E31: =IF($B31="",0,SUMIFS('Lanç. Pessoal'!$F$11:$F$1510,'Lanç. Pessoal'!$D$11:$D$1510,$B31,'Lanç. Pessoal'!$B$11:$B$1510,">="&E$7,'Lanç. Pessoal'!$B$11:$B$1510,"<"&EDATE(E$7,1))) -> 50 | F31: =IF($B31="",0,SUMIFS('Lanç. Pessoal'!$F$11:$F$1510,'Lanç. Pessoal'!$D$11:$D$1510,$B31,'Lanç. Pessoal'!$B$11:$B$1510,">="&F$7,'Lanç. Pessoal'!$B$11:$B$1510,"<"&EDATE(F$7,1))) -> 50 | G31: =IF($B31="",0,SUMIFS('Lanç. Pessoal'!$F$11:$F$1510,'Lanç. Pessoal'!$D$11:$D$1510,$B31,'Lanç. Pessoal'!$B$11:$B$1510,">="&G$7,'Lanç. Pessoal'!$B$11:$B$1510,"<"&EDATE(G$7,1))) -> 205 | H31: =IF($B31="",0,SUMIFS('Lanç. Pessoal'!$F$11:$F$1510,'Lanç. Pessoal'!$D$11:$D$1510,$B31,'Lanç. Pessoal'!$B$11:$B$1510,">="&H$7,'Lanç. Pessoal'!$B$11:$B$1510,"<"&EDATE(H$7,1))) -> 50 | I31: =IF($B31="",0,SUMIFS('Lanç. Pessoal'!$F$11:$F$1510,'Lanç. Pessoal'!$D$11:$D$1510,$B31,'Lanç. Pessoal'!$B$11:$B$1510,">="&I$7,'Lanç. Pessoal'!$B$11:$B$1510,"<"&EDATE(I$7,1))) -> 50 | J31: =IF($B31="",0,SUMIFS('Lanç. Pessoal'!$F$11:$F$1510,'Lanç. Pessoal'!$D$11:$D$1510,$B31,'Lanç. Pessoal'!$B$11:$B$1510,">="&J$7,'Lanç. Pessoal'!$B$11:$B$1510,"<"&EDATE(J$7,1))) -> 161.6 | ... N31: =IF($B31="",0,SUMIFS('Lanç. Pessoal'!$F$11:$F$1510,'Lanç. Pessoal'!$D$11:$D$1510,$B31,'Lanç. Pessoal'!$B$11:$B$1510,">="&N$7,'Lanç. Pessoal'!$B$11:$B$1510,"<"&EDATE(N$7,1))) -> 0 | O31: =SUM(C31:N31) -> 716.6 | P31: =IFERROR(O31/'Dados'!$C$11,0) -> 79.622222 | Q31: =IFERROR(O31/$O$36,0) -> 0.017636116
B32: =IF('Config'!$G$20="","",'Config'!$G$20) -> Dívidas e financiamentos | C32: =IF($B32="",0,SUMIFS('Lanç. Pessoal'!$F$11:$F$1510,'Lanç. Pessoal'!$D$11:$D$1510,$B32,'Lanç. Pessoal'!$B$11:$B$1510,">="&C$7,'Lanç. Pessoal'!$B$11:$B$1510,"<"&EDATE(C$7,1))) -> 0 | D32: =IF($B32="",0,SUMIFS('Lanç. Pessoal'!$F$11:$F$1510,'Lanç. Pessoal'!$D$11:$D$1510,$B32,'Lanç. Pessoal'!$B$11:$B$1510,">="&D$7,'Lanç. Pessoal'!$B$11:$B$1510,"<"&EDATE(D$7,1))) -> 0 | E32: =IF($B32="",0,SUMIFS('Lanç. Pessoal'!$F$11:$F$1510,'Lanç. Pessoal'!$D$11:$D$1510,$B32,'Lanç. Pessoal'!$B$11:$B$1510,">="&E$7,'Lanç. Pessoal'!$B$11:$B$1510,"<"&EDATE(E$7,1))) -> 0 | F32: =IF($B32="",0,SUMIFS('Lanç. Pessoal'!$F$11:$F$1510,'Lanç. Pessoal'!$D$11:$D$1510,$B32,'Lanç. Pessoal'!$B$11:$B$1510,">="&F$7,'Lanç. Pessoal'!$B$11:$B$1510,"<"&EDATE(F$7,1))) -> 0 | G32: =IF($B32="",0,SUMIFS('Lanç. Pessoal'!$F$11:$F$1510,'Lanç. Pessoal'!$D$11:$D$1510,$B32,'Lanç. Pessoal'!$B$11:$B$1510,">="&G$7,'Lanç. Pessoal'!$B$11:$B$1510,"<"&EDATE(G$7,1))) -> 0 | H32: =IF($B32="",0,SUMIFS('Lanç. Pessoal'!$F$11:$F$1510,'Lanç. Pessoal'!$D$11:$D$1510,$B32,'Lanç. Pessoal'!$B$11:$B$1510,">="&H$7,'Lanç. Pessoal'!$B$11:$B$1510,"<"&EDATE(H$7,1))) -> 0 | I32: =IF($B32="",0,SUMIFS('Lanç. Pessoal'!$F$11:$F$1510,'Lanç. Pessoal'!$D$11:$D$1510,$B32,'Lanç. Pessoal'!$B$11:$B$1510,">="&I$7,'Lanç. Pessoal'!$B$11:$B$1510,"<"&EDATE(I$7,1))) -> 0 | J32: =IF($B32="",0,SUMIFS('Lanç. Pessoal'!$F$11:$F$1510,'Lanç. Pessoal'!$D$11:$D$1510,$B32,'Lanç. Pessoal'!$B$11:$B$1510,">="&J$7,'Lanç. Pessoal'!$B$11:$B$1510,"<"&EDATE(J$7,1))) -> 0 | ... N32: =IF($B32="",0,SUMIFS('Lanç. Pessoal'!$F$11:$F$1510,'Lanç. Pessoal'!$D$11:$D$1510,$B32,'Lanç. Pessoal'!$B$11:$B$1510,">="&N$7,'Lanç. Pessoal'!$B$11:$B$1510,"<"&EDATE(N$7,1))) -> 0 | O32: =SUM(C32:N32) -> 0 | P32: =IFERROR(O32/'Dados'!$C$11,0) -> 0 | Q32: =IFERROR(O32/$O$36,0) -> 0
B33: =IF('Config'!$G$21="","",'Config'!$G$21) -> Reserva e Metas | C33: =IF($B33="",0,SUMIFS('Lanç. Pessoal'!$F$11:$F$1510,'Lanç. Pessoal'!$D$11:$D$1510,$B33,'Lanç. Pessoal'!$B$11:$B$1510,">="&C$7,'Lanç. Pessoal'!$B$11:$B$1510,"<"&EDATE(C$7,1))) -> 450 | D33: =IF($B33="",0,SUMIFS('Lanç. Pessoal'!$F$11:$F$1510,'Lanç. Pessoal'!$D$11:$D$1510,$B33,'Lanç. Pessoal'!$B$11:$B$1510,">="&D$7,'Lanç. Pessoal'!$B$11:$B$1510,"<"&EDATE(D$7,1))) -> 450 | E33: =IF($B33="",0,SUMIFS('Lanç. Pessoal'!$F$11:$F$1510,'Lanç. Pessoal'!$D$11:$D$1510,$B33,'Lanç. Pessoal'!$B$11:$B$1510,">="&E$7,'Lanç. Pessoal'!$B$11:$B$1510,"<"&EDATE(E$7,1))) -> 450 | F33: =IF($B33="",0,SUMIFS('Lanç. Pessoal'!$F$11:$F$1510,'Lanç. Pessoal'!$D$11:$D$1510,$B33,'Lanç. Pessoal'!$B$11:$B$1510,">="&F$7,'Lanç. Pessoal'!$B$11:$B$1510,"<"&EDATE(F$7,1))) -> 600 | G33: =IF($B33="",0,SUMIFS('Lanç. Pessoal'!$F$11:$F$1510,'Lanç. Pessoal'!$D$11:$D$1510,$B33,'Lanç. Pessoal'!$B$11:$B$1510,">="&G$7,'Lanç. Pessoal'!$B$11:$B$1510,"<"&EDATE(G$7,1))) -> 600 | H33: =IF($B33="",0,SUMIFS('Lanç. Pessoal'!$F$11:$F$1510,'Lanç. Pessoal'!$D$11:$D$1510,$B33,'Lanç. Pessoal'!$B$11:$B$1510,">="&H$7,'Lanç. Pessoal'!$B$11:$B$1510,"<"&EDATE(H$7,1))) -> 600 | I33: =IF($B33="",0,SUMIFS('Lanç. Pessoal'!$F$11:$F$1510,'Lanç. Pessoal'!$D$11:$D$1510,$B33,'Lanç. Pessoal'!$B$11:$B$1510,">="&I$7,'Lanç. Pessoal'!$B$11:$B$1510,"<"&EDATE(I$7,1))) -> 600 | J33: =IF($B33="",0,SUMIFS('Lanç. Pessoal'!$F$11:$F$1510,'Lanç. Pessoal'!$D$11:$D$1510,$B33,'Lanç. Pessoal'!$B$11:$B$1510,">="&J$7,'Lanç. Pessoal'!$B$11:$B$1510,"<"&EDATE(J$7,1))) -> 600 | ... N33: =IF($B33="",0,SUMIFS('Lanç. Pessoal'!$F$11:$F$1510,'Lanç. Pessoal'!$D$11:$D$1510,$B33,'Lanç. Pessoal'!$B$11:$B$1510,">="&N$7,'Lanç. Pessoal'!$B$11:$B$1510,"<"&EDATE(N$7,1))) -> 0 | O33: =SUM(C33:N33) -> 4950 | P33: =IFERROR(O33/'Dados'!$C$11,0) -> 550 | Q33: =IFERROR(O33/$O$36,0) -> 0.12182357
B34: =IF('Config'!$G$22="","",'Config'!$G$22) -> Impostos pessoais | C34: =IF($B34="",0,SUMIFS('Lanç. Pessoal'!$F$11:$F$1510,'Lanç. Pessoal'!$D$11:$D$1510,$B34,'Lanç. Pessoal'!$B$11:$B$1510,">="&C$7,'Lanç. Pessoal'!$B$11:$B$1510,"<"&EDATE(C$7,1))) -> 0 | D34: =IF($B34="",0,SUMIFS('Lanç. Pessoal'!$F$11:$F$1510,'Lanç. Pessoal'!$D$11:$D$1510,$B34,'Lanç. Pessoal'!$B$11:$B$1510,">="&D$7,'Lanç. Pessoal'!$B$11:$B$1510,"<"&EDATE(D$7,1))) -> 704 | E34: =IF($B34="",0,SUMIFS('Lanç. Pessoal'!$F$11:$F$1510,'Lanç. Pessoal'!$D$11:$D$1510,$B34,'Lanç. Pessoal'!$B$11:$B$1510,">="&E$7,'Lanç. Pessoal'!$B$11:$B$1510,"<"&EDATE(E$7,1))) -> 0 | F34: =IF($B34="",0,SUMIFS('Lanç. Pessoal'!$F$11:$F$1510,'Lanç. Pessoal'!$D$11:$D$1510,$B34,'Lanç. Pessoal'!$B$11:$B$1510,">="&F$7,'Lanç. Pessoal'!$B$11:$B$1510,"<"&EDATE(F$7,1))) -> 0 | G34: =IF($B34="",0,SUMIFS('Lanç. Pessoal'!$F$11:$F$1510,'Lanç. Pessoal'!$D$11:$D$1510,$B34,'Lanç. Pessoal'!$B$11:$B$1510,">="&G$7,'Lanç. Pessoal'!$B$11:$B$1510,"<"&EDATE(G$7,1))) -> 0 | H34: =IF($B34="",0,SUMIFS('Lanç. Pessoal'!$F$11:$F$1510,'Lanç. Pessoal'!$D$11:$D$1510,$B34,'Lanç. Pessoal'!$B$11:$B$1510,">="&H$7,'Lanç. Pessoal'!$B$11:$B$1510,"<"&EDATE(H$7,1))) -> 0 | I34: =IF($B34="",0,SUMIFS('Lanç. Pessoal'!$F$11:$F$1510,'Lanç. Pessoal'!$D$11:$D$1510,$B34,'Lanç. Pessoal'!$B$11:$B$1510,">="&I$7,'Lanç. Pessoal'!$B$11:$B$1510,"<"&EDATE(I$7,1))) -> 0 | J34: =IF($B34="",0,SUMIFS('Lanç. Pessoal'!$F$11:$F$1510,'Lanç. Pessoal'!$D$11:$D$1510,$B34,'Lanç. Pessoal'!$B$11:$B$1510,">="&J$7,'Lanç. Pessoal'!$B$11:$B$1510,"<"&EDATE(J$7,1))) -> 0 | ... N34: =IF($B34="",0,SUMIFS('Lanç. Pessoal'!$F$11:$F$1510,'Lanç. Pessoal'!$D$11:$D$1510,$B34,'Lanç. Pessoal'!$B$11:$B$1510,">="&N$7,'Lanç. Pessoal'!$B$11:$B$1510,"<"&EDATE(N$7,1))) -> 0 | O34: =SUM(C34:N34) -> 704 | P34: =IFERROR(O34/'Dados'!$C$11,0) -> 78.222222 | Q34: =IFERROR(O34/$O$36,0) -> 0.017326019
B35: =IF('Config'!$G$23="","",'Config'!$G$23) -> Outros | C35: =IF($B35="",0,SUMIFS('Lanç. Pessoal'!$F$11:$F$1510,'Lanç. Pessoal'!$D$11:$D$1510,$B35,'Lanç. Pessoal'!$B$11:$B$1510,">="&C$7,'Lanç. Pessoal'!$B$11:$B$1510,"<"&EDATE(C$7,1))) -> 39.72 | D35: =IF($B35="",0,SUMIFS('Lanç. Pessoal'!$F$11:$F$1510,'Lanç. Pessoal'!$D$11:$D$1510,$B35,'Lanç. Pessoal'!$B$11:$B$1510,">="&D$7,'Lanç. Pessoal'!$B$11:$B$1510,"<"&EDATE(D$7,1))) -> 47.64 | E35: =IF($B35="",0,SUMIFS('Lanç. Pessoal'!$F$11:$F$1510,'Lanç. Pessoal'!$D$11:$D$1510,$B35,'Lanç. Pessoal'!$B$11:$B$1510,">="&E$7,'Lanç. Pessoal'!$B$11:$B$1510,"<"&EDATE(E$7,1))) -> 85.52 | F35: =IF($B35="",0,SUMIFS('Lanç. Pessoal'!$F$11:$F$1510,'Lanç. Pessoal'!$D$11:$D$1510,$B35,'Lanç. Pessoal'!$B$11:$B$1510,">="&F$7,'Lanç. Pessoal'!$B$11:$B$1510,"<"&EDATE(F$7,1))) -> 62.25 | G35: =IF($B35="",0,SUMIFS('Lanç. Pessoal'!$F$11:$F$1510,'Lanç. Pessoal'!$D$11:$D$1510,$B35,'Lanç. Pessoal'!$B$11:$B$1510,">="&G$7,'Lanç. Pessoal'!$B$11:$B$1510,"<"&EDATE(G$7,1))) -> 61.34 | H35: =IF($B35="",0,SUMIFS('Lanç. Pessoal'!$F$11:$F$1510,'Lanç. Pessoal'!$D$11:$D$1510,$B35,'Lanç. Pessoal'!$B$11:$B$1510,">="&H$7,'Lanç. Pessoal'!$B$11:$B$1510,"<"&EDATE(H$7,1))) -> 49.36 | I35: =IF($B35="",0,SUMIFS('Lanç. Pessoal'!$F$11:$F$1510,'Lanç. Pessoal'!$D$11:$D$1510,$B35,'Lanç. Pessoal'!$B$11:$B$1510,">="&I$7,'Lanç. Pessoal'!$B$11:$B$1510,"<"&EDATE(I$7,1))) -> 102.69 | J35: =IF($B35="",0,SUMIFS('Lanç. Pessoal'!$F$11:$F$1510,'Lanç. Pessoal'!$D$11:$D$1510,$B35,'Lanç. Pessoal'!$B$11:$B$1510,">="&J$7,'Lanç. Pessoal'!$B$11:$B$1510,"<"&EDATE(J$7,1))) -> 103.09 | ... N35: =IF($B35="",0,SUMIFS('Lanç. Pessoal'!$F$11:$F$1510,'Lanç. Pessoal'!$D$11:$D$1510,$B35,'Lanç. Pessoal'!$B$11:$B$1510,">="&N$7,'Lanç. Pessoal'!$B$11:$B$1510,"<"&EDATE(N$7,1))) -> 0 | O35: =SUM(C35:N35) -> 605.07 | P35: =IFERROR(O35/'Dados'!$C$11,0) -> 67.23 | Q35: =IFERROR(O35/$O$36,0) -> 0.014891271
B36: Total de saídas | C36: =SUM(C20:C35) -> 3820.83 | D36: =SUM(D20:D35) -> 4753.13 | E36: =SUM(E20:E35) -> 4238.38 | F36: =SUM(F20:F35) -> 4786.95 | G36: =SUM(G20:G35) -> 4658.59 | H36: =SUM(H20:H35) -> 4032.46 | I36: =SUM(I20:I35) -> 5693.25 | J36: =SUM(J20:J35) -> 4656.1 | ... P36: =SUM(P20:P35) -> 4514.7256
B37: 💰 Saldo do mês (entradas − saídas) | C37: =C18-C36 -> 725.8 | D37: =D18-D36 -> -202.35 | E37: =E18-E36 -> 706.3 | F37: =F18-F36 -> -217.54 | G37: =G18-G36 -> -105.37 | H37: =H18-H36 -> 869.54 | I37: =I18-I36 -> -1132.66 | J37: =J18-J36 -> -111.18 | ... O37: =O18-O36 -> 1092.59
B38: 📈 Saldo acumulado (inclui saldo inicial) | C38: ='Config'!$C$12+C37 -> 3225.8 | D38: =C38+D37 -> 3023.45 | E38: =D38+E37 -> 3729.75 | F38: =E38+F37 -> 3512.21 | G38: =F38+G37 -> 3406.84 | H38: =G38+H37 -> 4276.38 | I38: =H38+I37 -> 3143.72 | J38: =I38+J37 -> 3032.54 | K38: =J38+K37 -> 3592.59 | ... N38: =M38+N37 -> 3592.59 | O38: =N38 -> 3592.59
B39: 🏦 Taxa de poupança | C39: =IF(C18=0,"",(C37+C33)/C18) -> 0.25860912 | D39: =IF(D18=0,"",(D37+D33)/D18) -> 0.054419242 | E39: =IF(E18=0,"",(E37+E33)/E18) -> 0.23384729 | F39: =IF(F18=0,"",(F37+F33)/F18) -> 0.083700084 | G39: =IF(G18=0,"",(G37+G33)/G18) -> 0.10863301 | H39: =IF(H18=0,"",(H37+H33)/H18) -> 0.29978376 | I39: =IF(I18=0,"",(I37+I33)/I18) -> -0.11679629 | J39: =IF(J18=0,"",(J37+J33)/J18) -> 0.10755305 | ... O39: =IF(O18=0,"",(O37+O33)/O18) -> 0.144819
B41: Taxa de poupança: o que sobrou + o que foi para 'Reserva e Metas' (14ª categoria de saída, tratada como poupança, não como gasto). Verde = meta atingida (Config); amarelo = abaixo da meta; vermelho = negativa.

Sheet Metas
B1: 🏠 Início | C1: 📊 Painel Geral | F1: 👤 Painel Pessoal | I1: 💼 Painel Negócio | K1: ⚙ Config
B2: PESSOAL | C2: 📝 Lançamentos | F2: 💳 Orçamento | I2: 📅 Resumo anual | K2: 🎯 Metas
B3: NEGÓCIO | C3: 📝 Lançamentos | F3: 🤝 Clientes | H3: 💰 Recebimentos | J3: 🧾 Impostos | L3: 📈 Fluxo de Caixa
B5: 🎯 Metas de economia
B6: Cadastre seus objetivos. Para registrar um aporte, lance uma SAÍDA na aba de lançamentos e escolha a meta na última coluna (um resgate é uma ENTRADA com a meta escolhida).
B7: Meta | C7: Valor alvo | D7: Já guardado (antes) | E7: Prazo | F7: Aportes lançados | G7: Total guardado | H7: % concl. | I7: Progresso | J7: Falta | K7: Meses restantes | L7: Aporte mensal necessário | M7: Situação
B8: Reserva de emergência | C8: 24000 | D8: 6000 | E8: 46752 | F8: =IF($B8="","",SUMIFS('Lanç. Pessoal'!$F$11:$F$1510,'Lanç. Pessoal'!$H$11:$H$1510,$B8,'Lanç. Pessoal'!$G$11:$G$1510,"Saída")-SUMIFS('Lanç. Pessoal'!$F$11:$F$1510,'Lanç. Pessoal'!$H$11:$H$1510,$B8,'Lanç. Pessoal'!$G$11:$G$1510,"Entrada")) -> 2700 | G8: =IF($B8="","",N(D8)+F8) -> 8700 | H8: =IF(OR($B8="",N(C8)=0),"",G8/C8) -> 0.3625 | I8: =IF(H8="","",REPT("█",MIN(24,ROUND(H8*20,0)))) -> ███████ | J8: =IF(H8="","",MAX(0,C8-G8)) -> 15300 | K8: =IF(OR($B8="",E8=""),"",MAX(0,(YEAR(E8)-YEAR('Config'!$C$9))*12+MONTH(E8)-MONTH('Config'!$C$9))) -> 15 | L8: =IF(OR(J8="",K8=""),"",IF(J8=0,0,IF(K8=0,J8,J8/K8))) -> 1020 | M8: =IF($B8="","",IF(N(C8)=0,"—",IF(G8>=C8,"✓ Concluída",IF(E8="","Em andamento",IF('Config'!$C$9>E8,"✖ Atrasada","● No prazo"))))) -> ● No prazo
B9: Reserva para impostos | C9: 4000 | D9: 0 | E9: 46387 | F9: =IF($B9="","",SUMIFS('Lanç. Pessoal'!$F$11:$F$1510,'Lanç. Pessoal'!$H$11:$H$1510,$B9,'Lanç. Pessoal'!$G$11:$G$1510,"Saída")-SUMIFS('Lanç. Pessoal'!$F$11:$F$1510,'Lanç. Pessoal'!$H$11:$H$1510,$B9,'Lanç. Pessoal'!$G$11:$G$1510,"Entrada")) -> 1350 | G9: =IF($B9="","",N(D9)+F9) -> 1350 | H9: =IF(OR($B9="",N(C9)=0),"",G9/C9) -> 0.3375 | I9: =IF(H9="","",REPT("█",MIN(24,ROUND(H9*20,0)))) -> ███████ | J9: =IF(H9="","",MAX(0,C9-G9)) -> 2650 | K9: =IF(OR($B9="",E9=""),"",MAX(0,(YEAR(E9)-YEAR('Config'!$C$9))*12+MONTH(E9)-MONTH('Config'!$C$9))) -> 3 | L9: =IF(OR(J9="",K9=""),"",IF(J9=0,0,IF(K9=0,J9,J9/K9))) -> 883.33333 | M9: =IF($B9="","",IF(N(C9)=0,"—",IF(G9>=C9,"✓ Concluída",IF(E9="","Em andamento",IF('Config'!$C$9>E9,"✖ Atrasada","● No prazo"))))) -> ● No prazo
B10: Viagem de férias | C10: 6000 | D10: 500 | E10: 46568 | F10: =IF($B10="","",SUMIFS('Lanç. Pessoal'!$F$11:$F$1510,'Lanç. Pessoal'!$H$11:$H$1510,$B10,'Lanç. Pessoal'!$G$11:$G$1510,"Saída")-SUMIFS('Lanç. Pessoal'!$F$11:$F$1510,'Lanç. Pessoal'!$H$11:$H$1510,$B10,'Lanç. Pessoal'!$G$11:$G$1510,"Entrada")) -> 900 | G10: =IF($B10="","",N(D10)+F10) -> 1400 | H10: =IF(OR($B10="",N(C10)=0),"",G10/C10) -> 0.23333333 | I10: =IF(H10="","",REPT("█",MIN(24,ROUND(H10*20,0)))) -> █████ | J10: =IF(H10="","",MAX(0,C10-G10)) -> 4600 | K10: =IF(OR($B10="",E10=""),"",MAX(0,(YEAR(E10)-YEAR('Config'!$C$9))*12+MONTH(E10)-MONTH('Config'!$C$9))) -> 9 | L10: =IF(OR(J10="",K10=""),"",IF(J10=0,0,IF(K10=0,J10,J10/K10))) -> 511.11111 | M10: =IF($B10="","",IF(N(C10)=0,"—",IF(G10>=C10,"✓ Concluída",IF(E10="","Em andamento",IF('Config'!$C$9>E10,"✖ Atrasada","● No prazo"))))) -> ● No prazo
F11: =IF($B11="","",SUMIFS('Lanç. Pessoal'!$F$11:$F$1510,'Lanç. Pessoal'!$H$11:$H$1510,$B11,'Lanç. Pessoal'!$G$11:$G$1510,"Saída")-SUMIFS('Lanç. Pessoal'!$F$11:$F$1510,'Lanç. Pessoal'!$H$11:$H$1510,$B11,'Lanç. Pessoal'!$G$11:$G$1510,"Entrada")) | G11: =IF($B11="","",N(D11)+F11) | H11: =IF(OR($B11="",N(C11)=0),"",G11/C11) | I11: =IF(H11="","",REPT("█",MIN(24,ROUND(H11*20,0)))) | J11: =IF(H11="","",MAX(0,C11-G11)) | K11: =IF(OR($B11="",E11=""),"",MAX(0,(YEAR(E11)-YEAR('Config'!$C$9))*12+MONTH(E11)-MONTH('Config'!$C$9))) | L11: =IF(OR(J11="",K11=""),"",IF(J11=0,0,IF(K11=0,J11,J11/K11))) | M11: =IF($B11="","",IF(N(C11)=0,"—",IF(G11>=C11,"✓ Concluída",IF(E11="","Em andamento",IF('Config'!$C$9>E11,"✖ Atrasada","● No prazo")))))
F12: =IF($B12="","",SUMIFS('Lanç. Pessoal'!$F$11:$F$1510,'Lanç. Pessoal'!$H$11:$H$1510,$B12,'Lanç. Pessoal'!$G$11:$G$1510,"Saída")-SUMIFS('Lanç. Pessoal'!$F$11:$F$1510,'Lanç. Pessoal'!$H$11:$H$1510,$B12,'Lanç. Pessoal'!$G$11:$G$1510,"Entrada")) | G12: =IF($B12="","",N(D12)+F12) | H12: =IF(OR($B12="",N(C12)=0),"",G12/C12) | I12: =IF(H12="","",REPT("█",MIN(24,ROUND(H12*20,0)))) | J12: =IF(H12="","",MAX(0,C12-G12)) | K12: =IF(OR($B12="",E12=""),"",MAX(0,(YEAR(E12)-YEAR('Config'!$C$9))*12+MONTH(E12)-MONTH('Config'!$C$9))) | L12: =IF(OR(J12="",K12=""),"",IF(J12=0,0,IF(K12=0,J12,J12/K12))) | M12: =IF($B12="","",IF(N(C12)=0,"—",IF(G12>=C12,"✓ Concluída",IF(E12="","Em andamento",IF('Config'!$C$9>E12,"✖ Atrasada","● No prazo")))))
F13: =IF($B13="","",SUMIFS('Lanç. Pessoal'!$F$11:$F$1510,'Lanç. Pessoal'!$H$11:$H$1510,$B13,'Lanç. Pessoal'!$G$11:$G$1510,"Saída")-SUMIFS('Lanç. Pessoal'!$F$11:$F$1510,'Lanç. Pessoal'!$H$11:$H$1510,$B13,'Lanç. Pessoal'!$G$11:$G$1510,"Entrada")) | G13: =IF($B13="","",N(D13)+F13) | H13: =IF(OR($B13="",N(C13)=0),"",G13/C13) | I13: =IF(H13="","",REPT("█",MIN(24,ROUND(H13*20,0)))) | J13: =IF(H13="","",MAX(0,C13-G13)) | K13: =IF(OR($B13="",E13=""),"",MAX(0,(YEAR(E13)-YEAR('Config'!$C$9))*12+MONTH(E13)-MONTH('Config'!$C$9))) | L13: =IF(OR(J13="",K13=""),"",IF(J13=0,0,IF(K13=0,J13,J13/K13))) | M13: =IF($B13="","",IF(N(C13)=0,"—",IF(G13>=C13,"✓ Concluída",IF(E13="","Em andamento",IF('Config'!$C$9>E13,"✖ Atrasada","● No prazo")))))
F14: =IF($B14="","",SUMIFS('Lanç. Pessoal'!$F$11:$F$1510,'Lanç. Pessoal'!$H$11:$H$1510,$B14,'Lanç. Pessoal'!$G$11:$G$1510,"Saída")-SUMIFS('Lanç. Pessoal'!$F$11:$F$1510,'Lanç. Pessoal'!$H$11:$H$1510,$B14,'Lanç. Pessoal'!$G$11:$G$1510,"Entrada")) | G14: =IF($B14="","",N(D14)+F14) | H14: =IF(OR($B14="",N(C14)=0),"",G14/C14) | I14: =IF(H14="","",REPT("█",MIN(24,ROUND(H14*20,0)))) | J14: =IF(H14="","",MAX(0,C14-G14)) | K14: =IF(OR($B14="",E14=""),"",MAX(0,(YEAR(E14)-YEAR('Config'!$C$9))*12+MONTH(E14)-MONTH('Config'!$C$9))) | L14: =IF(OR(J14="",K14=""),"",IF(J14=0,0,IF(K14=0,J14,J14/K14))) | M14: =IF($B14="","",IF(N(C14)=0,"—",IF(G14>=C14,"✓ Concluída",IF(E14="","Em andamento",IF('Config'!$C$9>E14,"✖ Atrasada","● No prazo")))))
F15: =IF($B15="","",SUMIFS('Lanç. Pessoal'!$F$11:$F$1510,'Lanç. Pessoal'!$H$11:$H$1510,$B15,'Lanç. Pessoal'!$G$11:$G$1510,"Saída")-SUMIFS('Lanç. Pessoal'!$F$11:$F$1510,'Lanç. Pessoal'!$H$11:$H$1510,$B15,'Lanç. Pessoal'!$G$11:$G$1510,"Entrada")) | G15: =IF($B15="","",N(D15)+F15) | H15: =IF(OR($B15="",N(C15)=0),"",G15/C15) | I15: =IF(H15="","",REPT("█",MIN(24,ROUND(H15*20,0)))) | J15: =IF(H15="","",MAX(0,C15-G15)) | K15: =IF(OR($B15="",E15=""),"",MAX(0,(YEAR(E15)-YEAR('Config'!$C$9))*12+MONTH(E15)-MONTH('Config'!$C$9))) | L15: =IF(OR(J15="",K15=""),"",IF(J15=0,0,IF(K15=0,J15,J15/K15))) | M15: =IF($B15="","",IF(N(C15)=0,"—",IF(G15>=C15,"✓ Concluída",IF(E15="","Em andamento",IF('Config'!$C$9>E15,"✖ Atrasada","● No prazo")))))
B17: 🛟 RESERVA DE EMERGÊNCIA IDEAL
B18: Meses de cobertura desejados | D18: 6
B19: Média mensal de saídas | D19: =IFERROR('Resumo Pessoal'!$O$36/'Dados'!$C$11,0) -> 4514.7256
B20: Reserva ideal (meses × média) | D20: =D18*D19 -> 27088.353
B21: Total guardado nas suas metas | D21: =SUM(G8:G15) -> 11450
B23: A regra de bolso: entre 3 e 6 meses do seu custo de vida (6 a 12 para autônomos e renda variável).

Sheet Lanç. Negócio
B1: 🏠 Início | D1: 📊 Painel Geral | E1: 👤 Painel Pessoal | G1: 💼 Painel Negócio | I1: ⚙ Config
B2: PESSOAL | D2: 📝 Lançamentos | E2: 💳 Orçamento | G2: 📅 Resumo anual | I2: 🎯 Metas
B3: NEGÓCIO | C3: 📝 Lançamentos | D3: 🤝 Clientes | E3: 💰 Recebimentos | G3: 🧾 Impostos | I3: 📈 Fluxo de Caixa
B5: 📝 Lançamentos do negócio — despesas e receitas avulsas
B6: Receitas de CLIENTES vão em Recebimentos (não duplique aqui). Aqui: despesas, retirada de pró-labore e receitas avulsas.
B7: ENTRADAS AVULSAS NO ANO | D7: DESPESAS NO ANO (SEM PRÓ-LABORE) | E7: PRÓ-LABORE RETIRADO | G7: VERIFICAÇÃO AUTOMÁTICA
B8: =SUMIFS('Lanç. Negócio'!$F$11:$F$1510,'Lanç. Negócio'!$G$11:$G$1510,"Entrada",'Lanç. Negócio'!$B$11:$B$1510,">="&DATE('Config'!$C$8,1,1),'Lanç. Negócio'!$B$11:$B$1510,"<"&DATE('Config'!$C$8+1,1,1)) -> 978.59 | D8: =SUMIFS('Lanç. Negócio'!$F$11:$F$1510,'Lanç. Negócio'!$G$11:$G$1510,"Saída",'Lanç. Negócio'!$B$11:$B$1510,">="&DATE('Config'!$C$8,1,1),'Lanç. Negócio'!$B$11:$B$1510,"<"&DATE('Config'!$C$8+1,1,1))-SUMIFS('Lanç. Negócio'!$F$11:$F$1510,'Lanç. Negócio'!$D$11:$D$1510,'Config'!$P$8,'Lanç. Negócio'!$B$11:$B$1510,">="&DATE('Config'!$C$8,1,1),'Lanç. Negócio'!$B$11:$B$1510,"<"&DATE('Config'!$C$8+1,1,1)) -> 15138.01 | E8: =SUMIFS('Lanç. Negócio'!$F$11:$F$1510,'Lanç. Negócio'!$D$11:$D$1510,'Config'!$P$8,'Lanç. Negócio'!$B$11:$B$1510,">="&DATE('Config'!$C$8,1,1),'Lanç. Negócio'!$B$11:$B$1510,"<"&DATE('Config'!$C$8+1,1,1)) -> 40500 | G8: =IF(SUMPRODUCT(('Lanç. Negócio'!$F$11:$F$1510>0)*('Lanç. Negócio'!$D$11:$D$1510=""))>0,"⚠ "&SUMPRODUCT(('Lanç. Negócio'!$F$11:$F$1510>0)*('Lanç. Negócio'!$D$11:$D$1510=""))&" lançamento(s) sem categoria — não entram nos painéis",IF(COUNTIF('Lanç. Negócio'!$G$11:$G$1510,"Verificar")>0,"⚠ "&COUNTIF('Lanç. Negócio'!$G$11:$G$1510,"Verificar")&" lançamento(s) com categoria inválida (coluna Tipo = Verificar)",IF((COUNT('Lanç. Negócio'!$F$11:$F$1510)-COUNTIFS('Lanç. Negócio'!$B$11:$B$1510,">="&DATE('Config'!$C$8,1,1),'Lanç. Negócio'!$B$11:$B$1510,"<"&DATE('Config'!$C$8+1,1,1),'Lanç. Negócio'!$F$11:$F$1510,">0"))>0,"⚠ "&(COUNT('Lanç. Negócio'!$F$11:$F$1510)-COUNTIFS('Lanç. Negócio'!$B$11:$B$1510,">="&DATE('Config'!$C$8,1,1),'Lanç. Negócio'!$B$11:$B$1510,"<"&DATE('Config'!$C$8+1,1,1),'Lanç. Negócio'!$F$11:$F$1510,">0"))&" lançamento(s) sem data ou fora de "&'Config'!$C$8&" — não entram nos painéis","✓ Tudo certo: "&COUNT('Lanç. Negócio'!$F$11:$F$1510)&" lançamento(s) registrados"))) -> ✓ Tudo certo: 93 lançamento(s) registrados
B10: Data | C10: Descrição | D10: Categoria | E10: Forma de pagamento | F10: Valor (R$) | G10: Tipo | H10: Cliente (opcional) | I10: Observação
B11: 46024 | C11: Adobe Creative Cloud | D11: Software e assinaturas | E11: Cartão de crédito | F11: 124 | G11: =IF($D11="","",IF(COUNTIF('Config'!$N$8:$N$15,$D11)>0,"Entrada",IF(COUNTIF('Config'!$P$8:$P$23,$D11)>0,"Saída","Verificar"))) -> Saída
B12: 46024 | C12: Canva Pro | D12: Software e assinaturas | E12: Cartão de crédito | F12: 34.9 | G12: =IF($D12="","",IF(COUNTIF('Config'!$N$8:$N$15,$D12)>0,"Entrada",IF(COUNTIF('Config'!$P$8:$P$23,$D12)>0,"Saída","Verificar"))) -> Saída
B13: 46027 | C13: Retirada de pró-labore | D13: Pró-labore / Retirada | E13: Transferência | F13: 4500 | G13: =IF($D13="","",IF(COUNTIF('Config'!$N$8:$N$15,$D13)>0,"Entrada",IF(COUNTIF('Config'!$P$8:$P$23,$D13)>0,"Saída","Verificar"))) -> Saída | I13: Vai para Pessoal
B14: 46032 | C14: Coworking | D14: Aluguel / coworking | E14: Boleto | F14: 450 | G14: =IF($D14="","",IF(COUNTIF('Config'!$N$8:$N$15,$D14)>0,"Entrada",IF(COUNTIF('Config'!$P$8:$P$23,$D14)>0,"Saída","Verificar"))) -> Saída
B15: 46034 | C15: Hospedagem e domínio | D15: Software e assinaturas | E15: Cartão de crédito | F15: 59.9 | G15: =IF($D15="","",IF(COUNTIF('Config'!$N$8:$N$15,$D15)>0,"Entrada",IF(COUNTIF('Config'!$P$8:$P$23,$D15)>0,"Saída","Verificar"))) -> Saída
B16: 46037 | C16: Internet e celular (parte profissional) | D16: Internet e telefone | E16: Débito automático | F16: 140 | G16: =IF($D16="","",IF(COUNTIF('Config'!$N$8:$N$15,$D16)>0,"Entrada",IF(COUNTIF('Config'!$P$8:$P$23,$D16)>0,"Saída","Verificar"))) -> Saída
B17: 46038 | C17: Anúncios (Meta Ads) | D17: Marketing e anúncios | E17: Cartão de crédito | F17: 247.43 | G17: =IF($D17="","",IF(COUNTIF('Config'!$N$8:$N$15,$D17)>0,"Entrada",IF(COUNTIF('Config'!$P$8:$P$23,$D17)>0,"Saída","Verificar"))) -> Saída
B18: 46042 | C18: Seguro de equipamentos | D18: Seguros | E18: Cartão de crédito | F18: 380 | G18: =IF($D18="","",IF(COUNTIF('Config'!$N$8:$N$15,$D18)>0,"Entrada",IF(COUNTIF('Config'!$P$8:$P$23,$D18)>0,"Saída","Verificar"))) -> Saída
B19: 46043 | C19: Transporte a clientes | D19: Transporte e viagens | E19: Cartão de crédito | F19: 117.27 | G19: =IF($D19="","",IF(COUNTIF('Config'!$N$8:$N$15,$D19)>0,"Entrada",IF(COUNTIF('Config'!$P$8:$P$23,$D19)>0,"Saída","Verificar"))) -> Saída
B20: 46050 | C20: Tarifas bancárias e maquininha | D20: Taxas e tarifas | E20: Débito automático | F20: 25.69 | G20: =IF($D20="","",IF(COUNTIF('Config'!$N$8:$N$15,$D20)>0,"Entrada",IF(COUNTIF('Config'!$P$8:$P$23,$D20)>0,"Saída","Verificar"))) -> Saída
B21: 46055 | C21: Adobe Creative Cloud | D21: Software e assinaturas | E21: Cartão de crédito | F21: 124 | G21: =IF($D21="","",IF(COUNTIF('Config'!$N$8:$N$15,$D21)>0,"Entrada",IF(COUNTIF('Config'!$P$8:$P$23,$D21)>0,"Saída","Verificar"))) -> Saída
B22: 46055 | C22: Canva Pro | D22: Software e assinaturas | E22: Cartão de crédito | F22: 34.9 | G22: =IF($D22="","",IF(COUNTIF('Config'!$N$8:$N$15,$D22)>0,"Entrada",IF(COUNTIF('Config'!$P$8:$P$23,$D22)>0,"Saída","Verificar"))) -> Saída
B23: 46058 | C23: Retirada de pró-labore | D23: Pró-labore / Retirada | E23: Transferência | F23: 4500 | G23: =IF($D23="","",IF(COUNTIF('Config'!$N$8:$N$15,$D23)>0,"Entrada",IF(COUNTIF('Config'!$P$8:$P$23,$D23)>0,"Saída","Verificar"))) -> Saída | I23: Vai para Pessoal
B24: 46063 | C24: Coworking | D24: Aluguel / coworking | E24: Boleto | F24: 450 | G24: =IF($D24="","",IF(COUNTIF('Config'!$N$8:$N$15,$D24)>0,"Entrada",IF(COUNTIF('Config'!$P$8:$P$23,$D24)>0,"Saída","Verificar"))) -> Saída
B25: 46065 | C25: Hospedagem e domínio | D25: Software e assinaturas | E25: Cartão de crédito | F25: 59.9 | G25: =IF($D25="","",IF(COUNTIF('Config'!$N$8:$N$15,$D25)>0,"Entrada",IF(COUNTIF('Config'!$P$8:$P$23,$D25)>0,"Saída","Verificar"))) -> Saída
B26: 46068 | C26: Internet e celular (parte profissional) | D26: Internet e telefone | E26: Débito automático | F26: 140 | G26: =IF($D26="","",IF(COUNTIF('Config'!$N$8:$N$15,$D26)>0,"Entrada",IF(COUNTIF('Config'!$P$8:$P$23,$D26)>0,"Saída","Verificar"))) -> Saída
B27: 46069 | C27: Anúncios (Meta Ads) | D27: Marketing e anúncios | E27: Cartão de crédito | F27: 259.02 | G27: =IF($D27="","",IF(COUNTIF('Config'!$N$8:$N$15,$D27)>0,"Entrada",IF(COUNTIF('Config'!$P$8:$P$23,$D27)>0,"Saída","Verificar"))) -> Saída
B28: 46071 | C28: Almoço com cliente | D28: Alimentação a trabalho | E28: Cartão de crédito | F28: 104.98 | G28: =IF($D28="","",IF(COUNTIF('Config'!$N$8:$N$15,$D28)>0,"Entrada",IF(COUNTIF('Config'!$P$8:$P$23,$D28)>0,"Saída","Verificar"))) -> Saída
B29: 46074 | C29: Transporte a clientes | D29: Transporte e viagens | E29: Cartão de crédito | F29: 143.24 | G29: =IF($D29="","",IF(COUNTIF('Config'!$N$8:$N$15,$D29)>0,"Entrada",IF(COUNTIF('Config'!$P$8:$P$23,$D29)>0,"Saída","Verificar"))) -> Saída
B30: 46080 | C30: Receita avulsa – venda de templates | D30: Receita avulsa (vendas/serviços) | E30: Pix | F30: 338.99 | G30: =IF($D30="","",IF(COUNTIF('Config'!$N$8:$N$15,$D30)>0,"Entrada",IF(COUNTIF('Config'!$P$8:$P$23,$D30)>0,"Saída","Verificar"))) -> Entrada
B31: 46081 | C31: Tarifas bancárias e maquininha | D31: Taxas e tarifas | E31: Débito automático | F31: 44.38 | G31: =IF($D31="","",IF(COUNTIF('Config'!$N$8:$N$15,$D31)>0,"Entrada",IF(COUNTIF('Config'!$P$8:$P$23,$D31)>0,"Saída","Verificar"))) -> Saída
B32: 46083 | C32: Adobe Creative Cloud | D32: Software e assinaturas | E32: Cartão de crédito | F32: 124 | G32: =IF($D32="","",IF(COUNTIF('Config'!$N$8:$N$15,$D32)>0,"Entrada",IF(COUNTIF('Config'!$P$8:$P$23,$D32)>0,"Saída","Verificar"))) -> Saída
B33: 46083 | C33: Canva Pro | D33: Software e assinaturas | E33: Cartão de crédito | F33: 34.9 | G33: =IF($D33="","",IF(COUNTIF('Config'!$N$8:$N$15,$D33)>0,"Entrada",IF(COUNTIF('Config'!$P$8:$P$23,$D33)>0,"Saída","Verificar"))) -> Saída
B34: 46086 | C34: Retirada de pró-labore | D34: Pró-labore / Retirada | E34: Transferência | F34: 4500 | G34: =IF($D34="","",IF(COUNTIF('Config'!$N$8:$N$15,$D34)>0,"Entrada",IF(COUNTIF('Config'!$P$8:$P$23,$D34)>0,"Saída","Verificar"))) -> Saída | I34: Vai para Pessoal
B35: 46091 | C35: Coworking | D35: Aluguel / coworking | E35: Boleto | F35: 450 | G35: =IF($D35="","",IF(COUNTIF('Config'!$N$8:$N$15,$D35)>0,"Entrada",IF(COUNTIF('Config'!$P$8:$P$23,$D35)>0,"Saída","Verificar"))) -> Saída
B36: 46093 | C36: Hospedagem e domínio | D36: Software e assinaturas | E36: Cartão de crédito | F36: 59.9 | G36: =IF($D36="","",IF(COUNTIF('Config'!$N$8:$N$15,$D36)>0,"Entrada",IF(COUNTIF('Config'!$P$8:$P$23,$D36)>0,"Saída","Verificar"))) -> Saída
B37: 46096 | C37: Internet e celular (parte profissional) | D37: Internet e telefone | E37: Débito automático | F37: 140 | G37: =IF($D37="","",IF(COUNTIF('Config'!$N$8:$N$15,$D37)>0,"Entrada",IF(COUNTIF('Config'!$P$8:$P$23,$D37)>0,"Saída","Verificar"))) -> Saída
B38: 46097 | C38: Anúncios (Meta Ads) | D38: Marketing e anúncios | E38: Cartão de crédito | F38: 208.41 | G38: =IF($D38="","",IF(COUNTIF('Config'!$N$8:$N$15,$D38)>0,"Entrada",IF(COUNTIF('Config'!$P$8:$P$23,$D38)>0,"Saída","Verificar"))) -> Saída
B39: 46102 | C39: Transporte a clientes | D39: Transporte e viagens | E39: Cartão de crédito | F39: 189.7 | G39: =IF($D39="","",IF(COUNTIF('Config'!$N$8:$N$15,$D39)>0,"Entrada",IF(COUNTIF('Config'!$P$8:$P$23,$D39)>0,"Saída","Verificar"))) -> Saída
B40: 46103 | C40: Freelancer de motion design | D40: Terceiros / freelancers | E40: Pix | F40: 600 | G40: =IF($D40="","",IF(COUNTIF('Config'!$N$8:$N$15,$D40)>0,"Entrada",IF(COUNTIF('Config'!$P$8:$P$23,$D40)>0,"Saída","Verificar"))) -> Saída
B41: 46109 | C41: Tarifas bancárias e maquininha | D41: Taxas e tarifas | E41: Débito automático | F41: 35.52 | G41: =IF($D41="","",IF(COUNTIF('Config'!$N$8:$N$15,$D41)>0,"Entrada",IF(COUNTIF('Config'!$P$8:$P$23,$D41)>0,"Saída","Verificar"))) -> Saída
B42: 46114 | C42: Adobe Creative Cloud | D42: Software e assinaturas | E42: Cartão de crédito | F42: 124 | G42: =IF($D42="","",IF(COUNTIF('Config'!$N$8:$N$15,$D42)>0,"Entrada",IF(COUNTIF('Config'!$P$8:$P$23,$D42)>0,"Saída","Verificar"))) -> Saída
B43: 46114 | C43: Canva Pro | D43: Software e assinaturas | E43: Cartão de crédito | F43: 34.9 | G43: =IF($D43="","",IF(COUNTIF('Config'!$N$8:$N$15,$D43)>0,"Entrada",IF(COUNTIF('Config'!$P$8:$P$23,$D43)>0,"Saída","Verificar"))) -> Saída
B44: 46117 | C44: Retirada de pró-labore | D44: Pró-labore / Retirada | E44: Transferência | F44: 4500 | G44: =IF($D44="","",IF(COUNTIF('Config'!$N$8:$N$15,$D44)>0,"Entrada",IF(COUNTIF('Config'!$P$8:$P$23,$D44)>0,"Saída","Verificar"))) -> Saída | I44: Vai para Pessoal
B45: 46121 | C45: Curso de especialização | D45: Capacitação e cursos | E45: Cartão de crédito | F45: 320 | G45: =IF($D45="","",IF(COUNTIF('Config'!$N$8:$N$15,$D45)>0,"Entrada",IF(COUNTIF('Config'!$P$8:$P$23,$D45)>0,"Saída","Verificar"))) -> Saída
B46: 46122 | C46: Coworking | D46: Aluguel / coworking | E46: Boleto | F46: 450 | G46: =IF($D46="","",IF(COUNTIF('Config'!$N$8:$N$15,$D46)>0,"Entrada",IF(COUNTIF('Config'!$P$8:$P$23,$D46)>0,"Saída","Verificar"))) -> Saída
B47: 46124 | C47: Hospedagem e domínio | D47: Software e assinaturas | E47: Cartão de crédito | F47: 59.9 | G47: =IF($D47="","",IF(COUNTIF('Config'!$N$8:$N$15,$D47)>0,"Entrada",IF(COUNTIF('Config'!$P$8:$P$23,$D47)>0,"Saída","Verificar"))) -> Saída
B48: 46127 | C48: Internet e celular (parte profissional) | D48: Internet e telefone | E48: Débito automático | F48: 140 | G48: =IF($D48="","",IF(COUNTIF('Config'!$N$8:$N$15,$D48)>0,"Entrada",IF(COUNTIF('Config'!$P$8:$P$23,$D48)>0,"Saída","Verificar"))) -> Saída
B49: 46128 | C49: Anúncios (Meta Ads) | D49: Marketing e anúncios | E49: Cartão de crédito | F49: 326.45 | G49: =IF($D49="","",IF(COUNTIF('Config'!$N$8:$N$15,$D49)>0,"Entrada",IF(COUNTIF('Config'!$P$8:$P$23,$D49)>0,"Saída","Verificar"))) -> Saída
B50: 46133 | C50: Transporte a clientes | D50: Transporte e viagens | E50: Cartão de crédito | F50: 152.02 | G50: =IF($D50="","",IF(COUNTIF('Config'!$N$8:$N$15,$D50)>0,"Entrada",IF(COUNTIF('Config'!$P$8:$P$23,$D50)>0,"Saída","Verificar"))) -> Saída
B51: 46140 | C51: Tarifas bancárias e maquininha | D51: Taxas e tarifas | E51: Débito automático | F51: 47.9 | G51: =IF($D51="","",IF(COUNTIF('Config'!$N$8:$N$15,$D51)>0,"Entrada",IF(COUNTIF('Config'!$P$8:$P$23,$D51)>0,"Saída","Verificar"))) -> Saída
B52: 46144 | C52: Adobe Creative Cloud | D52: Software e assinaturas | E52: Cartão de crédito | F52: 124 | G52: =IF($D52="","",IF(COUNTIF('Config'!$N$8:$N$15,$D52)>0,"Entrada",IF(COUNTIF('Config'!$P$8:$P$23,$D52)>0,"Saída","Verificar"))) -> Saída
B53: 46144 | C53: Canva Pro | D53: Software e assinaturas | E53: Cartão de crédito | F53: 34.9 | G53: =IF($D53="","",IF(COUNTIF('Config'!$N$8:$N$15,$D53)>0,"Entrada",IF(COUNTIF('Config'!$P$8:$P$23,$D53)>0,"Saída","Verificar"))) -> Saída
B54: 46147 | C54: Retirada de pró-labore | D54: Pró-labore / Retirada | E54: Transferência | F54: 4500 | G54: =IF($D54="","",IF(COUNTIF('Config'!$N$8:$N$15,$D54)>0,"Entrada",IF(COUNTIF('Config'!$P$8:$P$23,$D54)>0,"Saída","Verificar"))) -> Saída | I54: Vai para Pessoal
B55: 46152 | C55: Coworking | D55: Aluguel / coworking | E55: Boleto | F55: 450 | G55: =IF($D55="","",IF(COUNTIF('Config'!$N$8:$N$15,$D55)>0,"Entrada",IF(COUNTIF('Config'!$P$8:$P$23,$D55)>0,"Saída","Verificar"))) -> Saída
B56: 46154 | C56: Hospedagem e domínio | D56: Software e assinaturas | E56: Cartão de crédito | F56: 59.9 | G56: =IF($D56="","",IF(COUNTIF('Config'!$N$8:$N$15,$D56)>0,"Entrada",IF(COUNTIF('Config'!$P$8:$P$23,$D56)>0,"Saída","Verificar"))) -> Saída
B57: 46157 | C57: Internet e celular (parte profissional) | D57: Internet e telefone | E57: Débito automático | F57: 140 | G57: =IF($D57="","",IF(COUNTIF('Config'!$N$8:$N$15,$D57)>0,"Entrada",IF(COUNTIF('Config'!$P$8:$P$23,$D57)>0,"Saída","Verificar"))) -> Saída
B58: 46158 | C58: Anúncios (Meta Ads) | D58: Marketing e anúncios | E58: Cartão de crédito | F58: 198.23 | G58: =IF($D58="","",IF(COUNTIF('Config'!$N$8:$N$15,$D58)>0,"Entrada",IF(COUNTIF('Config'!$P$8:$P$23,$D58)>0,"Saída","Verificar"))) -> Saída
B59: 46160 | C59: Almoço com cliente | D59: Alimentação a trabalho | E59: Cartão de crédito | F59: 74.92 | G59: =IF($D59="","",IF(COUNTIF('Config'!$N$8:$N$15,$D59)>0,"Entrada",IF(COUNTIF('Config'!$P$8:$P$23,$D59)>0,"Saída","Verificar"))) -> Saída
B60: 46163 | C60: Transporte a clientes | D60: Transporte e viagens | E60: Cartão de crédito | F60: 97.58 | G60: =IF($D60="","",IF(COUNTIF('Config'!$N$8:$N$15,$D60)>0,"Entrada",IF(COUNTIF('Config'!$P$8:$P$23,$D60)>0,"Saída","Verificar"))) -> Saída
B61: 46170 | C61: Tarifas bancárias e maquininha | D61: Taxas e tarifas | E61: Débito automático | F61: 32.25 | G61: =IF($D61="","",IF(COUNTIF('Config'!$N$8:$N$15,$D61)>0,"Entrada",IF(COUNTIF('Config'!$P$8:$P$23,$D61)>0,"Saída","Verificar"))) -> Saída
B62: 46175 | C62: Adobe Creative Cloud | D62: Software e assinaturas | E62: Cartão de crédito | F62: 124 | G62: =IF($D62="","",IF(COUNTIF('Config'!$N$8:$N$15,$D62)>0,"Entrada",IF(COUNTIF('Config'!$P$8:$P$23,$D62)>0,"Saída","Verificar"))) -> Saída
B63: 46175 | C63: Canva Pro | D63: Software e assinaturas | E63: Cartão de crédito | F63: 34.9 | G63: =IF($D63="","",IF(COUNTIF('Config'!$N$8:$N$15,$D63)>0,"Entrada",IF(COUNTIF('Config'!$P$8:$P$23,$D63)>0,"Saída","Verificar"))) -> Saída
B64: 46178 | C64: Retirada de pró-labore | D64: Pró-labore / Retirada | E64: Transferência | F64: 4500 | G64: =IF($D64="","",IF(COUNTIF('Config'!$N$8:$N$15,$D64)>0,"Entrada",IF(COUNTIF('Config'!$P$8:$P$23,$D64)>0,"Saída","Verificar"))) -> Saída | I64: Vai para Pessoal
B65: 46183 | C65: Coworking | D65: Aluguel / coworking | E65: Boleto | F65: 450 | G65: =IF($D65="","",IF(COUNTIF('Config'!$N$8:$N$15,$D65)>0,"Entrada",IF(COUNTIF('Config'!$P$8:$P$23,$D65)>0,"Saída","Verificar"))) -> Saída
B66: 46185 | C66: Hospedagem e domínio | D66: Software e assinaturas | E66: Cartão de crédito | F66: 59.9 | G66: =IF($D66="","",IF(COUNTIF('Config'!$N$8:$N$15,$D66)>0,"Entrada",IF(COUNTIF('Config'!$P$8:$P$23,$D66)>0,"Saída","Verificar"))) -> Saída
B67: 46187 | C67: Monitor 27" 4K | D67: Equipamentos | E67: Cartão de crédito | F67: 1480 | G67: =IF($D67="","",IF(COUNTIF('Config'!$N$8:$N$15,$D67)>0,"Entrada",IF(COUNTIF('Config'!$P$8:$P$23,$D67)>0,"Saída","Verificar"))) -> Saída | I67: Equipamento
B68: 46188 | C68: Internet e celular (parte profissional) | D68: Internet e telefone | E68: Débito automático | F68: 140 | G68: =IF($D68="","",IF(COUNTIF('Config'!$N$8:$N$15,$D68)>0,"Entrada",IF(COUNTIF('Config'!$P$8:$P$23,$D68)>0,"Saída","Verificar"))) -> Saída
B69: 46189 | C69: Anúncios (Meta Ads) | D69: Marketing e anúncios | E69: Cartão de crédito | F69: 234.08 | G69: =IF($D69="","",IF(COUNTIF('Config'!$N$8:$N$15,$D69)>0,"Entrada",IF(COUNTIF('Config'!$P$8:$P$23,$D69)>0,"Saída","Verificar"))) -> Saída
B70: 46194 | C70: Transporte a clientes | D70: Transporte e viagens | E70: Cartão de crédito | F70: 170.06 | G70: =IF($D70="","",IF(COUNTIF('Config'!$N$8:$N$15,$D70)>0,"Entrada",IF(COUNTIF('Config'!$P$8:$P$23,$D70)>0,"Saída","Verificar"))) -> Saída
B71: 46200 | C71: Receita avulsa – venda de templates | D71: Receita avulsa (vendas/serviços) | E71: Pix | F71: 272.76 | G71: =IF($D71="","",IF(COUNTIF('Config'!$N$8:$N$15,$D71)>0,"Entrada",IF(COUNTIF('Config'!$P$8:$P$23,$D71)>0,"Saída","Verificar"))) -> Entrada
B72: 46201 | C72: Tarifas bancárias e maquininha | D72: Taxas e tarifas | E72: Débito automático | F72: 42.62 | G72: =IF($D72="","",IF(COUNTIF('Config'!$N$8:$N$15,$D72)>0,"Entrada",IF(COUNTIF('Config'!$P$8:$P$23,$D72)>0,"Saída","Verificar"))) -> Saída
B73: 46205 | C73: Adobe Creative Cloud | D73: Software e assinaturas | E73: Cartão de crédito | F73: 124 | G73: =IF($D73="","",IF(COUNTIF('Config'!$N$8:$N$15,$D73)>0,"Entrada",IF(COUNTIF('Config'!$P$8:$P$23,$D73)>0,"Saída","Verificar"))) -> Saída
B74: 46205 | C74: Canva Pro | D74: Software e assinaturas | E74: Cartão de crédito | F74: 34.9 | G74: =IF($D74="","",IF(COUNTIF('Config'!$N$8:$N$15,$D74)>0,"Entrada",IF(COUNTIF('Config'!$P$8:$P$23,$D74)>0,"Saída","Verificar"))) -> Saída
B75: 46208 | C75: Retirada de pró-labore | D75: Pró-labore / Retirada | E75: Transferência | F75: 4500 | G75: =IF($D75="","",IF(COUNTIF('Config'!$N$8:$N$15,$D75)>0,"Entrada",IF(COUNTIF('Config'!$P$8:$P$23,$D75)>0,"Saída","Verificar"))) -> Saída | I75: Vai para Pessoal
B76: 46213 | C76: Coworking | D76: Aluguel / coworking | E76: Boleto | F76: 450 | G76: =IF($D76="","",IF(COUNTIF('Config'!$N$8:$N$15,$D76)>0,"Entrada",IF(COUNTIF('Config'!$P$8:$P$23,$D76)>0,"Saída","Verificar"))) -> Saída
B77: 46215 | C77: Hospedagem e domínio | D77: Software e assinaturas | E77: Cartão de crédito | F77: 59.9 | G77: =IF($D77="","",IF(COUNTIF('Config'!$N$8:$N$15,$D77)>0,"Entrada",IF(COUNTIF('Config'!$P$8:$P$23,$D77)>0,"Saída","Verificar"))) -> Saída
B78: 46218 | C78: Internet e celular (parte profissional) | D78: Internet e telefone | E78: Débito automático | F78: 140 | G78: =IF($D78="","",IF(COUNTIF('Config'!$N$8:$N$15,$D78)>0,"Entrada",IF(COUNTIF('Config'!$P$8:$P$23,$D78)>0,"Saída","Verificar"))) -> Saída
B79: 46219 | C79: Anúncios (Meta Ads) | D79: Marketing e anúncios | E79: Cartão de crédito | F79: 327.94 | G79: =IF($D79="","",IF(COUNTIF('Config'!$N$8:$N$15,$D79)>0,"Entrada",IF(COUNTIF('Config'!$P$8:$P$23,$D79)>0,"Saída","Verificar"))) -> Saída
B80: 46224 | C80: Transporte a clientes | D80: Transporte e viagens | E80: Cartão de crédito | F80: 60.07 | G80: =IF($D80="","",IF(COUNTIF('Config'!$N$8:$N$15,$D80)>0,"Entrada",IF(COUNTIF('Config'!$P$8:$P$23,$D80)>0,"Saída","Verificar"))) -> Saída
B81: 46225 | C81: Freelancer de motion design | D81: Terceiros / freelancers | E81: Pix | F81: 600 | G81: =IF($D81="","",IF(COUNTIF('Config'!$N$8:$N$15,$D81)>0,"Entrada",IF(COUNTIF('Config'!$P$8:$P$23,$D81)>0,"Saída","Verificar"))) -> Saída
B82: 46231 | C82: Tarifas bancárias e maquininha | D82: Taxas e tarifas | E82: Débito automático | F82: 47.03 | G82: =IF($D82="","",IF(COUNTIF('Config'!$N$8:$N$15,$D82)>0,"Entrada",IF(COUNTIF('Config'!$P$8:$P$23,$D82)>0,"Saída","Verificar"))) -> Saída
B83: 46236 | C83: Adobe Creative Cloud | D83: Software e assinaturas | E83: Cartão de crédito | F83: 124 | G83: =IF($D83="","",IF(COUNTIF('Config'!$N$8:$N$15,$D83)>0,"Entrada",IF(COUNTIF('Config'!$P$8:$P$23,$D83)>0,"Saída","Verificar"))) -> Saída
B84: 46236 | C84: Canva Pro | D84: Software e assinaturas | E84: Cartão de crédito | F84: 34.9 | G84: =IF($D84="","",IF(COUNTIF('Config'!$N$8:$N$15,$D84)>0,"Entrada",IF(COUNTIF('Config'!$P$8:$P$23,$D84)>0,"Saída","Verificar"))) -> Saída
B85: 46239 | C85: Retirada de pró-labore | D85: Pró-labore / Retirada | E85: Transferência | F85: 4500 | G85: =IF($D85="","",IF(COUNTIF('Config'!$N$8:$N$15,$D85)>0,"Entrada",IF(COUNTIF('Config'!$P$8:$P$23,$D85)>0,"Saída","Verificar"))) -> Saída | I85: Vai para Pessoal
B86: 46244 | C86: Coworking | D86: Aluguel / coworking | E86: Boleto | F86: 450 | G86: =IF($D86="","",IF(COUNTIF('Config'!$N$8:$N$15,$D86)>0,"Entrada",IF(COUNTIF('Config'!$P$8:$P$23,$D86)>0,"Saída","Verificar"))) -> Saída
B87: 46246 | C87: Hospedagem e domínio | D87: Software e assinaturas | E87: Cartão de crédito | F87: 59.9 | G87: =IF($D87="","",IF(COUNTIF('Config'!$N$8:$N$15,$D87)>0,"Entrada",IF(COUNTIF('Config'!$P$8:$P$23,$D87)>0,"Saída","Verificar"))) -> Saída
B88: 46249 | C88: Internet e celular (parte profissional) | D88: Internet e telefone | E88: Débito automático | F88: 140 | G88: =IF($D88="","",IF(COUNTIF('Config'!$N$8:$N$15,$D88)>0,"Entrada",IF(COUNTIF('Config'!$P$8:$P$23,$D88)>0,"Saída","Verificar"))) -> Saída
B89: 46250 | C89: Anúncios (Meta Ads) | D89: Marketing e anúncios | E89: Cartão de crédito | F89: 341.16 | G89: =IF($D89="","",IF(COUNTIF('Config'!$N$8:$N$15,$D89)>0,"Entrada",IF(COUNTIF('Config'!$P$8:$P$23,$D89)>0,"Saída","Verificar"))) -> Saída
B90: 46252 | C90: Almoço com cliente | D90: Alimentação a trabalho | E90: Cartão de crédito | F90: 138.63 | G90: =IF($D90="","",IF(COUNTIF('Config'!$N$8:$N$15,$D90)>0,"Entrada",IF(COUNTIF('Config'!$P$8:$P$23,$D90)>0,"Saída","Verificar"))) -> Saída
B91: 46255 | C91: Transporte a clientes | D91: Transporte e viagens | E91: Cartão de crédito | F91: 121.1 | G91: =IF($D91="","",IF(COUNTIF('Config'!$N$8:$N$15,$D91)>0,"Entrada",IF(COUNTIF('Config'!$P$8:$P$23,$D91)>0,"Saída","Verificar"))) -> Saída
B92: 46262 | C92: Tarifas bancárias e maquininha | D92: Taxas e tarifas | E92: Débito automático | F92: 29.82 | G92: =IF($D92="","",IF(COUNTIF('Config'!$N$8:$N$15,$D92)>0,"Entrada",IF(COUNTIF('Config'!$P$8:$P$23,$D92)>0,"Saída","Verificar"))) -> Saída
B93: 46267 | C93: Adobe Creative Cloud | D93: Software e assinaturas | E93: Cartão de crédito | F93: 124 | G93: =IF($D93="","",IF(COUNTIF('Config'!$N$8:$N$15,$D93)>0,"Entrada",IF(COUNTIF('Config'!$P$8:$P$23,$D93)>0,"Saída","Verificar"))) -> Saída
B94: 46267 | C94: Canva Pro | D94: Software e assinaturas | E94: Cartão de crédito | F94: 34.9 | G94: =IF($D94="","",IF(COUNTIF('Config'!$N$8:$N$15,$D94)>0,"Entrada",IF(COUNTIF('Config'!$P$8:$P$23,$D94)>0,"Saída","Verificar"))) -> Saída
B95: 46270 | C95: Retirada de pró-labore | D95: Pró-labore / Retirada | E95: Transferência | F95: 4500 | G95: =IF($D95="","",IF(COUNTIF('Config'!$N$8:$N$15,$D95)>0,"Entrada",IF(COUNTIF('Config'!$P$8:$P$23,$D95)>0,"Saída","Verificar"))) -> Saída | I95: Vai para Pessoal
B96: 46274 | C96: Curso de especialização | D96: Capacitação e cursos | E96: Cartão de crédito | F96: 320 | G96: =IF($D96="","",IF(COUNTIF('Config'!$N$8:$N$15,$D96)>0,"Entrada",IF(COUNTIF('Config'!$P$8:$P$23,$D96)>0,"Saída","Verificar"))) -> Saída
B97: 46275 | C97: Coworking | D97: Aluguel / coworking | E97: Boleto | F97: 450 | G97: =IF($D97="","",IF(COUNTIF('Config'!$N$8:$N$15,$D97)>0,"Entrada",IF(COUNTIF('Config'!$P$8:$P$23,$D97)>0,"Saída","Verificar"))) -> Saída
B98: 46277 | C98: Hospedagem e domínio | D98: Software e assinaturas | E98: Cartão de crédito | F98: 59.9 | G98: =IF($D98="","",IF(COUNTIF('Config'!$N$8:$N$15,$D98)>0,"Entrada",IF(COUNTIF('Config'!$P$8:$P$23,$D98)>0,"Saída","Verificar"))) -> Saída
B99: 46280 | C99: Internet e celular (parte profissional) | D99: Internet e telefone | E99: Débito automático | F99: 140 | G99: =IF($D99="","",IF(COUNTIF('Config'!$N$8:$N$15,$D99)>0,"Entrada",IF(COUNTIF('Config'!$P$8:$P$23,$D99)>0,"Saída","Verificar"))) -> Saída
B100: 46281 | C100: Anúncios (Meta Ads) | D100: Marketing e anúncios | E100: Cartão de crédito | F100: 165.34 | G100: =IF($D100="","",IF(COUNTIF('Config'!$N$8:$N$15,$D100)>0,"Entrada",IF(COUNTIF('Config'!$P$8:$P$23,$D100)>0,"Saída","Verificar"))) -> Saída
B101: 46286 | C101: Transporte a clientes | D101: Transporte e viagens | E101: Cartão de crédito | F101: 141.83 | G101: =IF($D101="","",IF(COUNTIF('Config'!$N$8:$N$15,$D101)>0,"Entrada",IF(COUNTIF('Config'!$P$8:$P$23,$D101)>0,"Saída","Verificar"))) -> Saída
B102: 46292 | C102: Receita avulsa – venda de templates | D102: Receita avulsa (vendas/serviços) | E102: Pix | F102: 366.84 | G102: =IF($D102="","",IF(COUNTIF('Config'!$N$8:$N$15,$D102)>0,"Entrada",IF(COUNTIF('Config'!$P$8:$P$23,$D102)>0,"Saída","Verificar"))) -> Entrada
...

Sheet Clientes
B1: 🏠 Início | D1: 📊 Painel Geral | E1: 👤 Painel Pessoal | H1: 💼 Painel Negócio | K1: ⚙ Config
B2: PESSOAL | D2: 📝 Lançamentos | E2: 💳 Orçamento | H2: 📅 Resumo anual | K2: 🎯 Metas
B3: NEGÓCIO | C3: 📝 Lançamentos | D3: 🤝 Clientes | E3: 💰 Recebimentos | H3: 🧾 Impostos | K3: 📈 Fluxo de Caixa
B5: 🤝 Clientes — quem paga, quanto e quando
B6: Cadastre o cliente (colunas amarelas). Os totais vêm da aba Recebimentos e se atualizam sozinhos.
B7: Cliente | C7: Contato | D7: E-mail / Telefone | E7: Origem | F7: Nº cobranças | G7: Faturado no ano | H7: Recebido no ano | I7: A receber | J7: Em atraso | K7: % da receita | L7: Ticket médio | M7: Situação
B8: Studio Aurora | C8: Camila Prado | D8: camila@studioaurora.com.br | E8: Indicação | F8: =IF($B8="","",COUNTIFS('Recebimentos'!$C$11:$C$1010,$B8,'Recebimentos'!$B$11:$B$1010,">="&DATE('Config'!$C$8,1,1),'Recebimentos'!$B$11:$B$1010,"<"&DATE('Config'!$C$8+1,1,1))) -> 9 | G8: =IF($B8="","",SUMIFS('Recebimentos'!$E$11:$E$1010,'Recebimentos'!$C$11:$C$1010,$B8,'Recebimentos'!$B$11:$B$1010,">="&DATE('Config'!$C$8,1,1),'Recebimentos'!$B$11:$B$1010,"<"&DATE('Config'!$C$8+1,1,1))) -> 16200 | H8: =IF($B8="","",SUMIFS('Recebimentos'!$E$11:$E$1010,'Recebimentos'!$C$11:$C$1010,$B8,'Recebimentos'!$G$11:$G$1010,">="&DATE('Config'!$C$8,1,1),'Recebimentos'!$G$11:$G$1010,"<"&DATE('Config'!$C$8+1,1,1))) -> 14400 | I8: =IF($B8="","",SUMIFS('Recebimentos'!$K$11:$K$1010,'Recebimentos'!$C$11:$C$1010,$B8)) -> 1800 | J8: =IF($B8="","",SUMIFS('Recebimentos'!$L$11:$L$1010,'Recebimentos'!$C$11:$C$1010,$B8)) -> 1800 | K8: =IF($B8="","",IF($H$38=0,0,H8/$H$38)) -> 0.25931929 | L8: =IF(OR($B8="",N(F8)=0),"",G8/F8) -> 1800 | M8: =IF($B8="","",IF(J8>0,"✖ Em atraso",IF(I8>0,"● A receber",IF(H8>0,"✓ Em dia","—")))) -> ✖ Em atraso
B9: Clínica Vida Plena | C9: Dr. Rafael Nunes | D9: (11) 98877-1020 | E9: Instagram | F9: =IF($B9="","",COUNTIFS('Recebimentos'!$C$11:$C$1010,$B9,'Recebimentos'!$B$11:$B$1010,">="&DATE('Config'!$C$8,1,1),'Recebimentos'!$B$11:$B$1010,"<"&DATE('Config'!$C$8+1,1,1))) -> 9 | G9: =IF($B9="","",SUMIFS('Recebimentos'!$E$11:$E$1010,'Recebimentos'!$C$11:$C$1010,$B9,'Recebimentos'!$B$11:$B$1010,">="&DATE('Config'!$C$8,1,1),'Recebimentos'!$B$11:$B$1010,"<"&DATE('Config'!$C$8+1,1,1))) -> 13500 | H9: =IF($B9="","",SUMIFS('Recebimentos'!$E$11:$E$1010,'Recebimentos'!$C$11:$C$1010,$B9,'Recebimentos'!$G$11:$G$1010,">="&DATE('Config'!$C$8,1,1),'Recebimentos'!$G$11:$G$1010,"<"&DATE('Config'!$C$8+1,1,1))) -> 12000 | I9: =IF($B9="","",SUMIFS('Recebimentos'!$K$11:$K$1010,'Recebimentos'!$C$11:$C$1010,$B9)) -> 1500 | J9: =IF($B9="","",SUMIFS('Recebimentos'!$L$11:$L$1010,'Recebimentos'!$C$11:$C$1010,$B9)) -> 1500 | K9: =IF($B9="","",IF($H$38=0,0,H9/$H$38)) -> 0.21609941 | L9: =IF(OR($B9="",N(F9)=0),"",G9/F9) -> 1500 | M9: =IF($B9="","",IF(J9>0,"✖ Em atraso",IF(I9>0,"● A receber",IF(H9>0,"✓ Em dia","—")))) -> ✖ Em atraso
B10: Padaria Dois Irmãos | C10: Seu Antônio | D10: (11) 3344-2211 | E10: Indicação | F10: =IF($B10="","",COUNTIFS('Recebimentos'!$C$11:$C$1010,$B10,'Recebimentos'!$B$11:$B$1010,">="&DATE('Config'!$C$8,1,1),'Recebimentos'!$B$11:$B$1010,"<"&DATE('Config'!$C$8+1,1,1))) -> 7 | G10: =IF($B10="","",SUMIFS('Recebimentos'!$E$11:$E$1010,'Recebimentos'!$C$11:$C$1010,$B10,'Recebimentos'!$B$11:$B$1010,">="&DATE('Config'!$C$8,1,1),'Recebimentos'!$B$11:$B$1010,"<"&DATE('Config'!$C$8+1,1,1))) -> 4550 | H10: =IF($B10="","",SUMIFS('Recebimentos'!$E$11:$E$1010,'Recebimentos'!$C$11:$C$1010,$B10,'Recebimentos'!$G$11:$G$1010,">="&DATE('Config'!$C$8,1,1),'Recebimentos'!$G$11:$G$1010,"<"&DATE('Config'!$C$8+1,1,1))) -> 3900 | I10: =IF($B10="","",SUMIFS('Recebimentos'!$K$11:$K$1010,'Recebimentos'!$C$11:$C$1010,$B10)) -> 650 | J10: =IF($B10="","",SUMIFS('Recebimentos'!$L$11:$L$1010,'Recebimentos'!$C$11:$C$1010,$B10)) -> 650 | K10: =IF($B10="","",IF($H$38=0,0,H10/$H$38)) -> 0.070232307 | L10: =IF(OR($B10="",N(F10)=0),"",G10/F10) -> 650 | M10: =IF($B10="","",IF(J10>0,"✖ Em atraso",IF(I10>0,"● A receber",IF(H10>0,"✓ Em dia","—")))) -> ✖ Em atraso
B11: Tech Nova Ltda | C11: Bianca Torres | D11: bianca@technova.com | E11: LinkedIn | F11: =IF($B11="","",COUNTIFS('Recebimentos'!$C$11:$C$1010,$B11,'Recebimentos'!$B$11:$B$1010,">="&DATE('Config'!$C$8,1,1),'Recebimentos'!$B$11:$B$1010,"<"&DATE('Config'!$C$8+1,1,1))) -> 4 | G11: =IF($B11="","",SUMIFS('Recebimentos'!$E$11:$E$1010,'Recebimentos'!$C$11:$C$1010,$B11,'Recebimentos'!$B$11:$B$1010,">="&DATE('Config'!$C$8,1,1),'Recebimentos'!$B$11:$B$1010,"<"&DATE('Config'!$C$8+1,1,1))) -> 8400 | H11: =IF($B11="","",SUMIFS('Recebimentos'!$E$11:$E$1010,'Recebimentos'!$C$11:$C$1010,$B11,'Recebimentos'!$G$11:$G$1010,">="&DATE('Config'!$C$8,1,1),'Recebimentos'!$G$11:$G$1010,"<"&DATE('Config'!$C$8+1,1,1))) -> 7500 | I11: =IF($B11="","",SUMIFS('Recebimentos'!$K$11:$K$1010,'Recebimentos'!$C$11:$C$1010,$B11)) -> 900 | J11: =IF($B11="","",SUMIFS('Recebimentos'!$L$11:$L$1010,'Recebimentos'!$C$11:$C$1010,$B11)) -> 0 | K11: =IF($B11="","",IF($H$38=0,0,H11/$H$38)) -> 0.13506213 | L11: =IF(OR($B11="",N(F11)=0),"",G11/F11) -> 2100 | M11: =IF($B11="","",IF(J11>0,"✖ Em atraso",IF(I11>0,"● A receber",IF(H11>0,"✓ Em dia","—")))) -> ● A receber
B12: Escola Horizonte | C12: Coord. Marta | D12: marta@escolahorizonte.edu.br | E12: Site | F12: =IF($B12="","",COUNTIFS('Recebimentos'!$C$11:$C$1010,$B12,'Recebimentos'!$B$11:$B$1010,">="&DATE('Config'!$C$8,1,1),'Recebimentos'!$B$11:$B$1010,"<"&DATE('Config'!$C$8+1,1,1))) -> 4 | G12: =IF($B12="","",SUMIFS('Recebimentos'!$E$11:$E$1010,'Recebimentos'!$C$11:$C$1010,$B12,'Recebimentos'!$B$11:$B$1010,">="&DATE('Config'!$C$8,1,1),'Recebimentos'!$B$11:$B$1010,"<"&DATE('Config'!$C$8+1,1,1))) -> 8000 | H12: =IF($B12="","",SUMIFS('Recebimentos'!$E$11:$E$1010,'Recebimentos'!$C$11:$C$1010,$B12,'Recebimentos'!$G$11:$G$1010,">="&DATE('Config'!$C$8,1,1),'Recebimentos'!$G$11:$G$1010,"<"&DATE('Config'!$C$8+1,1,1))) -> 8000 | I12: =IF($B12="","",SUMIFS('Recebimentos'!$K$11:$K$1010,'Recebimentos'!$C$11:$C$1010,$B12)) -> 0 | J12: =IF($B12="","",SUMIFS('Recebimentos'!$L$11:$L$1010,'Recebimentos'!$C$11:$C$1010,$B12)) -> 0 | K12: =IF($B12="","",IF($H$38=0,0,H12/$H$38)) -> 0.14406627 | L12: =IF(OR($B12="",N(F12)=0),"",G12/F12) -> 2000 | M12: =IF($B12="","",IF(J12>0,"✖ Em atraso",IF(I12>0,"● A receber",IF(H12>0,"✓ Em dia","—")))) -> ✓ Em dia
B13: Loja Bella Moda | C13: Juliana Reis | D13: (21) 99120-4455 | E13: Instagram | F13: =IF($B13="","",COUNTIFS('Recebimentos'!$C$11:$C$1010,$B13,'Recebimentos'!$B$11:$B$1010,">="&DATE('Config'!$C$8,1,1),'Recebimentos'!$B$11:$B$1010,"<"&DATE('Config'!$C$8+1,1,1))) -> 4 | G13: =IF($B13="","",SUMIFS('Recebimentos'!$E$11:$E$1010,'Recebimentos'!$C$11:$C$1010,$B13,'Recebimentos'!$B$11:$B$1010,">="&DATE('Config'!$C$8,1,1),'Recebimentos'!$B$11:$B$1010,"<"&DATE('Config'!$C$8+1,1,1))) -> 6800 | H13: =IF($B13="","",SUMIFS('Recebimentos'!$E$11:$E$1010,'Recebimentos'!$C$11:$C$1010,$B13,'Recebimentos'!$G$11:$G$1010,">="&DATE('Config'!$C$8,1,1),'Recebimentos'!$G$11:$G$1010,"<"&DATE('Config'!$C$8+1,1,1))) -> 5400 | I13: =IF($B13="","",SUMIFS('Recebimentos'!$K$11:$K$1010,'Recebimentos'!$C$11:$C$1010,$B13)) -> 1400 | J13: =IF($B13="","",SUMIFS('Recebimentos'!$L$11:$L$1010,'Recebimentos'!$C$11:$C$1010,$B13)) -> 0 | K13: =IF($B13="","",IF($H$38=0,0,H13/$H$38)) -> 0.097244733 | L13: =IF(OR($B13="",N(F13)=0),"",G13/F13) -> 1700 | M13: =IF($B13="","",IF(J13>0,"✖ Em atraso",IF(I13>0,"● A receber",IF(H13>0,"✓ Em dia","—")))) -> ● A receber
B14: Café do Centro | C14: Paulo Menezes | D14: (11) 97766-3300 | E14: Indicação | F14: =IF($B14="","",COUNTIFS('Recebimentos'!$C$11:$C$1010,$B14,'Recebimentos'!$B$11:$B$1010,">="&DATE('Config'!$C$8,1,1),'Recebimentos'!$B$11:$B$1010,"<"&DATE('Config'!$C$8+1,1,1))) -> 3 | G14: =IF($B14="","",SUMIFS('Recebimentos'!$E$11:$E$1010,'Recebimentos'!$C$11:$C$1010,$B14,'Recebimentos'!$B$11:$B$1010,">="&DATE('Config'!$C$8,1,1),'Recebimentos'!$B$11:$B$1010,"<"&DATE('Config'!$C$8+1,1,1))) -> 2530 | H14: =IF($B14="","",SUMIFS('Recebimentos'!$E$11:$E$1010,'Recebimentos'!$C$11:$C$1010,$B14,'Recebimentos'!$G$11:$G$1010,">="&DATE('Config'!$C$8,1,1),'Recebimentos'!$G$11:$G$1010,"<"&DATE('Config'!$C$8+1,1,1))) -> 2050 | I14: =IF($B14="","",SUMIFS('Recebimentos'!$K$11:$K$1010,'Recebimentos'!$C$11:$C$1010,$B14)) -> 480 | J14: =IF($B14="","",SUMIFS('Recebimentos'!$L$11:$L$1010,'Recebimentos'!$C$11:$C$1010,$B14)) -> 480 | K14: =IF($B14="","",IF($H$38=0,0,H14/$H$38)) -> 0.036916982 | L14: =IF(OR($B14="",N(F14)=0),"",G14/F14) -> 843.33333 | M14: =IF($B14="","",IF(J14>0,"✖ Em atraso",IF(I14>0,"● A receber",IF(H14>0,"✓ Em dia","—")))) -> ✖ Em atraso
B15: Maria Oliveira (PF) | C15: Maria Oliveira | D15: maria.oliveira@email.com | E15: Indicação | F15: =IF($B15="","",COUNTIFS('Recebimentos'!$C$11:$C$1010,$B15,'Recebimentos'!$B$11:$B$1010,">="&DATE('Config'!$C$8,1,1),'Recebimentos'!$B$11:$B$1010,"<"&DATE('Config'!$C$8+1,1,1))) -> 2 | G15: =IF($B15="","",SUMIFS('Recebimentos'!$E$11:$E$1010,'Recebimentos'!$C$11:$C$1010,$B15,'Recebimentos'!$B$11:$B$1010,">="&DATE('Config'!$C$8,1,1),'Recebimentos'!$B$11:$B$1010,"<"&DATE('Config'!$C$8+1,1,1))) -> 2280 | H15: =IF($B15="","",SUMIFS('Recebimentos'!$E$11:$E$1010,'Recebimentos'!$C$11:$C$1010,$B15,'Recebimentos'!$G$11:$G$1010,">="&DATE('Config'!$C$8,1,1),'Recebimentos'!$G$11:$G$1010,"<"&DATE('Config'!$C$8+1,1,1))) -> 2280 | I15: =IF($B15="","",SUMIFS('Recebimentos'!$K$11:$K$1010,'Recebimentos'!$C$11:$C$1010,$B15)) -> 0 | J15: =IF($B15="","",SUMIFS('Recebimentos'!$L$11:$L$1010,'Recebimentos'!$C$11:$C$1010,$B15)) -> 0 | K15: =IF($B15="","",IF($H$38=0,0,H15/$H$38)) -> 0.041058887 | L15: =IF(OR($B15="",N(F15)=0),"",G15/F15) -> 1140 | M15: =IF($B15="","",IF(J15>0,"✖ Em atraso",IF(I15>0,"● A receber",IF(H15>0,"✓ Em dia","—")))) -> ✓ Em dia
F16: =IF($B16="","",COUNTIFS('Recebimentos'!$C$11:$C$1010,$B16,'Recebimentos'!$B$11:$B$1010,">="&DATE('Config'!$C$8,1,1),'Recebimentos'!$B$11:$B$1010,"<"&DATE('Config'!$C$8+1,1,1))) | G16: =IF($B16="","",SUMIFS('Recebimentos'!$E$11:$E$1010,'Recebimentos'!$C$11:$C$1010,$B16,'Recebimentos'!$B$11:$B$1010,">="&DATE('Config'!$C$8,1,1),'Recebimentos'!$B$11:$B$1010,"<"&DATE('Config'!$C$8+1,1,1))) | H16: =IF($B16="","",SUMIFS('Recebimentos'!$E$11:$E$1010,'Recebimentos'!$C$11:$C$1010,$B16,'Recebimentos'!$G$11:$G$1010,">="&DATE('Config'!$C$8,1,1),'Recebimentos'!$G$11:$G$1010,"<"&DATE('Config'!$C$8+1,1,1))) | I16: =IF($B16="","",SUMIFS('Recebimentos'!$K$11:$K$1010,'Recebimentos'!$C$11:$C$1010,$B16)) | J16: =IF($B16="","",SUMIFS('Recebimentos'!$L$11:$L$1010,'Recebimentos'!$C$11:$C$1010,$B16)) | K16: =IF($B16="","",IF($H$38=0,0,H16/$H$38)) | L16: =IF(OR($B16="",N(F16)=0),"",G16/F16) | M16: =IF($B16="","",IF(J16>0,"✖ Em atraso",IF(I16>0,"● A receber",IF(H16>0,"✓ Em dia","—"))))
F17: =IF($B17="","",COUNTIFS('Recebimentos'!$C$11:$C$1010,$B17,'Recebimentos'!$B$11:$B$1010,">="&DATE('Config'!$C$8,1,1),'Recebimentos'!$B$11:$B$1010,"<"&DATE('Config'!$C$8+1,1,1))) | G17: =IF($B17="","",SUMIFS('Recebimentos'!$E$11:$E$1010,'Recebimentos'!$C$11:$C$1010,$B17,'Recebimentos'!$B$11:$B$1010,">="&DATE('Config'!$C$8,1,1),'Recebimentos'!$B$11:$B$1010,"<"&DATE('Config'!$C$8+1,1,1))) | H17: =IF($B17="","",SUMIFS('Recebimentos'!$E$11:$E$1010,'Recebimentos'!$C$11:$C$1010,$B17,'Recebimentos'!$G$11:$G$1010,">="&DATE('Config'!$C$8,1,1),'Recebimentos'!$G$11:$G$1010,"<"&DATE('Config'!$C$8+1,1,1))) | I17: =IF($B17="","",SUMIFS('Recebimentos'!$K$11:$K$1010,'Recebimentos'!$C$11:$C$1010,$B17)) | J17: =IF($B17="","",SUMIFS('Recebimentos'!$L$11:$L$1010,'Recebimentos'!$C$11:$C$1010,$B17)) | K17: =IF($B17="","",IF($H$38=0,0,H17/$H$38)) | L17: =IF(OR($B17="",N(F17)=0),"",G17/F17) | M17: =IF($B17="","",IF(J17>0,"✖ Em atraso",IF(I17>0,"● A receber",IF(H17>0,"✓ Em dia","—"))))
F18: =IF($B18="","",COUNTIFS('Recebimentos'!$C$11:$C$1010,$B18,'Recebimentos'!$B$11:$B$1010,">="&DATE('Config'!$C$8,1,1),'Recebimentos'!$B$11:$B$1010,"<"&DATE('Config'!$C$8+1,1,1))) | G18: =IF($B18="","",SUMIFS('Recebimentos'!$E$11:$E$1010,'Recebimentos'!$C$11:$C$1010,$B18,'Recebimentos'!$B$11:$B$1010,">="&DATE('Config'!$C$8,1,1),'Recebimentos'!$B$11:$B$1010,"<"&DATE('Config'!$C$8+1,1,1))) | H18: =IF($B18="","",SUMIFS('Recebimentos'!$E$11:$E$1010,'Recebimentos'!$C$11:$C$1010,$B18,'Recebimentos'!$G$11:$G$1010,">="&DATE('Config'!$C$8,1,1),'Recebimentos'!$G$11:$G$1010,"<"&DATE('Config'!$C$8+1,1,1))) | I18: =IF($B18="","",SUMIFS('Recebimentos'!$K$11:$K$1010,'Recebimentos'!$C$11:$C$1010,$B18)) | J18: =IF($B18="","",SUMIFS('Recebimentos'!$L$11:$L$1010,'Recebimentos'!$C$11:$C$1010,$B18)) | K18: =IF($B18="","",IF($H$38=0,0,H18/$H$38)) | L18: =IF(OR($B18="",N(F18)=0),"",G18/F18) | M18: =IF($B18="","",IF(J18>0,"✖ Em atraso",IF(I18>0,"● A receber",IF(H18>0,"✓ Em dia","—"))))
F19: =IF($B19="","",COUNTIFS('Recebimentos'!$C$11:$C$1010,$B19,'Recebimentos'!$B$11:$B$1010,">="&DATE('Config'!$C$8,1,1),'Recebimentos'!$B$11:$B$1010,"<"&DATE('Config'!$C$8+1,1,1))) | G19: =IF($B19="","",SUMIFS('Recebimentos'!$E$11:$E$1010,'Recebimentos'!$C$11:$C$1010,$B19,'Recebimentos'!$B$11:$B$1010,">="&DATE('Config'!$C$8,1,1),'Recebimentos'!$B$11:$B$1010,"<"&DATE('Config'!$C$8+1,1,1))) | H19: =IF($B19="","",SUMIFS('Recebimentos'!$E$11:$E$1010,'Recebimentos'!$C$11:$C$1010,$B19,'Recebimentos'!$G$11:$G$1010,">="&DATE('Config'!$C$8,1,1),'Recebimentos'!$G$11:$G$1010,"<"&DATE('Config'!$C$8+1,1,1))) | I19: =IF($B19="","",SUMIFS('Recebimentos'!$K$11:$K$1010,'Recebimentos'!$C$11:$C$1010,$B19)) | J19: =IF($B19="","",SUMIFS('Recebimentos'!$L$11:$L$1010,'Recebimentos'!$C$11:$C$1010,$B19)) | K19: =IF($B19="","",IF($H$38=0,0,H19/$H$38)) | L19: =IF(OR($B19="",N(F19)=0),"",G19/F19) | M19: =IF($B19="","",IF(J19>0,"✖ Em atraso",IF(I19>0,"● A receber",IF(H19>0,"✓ Em dia","—"))))
F20: =IF($B20="","",COUNTIFS('Recebimentos'!$C$11:$C$1010,$B20,'Recebimentos'!$B$11:$B$1010,">="&DATE('Config'!$C$8,1,1),'Recebimentos'!$B$11:$B$1010,"<"&DATE('Config'!$C$8+1,1,1))) | G20: =IF($B20="","",SUMIFS('Recebimentos'!$E$11:$E$1010,'Recebimentos'!$C$11:$C$1010,$B20,'Recebimentos'!$B$11:$B$1010,">="&DATE('Config'!$C$8,1,1),'Recebimentos'!$B$11:$B$1010,"<"&DATE('Config'!$C$8+1,1,1))) | H20: =IF($B20="","",SUMIFS('Recebimentos'!$E$11:$E$1010,'Recebimentos'!$C$11:$C$1010,$B20,'Recebimentos'!$G$11:$G$1010,">="&DATE('Config'!$C$8,1,1),'Recebimentos'!$G$11:$G$1010,"<"&DATE('Config'!$C$8+1,1,1))) | I20: =IF($B20="","",SUMIFS('Recebimentos'!$K$11:$K$1010,'Recebimentos'!$C$11:$C$1010,$B20)) | J20: =IF($B20="","",SUMIFS('Recebimentos'!$L$11:$L$1010,'Recebimentos'!$C$11:$C$1010,$B20)) | K20: =IF($B20="","",IF($H$38=0,0,H20/$H$38)) | L20: =IF(OR($B20="",N(F20)=0),"",G20/F20) | M20: =IF($B20="","",IF(J20>0,"✖ Em atraso",IF(I20>0,"● A receber",IF(H20>0,"✓ Em dia","—"))))
F21: =IF($B21="","",COUNTIFS('Recebimentos'!$C$11:$C$1010,$B21,'Recebimentos'!$B$11:$B$1010,">="&DATE('Config'!$C$8,1,1),'Recebimentos'!$B$11:$B$1010,"<"&DATE('Config'!$C$8+1,1,1))) | G21: =IF($B21="","",SUMIFS('Recebimentos'!$E$11:$E$1010,'Recebimentos'!$C$11:$C$1010,$B21,'Recebimentos'!$B$11:$B$1010,">="&DATE('Config'!$C$8,1,1),'Recebimentos'!$B$11:$B$1010,"<"&DATE('Config'!$C$8+1,1,1))) | H21: =IF($B21="","",SUMIFS('Recebimentos'!$E$11:$E$1010,'Recebimentos'!$C$11:$C$1010,$B21,'Recebimentos'!$G$11:$G$1010,">="&DATE('Config'!$C$8,1,1),'Recebimentos'!$G$11:$G$1010,"<"&DATE('Config'!$C$8+1,1,1))) | I21: =IF($B21="","",SUMIFS('Recebimentos'!$K$11:$K$1010,'Recebimentos'!$C$11:$C$1010,$B21)) | J21: =IF($B21="","",SUMIFS('Recebimentos'!$L$11:$L$1010,'Recebimentos'!$C$11:$C$1010,$B21)) | K21: =IF($B21="","",IF($H$38=0,0,H21/$H$38)) | L21: =IF(OR($B21="",N(F21)=0),"",G21/F21) | M21: =IF($B21="","",IF(J21>0,"✖ Em atraso",IF(I21>0,"● A receber",IF(H21>0,"✓ Em dia","—"))))
F22: =IF($B22="","",COUNTIFS('Recebimentos'!$C$11:$C$1010,$B22,'Recebimentos'!$B$11:$B$1010,">="&DATE('Config'!$C$8,1,1),'Recebimentos'!$B$11:$B$1010,"<"&DATE('Config'!$C$8+1,1,1))) | G22: =IF($B22="","",SUMIFS('Recebimentos'!$E$11:$E$1010,'Recebimentos'!$C$11:$C$1010,$B22,'Recebimentos'!$B$11:$B$1010,">="&DATE('Config'!$C$8,1,1),'Recebimentos'!$B$11:$B$1010,"<"&DATE('Config'!$C$8+1,1,1))) | H22: =IF($B22="","",SUMIFS('Recebimentos'!$E$11:$E$1010,'Recebimentos'!$C$11:$C$1010,$B22,'Recebimentos'!$G$11:$G$1010,">="&DATE('Config'!$C$8,1,1),'Recebimentos'!$G$11:$G$1010,"<"&DATE('Config'!$C$8+1,1,1))) | I22: =IF($B22="","",SUMIFS('Recebimentos'!$K$11:$K$1010,'Recebimentos'!$C$11:$C$1010,$B22)) | J22: =IF($B22="","",SUMIFS('Recebimentos'!$L$11:$L$1010,'Recebimentos'!$C$11:$C$1010,$B22)) | K22: =IF($B22="","",IF($H$38=0,0,H22/$H$38)) | L22: =IF(OR($B22="",N(F22)=0),"",G22/F22) | M22: =IF($B22="","",IF(J22>0,"✖ Em atraso",IF(I22>0,"● A receber",IF(H22>0,"✓ Em dia","—"))))
F23: =IF($B23="","",COUNTIFS('Recebimentos'!$C$11:$C$1010,$B23,'Recebimentos'!$B$11:$B$1010,">="&DATE('Config'!$C$8,1,1),'Recebimentos'!$B$11:$B$1010,"<"&DATE('Config'!$C$8+1,1,1))) | G23: =IF($B23="","",SUMIFS('Recebimentos'!$E$11:$E$1010,'Recebimentos'!$C$11:$C$1010,$B23,'Recebimentos'!$B$11:$B$1010,">="&DATE('Config'!$C$8,1,1),'Recebimentos'!$B$11:$B$1010,"<"&DATE('Config'!$C$8+1,1,1))) | H23: =IF($B23="","",SUMIFS('Recebimentos'!$E$11:$E$1010,'Recebimentos'!$C$11:$C$1010,$B23,'Recebimentos'!$G$11:$G$1010,">="&DATE('Config'!$C$8,1,1),'Recebimentos'!$G$11:$G$1010,"<"&DATE('Config'!$C$8+1,1,1))) | I23: =IF($B23="","",SUMIFS('Recebimentos'!$K$11:$K$1010,'Recebimentos'!$C$11:$C$1010,$B23)) | J23: =IF($B23="","",SUMIFS('Recebimentos'!$L$11:$L$1010,'Recebimentos'!$C$11:$C$1010,$B23)) | K23: =IF($B23="","",IF($H$38=0,0,H23/$H$38)) | L23: =IF(OR($B23="",N(F23)=0),"",G23/F23) | M23: =IF($B23="","",IF(J23>0,"✖ Em atraso",IF(I23>0,"● A receber",IF(H23>0,"✓ Em dia","—"))))
F24: =IF($B24="","",COUNTIFS('Recebimentos'!$C$11:$C$1010,$B24,'Recebimentos'!$B$11:$B$1010,">="&DATE('Config'!$C$8,1,1),'Recebimentos'!$B$11:$B$1010,"<"&DATE('Config'!$C$8+1,1,1))) | G24: =IF($B24="","",SUMIFS('Recebimentos'!$E$11:$E$1010,'Recebimentos'!$C$11:$C$1010,$B24,'Recebimentos'!$B$11:$B$1010,">="&DATE('Config'!$C$8,1,1),'Recebimentos'!$B$11:$B$1010,"<"&DATE('Config'!$C$8+1,1,1))) | H24: =IF($B24="","",SUMIFS('Recebimentos'!$E$11:$E$1010,'Recebimentos'!$C$11:$C$1010,$B24,'Recebimentos'!$G$11:$G$1010,">="&DATE('Config'!$C$8,1,1),'Recebimentos'!$G$11:$G$1010,"<"&DATE('Config'!$C$8+1,1,1))) | I24: =IF($B24="","",SUMIFS('Recebimentos'!$K$11:$K$1010,'Recebimentos'!$C$11:$C$1010,$B24)) | J24: =IF($B24="","",SUMIFS('Recebimentos'!$L$11:$L$1010,'Recebimentos'!$C$11:$C$1010,$B24)) | K24: =IF($B24="","",IF($H$38=0,0,H24/$H$38)) | L24: =IF(OR($B24="",N(F24)=0),"",G24/F24) | M24: =IF($B24="","",IF(J24>0,"✖ Em atraso",IF(I24>0,"● A receber",IF(H24>0,"✓ Em dia","—"))))
F25: =IF($B25="","",COUNTIFS('Recebimentos'!$C$11:$C$1010,$B25,'Recebimentos'!$B$11:$B$1010,">="&DATE('Config'!$C$8,1,1),'Recebimentos'!$B$11:$B$1010,"<"&DATE('Config'!$C$8+1,1,1))) | G25: =IF($B25="","",SUMIFS('Recebimentos'!$E$11:$E$1010,'Recebimentos'!$C$11:$C$1010,$B25,'Recebimentos'!$B$11:$B$1010,">="&DATE('Config'!$C$8,1,1),'Recebimentos'!$B$11:$B$1010,"<"&DATE('Config'!$C$8+1,1,1))) | H25: =IF($B25="","",SUMIFS('Recebimentos'!$E$11:$E$1010,'Recebimentos'!$C$11:$C$1010,$B25,'Recebimentos'!$G$11:$G$1010,">="&DATE('Config'!$C$8,1,1),'Recebimentos'!$G$11:$G$1010,"<"&DATE('Config'!$C$8+1,1,1))) | I25: =IF($B25="","",SUMIFS('Recebimentos'!$K$11:$K$1010,'Recebimentos'!$C$11:$C$1010,$B25)) | J25: =IF($B25="","",SUMIFS('Recebimentos'!$L$11:$L$1010,'Recebimentos'!$C$11:$C$1010,$B25)) | K25: =IF($B25="","",IF($H$38=0,0,H25/$H$38)) | L25: =IF(OR($B25="",N(F25)=0),"",G25/F25) | M25: =IF($B25="","",IF(J25>0,"✖ Em atraso",IF(I25>0,"● A receber",IF(H25>0,"✓ Em dia","—"))))
F26: =IF($B26="","",COUNTIFS('Recebimentos'!$C$11:$C$1010,$B26,'Recebimentos'!$B$11:$B$1010,">="&DATE('Config'!$C$8,1,1),'Recebimentos'!$B$11:$B$1010,"<"&DATE('Config'!$C$8+1,1,1))) | G26: =IF($B26="","",SUMIFS('Recebimentos'!$E$11:$E$1010,'Recebimentos'!$C$11:$C$1010,$B26,'Recebimentos'!$B$11:$B$1010,">="&DATE('Config'!$C$8,1,1),'Recebimentos'!$B$11:$B$1010,"<"&DATE('Config'!$C$8+1,1,1))) | H26: =IF($B26="","",SUMIFS('Recebimentos'!$E$11:$E$1010,'Recebimentos'!$C$11:$C$1010,$B26,'Recebimentos'!$G$11:$G$1010,">="&DATE('Config'!$C$8,1,1),'Recebimentos'!$G$11:$G$1010,"<"&DATE('Config'!$C$8+1,1,1))) | I26: =IF($B26="","",SUMIFS('Recebimentos'!$K$11:$K$1010,'Recebimentos'!$C$11:$C$1010,$B26)) | J26: =IF($B26="","",SUMIFS('Recebimentos'!$L$11:$L$1010,'Recebimentos'!$C$11:$C$1010,$B26)) | K26: =IF($B26="","",IF($H$38=0,0,H26/$H$38)) | L26: =IF(OR($B26="",N(F26)=0),"",G26/F26) | M26: =IF($B26="","",IF(J26>0,"✖ Em atraso",IF(I26>0,"● A receber",IF(H26>0,"✓ Em dia","—"))))
F27: =IF($B27="","",COUNTIFS('Recebimentos'!$C$11:$C$1010,$B27,'Recebimentos'!$B$11:$B$1010,">="&DATE('Config'!$C$8,1,1),'Recebimentos'!$B$11:$B$1010,"<"&DATE('Config'!$C$8+1,1,1))) | G27: =IF($B27="","",SUMIFS('Recebimentos'!$E$11:$E$1010,'Recebimentos'!$C$11:$C$1010,$B27,'Recebimentos'!$B$11:$B$1010,">="&DATE('Config'!$C$8,1,1),'Recebimentos'!$B$11:$B$1010,"<"&DATE('Config'!$C$8+1,1,1))) | H27: =IF($B27="","",SUMIFS('Recebimentos'!$E$11:$E$1010,'Recebimentos'!$C$11:$C$1010,$B27,'Recebimentos'!$G$11:$G$1010,">="&DATE('Config'!$C$8,1,1),'Recebimentos'!$G$11:$G$1010,"<"&DATE('Config'!$C$8+1,1,1))) | I27: =IF($B27="","",SUMIFS('Recebimentos'!$K$11:$K$1010,'Recebimentos'!$C$11:$C$1010,$B27)) | J27: =IF($B27="","",SUMIFS('Recebimentos'!$L$11:$L$1010,'Recebimentos'!$C$11:$C$1010,$B27)) | K27: =IF($B27="","",IF($H$38=0,0,H27/$H$38)) | L27: =IF(OR($B27="",N(F27)=0),"",G27/F27) | M27: =IF($B27="","",IF(J27>0,"✖ Em atraso",IF(I27>0,"● A receber",IF(H27>0,"✓ Em dia","—"))))
... F37: =IF($B37="","",COUNTIFS('Recebimentos'!$C$11:$C$1010,$B37,'Recebimentos'!$B$11:$B$1010,">="&DATE('Config'!$C$8,1,1),'Recebimentos'!$B$11:$B$1010,"<"&DATE('Config'!$C$8+1,1,1))) | G37: =IF($B37="","",SUMIFS('Recebimentos'!$E$11:$E$1010,'Recebimentos'!$C$11:$C$1010,$B37,'Recebimentos'!$B$11:$B$1010,">="&DATE('Config'!$C$8,1,1),'Recebimentos'!$B$11:$B$1010,"<"&DATE('Config'!$C$8+1,1,1))) | H37: =IF($B37="","",SUMIFS('Recebimentos'!$E$11:$E$1010,'Recebimentos'!$C$11:$C$1010,$B37,'Recebimentos'!$G$11:$G$1010,">="&DATE('Config'!$C$8,1,1),'Recebimentos'!$G$11:$G$1010,"<"&DATE('Config'!$C$8+1,1,1))) | I37: =IF($B37="","",SUMIFS('Recebimentos'!$K$11:$K$1010,'Recebimentos'!$C$11:$C$1010,$B37)) | J37: =IF($B37="","",SUMIFS('Recebimentos'!$L$11:$L$1010,'Recebimentos'!$C$11:$C$1010,$B37)) | K37: =IF($B37="","",IF($H$38=0,0,H37/$H$38)) | L37: =IF(OR($B37="",N(F37)=0),"",G37/F37) | M37: =IF($B37="","",IF(J37>0,"✖ Em atraso",IF(I37>0,"● A receber",IF(H37>0,"✓ Em dia","—"))))
F38: =SUM(F8:F37) -> 42 | G38: =SUM(G8:G37) -> 62260 | H38: =SUM(H8:H37) -> 55530 | I38: =SUM(I8:I37) -> 6730 | J38: =SUM(J8:J37) -> 4430 | K38: =IF(H38=0,0,1) -> 1 | L38: =IF(F38=0,"",G38/F38) -> 1482.381
B40: =IF(H38=0,"",IF(MAX(K8:K37)>0.5,"⚠ Concentração alta: um único cliente responde por "&TEXT(MAX(K8:K37),"0%")&" da receita recebida. Diversificar reduz o risco.","✓ Receita bem distribuída entre clientes (maior cliente: "&TEXT(MAX(K8:K37),"0%")&").")) -> ✓ Receita bem distribuída entre clientes (maior cliente: 26%).

Sheet Recebimentos
B1: 🏠 Início | D1: 📊 Painel Geral | E1: 👤 Painel Pessoal | H1: 💼 Painel Negócio | K1: ⚙ Config
B2: PESSOAL | D2: 📝 Lançamentos | E2: 💳 Orçamento | H2: 📅 Resumo anual | K2: 🎯 Metas
B3: NEGÓCIO | D3: 📝 Lançamentos | E3: 🤝 Clientes | G3: 💰 Recebimentos | I3: 🧾 Impostos | L3: 📈 Fluxo de Caixa
B5: 💰 Recebimentos — cobranças e pagamentos de clientes
B6: Registre cada cobrança com vencimento. Quando o cliente pagar, preencha a data do pagamento: o status é automático.
B7: EM ABERTO (A RECEBER) | D7: EM ATRASO | E7: RECEBIDO NO ANO | G7: VERIFICAÇÃO AUTOMÁTICA
B8: =SUM('Recebimentos'!$K$11:$K$1010) -> 6730 | D8: =SUM('Recebimentos'!$L$11:$L$1010) -> 4430 | E8: =SUMIFS('Recebimentos'!$E$11:$E$1010,'Recebimentos'!$G$11:$G$1010,">="&DATE('Config'!$C$8,1,1),'Recebimentos'!$G$11:$G$1010,"<"&DATE('Config'!$C$8+1,1,1)) -> 55530 | G8: =IF(SUMPRODUCT(('Recebimentos'!$E$11:$E$1010>0)*('Recebimentos'!$C$11:$C$1010=""))>0,"⚠ "&SUMPRODUCT(('Recebimentos'!$E$11:$E$1010>0)*('Recebimentos'!$C$11:$C$1010=""))&" cobrança(s) sem cliente",IF(SUMPRODUCT(('Recebimentos'!$E$11:$E$1010>0)*('Recebimentos'!$F$11:$F$1010="")*('Recebimentos'!$G$11:$G$1010=""))>0,"⚠ "&SUMPRODUCT(('Recebimentos'!$E$11:$E$1010>0)*('Recebimentos'!$F$11:$F$1010="")*('Recebimentos'!$G$11:$G$1010=""))&" cobrança(s) em aberto sem vencimento — informe para projetar o caixa","✓ Tudo certo: "&COUNT('Recebimentos'!$E$11:$E$1010)&" cobrança(s) registradas")) -> ✓ Tudo certo: 42 cobrança(s) registradas
B10: Data do serviço | C10: Cliente | D10: Descrição | E10: Valor (R$) | F10: Vencimento | G10: Data do pagamento | H10: Forma | I10: Status | J10: Dias de atraso | K10: Em aberto | L10: Em atraso | M10: aux.
B11: 46025 | C11: Studio Aurora | D11: Gestão de redes sociais – 01/2026 | E11: 1800 | F11: 46035 | G11: 46035 | H11: Pix | I11: =IF($E11="","",IF($G11<>"","Pago",IF($F11="","Pendente",IF('Config'!$C$9>$F11,"Atrasado","Pendente")))) -> Pago | J11: =IF($I11="Atrasado",'Config'!$C$9-$F11,"") | K11: =IF(AND($E11<>"",$G11=""),$E11,0) -> 0 | L11: =IF($I11="Atrasado",$E11,0) -> 0 | M11: =IF($I11="Atrasado",$J11+ROW()/1000000,0) -> 0
B12: 46027 | C12: Clínica Vida Plena | D12: Pacote de conteúdo mensal – 01/2026 | E12: 1500 | F12: 46037 | G12: 46039 | H12: Pix | I12: =IF($E12="","",IF($G12<>"","Pago",IF($F12="","Pendente",IF('Config'!$C$9>$F12,"Atrasado","Pendente")))) -> Pago | J12: =IF($I12="Atrasado",'Config'!$C$9-$F12,"") | K12: =IF(AND($E12<>"",$G12=""),$E12,0) -> 0 | L12: =IF($I12="Atrasado",$E12,0) -> 0 | M12: =IF($I12="Atrasado",$J12+ROW()/1000000,0) -> 0
B13: 46036 | C13: Tech Nova Ltda | D13: Identidade visual completa | E13: 3200 | F13: 46051 | G13: 46056 | H13: Pix | I13: =IF($E13="","",IF($G13<>"","Pago",IF($F13="","Pendente",IF('Config'!$C$9>$F13,"Atrasado","Pendente")))) -> Pago | J13: =IF($I13="Atrasado",'Config'!$C$9-$F13,"") | K13: =IF(AND($E13<>"",$G13=""),$E13,0) -> 0 | L13: =IF($I13="Atrasado",$E13,0) -> 0 | M13: =IF($I13="Atrasado",$J13+ROW()/1000000,0) -> 0
B14: 46056 | C14: Studio Aurora | D14: Gestão de redes sociais – 02/2026 | E14: 1800 | F14: 46066 | G14: 46066 | H14: Pix | I14: =IF($E14="","",IF($G14<>"","Pago",IF($F14="","Pendente",IF('Config'!$C$9>$F14,"Atrasado","Pendente")))) -> Pago | J14: =IF($I14="Atrasado",'Config'!$C$9-$F14,"") | K14: =IF(AND($E14<>"",$G14=""),$E14,0) -> 0 | L14: =IF($I14="Atrasado",$E14,0) -> 0 | M14: =IF($I14="Atrasado",$J14+ROW()/1000000,0) -> 0
B15: 46058 | C15: Clínica Vida Plena | D15: Pacote de conteúdo mensal – 02/2026 | E15: 1500 | F15: 46068 | G15: 46068 | H15: Pix | I15: =IF($E15="","",IF($G15<>"","Pago",IF($F15="","Pendente",IF('Config'!$C$9>$F15,"Atrasado","Pendente")))) -> Pago | J15: =IF($I15="Atrasado",'Config'!$C$9-$F15,"") | K15: =IF(AND($E15<>"",$G15=""),$E15,0) -> 0 | L15: =IF($I15="Atrasado",$E15,0) -> 0 | M15: =IF($I15="Atrasado",$J15+ROW()/1000000,0) -> 0
B16: 46073 | C16: Loja Bella Moda | D16: Catálogo digital | E16: 1850 | F16: 46088 | G16: 46093 | H16: Pix | I16: =IF($E16="","",IF($G16<>"","Pago",IF($F16="","Pendente",IF('Config'!$C$9>$F16,"Atrasado","Pendente")))) -> Pago | J16: =IF($I16="Atrasado",'Config'!$C$9-$F16,"") | K16: =IF(AND($E16<>"",$G16=""),$E16,0) -> 0 | L16: =IF($I16="Atrasado",$E16,0) -> 0 | M16: =IF($I16="Atrasado",$J16+ROW()/1000000,0) -> 0
B17: 46084 | C17: Studio Aurora | D17: Gestão de redes sociais – 03/2026 | E17: 1800 | F17: 46094 | G17: 46096 | H17: Pix | I17: =IF($E17="","",IF($G17<>"","Pago",IF($F17="","Pendente",IF('Config'!$C$9>$F17,"Atrasado","Pendente")))) -> Pago | J17: =IF($I17="Atrasado",'Config'!$C$9-$F17,"") | K17: =IF(AND($E17<>"",$G17=""),$E17,0) -> 0 | L17: =IF($I17="Atrasado",$E17,0) -> 0 | M17: =IF($I17="Atrasado",$J17+ROW()/1000000,0) -> 0
B18: 46086 | C18: Clínica Vida Plena | D18: Pacote de conteúdo mensal – 03/2026 | E18: 1500 | F18: 46096 | G18: 46098 | H18: Pix | I18: =IF($E18="","",IF($G18<>"","Pago",IF($F18="","Pendente",IF('Config'!$C$9>$F18,"Atrasado","Pendente")))) -> Pago | J18: =IF($I18="Atrasado",'Config'!$C$9-$F18,"") | K18: =IF(AND($E18<>"",$G18=""),$E18,0) -> 0 | L18: =IF($I18="Atrasado",$E18,0) -> 0 | M18: =IF($I18="Atrasado",$J18+ROW()/1000000,0) -> 0
B19: 46089 | C19: Padaria Dois Irmãos | D19: Materiais e cardápio – 03/2026 | E19: 650 | F19: 46099 | G19: 46098 | H19: Pix | I19: =IF($E19="","",IF($G19<>"","Pago",IF($F19="","Pendente",IF('Config'!$C$9>$F19,"Atrasado","Pendente")))) -> Pago | J19: =IF($I19="Atrasado",'Config'!$C$9-$F19,"") | K19: =IF(AND($E19<>"",$G19=""),$E19,0) -> 0 | L19: =IF($I19="Atrasado",$E19,0) -> 0 | M19: =IF($I19="Atrasado",$J19+ROW()/1000000,0) -> 0
B20: 46093 | C20: Maria Oliveira (PF) | D20: Logotipo e cartão de visita | E20: 780 | F20: 46108 | G20: 46110 | H20: Pix | I20: =IF($E20="","",IF($G20<>"","Pago",IF($F20="","Pendente",IF('Config'!$C$9>$F20,"Atrasado","Pendente")))) -> Pago | J20: =IF($I20="Atrasado",'Config'!$C$9-$F20,"") | K20: =IF(AND($E20<>"",$G20=""),$E20,0) -> 0 | L20: =IF($I20="Atrasado",$E20,0) -> 0 | M20: =IF($I20="Atrasado",$J20+ROW()/1000000,0) -> 0
B21: 46115 | C21: Studio Aurora | D21: Gestão de redes sociais – 04/2026 | E21: 1800 | F21: 46125 | G21: 46124 | H21: Pix | I21: =IF($E21="","",IF($G21<>"","Pago",IF($F21="","Pendente",IF('Config'!$C$9>$F21,"Atrasado","Pendente")))) -> Pago | J21: =IF($I21="Atrasado",'Config'!$C$9-$F21,"") | K21: =IF(AND($E21<>"",$G21=""),$E21,0) -> 0 | L21: =IF($I21="Atrasado",$E21,0) -> 0 | M21: =IF($I21="Atrasado",$J21+ROW()/1000000,0) -> 0
B22: 46117 | C22: Clínica Vida Plena | D22: Pacote de conteúdo mensal – 04/2026 | E22: 1500 | F22: 46127 | G22: 46129 | H22: Pix | I22: =IF($E22="","",IF($G22<>"","Pago",IF($F22="","Pendente",IF('Config'!$C$9>$F22,"Atrasado","Pendente")))) -> Pago | J22: =IF($I22="Atrasado",'Config'!$C$9-$F22,"") | K22: =IF(AND($E22<>"",$G22=""),$E22,0) -> 0 | L22: =IF($I22="Atrasado",$E22,0) -> 0 | M22: =IF($I22="Atrasado",$J22+ROW()/1000000,0) -> 0
... B43: 46242 | C43: Padaria Dois Irmãos | D43: Materiais e cardápio – 08/2026 | E43: 650 | F43: 46252 | G43: 46249 | H43: Pix | I43: =IF($E43="","",IF($G43<>"","Pago",IF($F43="","Pendente",IF('Config'!$C$9>$F43,"Atrasado","Pendente")))) -> Pago | J43: =IF($I43="Atrasado",'Config'!$C$9-$F43,"") | K43: =IF(AND($E43<>"",$G43=""),$E43,0) -> 0 | L43: =IF($I43="Atrasado",$E43,0) -> 0 | M43: =IF($I43="Atrasado",$J43+ROW()/1000000,0) -> 0
B44: 46246 | C44: Café do Centro | D44: Reimpressão de materiais | E44: 480 | F44: 46261 | H44: Pix | I44: =IF($E44="","",IF($G44<>"","Pago",IF($F44="","Pendente",IF('Config'!$C$9>$F44,"Atrasado","Pendente")))) -> Atrasado | J44: =IF($I44="Atrasado",'Config'!$C$9-$F44,"") -> 34 | K44: =IF(AND($E44<>"",$G44=""),$E44,0) -> 480 | L44: =IF($I44="Atrasado",$E44,0) -> 480 | M44: =IF($I44="Atrasado",$J44+ROW()/1000000,0) -> 34.000044
B45: 46252 | C45: Escola Horizonte | D45: Site institucional – 1ª parcela | E45: 2200 | F45: 46267 | G45: 46266 | H45: Pix | I45: =IF($E45="","",IF($G45<>"","Pago",IF($F45="","Pendente",IF('Config'!$C$9>$F45,"Atrasado","Pendente")))) -> Pago | J45: =IF($I45="Atrasado",'Config'!$C$9-$F45,"") | K45: =IF(AND($E45<>"",$G45=""),$E45,0) -> 0 | L45: =IF($I45="Atrasado",$E45,0) -> 0 | M45: =IF($I45="Atrasado",$J45+ROW()/1000000,0) -> 0
B46: 46267 | C46: Escola Horizonte | D46: Site institucional – 2ª parcela | E46: 2200 | F46: 46282 | G46: 46281 | H46: Pix | I46: =IF($E46="","",IF($G46<>"","Pago",IF($F46="","Pendente",IF('Config'!$C$9>$F46,"Atrasado","Pendente")))) -> Pago | J46: =IF($I46="Atrasado",'Config'!$C$9-$F46,"") | K46: =IF(AND($E46<>"",$G46=""),$E46,0) -> 0 | L46: =IF($I46="Atrasado",$E46,0) -> 0 | M46: =IF($I46="Atrasado",$J46+ROW()/1000000,0) -> 0
B47: 46268 | C47: Studio Aurora | D47: Gestão de redes sociais – 09/2026 | E47: 1800 | F47: 46278 | H47: Pix | I47: =IF($E47="","",IF($G47<>"","Pago",IF($F47="","Pendente",IF('Config'!$C$9>$F47,"Atrasado","Pendente")))) -> Atrasado | J47: =IF($I47="Atrasado",'Config'!$C$9-$F47,"") -> 17 | K47: =IF(AND($E47<>"",$G47=""),$E47,0) -> 1800 | L47: =IF($I47="Atrasado",$E47,0) -> 1800 | M47: =IF($I47="Atrasado",$J47+ROW()/1000000,0) -> 17.000047
B48: 46270 | C48: Clínica Vida Plena | D48: Pacote de conteúdo mensal – 09/2026 | E48: 1500 | F48: 46280 | H48: Pix | I48: =IF($E48="","",IF($G48<>"","Pago",IF($F48="","Pendente",IF('Config'!$C$9>$F48,"Atrasado","Pendente")))) -> Atrasado | J48: =IF($I48="Atrasado",'Config'!$C$9-$F48,"") -> 15 | K48: =IF(AND($E48<>"",$G48=""),$E48,0) -> 1500 | L48: =IF($I48="Atrasado",$E48,0) -> 1500 | M48: =IF($I48="Atrasado",$J48+ROW()/1000000,0) -> 15.000048
B49: 46273 | C49: Padaria Dois Irmãos | D49: Materiais e cardápio – 09/2026 | E49: 650 | F49: 46283 | H49: Pix | I49: =IF($E49="","",IF($G49<>"","Pago",IF($F49="","Pendente",IF('Config'!$C$9>$F49,"Atrasado","Pendente")))) -> Atrasado | J49: =IF($I49="Atrasado",'Config'!$C$9-$F49,"") -> 12 | K49: =IF(AND($E49<>"",$G49=""),$E49,0) -> 650 | L49: =IF($I49="Atrasado",$E49,0) -> 650 | M49: =IF($I49="Atrasado",$J49+ROW()/1000000,0) -> 12.000049
B50: 46274 | C50: Maria Oliveira (PF) | D50: Identidade para consultório | E50: 1500 | F50: 46289 | G50: 46291 | H50: Pix | I50: =IF($E50="","",IF($G50<>"","Pago",IF($F50="","Pendente",IF('Config'!$C$9>$F50,"Atrasado","Pendente")))) -> Pago | J50: =IF($I50="Atrasado",'Config'!$C$9-$F50,"") | K50: =IF(AND($E50<>"",$G50=""),$E50,0) -> 0 | L50: =IF($I50="Atrasado",$E50,0) -> 0 | M50: =IF($I50="Atrasado",$J50+ROW()/1000000,0) -> 0
B51: 46289 | C51: Tech Nova Ltda | D51: Manutenção da landing page | E51: 900 | F51: 46309 | H51: Pix | I51: =IF($E51="","",IF($G51<>"","Pago",IF($F51="","Pendente",IF('Config'!$C$9>$F51,"Atrasado","Pendente")))) -> Pendente | J51: =IF($I51="Atrasado",'Config'!$C$9-$F51,"") | K51: =IF(AND($E51<>"",$G51=""),$E51,0) -> 900 | L51: =IF($I51="Atrasado",$E51,0) -> 0 | M51: =IF($I51="Atrasado",$J51+ROW()/1000000,0) -> 0
B52: 46293 | C52: Loja Bella Moda | D52: Campanha Black Friday (sinal) | E52: 1400 | F52: 46318 | H52: Pix | I52: =IF($E52="","",IF($G52<>"","Pago",IF($F52="","Pendente",IF('Config'!$C$9>$F52,"Atrasado","Pendente")))) -> Pendente | J52: =IF($I52="Atrasado",'Config'!$C$9-$F52,"") | K52: =IF(AND($E52<>"",$G52=""),$E52,0) -> 1400 | L52: =IF($I52="Atrasado",$E52,0) -> 0 | M52: =IF($I52="Atrasado",$J52+ROW()/1000000,0) -> 0
I53: =IF($E53="","",IF($G53<>"","Pago",IF($F53="","Pendente",IF('Config'!$C$9>$F53,"Atrasado","Pendente")))) | J53: =IF($I53="Atrasado",'Config'!$C$9-$F53,"") | K53: =IF(AND($E53<>"",$G53=""),$E53,0) -> 0 | L53: =IF($I53="Atrasado",$E53,0) -> 0 | M53: =IF($I53="Atrasado",$J53+ROW()/1000000,0) -> 0
I54: =IF($E54="","",IF($G54<>"","Pago",IF($F54="","Pendente",IF('Config'!$C$9>$F54,"Atrasado","Pendente")))) | J54: =IF($I54="Atrasado",'Config'!$C$9-$F54,"") | K54: =IF(AND($E54<>"",$G54=""),$E54,0) -> 0 | L54: =IF($I54="Atrasado",$E54,0) -> 0 | M54: =IF($I54="Atrasado",$J54+ROW()/1000000,0) -> 0
I55: =IF($E55="","",IF($G55<>"","Pago",IF($F55="","Pendente",IF('Config'!$C$9>$F55,"Atrasado","Pendente")))) | J55: =IF($I55="Atrasado",'Config'!$C$9-$F55,"") | K55: =IF(AND($E55<>"",$G55=""),$E55,0) -> 0 | L55: =IF($I55="Atrasado",$E55,0) -> 0 | M55: =IF($I55="Atrasado",$J55+ROW()/1000000,0) -> 0
I56: =IF($E56="","",IF($G56<>"","Pago",IF($F56="","Pendente",IF('Config'!$C$9>$F56,"Atrasado","Pendente")))) | J56: =IF($I56="Atrasado",'Config'!$C$9-$F56,"") | K56: =IF(AND($E56<>"",$G56=""),$E56,0) -> 0 | L56: =IF($I56="Atrasado",$E56,0) -> 0 | M56: =IF($I56="Atrasado",$J56+ROW()/1000000,0) -> 0
I57: =IF($E57="","",IF($G57<>"","Pago",IF($F57="","Pendente",IF('Config'!$C$9>$F57,"Atrasado","Pendente")))) | J57: =IF($I57="Atrasado",'Config'!$C$9-$F57,"") | K57: =IF(AND($E57<>"",$G57=""),$E57,0) -> 0 | L57: =IF($I57="Atrasado",$E57,0) -> 0 | M57: =IF($I57="Atrasado",$J57+ROW()/1000000,0) -> 0
I58: =IF($E58="","",IF($G58<>"","Pago",IF($F58="","Pendente",IF('Config'!$C$9>$F58,"Atrasado","Pendente")))) | J58: =IF($I58="Atrasado",'Config'!$C$9-$F58,"") | K58: =IF(AND($E58<>"",$G58=""),$E58,0) -> 0 | L58: =IF($I58="Atrasado",$E58,0) -> 0 | M58: =IF($I58="Atrasado",$J58+ROW()/1000000,0) -> 0
I59: =IF($E59="","",IF($G59<>"","Pago",IF($F59="","Pendente",IF('Config'!$C$9>$F59,"Atrasado","Pendente")))) | J59: =IF($I59="Atrasado",'Config'!$C$9-$F59,"") | K59: =IF(AND($E59<>"",$G59=""),$E59,0) -> 0 | L59: =IF($I59="Atrasado",$E59,0) -> 0 | M59: =IF($I59="Atrasado",$J59+ROW()/1000000,0) -> 0
I60: =IF($E60="","",IF($G60<>"","Pago",IF($F60="","Pendente",IF('Config'!$C$9>$F60,"Atrasado","Pendente")))) | J60: =IF($I60="Atrasado",'Config'!$C$9-$F60,"") | K60: =IF(AND($E60<>"",$G60=""),$E60,0) -> 0 | L60: =IF($I60="Atrasado",$E60,0) -> 0 | M60: =IF($I60="Atrasado",$J60+ROW()/1000000,0) -> 0
I61: =IF($E61="","",IF($G61<>"","Pago",IF($F61="","Pendente",IF('Config'!$C$9>$F61,"Atrasado","Pendente")))) | J61: =IF($I61="Atrasado",'Config'!$C$9-$F61,"") | K61: =IF(AND($E61<>"",$G61=""),$E61,0) -> 0 | L61: =IF($I61="Atrasado",$E61,0) -> 0 | M61: =IF($I61="Atrasado",$J61+ROW()/1000000,0) -> 0
I62: =IF($E62="","",IF($G62<>"","Pago",IF($F62="","Pendente",IF('Config'!$C$9>$F62,"Atrasado","Pendente")))) | J62: =IF($I62="Atrasado",'Config'!$C$9-$F62,"") | K62: =IF(AND($E62<>"",$G62=""),$E62,0) -> 0 | L62: =IF($I62="Atrasado",$E62,0) -> 0 | M62: =IF($I62="Atrasado",$J62+ROW()/1000000,0) -> 0
I63: =IF($E63="","",IF($G63<>"","Pago",IF($F63="","Pendente",IF('Config'!$C$9>$F63,"Atrasado","Pendente")))) | J63: =IF($I63="Atrasado",'Config'!$C$9-$F63,"") | K63: =IF(AND($E63<>"",$G63=""),$E63,0) -> 0 | L63: =IF($I63="Atrasado",$E63,0) -> 0 | M63: =IF($I63="Atrasado",$J63+ROW()/1000000,0) -> 0
I64: =IF($E64="","",IF($G64<>"","Pago",IF($F64="","Pendente",IF('Config'!$C$9>$F64,"Atrasado","Pendente")))) | J64: =IF($I64="Atrasado",'Config'!$C$9-$F64,"") | K64: =IF(AND($E64<>"",$G64=""),$E64,0) -> 0 | L64: =IF($I64="Atrasado",$E64,0) -> 0 | M64: =IF($I64="Atrasado",$J64+ROW()/1000000,0) -> 0
... I1010: =IF($E1010="","",IF($G1010<>"","Pago",IF($F1010="","Pendente",IF('Config'!$C$9>$F1010,"Atrasado","Pendente")))) | J1010: =IF($I1010="Atrasado",'Config'!$C$9-$F1010,"") | K1010: =IF(AND($E1010<>"",$G1010=""),$E1010,0) -> 0 | L1010: =IF($I1010="Atrasado",$E1010,0) -> 0 | M1010: =IF($I1010="Atrasado",$J1010+ROW()/1000000,0) -> 0

Sheet Impostos
B1: 🏠 Início | D1: 📊 Painel Geral | G1: 👤 Painel Pessoal | J1: 💼 Painel Negócio | L1: ⚙ Config
B2: PESSOAL | D2: 📝 Lançamentos | G2: 💳 Orçamento | J2: 📅 Resumo anual | L2: 🎯 Metas
B3: NEGÓCIO | D3: 📝 Lançamentos | F3: 🤝 Clientes | H3: 💰 Recebimentos | J3: 🧾 Impostos | L3: 📈 Fluxo de Caixa
B5: 🧾 Impostos — DAS do MEI, vencimentos e limite anual
B6: Escolha seu regime e confira os parâmetros (amarelo). A tabela mostra o imposto de cada mês, vencimento e status.
B7: PARÂMETROS | H7: LIMITE ANUAL DO MEI
B8: Regime tributário | E8: MEI | H8: Receita bruta acumulada (até o mês de referência) | L8: =IF('Dados'!$C$10=0,0,INDEX($L$23:$L$34,'Dados'!$C$10)) -> 56508.59
B9: Atividade do MEI | E9: Serviços | H9: Limite proporcional ao período de atividade | L9: =('Impostos'!$E$15/12*(13-'Impostos'!$E$16)) -> 81000
B10: Salário mínimo vigente (R$) | E10: 1621 | H10: % do limite utilizado | L10: =IF(('Impostos'!$E$15/12*(13-'Impostos'!$E$16))=0,0,IF('Dados'!$C$10=0,0,INDEX($L$23:$L$34,'Dados'!$C$10))/('Impostos'!$E$15/12*(13-'Impostos'!$E$16))) -> 0.69763691
B11: % de INSS do MEI (sobre o salário mínimo) | E11: 0.05 | H11: Projeção de faturamento no ano (ritmo atual) | L11: =IF('Dados'!$C$10=0,0,IF('Dados'!$C$10=0,0,INDEX($L$23:$L$34,'Dados'!$C$10))/MAX(1,'Dados'!$C$10-'Impostos'!$E$16+1)*(13-'Impostos'!$E$16)) -> 75344.787
B12: ICMS fixo — comércio/indústria (R$) | E12: 1 | H12: Projeção ÷ limite | L12: =IF(('Impostos'!$E$15/12*(13-'Impostos'!$E$16))=0,0,L11/('Impostos'!$E$15/12*(13-'Impostos'!$E$16))) -> 0.93018255
B13: ISS fixo — serviços (R$) | E13: 5 | H13: =IF('Impostos'!$E$8<>"MEI","ℹ Limite do MEI não se aplica ao regime selecionado.",IF(IF('Dados'!$C$10=0,0,INDEX($L$23:$L$34,'Dados'!$C$10))>('Impostos'!$E$15/12*(13-'Impostos'!$E$16)),"✖ Limite ultrapassado! Procure seu contador: o excesso pode exigir DAS complementar ou desenquadramento.",IF(L11>('Impostos'!$E$15/12*(13-'Impostos'!$E$16)),"⚠ Pelo ritmo atual você ultrapassa o limite antes do fim do ano. Avalie com seu contador.",IF($L$10>=0.8,"⚠ Atenção: mais de 80% do limite anual já foi utilizado.","✓ Dentro do limite anual do MEI.")))) -> ✓ Dentro do limite anual do MEI.
B14: Alíquota sobre a receita (Simples/outro) | E14: 0.06
B15: Limite anual de faturamento do MEI (R$) | E15: 81000
B16: Início da atividade neste ano (mês 1-12) | E16: 1 | H16: Até 20% acima do limite: DAS complementar. Acima de 20%: desenquadramento retroativo (consulte seu contador).
B17: Valor do DAS mensal (calculado) | E17: ='Impostos'!$E$10*'Impostos'!$E$11+IF(OR('Impostos'!$E$9="Comércio e indústria",'Impostos'!$E$9="Comércio e serviços"),'Impostos'!$E$12,0)+IF(OR('Impostos'!$E$9="Serviços",'Impostos'!$E$9="Comércio e serviços"),'Impostos'!$E$13,0) -> 86.05 | H17: Entrega da DASN-SIMEI (declaração anual): até 31 de maio do ano seguinte.
B18: Valores de referência para 2026 (salário mínimo R$ 1.621; DAS-MEI = 5% do salário mínimo + ICMS/ISS fixos). Confirme sempre no Portal do Simples Nacional/Receita Federal, pois podem mudar. Para Simples Nacional ou outro regime, o imposto é estimado como % da receita recebida. Esta aba organiza — não substitui seu contador.
B22: Competência | C22: Receita recebida | D22: Imposto devido | E22: Vencimento | F22: Data do pagamento | G22: Valor pago (se diferente) | H22: Pago (R$) | I22: Status | J22: Em aberto | K22: Observação | L22: Receita acumulada | M22: Limite do período
B23: =DATE('Config'!$C$8,1,1) -> 46023 | C23: =SUMIFS('Recebimentos'!$E$11:$E$1010,'Recebimentos'!$G$11:$G$1010,">="&$B23,'Recebimentos'!$G$11:$G$1010,"<"&EDATE($B23,1))+IF('Config'!$N$8="",0,SUMIFS('Lanç. Negócio'!$F$11:$F$1510,'Lanç. Negócio'!$D$11:$D$1510,'Config'!$N$8,'Lanç. Negócio'!$B$11:$B$1510,">="&$B23,'Lanç. Negócio'!$B$11:$B$1510,"<"&EDATE($B23,1))) -> 3300 | D23: =IF($B23<DATE('Config'!$C$8,'Impostos'!$E$16,1),0,IF('Impostos'!$E$8="MEI",'Impostos'!$E$17,ROUND($C23*'Impostos'!$E$14,2))) -> 86.05 | E23: =DATE(YEAR($B23),MONTH($B23)+1,20) -> 46073 | F23: 46072 | H23: =IF($F23="",0,IF($G23="",$D23,$G23)) -> 86.05 | I23: =IF($D23=0,"—",IF($F23<>"","Pago",IF('Config'!$C$9>$E23,"Atrasado",IF($B23>'Config'!$C$9,"Futuro","A pagar")))) -> Pago | J23: =IF(AND($D23>0,$F23=""),$D23,0) -> 0 | L23: =SUM($C$23:C23) -> 3300 | M23: ='Impostos'!$E$15/12*(13-'Impostos'!$E$16) -> 81000
B24: =DATE('Config'!$C$8,2,1) -> 46054 | C24: =SUMIFS('Recebimentos'!$E$11:$E$1010,'Recebimentos'!$G$11:$G$1010,">="&$B24,'Recebimentos'!$G$11:$G$1010,"<"&EDATE($B24,1))+IF('Config'!$N$8="",0,SUMIFS('Lanç. Negócio'!$F$11:$F$1510,'Lanç. Negócio'!$D$11:$D$1510,'Config'!$N$8,'Lanç. Negócio'!$B$11:$B$1510,">="&$B24,'Lanç. Negócio'!$B$11:$B$1510,"<"&EDATE($B24,1))) -> 6838.99 | D24: =IF($B24<DATE('Config'!$C$8,'Impostos'!$E$16,1),0,IF('Impostos'!$E$8="MEI",'Impostos'!$E$17,ROUND($C24*'Impostos'!$E$14,2))) -> 86.05 | E24: =DATE(YEAR($B24),MONTH($B24)+1,20) -> 46101 | F24: 46099 | H24: =IF($F24="",0,IF($G24="",$D24,$G24)) -> 86.05 | I24: =IF($D24=0,"—",IF($F24<>"","Pago",IF('Config'!$C$9>$E24,"Atrasado",IF($B24>'Config'!$C$9,"Futuro","A pagar")))) -> Pago | J24: =IF(AND($D24>0,$F24=""),$D24,0) -> 0 | L24: =SUM($C$23:C24) -> 10138.99 | M24: ='Impostos'!$E$15/12*(13-'Impostos'!$E$16) -> 81000
B25: =DATE('Config'!$C$8,3,1) -> 46082 | C25: =SUMIFS('Recebimentos'!$E$11:$E$1010,'Recebimentos'!$G$11:$G$1010,">="&$B25,'Recebimentos'!$G$11:$G$1010,"<"&EDATE($B25,1))+IF('Config'!$N$8="",0,SUMIFS('Lanç. Negócio'!$F$11:$F$1510,'Lanç. Negócio'!$D$11:$D$1510,'Config'!$N$8,'Lanç. Negócio'!$B$11:$B$1510,">="&$B25,'Lanç. Negócio'!$B$11:$B$1510,"<"&EDATE($B25,1))) -> 6580 | D25: =IF($B25<DATE('Config'!$C$8,'Impostos'!$E$16,1),0,IF('Impostos'!$E$8="MEI",'Impostos'!$E$17,ROUND($C25*'Impostos'!$E$14,2))) -> 86.05 | E25: =DATE(YEAR($B25),MONTH($B25)+1,20) -> 46132 | F25: 46130 | H25: =IF($F25="",0,IF($G25="",$D25,$G25)) -> 86.05 | I25: =IF($D25=0,"—",IF($F25<>"","Pago",IF('Config'!$C$9>$E25,"Atrasado",IF($B25>'Config'!$C$9,"Futuro","A pagar")))) -> Pago | J25: =IF(AND($D25>0,$F25=""),$D25,0) -> 0 | L25: =SUM($C$23:C25) -> 16718.99 | M25: ='Impostos'!$E$15/12*(13-'Impostos'!$E$16) -> 81000
B26: =DATE('Config'!$C$8,4,1) -> 46113 | C26: =SUMIFS('Recebimentos'!$E$11:$E$1010,'Recebimentos'!$G$11:$G$1010,">="&$B26,'Recebimentos'!$G$11:$G$1010,"<"&EDATE($B26,1))+IF('Config'!$N$8="",0,SUMIFS('Lanç. Negócio'!$F$11:$F$1510,'Lanç. Negócio'!$D$11:$D$1510,'Config'!$N$8,'Lanç. Negócio'!$B$11:$B$1510,">="&$B26,'Lanç. Negócio'!$B$11:$B$1510,"<"&EDATE($B26,1))) -> 6350 | D26: =IF($B26<DATE('Config'!$C$8,'Impostos'!$E$16,1),0,IF('Impostos'!$E$8="MEI",'Impostos'!$E$17,ROUND($C26*'Impostos'!$E$14,2))) -> 86.05 | E26: =DATE(YEAR($B26),MONTH($B26)+1,20) -> 46162 | F26: 46161 | H26: =IF($F26="",0,IF($G26="",$D26,$G26)) -> 86.05 | I26: =IF($D26=0,"—",IF($F26<>"","Pago",IF('Config'!$C$9>$E26,"Atrasado",IF($B26>'Config'!$C$9,"Futuro","A pagar")))) -> Pago | J26: =IF(AND($D26>0,$F26=""),$D26,0) -> 0 | L26: =SUM($C$23:C26) -> 23068.99 | M26: ='Impostos'!$E$15/12*(13-'Impostos'!$E$16) -> 81000
B27: =DATE('Config'!$C$8,5,1) -> 46143 | C27: =SUMIFS('Recebimentos'!$E$11:$E$1010,'Recebimentos'!$G$11:$G$1010,">="&$B27,'Recebimentos'!$G$11:$G$1010,"<"&EDATE($B27,1))+IF('Config'!$N$8="",0,SUMIFS('Lanç. Negócio'!$F$11:$F$1510,'Lanç. Negócio'!$D$11:$D$1510,'Config'!$N$8,'Lanç. Negócio'!$B$11:$B$1510,">="&$B27,'Lanç. Negócio'!$B$11:$B$1510,"<"&EDATE($B27,1))) -> 4900 | D27: =IF($B27<DATE('Config'!$C$8,'Impostos'!$E$16,1),0,IF('Impostos'!$E$8="MEI",'Impostos'!$E$17,ROUND($C27*'Impostos'!$E$14,2))) -> 86.05 | E27: =DATE(YEAR($B27),MONTH($B27)+1,20) -> 46193 | F27: 46191 | H27: =IF($F27="",0,IF($G27="",$D27,$G27)) -> 86.05 | I27: =IF($D27=0,"—",IF($F27<>"","Pago",IF('Config'!$C$9>$E27,"Atrasado",IF($B27>'Config'!$C$9,"Futuro","A pagar")))) -> Pago | J27: =IF(AND($D27>0,$F27=""),$D27,0) -> 0 | L27: =SUM($C$23:C27) -> 27968.99 | M27: ='Impostos'!$E$15/12*(13-'Impostos'!$E$16) -> 81000
B28: =DATE('Config'!$C$8,6,1) -> 46174 | C28: =SUMIFS('Recebimentos'!$E$11:$E$1010,'Recebimentos'!$G$11:$G$1010,">="&$B28,'Recebimentos'!$G$11:$G$1010,"<"&EDATE($B28,1))+IF('Config'!$N$8="",0,SUMIFS('Lanç. Negócio'!$F$11:$F$1510,'Lanç. Negócio'!$D$11:$D$1510,'Config'!$N$8,'Lanç. Negócio'!$B$11:$B$1510,">="&$B28,'Lanç. Negócio'!$B$11:$B$1510,"<"&EDATE($B28,1))) -> 8722.76 | D28: =IF($B28<DATE('Config'!$C$8,'Impostos'!$E$16,1),0,IF('Impostos'!$E$8="MEI",'Impostos'!$E$17,ROUND($C28*'Impostos'!$E$14,2))) -> 86.05 | E28: =DATE(YEAR($B28),MONTH($B28)+1,20) -> 46223 | F28: 46221 | H28: =IF($F28="",0,IF($G28="",$D28,$G28)) -> 86.05 | I28: =IF($D28=0,"—",IF($F28<>"","Pago",IF('Config'!$C$9>$E28,"Atrasado",IF($B28>'Config'!$C$9,"Futuro","A pagar")))) -> Pago | J28: =IF(AND($D28>0,$F28=""),$D28,0) -> 0 | L28: =SUM($C$23:C28) -> 36691.75 | M28: ='Impostos'!$E$15/12*(13-'Impostos'!$E$16) -> 81000
B29: =DATE('Config'!$C$8,7,1) -> 46204 | C29: =SUMIFS('Recebimentos'!$E$11:$E$1010,'Recebimentos'!$G$11:$G$1010,">="&$B29,'Recebimentos'!$G$11:$G$1010,"<"&EDATE($B29,1))+IF('Config'!$N$8="",0,SUMIFS('Lanç. Negócio'!$F$11:$F$1510,'Lanç. Negócio'!$D$11:$D$1510,'Config'!$N$8,'Lanç. Negócio'!$B$11:$B$1510,">="&$B29,'Lanç. Negócio'!$B$11:$B$1510,"<"&EDATE($B29,1))) -> 6250 | D29: =IF($B29<DATE('Config'!$C$8,'Impostos'!$E$16,1),0,IF('Impostos'!$E$8="MEI",'Impostos'!$E$17,ROUND($C29*'Impostos'!$E$14,2))) -> 86.05 | E29: =DATE(YEAR($B29),MONTH($B29)+1,20) -> 46254 | F29: 46253 | H29: =IF($F29="",0,IF($G29="",$D29,$G29)) -> 86.05 | I29: =IF($D29=0,"—",IF($F29<>"","Pago",IF('Config'!$C$9>$E29,"Atrasado",IF($B29>'Config'!$C$9,"Futuro","A pagar")))) -> Pago | J29: =IF(AND($D29>0,$F29=""),$D29,0) -> 0 | L29: =SUM($C$23:C29) -> 42941.75 | M29: ='Impostos'!$E$15/12*(13-'Impostos'!$E$16) -> 81000
B30: =DATE('Config'!$C$8,8,1) -> 46235 | C30: =SUMIFS('Recebimentos'!$E$11:$E$1010,'Recebimentos'!$G$11:$G$1010,">="&$B30,'Recebimentos'!$G$11:$G$1010,"<"&EDATE($B30,1))+IF('Config'!$N$8="",0,SUMIFS('Lanç. Negócio'!$F$11:$F$1510,'Lanç. Negócio'!$D$11:$D$1510,'Config'!$N$8,'Lanç. Negócio'!$B$11:$B$1510,">="&$B30,'Lanç. Negócio'!$B$11:$B$1510,"<"&EDATE($B30,1))) -> 7300 | D30: =IF($B30<DATE('Config'!$C$8,'Impostos'!$E$16,1),0,IF('Impostos'!$E$8="MEI",'Impostos'!$E$17,ROUND($C30*'Impostos'!$E$14,2))) -> 86.05 | E30: =DATE(YEAR($B30),MONTH($B30)+1,20) -> 46285 | F30: 46283 | H30: =IF($F30="",0,IF($G30="",$D30,$G30)) -> 86.05 | I30: =IF($D30=0,"—",IF($F30<>"","Pago",IF('Config'!$C$9>$E30,"Atrasado",IF($B30>'Config'!$C$9,"Futuro","A pagar")))) -> Pago | J30: =IF(AND($D30>0,$F30=""),$D30,0) -> 0 | L30: =SUM($C$23:C30) -> 50241.75 | M30: ='Impostos'!$E$15/12*(13-'Impostos'!$E$16) -> 81000
B31: =DATE('Config'!$C$8,9,1) -> 46266 | C31: =SUMIFS('Recebimentos'!$E$11:$E$1010,'Recebimentos'!$G$11:$G$1010,">="&$B31,'Recebimentos'!$G$11:$G$1010,"<"&EDATE($B31,1))+IF('Config'!$N$8="",0,SUMIFS('Lanç. Negócio'!$F$11:$F$1510,'Lanç. Negócio'!$D$11:$D$1510,'Config'!$N$8,'Lanç. Negócio'!$B$11:$B$1510,">="&$B31,'Lanç. Negócio'!$B$11:$B$1510,"<"&EDATE($B31,1))) -> 6266.84 | D31: =IF($B31<DATE('Config'!$C$8,'Impostos'!$E$16,1),0,IF('Impostos'!$E$8="MEI",'Impostos'!$E$17,ROUND($C31*'Impostos'!$E$14,2))) -> 86.05 | E31: =DATE(YEAR($B31),MONTH($B31)+1,20) -> 46315 | H31: =IF($F31="",0,IF($G31="",$D31,$G31)) -> 0 | I31: =IF($D31=0,"—",IF($F31<>"","Pago",IF('Config'!$C$9>$E31,"Atrasado",IF($B31>'Config'!$C$9,"Futuro","A pagar")))) -> A pagar | J31: =IF(AND($D31>0,$F31=""),$D31,0) -> 86.05 | L31: =SUM($C$23:C31) -> 56508.59 | M31: ='Impostos'!$E$15/12*(13-'Impostos'!$E$16) -> 81000
B32: =DATE('Config'!$C$8,10,1) -> 46296 | C32: =SUMIFS('Recebimentos'!$E$11:$E$1010,'Recebimentos'!$G$11:$G$1010,">="&$B32,'Recebimentos'!$G$11:$G$1010,"<"&EDATE($B32,1))+IF('Config'!$N$8="",0,SUMIFS('Lanç. Negócio'!$F$11:$F$1510,'Lanç. Negócio'!$D$11:$D$1510,'Config'!$N$8,'Lanç. Negócio'!$B$11:$B$1510,">="&$B32,'Lanç. Negócio'!$B$11:$B$1510,"<"&EDATE($B32,1))) -> 0 | D32: =IF($B32<DATE('Config'!$C$8,'Impostos'!$E$16,1),0,IF('Impostos'!$E$8="MEI",'Impostos'!$E$17,ROUND($C32*'Impostos'!$E$14,2))) -> 86.05 | E32: =DATE(YEAR($B32),MONTH($B32)+1,20) -> 46346 | H32: =IF($F32="",0,IF($G32="",$D32,$G32)) -> 0 | I32: =IF($D32=0,"—",IF($F32<>"","Pago",IF('Config'!$C$9>$E32,"Atrasado",IF($B32>'Config'!$C$9,"Futuro","A pagar")))) -> Futuro | J32: =IF(AND($D32>0,$F32=""),$D32,0) -> 86.05 | L32: =SUM($C$23:C32) -> 56508.59 | M32: ='Impostos'!$E$15/12*(13-'Impostos'!$E$16) -> 81000
B33: =DATE('Config'!$C$8,11,1) -> 46327 | C33: =SUMIFS('Recebimentos'!$E$11:$E$1010,'Recebimentos'!$G$11:$G$1010,">="&$B33,'Recebimentos'!$G$11:$G$1010,"<"&EDATE($B33,1))+IF('Config'!$N$8="",0,SUMIFS('Lanç. Negócio'!$F$11:$F$1510,'Lanç. Negócio'!$D$11:$D$1510,'Config'!$N$8,'Lanç. Negócio'!$B$11:$B$1510,">="&$B33,'Lanç. Negócio'!$B$11:$B$1510,"<"&EDATE($B33,1))) -> 0 | D33: =IF($B33<DATE('Config'!$C$8,'Impostos'!$E$16,1),0,IF('Impostos'!$E$8="MEI",'Impostos'!$E$17,ROUND($C33*'Impostos'!$E$14,2))) -> 86.05 | E33: =DATE(YEAR($B33),MONTH($B33)+1,20) -> 46376 | H33: =IF($F33="",0,IF($G33="",$D33,$G33)) -> 0 | I33: =IF($D33=0,"—",IF($F33<>"","Pago",IF('Config'!$C$9>$E33,"Atrasado",IF($B33>'Config'!$C$9,"Futuro","A pagar")))) -> Futuro | J33: =IF(AND($D33>0,$F33=""),$D33,0) -> 86.05 | L33: =SUM($C$23:C33) -> 56508.59 | M33: ='Impostos'!$E$15/12*(13-'Impostos'!$E$16) -> 81000
B34: =DATE('Config'!$C$8,12,1) -> 46357 | C34: =SUMIFS('Recebimentos'!$E$11:$E$1010,'Recebimentos'!$G$11:$G$1010,">="&$B34,'Recebimentos'!$G$11:$G$1010,"<"&EDATE($B34,1))+IF('Config'!$N$8="",0,SUMIFS('Lanç. Negócio'!$F$11:$F$1510,'Lanç. Negócio'!$D$11:$D$1510,'Config'!$N$8,'Lanç. Negócio'!$B$11:$B$1510,">="&$B34,'Lanç. Negócio'!$B$11:$B$1510,"<"&EDATE($B34,1))) -> 0 | D34: =IF($B34<DATE('Config'!$C$8,'Impostos'!$E$16,1),0,IF('Impostos'!$E$8="MEI",'Impostos'!$E$17,ROUND($C34*'Impostos'!$E$14,2))) -> 86.05 | E34: =DATE(YEAR($B34),MONTH($B34)+1,20) -> 46407 | H34: =IF($F34="",0,IF($G34="",$D34,$G34)) -> 0 | I34: =IF($D34=0,"—",IF($F34<>"","Pago",IF('Config'!$C$9>$E34,"Atrasado",IF($B34>'Config'!$C$9,"Futuro","A pagar")))) -> Futuro | J34: =IF(AND($D34>0,$F34=""),$D34,0) -> 86.05 | L34: =SUM($C$23:C34) -> 56508.59 | M34: ='Impostos'!$E$15/12*(13-'Impostos'!$E$16) -> 81000
B35: TOTAL | C35: =SUM(C23:C34) -> 56508.59 | D35: =SUM(D23:D34) -> 1032.6 | H35: =SUM(H23:H34) -> 688.4 | J35: =SUM(J23:J34) -> 344.2

Sheet Fluxo de Caixa
B1: 🏠 Início | C1: 📊 Painel Geral | F1: 👤 Painel Pessoal | I1: 💼 Painel Negócio | M1: ⚙ Config
B2: PESSOAL | C2: 📝 Lançamentos | F2: 💳 Orçamento | I2: 📅 Resumo anual | M2: 🎯 Metas
B3: NEGÓCIO | C3: 📝 Lançamentos | E3: 🤝 Clientes | H3: 💰 Recebimentos | K3: 🧾 Impostos | N3: 📈 Fluxo de Caixa
B5: 📈 Fluxo de caixa do negócio — realizado e projetado
B6: Até o mês de referência os números são REALIZADOS; depois, PROJETADOS (a receber em aberto, DAS em aberto, média de despesas e pró-labore previsto).
B7: PREMISSAS
B8: Saldo do caixa em 1º de janeiro (R$) | C8: 4000
B9: Pró-labore mensal previsto (R$) | C9: 4500
B10: Despesa operacional média (R$) | C10: =IF('Dados'!$C$10=0,0,SUMPRODUCT((COLUMN($C$80:$N$80)-2<='Dados'!$C$10)*$C$80:$N$80)/'Dados'!$C$10) -> 1682.0011
B11: Mês de referência (último realizado) | C11: =IF('Dados'!$C$10=0,"nenhum",INDEX('Config'!$K$8:$K$19,'Dados'!$C$10)) -> Setembro
B12: Receita média mensal realizada (R$) | C12: =IF('Dados'!$C$10=0,0,SUMPRODUCT((COLUMN($C$19:$N$19)-2<='Dados'!$C$10)*($C$19:$N$19+$C$20:$N$20))/'Dados'!$C$10) -> 6278.7322
B13: % da receita média esperada nos meses futuros | C13: 0.8
C15: =DATE('Config'!$C$8,1,1) -> 46023 | D15: =DATE('Config'!$C$8,2,1) -> 46054 | E15: =DATE('Config'!$C$8,3,1) -> 46082 | F15: =DATE('Config'!$C$8,4,1) -> 46113 | G15: =DATE('Config'!$C$8,5,1) -> 46143 | H15: =DATE('Config'!$C$8,6,1) -> 46174 | I15: =DATE('Config'!$C$8,7,1) -> 46204 | J15: =DATE('Config'!$C$8,8,1) -> 46235 | K15: =DATE('Config'!$C$8,9,1) -> 46266 | L15: =DATE('Config'!$C$8,10,1) -> 46296 | M15: =DATE('Config'!$C$8,11,1) -> 46327 | N15: =DATE('Config'!$C$8,12,1) -> 46357
B16: Em R$ | C16: =INDEX('Config'!$L$8:$L$19,1) -> Jan | D16: =INDEX('Config'!$L$8:$L$19,2) -> Fev | E16: =INDEX('Config'!$L$8:$L$19,3) -> Mar | F16: =INDEX('Config'!$L$8:$L$19,4) -> Abr | G16: =INDEX('Config'!$L$8:$L$19,5) -> Mai | H16: =INDEX('Config'!$L$8:$L$19,6) -> Jun | I16: =INDEX('Config'!$L$8:$L$19,7) -> Jul | J16: =INDEX('Config'!$L$8:$L$19,8) -> Ago | K16: =INDEX('Config'!$L$8:$L$19,9) -> Set | L16: =INDEX('Config'!$L$8:$L$19,10) -> Out | M16: =INDEX('Config'!$L$8:$L$19,11) -> Nov | N16: =INDEX('Config'!$L$8:$L$19,12) -> Dez | O16: Ano
C17: =IF(1<='Dados'!$C$10,"REALIZADO","PROJETADO") -> REALIZADO | D17: =IF(2<='Dados'!$C$10,"REALIZADO","PROJETADO") -> REALIZADO | E17: =IF(3<='Dados'!$C$10,"REALIZADO","PROJETADO") -> REALIZADO | F17: =IF(4<='Dados'!$C$10,"REALIZADO","PROJETADO") -> REALIZADO | G17: =IF(5<='Dados'!$C$10,"REALIZADO","PROJETADO") -> REALIZADO | H17: =IF(6<='Dados'!$C$10,"REALIZADO","PROJETADO") -> REALIZADO | I17: =IF(7<='Dados'!$C$10,"REALIZADO","PROJETADO") -> REALIZADO | J17: =IF(8<='Dados'!$C$10,"REALIZADO","PROJETADO") -> REALIZADO | K17: =IF(9<='Dados'!$C$10,"REALIZADO","PROJETADO") -> REALIZADO | L17: =IF(10<='Dados'!$C$10,"REALIZADO","PROJETADO") -> PROJETADO | M17: =IF(11<='Dados'!$C$10,"REALIZADO","PROJETADO") -> PROJETADO | N17: =IF(12<='Dados'!$C$10,"REALIZADO","PROJETADO") -> PROJETADO
B18: Saldo inicial do mês | C18: ='Fluxo de Caixa'!$C$8 -> 4000 | D18: =C29 -> 1220.81 | E18: =D29 -> 2113.33 | F18: =E29 -> 2264.85 | G18: =F29 -> 2373.63 | H18: =G29 -> 1475.8 | I18: =H29 -> 2876.95 | J18: =I29 -> 2697.06 | K18: =J29 -> 3971.5 | ... N18: =M29 -> 8422.0493 | O18: =C18 -> 4000
B19: (+) Recebimentos de clientes | C19: =IF(1<='Dados'!$C$10,SUMIFS('Recebimentos'!$E$11:$E$1010,'Recebimentos'!$G$11:$G$1010,">="&C$15,'Recebimentos'!$G$11:$G$1010,"<"&EDATE(C$15,1)),IF(1='Dados'!$C$10+1,SUMIFS('Recebimentos'!$K$11:$K$1010,'Recebimentos'!$F$11:$F$1010,"<"&EDATE(C$15,1)),SUMIFS('Recebimentos'!$K$11:$K$1010,'Recebimentos'!$F$11:$F$1010,">="&C$15,'Recebimentos'!$F$11:$F$1010,"<"&EDATE(C$15,1)))) -> 3300 | D19: =IF(2<='Dados'!$C$10,SUMIFS('Recebimentos'!$E$11:$E$1010,'Recebimentos'!$G$11:$G$1010,">="&D$15,'Recebimentos'!$G$11:$G$1010,"<"&EDATE(D$15,1)),IF(2='Dados'!$C$10+1,SUMIFS('Recebimentos'!$K$11:$K$1010,'Recebimentos'!$F$11:$F$1010,"<"&EDATE(D$15,1)),SUMIFS('Recebimentos'!$K$11:$K$1010,'Recebimentos'!$F$11:$F$1010,">="&D$15,'Recebimentos'!$F$11:$F$1010,"<"&EDATE(D$15,1)))) -> 6500 | E19: =IF(3<='Dados'!$C$10,SUMIFS('Recebimentos'!$E$11:$E$1010,'Recebimentos'!$G$11:$G$1010,">="&E$15,'Recebimentos'!$G$11:$G$1010,"<"&EDATE(E$15,1)),IF(3='Dados'!$C$10+1,SUMIFS('Recebimentos'!$K$11:$K$1010,'Recebimentos'!$F$11:$F$1010,"<"&EDATE(E$15,1)),SUMIFS('Recebimentos'!$K$11:$K$1010,'Recebimentos'!$F$11:$F$1010,">="&E$15,'Recebimentos'!$F$11:$F$1010,"<"&EDATE(E$15,1)))) -> 6580 | F19: =IF(4<='Dados'!$C$10,SUMIFS('Recebimentos'!$E$11:$E$1010,'Recebimentos'!$G$11:$G$1010,">="&F$15,'Recebimentos'!$G$11:$G$1010,"<"&EDATE(F$15,1)),IF(4='Dados'!$C$10+1,SUMIFS('Recebimentos'!$K$11:$K$1010,'Recebimentos'!$F$11:$F$1010,"<"&EDATE(F$15,1)),SUMIFS('Recebimentos'!$K$11:$K$1010,'Recebimentos'!$F$11:$F$1010,">="&F$15,'Recebimentos'!$F$11:$F$1010,"<"&EDATE(F$15,1)))) -> 6350 | G19: =IF(5<='Dados'!$C$10,SUMIFS('Recebimentos'!$E$11:$E$1010,'Recebimentos'!$G$11:$G$1010,">="&G$15,'Recebimentos'!$G$11:$G$1010,"<"&EDATE(G$15,1)),IF(5='Dados'!$C$10+1,SUMIFS('Recebimentos'!$K$11:$K$1010,'Recebimentos'!$F$11:$F$1010,"<"&EDATE(G$15,1)),SUMIFS('Recebimentos'!$K$11:$K$1010,'Recebimentos'!$F$11:$F$1010,">="&G$15,'Recebimentos'!$F$11:$F$1010,"<"&EDATE(G$15,1)))) -> 4900 | H19: =IF(6<='Dados'!$C$10,SUMIFS('Recebimentos'!$E$11:$E$1010,'Recebimentos'!$G$11:$G$1010,">="&H$15,'Recebimentos'!$G$11:$G$1010,"<"&EDATE(H$15,1)),IF(6='Dados'!$C$10+1,SUMIFS('Recebimentos'!$K$11:$K$1010,'Recebimentos'!$F$11:$F$1010,"<"&EDATE(H$15,1)),SUMIFS('Recebimentos'!$K$11:$K$1010,'Recebimentos'!$F$11:$F$1010,">="&H$15,'Recebimentos'!$F$11:$F$1010,"<"&EDATE(H$15,1)))) -> 8450 | I19: =IF(7<='Dados'!$C$10,SUMIFS('Recebimentos'!$E$11:$E$1010,'Recebimentos'!$G$11:$G$1010,">="&I$15,'Recebimentos'!$G$11:$G$1010,"<"&EDATE(I$15,1)),IF(7='Dados'!$C$10+1,SUMIFS('Recebimentos'!$K$11:$K$1010,'Recebimentos'!$F$11:$F$1010,"<"&EDATE(I$15,1)),SUMIFS('Recebimentos'!$K$11:$K$1010,'Recebimentos'!$F$11:$F$1010,">="&I$15,'Recebimentos'!$F$11:$F$1010,"<"&EDATE(I$15,1)))) -> 6250 | J19: =IF(8<='Dados'!$C$10,SUMIFS('Recebimentos'!$E$11:$E$1010,'Recebimentos'!$G$11:$G$1010,">="&J$15,'Recebimentos'!$G$11:$G$1010,"<"&EDATE(J$15,1)),IF(8='Dados'!$C$10+1,SUMIFS('Recebimentos'!$K$11:$K$1010,'Recebimentos'!$F$11:$F$1010,"<"&EDATE(J$15,1)),SUMIFS('Recebimentos'!$K$11:$K$1010,'Recebimentos'!$F$11:$F$1010,">="&J$15,'Recebimentos'!$F$11:$F$1010,"<"&EDATE(J$15,1)))) -> 7300 | K19: =IF(9<='Dados'!$C$10,SUMIFS('Recebimentos'!$E$11:$E$1010,'Recebimentos'!$G$11:$G$1010,">="&K$15,'Recebimentos'!$G$11:$G$1010,"<"&EDATE(K$15,1)),IF(9='Dados'!$C$10+1,SUMIFS('Recebimentos'!$K$11:$K$1010,'Recebimentos'!$F$11:$F$1010,"<"&EDATE(K$15,1)),SUMIFS('Recebimentos'!$K$11:$K$1010,'Recebimentos'!$F$11:$F$1010,">="&K$15,'Recebimentos'!$F$11:$F$1010,"<"&EDATE(K$15,1)))) -> 5900 | L19: =IF(10<='Dados'!$C$10,SUMIFS('Recebimentos'!$E$11:$E$1010,'Recebimentos'!$G$11:$G$1010,">="&L$15,'Recebimentos'!$G$11:$G$1010,"<"&EDATE(L$15,1)),IF(10='Dados'!$C$10+1,SUMIFS('Recebimentos'!$K$11:$K$1010,'Recebimentos'!$F$11:$F$1010,"<"&EDATE(L$15,1)),SUMIFS('Recebimentos'!$K$11:$K$1010,'Recebimentos'!$F$11:$F$1010,">="&L$15,'Recebimentos'!$F$11:$F$1010,"<"&EDATE(L$15,1)))) -> 6730 | M19: =IF(11<='Dados'!$C$10,SUMIFS('Recebimentos'!$E$11:$E$1010,'Recebimentos'!$G$11:$G$1010,">="&M$15,'Recebimentos'!$G$11:$G$1010,"<"&EDATE(M$15,1)),IF(11='Dados'!$C$10+1,SUMIFS('Recebimentos'!$K$11:$K$1010,'Recebimentos'!$F$11:$F$1010,"<"&EDATE(M$15,1)),SUMIFS('Recebimentos'!$K$11:$K$1010,'Recebimentos'!$F$11:$F$1010,">="&M$15,'Recebimentos'!$F$11:$F$1010,"<"&EDATE(M$15,1)))) -> 0 | N19: =IF(12<='Dados'!$C$10,SUMIFS('Recebimentos'!$E$11:$E$1010,'Recebimentos'!$G$11:$G$1010,">="&N$15,'Recebimentos'!$G$11:$G$1010,"<"&EDATE(N$15,1)),IF(12='Dados'!$C$10+1,SUMIFS('Recebimentos'!$K$11:$K$1010,'Recebimentos'!$F$11:$F$1010,"<"&EDATE(N$15,1)),SUMIFS('Recebimentos'!$K$11:$K$1010,'Recebimentos'!$F$11:$F$1010,">="&N$15,'Recebimentos'!$F$11:$F$1010,"<"&EDATE(N$15,1)))) -> 0 | O19: =SUM(C19:N19) -> 62260
B20: (+) Receitas avulsas | C20: =IF(1<='Dados'!$C$10,C53,0) -> 0 | D20: =IF(2<='Dados'!$C$10,D53,0) -> 338.99 | E20: =IF(3<='Dados'!$C$10,E53,0) -> 0 | F20: =IF(4<='Dados'!$C$10,F53,0) -> 0 | G20: =IF(5<='Dados'!$C$10,G53,0) -> 0 | H20: =IF(6<='Dados'!$C$10,H53,0) -> 272.76 | I20: =IF(7<='Dados'!$C$10,I53,0) -> 0 | J20: =IF(8<='Dados'!$C$10,J53,0) -> 0 | K20: =IF(9<='Dados'!$C$10,K53,0) -> 366.84 | L20: =IF(10<='Dados'!$C$10,L53,0) -> 0 | M20: =IF(11<='Dados'!$C$10,M53,0) -> 0 | N20: =IF(12<='Dados'!$C$10,N53,0) -> 0 | O20: =SUM(C20:N20) -> 978.59
B21: (+) Outras entradas | C21: =IF(1<='Dados'!$C$10,SUM(C54:C60),0) -> 0 | D21: =IF(2<='Dados'!$C$10,SUM(D54:D60),0) -> 0 | E21: =IF(3<='Dados'!$C$10,SUM(E54:E60),0) -> 0 | F21: =IF(4<='Dados'!$C$10,SUM(F54:F60),0) -> 0 | G21: =IF(5<='Dados'!$C$10,SUM(G54:G60),0) -> 0 | H21: =IF(6<='Dados'!$C$10,SUM(H54:H60),0) -> 0 | I21: =IF(7<='Dados'!$C$10,SUM(I54:I60),0) -> 0 | J21: =IF(8<='Dados'!$C$10,SUM(J54:J60),0) -> 0 | K21: =IF(9<='Dados'!$C$10,SUM(K54:K60),0) -> 0 | L21: =IF(10<='Dados'!$C$10,SUM(L54:L60),0) -> 0 | M21: =IF(11<='Dados'!$C$10,SUM(M54:M60),0) -> 0 | N21: =IF(12<='Dados'!$C$10,SUM(N54:N60),0) -> 0 | O21: =SUM(C21:N21) -> 0
B22: (+) Receita nova prevista (média × %) | C22: =IF(1<='Dados'!$C$10,0,'Fluxo de Caixa'!$C$12*'Fluxo de Caixa'!$C$13) -> 0 | D22: =IF(2<='Dados'!$C$10,0,'Fluxo de Caixa'!$C$12*'Fluxo de Caixa'!$C$13) -> 0 | E22: =IF(3<='Dados'!$C$10,0,'Fluxo de Caixa'!$C$12*'Fluxo de Caixa'!$C$13) -> 0 | F22: =IF(4<='Dados'!$C$10,0,'Fluxo de Caixa'!$C$12*'Fluxo de Caixa'!$C$13) -> 0 | G22: =IF(5<='Dados'!$C$10,0,'Fluxo de Caixa'!$C$12*'Fluxo de Caixa'!$C$13) -> 0 | H22: =IF(6<='Dados'!$C$10,0,'Fluxo de Caixa'!$C$12*'Fluxo de Caixa'!$C$13) -> 0 | I22: =IF(7<='Dados'!$C$10,0,'Fluxo de Caixa'!$C$12*'Fluxo de Caixa'!$C$13) -> 0 | J22: =IF(8<='Dados'!$C$10,0,'Fluxo de Caixa'!$C$12*'Fluxo de Caixa'!$C$13) -> 0 | K22: =IF(9<='Dados'!$C$10,0,'Fluxo de Caixa'!$C$12*'Fluxo de Caixa'!$C$13) -> 0 | L22: =IF(10<='Dados'!$C$10,0,'Fluxo de Caixa'!$C$12*'Fluxo de Caixa'!$C$13) -> 5022.9858 | M22: =IF(11<='Dados'!$C$10,0,'Fluxo de Caixa'!$C$12*'Fluxo de Caixa'!$C$13) -> 5022.9858 | N22: =IF(12<='Dados'!$C$10,0,'Fluxo de Caixa'!$C$12*'Fluxo de Caixa'!$C$13) -> 5022.9858 | O22: =SUM(C22:N22) -> 15068.957
B23: TOTAL DE ENTRADAS | C23: =SUM(C19:C22) -> 3300 | D23: =SUM(D19:D22) -> 6838.99 | E23: =SUM(E19:E22) -> 6580 | F23: =SUM(F19:F22) -> 6350 | G23: =SUM(G19:G22) -> 4900 | H23: =SUM(H19:H22) -> 8722.76 | I23: =SUM(I19:I22) -> 6250 | J23: =SUM(J19:J22) -> 7300 | ... N23: =SUM(N19:N22) -> 5022.9858 | O23: =SUM(C23:N23) -> 78307.547
B24: (−) Despesas operacionais | C24: =IF(1<='Dados'!$C$10,C80,'Fluxo de Caixa'!$C$10) -> 1579.19 | D24: =IF(2<='Dados'!$C$10,D80,'Fluxo de Caixa'!$C$10) -> 1360.42 | E24: =IF(3<='Dados'!$C$10,E80,'Fluxo de Caixa'!$C$10) -> 1842.43 | F24: =IF(4<='Dados'!$C$10,F80,'Fluxo de Caixa'!$C$10) -> 1655.17 | G24: =IF(5<='Dados'!$C$10,G80,'Fluxo de Caixa'!$C$10) -> 1211.78 | H24: =IF(6<='Dados'!$C$10,H80,'Fluxo de Caixa'!$C$10) -> 2735.56 | I24: =IF(7<='Dados'!$C$10,I80,'Fluxo de Caixa'!$C$10) -> 1843.84 | J24: =IF(8<='Dados'!$C$10,J80,'Fluxo de Caixa'!$C$10) -> 1439.51 | K24: =IF(9<='Dados'!$C$10,K80,'Fluxo de Caixa'!$C$10) -> 1470.11 | L24: =IF(10<='Dados'!$C$10,L80,'Fluxo de Caixa'!$C$10) -> 1682.0011 | M24: =IF(11<='Dados'!$C$10,M80,'Fluxo de Caixa'!$C$10) -> 1682.0011 | N24: =IF(12<='Dados'!$C$10,N80,'Fluxo de Caixa'!$C$10) -> 1682.0011 | O24: =SUM(C24:N24) -> 20184.013
B25: (−) Impostos (DAS / %) | C25: =IF(1<='Dados'!$C$10,SUMIFS('Impostos'!$H$23:$H$34,'Impostos'!$F$23:$F$34,">="&C$15,'Impostos'!$F$23:$F$34,"<"&EDATE(C$15,1)),IF(1='Dados'!$C$10+1,SUMIFS('Impostos'!$J$23:$J$34,'Impostos'!$E$23:$E$34,"<"&EDATE(C$15,1)),SUMIFS('Impostos'!$J$23:$J$34,'Impostos'!$E$23:$E$34,">="&C$15,'Impostos'!$E$23:$E$34,"<"&EDATE(C$15,1)))) -> 0 | D25: =IF(2<='Dados'!$C$10,SUMIFS('Impostos'!$H$23:$H$34,'Impostos'!$F$23:$F$34,">="&D$15,'Impostos'!$F$23:$F$34,"<"&EDATE(D$15,1)),IF(2='Dados'!$C$10+1,SUMIFS('Impostos'!$J$23:$J$34,'Impostos'!$E$23:$E$34,"<"&EDATE(D$15,1)),SUMIFS('Impostos'!$J$23:$J$34,'Impostos'!$E$23:$E$34,">="&D$15,'Impostos'!$E$23:$E$34,"<"&EDATE(D$15,1)))) -> 86.05 | E25: =IF(3<='Dados'!$C$10,SUMIFS('Impostos'!$H$23:$H$34,'Impostos'!$F$23:$F$34,">="&E$15,'Impostos'!$F$23:$F$34,"<"&EDATE(E$15,1)),IF(3='Dados'!$C$10+1,SUMIFS('Impostos'!$J$23:$J$34,'Impostos'!$E$23:$E$34,"<"&EDATE(E$15,1)),SUMIFS('Impostos'!$J$23:$J$34,'Impostos'!$E$23:$E$34,">="&E$15,'Impostos'!$E$23:$E$34,"<"&EDATE(E$15,1)))) -> 86.05 | F25: =IF(4<='Dados'!$C$10,SUMIFS('Impostos'!$H$23:$H$34,'Impostos'!$F$23:$F$34,">="&F$15,'Impostos'!$F$23:$F$34,"<"&EDATE(F$15,1)),IF(4='Dados'!$C$10+1,SUMIFS('Impostos'!$J$23:$J$34,'Impostos'!$E$23:$E$34,"<"&EDATE(F$15,1)),SUMIFS('Impostos'!$J$23:$J$34,'Impostos'!$E$23:$E$34,">="&F$15,'Impostos'!$E$23:$E$34,"<"&EDATE(F$15,1)))) -> 86.05 | G25: =IF(5<='Dados'!$C$10,SUMIFS('Impostos'!$H$23:$H$34,'Impostos'!$F$23:$F$34,">="&G$15,'Impostos'!$F$23:$F$34,"<"&EDATE(G$15,1)),IF(5='Dados'!$C$10+1,SUMIFS('Impostos'!$J$23:$J$34,'Impostos'!$E$23:$E$34,"<"&EDATE(G$15,1)),SUMIFS('Impostos'!$J$23:$J$34,'Impostos'!$E$23:$E$34,">="&G$15,'Impostos'!$E$23:$E$34,"<"&EDATE(G$15,1)))) -> 86.05 | H25: =IF(6<='Dados'!$C$10,SUMIFS('Impostos'!$H$23:$H$34,'Impostos'!$F$23:$F$34,">="&H$15,'Impostos'!$F$23:$F$34,"<"&EDATE(H$15,1)),IF(6='Dados'!$C$10+1,SUMIFS('Impostos'!$J$23:$J$34,'Impostos'!$E$23:$E$34,"<"&EDATE(H$15,1)),SUMIFS('Impostos'!$J$23:$J$34,'Impostos'!$E$23:$E$34,">="&H$15,'Impostos'!$E$23:$E$34,"<"&EDATE(H$15,1)))) -> 86.05 | I25: =IF(7<='Dados'!$C$10,SUMIFS('Impostos'!$H$23:$H$34,'Impostos'!$F$23:$F$34,">="&I$15,'Impostos'!$F$23:$F$34,"<"&EDATE(I$15,1)),IF(7='Dados'!$C$10+1,SUMIFS('Impostos'!$J$23:$J$34,'Impostos'!$E$23:$E$34,"<"&EDATE(I$15,1)),SUMIFS('Impostos'!$J$23:$J$34,'Impostos'!$E$23:$E$34,">="&I$15,'Impostos'!$E$23:$E$34,"<"&EDATE(I$15,1)))) -> 86.05 | J25: =IF(8<='Dados'!$C$10,SUMIFS('Impostos'!$H$23:$H$34,'Impostos'!$F$23:$F$34,">="&J$15,'Impostos'!$F$23:$F$34,"<"&EDATE(J$15,1)),IF(8='Dados'!$C$10+1,SUMIFS('Impostos'!$J$23:$J$34,'Impostos'!$E$23:$E$34,"<"&EDATE(J$15,1)),SUMIFS('Impostos'!$J$23:$J$34,'Impostos'!$E$23:$E$34,">="&J$15,'Impostos'!$E$23:$E$34,"<"&EDATE(J$15,1)))) -> 86.05 | K25: =IF(9<='Dados'!$C$10,SUMIFS('Impostos'!$H$23:$H$34,'Impostos'!$F$23:$F$34,">="&K$15,'Impostos'!$F$23:$F$34,"<"&EDATE(K$15,1)),IF(9='Dados'!$C$10+1,SUMIFS('Impostos'!$J$23:$J$34,'Impostos'!$E$23:$E$34,"<"&EDATE(K$15,1)),SUMIFS('Impostos'!$J$23:$J$34,'Impostos'!$E$23:$E$34,">="&K$15,'Impostos'!$E$23:$E$34,"<"&EDATE(K$15,1)))) -> 86.05 | L25: =IF(10<='Dados'!$C$10,SUMIFS('Impostos'!$H$23:$H$34,'Impostos'!$F$23:$F$34,">="&L$15,'Impostos'!$F$23:$F$34,"<"&EDATE(L$15,1)),IF(10='Dados'!$C$10+1,SUMIFS('Impostos'!$J$23:$J$34,'Impostos'!$E$23:$E$34,"<"&EDATE(L$15,1)),SUMIFS('Impostos'!$J$23:$J$34,'Impostos'!$E$23:$E$34,">="&L$15,'Impostos'!$E$23:$E$34,"<"&EDATE(L$15,1)))) -> 86.05 | M25: =IF(11<='Dados'!$C$10,SUMIFS('Impostos'!$H$23:$H$34,'Impostos'!$F$23:$F$34,">="&M$15,'Impostos'!$F$23:$F$34,"<"&EDATE(M$15,1)),IF(11='Dados'!$C$10+1,SUMIFS('Impostos'!$J$23:$J$34,'Impostos'!$E$23:$E$34,"<"&EDATE(M$15,1)),SUMIFS('Impostos'!$J$23:$J$34,'Impostos'!$E$23:$E$34,">="&M$15,'Impostos'!$E$23:$E$34,"<"&EDATE(M$15,1)))) -> 86.05 | N25: =IF(12<='Dados'!$C$10,SUMIFS('Impostos'!$H$23:$H$34,'Impostos'!$F$23:$F$34,">="&N$15,'Impostos'!$F$23:$F$34,"<"&EDATE(N$15,1)),IF(12='Dados'!$C$10+1,SUMIFS('Impostos'!$J$23:$J$34,'Impostos'!$E$23:$E$34,"<"&EDATE(N$15,1)),SUMIFS('Impostos'!$J$23:$J$34,'Impostos'!$E$23:$E$34,">="&N$15,'Impostos'!$E$23:$E$34,"<"&EDATE(N$15,1)))) -> 86.05 | O25: =SUM(C25:N25) -> 946.55
B26: (−) Pró-labore / retiradas | C26: =IF(1<='Dados'!$C$10,C63,'Fluxo de Caixa'!$C$9) -> 4500 | D26: =IF(2<='Dados'!$C$10,D63,'Fluxo de Caixa'!$C$9) -> 4500 | E26: =IF(3<='Dados'!$C$10,E63,'Fluxo de Caixa'!$C$9) -> 4500 | F26: =IF(4<='Dados'!$C$10,F63,'Fluxo de Caixa'!$C$9) -> 4500 | G26: =IF(5<='Dados'!$C$10,G63,'Fluxo de Caixa'!$C$9) -> 4500 | H26: =IF(6<='Dados'!$C$10,H63,'Fluxo de Caixa'!$C$9) -> 4500 | I26: =IF(7<='Dados'!$C$10,I63,'Fluxo de Caixa'!$C$9) -> 4500 | J26: =IF(8<='Dados'!$C$10,J63,'Fluxo de Caixa'!$C$9) -> 4500 | K26: =IF(9<='Dados'!$C$10,K63,'Fluxo de Caixa'!$C$9) -> 4500 | L26: =IF(10<='Dados'!$C$10,L63,'Fluxo de Caixa'!$C$9) -> 4500 | M26: =IF(11<='Dados'!$C$10,M63,'Fluxo de Caixa'!$C$9) -> 4500 | N26: =IF(12<='Dados'!$C$10,N63,'Fluxo de Caixa'!$C$9) -> 4500 | O26: =SUM(C26:N26) -> 54000
B27: TOTAL DE SAÍDAS | C27: =SUM(C24:C26) -> 6079.19 | D27: =SUM(D24:D26) -> 5946.47 | E27: =SUM(E24:E26) -> 6428.48 | F27: =SUM(F24:F26) -> 6241.22 | G27: =SUM(G24:G26) -> 5797.83 | H27: =SUM(H24:H26) -> 7321.61 | I27: =SUM(I24:I26) -> 6429.89 | J27: =SUM(J24:J26) -> 6025.56 | ... N27: =SUM(N24:N26) -> 6268.0511 | O27: =SUM(C27:N27) -> 75130.563
B28: Variação do caixa no mês | C28: =C23-C27 -> -2779.19 | D28: =D23-D27 -> 892.52 | E28: =E23-E27 -> 151.52 | F28: =F23-F27 -> 108.78 | G28: =G23-G27 -> -897.83 | H28: =H23-H27 -> 1401.15 | I28: =I23-I27 -> -179.89 | J28: =J23-J27 -> 1274.44 | ... N28: =N23-N27 -> -1245.0653 | O28: =SUM(C28:N28) -> 3176.984
B29: 💰 SALDO FINAL DO MÊS | C29: =C18+C28 -> 1220.81 | D29: =D18+D28 -> 2113.33 | E29: =E18+E28 -> 2264.85 | F29: =F18+F28 -> 2373.63 | G29: =G18+G28 -> 1475.8 | H29: =H18+H28 -> 2876.95 | I29: =I18+I28 -> 2697.06 | J29: =J18+J28 -> 3971.5 | ... N29: =N18+N28 -> 7176.984 | O29: =N29 -> 7176.984
B30: Resultado operacional (lucro de caixa) | C30: =C23-C24-C25 -> 1720.81 | D30: =D23-D24-D25 -> 5392.52 | E30: =E23-E24-E25 -> 4651.52 | F30: =F23-F24-F25 -> 4608.78 | G30: =G23-G24-G25 -> 3602.17 | H30: =H23-H24-H25 -> 5901.15 | I30: =I23-I24-I25 -> 4320.11 | J30: =J23-J24-J25 -> 5774.44 | ... N30: =N23-N24-N25 -> 3254.9347 | O30: =SUM(C30:N30) -> 57176.984
