Workbook

Sheet Início
B1: 🏠 Início | C1: 📊 Painel | D1: 📝 Lançamentos | F1: 💳 Orçamento | H1: 📅 Resumo Anual | J1: 🎯 Metas | L1: ⚙ Config
B3: Finanças em Dia — Pessoal
B4: Controle financeiro pessoal e doméstico • Excel e Google Sheets
B5: Bem-vindo(a)! Esta planilha organiza suas finanças do jeito mais simples: você só LANÇA os valores e todo o resto — resumos, gráficos, alertas e metas — é calculado automaticamente. Use o Painel para enxergar para onde o dinheiro vai e a aba Metas para transformar sonhos em planos.
B7: 🚀 COMECE EM 5 MINUTOS
B8: 1 | C8: Em ⚙ Config: confira o ANO, escreva seu nome e renomeie as categorias, se quiser.
B9: 2 | C9: Em 💳 Orçamento: informe a renda prevista e quanto pretende gastar em cada categoria.
B10: 3 | C10: Em 🎯 Metas: cadastre seus objetivos (reserva de emergência, viagem, carro...).
B11: 4 | C11: No dia a dia: registre cada entrada e saída em 📝 Lançamentos — escolha a categoria no menu suspenso.
B12: 5 | C12: Abra o 📊 Painel, escolha o mês e veja gráficos, alertas e a evolução das suas metas.
B14: 🗺 MAPA DA PLANILHA — clique no botão para navegar
B15: 📊 Painel | E15: Cartões, gráficos e alertas do mês escolhido: entradas, saídas, saldo e poupança.
B16: 📝 Lançamentos | E16: Registro de todas as entradas e saídas (tipo automático pela categoria).
B17: 💳 Orçamento | E17: Planejado × realizado por categoria, com barras de progresso e alertas.
B18: 📅 Resumo Anual | E18: Quadro mês a mês por categoria (entradas e saídas), com mapa de calor.
B19: 🎯 Metas | E19: Objetivos de economia, aporte mensal necessário e reserva de emergência.
B20: ⚙ Config | E20: Ano, nome, categorias, formas de pagamento e meta de poupança.
B22: 🎨 LEGENDA DE CORES
B23: Você preenche | D23: Fórmula (automático) | F23: Positivo / bom | H23: Atenção | J23: Negativo / alerta | L23: Informação
B25: 💡 DICAS IMPORTANTES
B26: • Google Sheets: envie o arquivo .xlsx para o Google Drive e abra com o Google Planilhas (ou Arquivo ▸ Importar). Os menus, gráficos, listas suspensas e cores funcionam igualmente.
B27: • Digite sempre valores POSITIVOS. Se a categoria for de entrada, o valor soma; se for de saída, subtrai — o tipo é automático.
B28: • Para começar um novo ano: salve uma cópia do arquivo, apague os lançamentos (colunas amarelas) e mude o ano em Config.
B29: • Não insira/apague linhas dentro das tabelas de fórmulas. Para ver mais lançamentos, use os filtros do cabeçalho; há espaço para 1500 linhas.
B30: • Cada aba tem botões de navegação no topo. Se algo parecer estranho, confira a faixa de VERIFICAÇÃO no topo de Lançamentos.
B32: Planilha educativa de organização financeira. Valores e exemplos são fictícios.

Sheet Painel
B1: 🏠 Início | C1: 📊 Painel | D1: 📝 Lançamentos | F1: 💳 Orçamento | H1: 📅 Resumo Anual | J1: 🎯 Metas | L1: ⚙ Config
B3: ="📊 Painel — "&'Config'!$C$8 -> 📊 Painel — Minhas Finanças
B4: Escolha o mês no menu suspenso: cartões, gráficos e alertas se atualizam sozinhos.
B5: 📅 Mês de análise | D5: =INDEX('Config'!$K$6:$K$17,MAX(1,'Dados'!$C$8)) -> Outubro | G5: Ano de referência | I5: ='Config'!$C$6 -> 2026 | J5: ← o ano e a meta de poupança ficam na aba Config
B7: ENTRADAS DO MÊS | D7: SAÍDAS DO MÊS | F7: SALDO DO MÊS | H7: TAXA DE POUPANÇA | J7: SALDO ACUMULADO | L7: MAIOR GASTO DO MÊS
B8: =INDEX('Resumo Anual'!$C$16:$N$16,'Dados'!$C$6) -> 0 | D8: =INDEX('Resumo Anual'!$C$34:$N$34,'Dados'!$C$6) -> 0 | F8: =INDEX('Resumo Anual'!$C$16:$N$16,'Dados'!$C$6)-INDEX('Resumo Anual'!$C$34:$N$34,'Dados'!$C$6) -> 0 | H8: =IF(INDEX('Resumo Anual'!$C$16:$N$16,'Dados'!$C$6)=0,0,INDEX('Resumo Anual'!$C$37:$N$37,'Dados'!$C$6)) -> 0 | J8: =INDEX('Resumo Anual'!$C$36:$N$36,'Dados'!$C$6) -> 0 | L8: ='Dados'!$J$16 -> —
B9: =IF('Dados'!$C$6=1,"—",IF(INDEX('Resumo Anual'!$C$16:$N$16,'Dados'!$C$6-1)=0,"—",IF(INDEX('Resumo Anual'!$C$16:$N$16,'Dados'!$C$6)>=INDEX('Resumo Anual'!$C$16:$N$16,'Dados'!$C$6-1),"▲ ","▼ ")&TEXT(ABS(INDEX('Resumo Anual'!$C$16:$N$16,'Dados'!$C$6)/INDEX('Resumo Anual'!$C$16:$N$16,'Dados'!$C$6-1)-1),"0%")&" vs mês anterior")) -> — | D9: =IF('Dados'!$C$6=1,"—",IF(INDEX('Resumo Anual'!$C$34:$N$34,'Dados'!$C$6-1)=0,"—",IF(INDEX('Resumo Anual'!$C$34:$N$34,'Dados'!$C$6)>=INDEX('Resumo Anual'!$C$34:$N$34,'Dados'!$C$6-1),"▲ ","▼ ")&TEXT(ABS(INDEX('Resumo Anual'!$C$34:$N$34,'Dados'!$C$6)/INDEX('Resumo Anual'!$C$34:$N$34,'Dados'!$C$6-1)-1),"0%")&" vs mês anterior")) -> — | F9: =IF(INDEX('Resumo Anual'!$C$16:$N$16,'Dados'!$C$6)-INDEX('Resumo Anual'!$C$34:$N$34,'Dados'!$C$6)>=0,"Sobrou dinheiro ✓","Gastou mais do que ganhou") -> Sobrou dinheiro ✓ | H9: ="Meta: "&TEXT('Config'!$C$9,"0%") -> Meta: 20% | J9: no ano, até o mês escolhido | L9: ='Dados'!$K$16 -> 0
B43: 🎯 METAS DE ECONOMIA
B44: Meta | E44: Guardado | G44: Valor alvo | I44: % | J44: Progresso | M44: Situação
B45: =IF('Metas'!$B$6="","",'Metas'!$B$6) | E45: =IF('Metas'!$B$6="","",'Metas'!$G$6) | G45: =IF('Metas'!$B$6="","",'Metas'!$C$6) | I45: =IF('Metas'!$H$6="","",'Metas'!$H$6) | J45: =IF('Metas'!$I$6="","",'Metas'!$I$6) | M45: =IF('Metas'!$B$6="","",'Metas'!$M$6)
B46: =IF('Metas'!$B$7="","",'Metas'!$B$7) | E46: =IF('Metas'!$B$7="","",'Metas'!$G$7) | G46: =IF('Metas'!$B$7="","",'Metas'!$C$7) | I46: =IF('Metas'!$H$7="","",'Metas'!$H$7) | J46: =IF('Metas'!$I$7="","",'Metas'!$I$7) | M46: =IF('Metas'!$B$7="","",'Metas'!$M$7)
B47: =IF('Metas'!$B$8="","",'Metas'!$B$8) | E47: =IF('Metas'!$B$8="","",'Metas'!$G$8) | G47: =IF('Metas'!$B$8="","",'Metas'!$C$8) | I47: =IF('Metas'!$H$8="","",'Metas'!$H$8) | J47: =IF('Metas'!$I$8="","",'Metas'!$I$8) | M47: =IF('Metas'!$B$8="","",'Metas'!$M$8)
B48: =IF('Metas'!$B$9="","",'Metas'!$B$9) | E48: =IF('Metas'!$B$9="","",'Metas'!$G$9) | G48: =IF('Metas'!$B$9="","",'Metas'!$C$9) | I48: =IF('Metas'!$H$9="","",'Metas'!$H$9) | J48: =IF('Metas'!$I$9="","",'Metas'!$I$9) | M48: =IF('Metas'!$B$9="","",'Metas'!$M$9)
B49: =IF('Metas'!$B$10="","",'Metas'!$B$10) | E49: =IF('Metas'!$B$10="","",'Metas'!$G$10) | G49: =IF('Metas'!$B$10="","",'Metas'!$C$10) | I49: =IF('Metas'!$H$10="","",'Metas'!$H$10) | J49: =IF('Metas'!$I$10="","",'Metas'!$I$10) | M49: =IF('Metas'!$B$10="","",'Metas'!$M$10)
B51: Veja todas as metas e o simulador de aportes na aba Metas.
B52: 🔔 ALERTAS E INSIGHTS DO MÊS
B53: =IF(AND(INDEX('Resumo Anual'!$C$16:$N$16,'Dados'!$C$6)=0,INDEX('Resumo Anual'!$C$34:$N$34,'Dados'!$C$6)=0),"ℹ Ainda não há lançamentos neste mês.",IF((INDEX('Resumo Anual'!$C$16:$N$16,'Dados'!$C$6)-INDEX('Resumo Anual'!$C$34:$N$34,'Dados'!$C$6))<0,"⚠ Você gastou R$ "&FIXED(-(INDEX('Resumo Anual'!$C$16:$N$16,'Dados'!$C$6)-INDEX('Resumo Anual'!$C$34:$N$34,'Dados'!$C$6)),2)&" a mais do que ganhou neste mês.","✓ Mês no azul: sobraram R$ "&FIXED((INDEX('Resumo Anual'!$C$16:$N$16,'Dados'!$C$6)-INDEX('Resumo Anual'!$C$34:$N$34,'Dados'!$C$6)),2)&" depois de todas as saídas.")) -> ℹ Ainda não há lançamentos neste mês.
B54: =IF('Orçamento'!$C$26=0,"ℹ Defina o orçamento por categoria na aba Orçamento para receber alertas de gastos.",IF('Dados'!$C$11=0,"✓ Nenhuma categoria acima do orçamento neste mês.","⚠ "&'Dados'!$C$11&" categoria(s) acima do orçamento planejado — veja a aba Orçamento.")) -> ℹ Defina o orçamento por categoria na aba Orçamento para receber alertas de gastos.
B55: =IF(INDEX('Resumo Anual'!$C$16:$N$16,'Dados'!$C$6)=0,"ℹ Registre suas entradas do mês para calcular a taxa de poupança.",IF(INDEX('Resumo Anual'!$C$37:$N$37,'Dados'!$C$6)>='Config'!$C$9,"✓ Meta de poupança atingida: "&TEXT(INDEX('Resumo Anual'!$C$37:$N$37,'Dados'!$C$6),"0%")&" (meta "&TEXT('Config'!$C$9,"0%")&").","⚠ Taxa de poupança de "&TEXT(INDEX('Resumo Anual'!$C$37:$N$37,'Dados'!$C$6),"0%")&", abaixo da meta de "&TEXT('Config'!$C$9,"0%")&".")) -> ℹ Registre suas entradas do mês para calcular a taxa de poupança.

Sheet Lançamentos
B1: 🏠 Início | C1: 📊 Painel | D1: 📝 Lançamentos | E1: 💳 Orçamento | F1: 📅 Resumo Anual | H1: 🎯 Metas | I1: ⚙ Config
B3: 📝 Lançamentos — registre cada entrada e saída
B4: Preencha as colunas amarelas. Valor sempre positivo; o Tipo (Entrada/Saída) é automático pela categoria.
B5: ENTRADAS NO ANO | D5: SAÍDAS NO ANO | E5: SALDO DO ANO | G5: VERIFICAÇÃO AUTOMÁTICA
B6: =SUMIFS('Lançamentos'!$F$9:$F$1508,'Lançamentos'!$G$9:$G$1508,"Entrada",'Lançamentos'!$B$9:$B$1508,">="&DATE('Config'!$C$6,1,1),'Lançamentos'!$B$9:$B$1508,"<"&DATE('Config'!$C$6+1,1,1)) -> 0 | D6: =SUMIFS('Lançamentos'!$F$9:$F$1508,'Lançamentos'!$G$9:$G$1508,"Saída",'Lançamentos'!$B$9:$B$1508,">="&DATE('Config'!$C$6,1,1),'Lançamentos'!$B$9:$B$1508,"<"&DATE('Config'!$C$6+1,1,1)) -> 0 | E6: =B6-D6 -> 0 | G6: =IF(SUMPRODUCT(('Lançamentos'!$F$9:$F$1508>0)*('Lançamentos'!$D$9:$D$1508=""))>0,"⚠ "&SUMPRODUCT(('Lançamentos'!$F$9:$F$1508>0)*('Lançamentos'!$D$9:$D$1508=""))&" lançamento(s) sem categoria — não entram nos painéis",IF(COUNTIF('Lançamentos'!$G$9:$G$1508,"Verificar")>0,"⚠ "&COUNTIF('Lançamentos'!$G$9:$G$1508,"Verificar")&" lançamento(s) com categoria inválida (coluna Tipo = Verificar)",IF((COUNT('Lançamentos'!$F$9:$F$1508)-COUNTIFS('Lançamentos'!$B$9:$B$1508,">="&DATE('Config'!$C$6,1,1),'Lançamentos'!$B$9:$B$1508,"<"&DATE('Config'!$C$6+1,1,1),'Lançamentos'!$F$9:$F$1508,">0"))>0,"⚠ "&(COUNT('Lançamentos'!$F$9:$F$1508)-COUNTIFS('Lançamentos'!$B$9:$B$1508,">="&DATE('Config'!$C$6,1,1),'Lançamentos'!$B$9:$B$1508,"<"&DATE('Config'!$C$6+1,1,1),'Lançamentos'!$F$9:$F$1508,">0"))&" lançamento(s) sem data ou fora de "&'Config'!$C$6&" — não entram nos painéis","✓ Tudo certo: "&COUNT('Lançamentos'!$F$9:$F$1508)&" lançamento(s) registrados"))) -> ✓ Tudo certo: 0 lançamento(s) registrados
B8: Data | C8: Descrição | D8: Categoria | E8: Forma de pagamento | F8: Valor (R$) | G8: Tipo | H8: Meta (opcional) | I8: Observação
G9: =IF($D9="","",IF(COUNTIF('Config'!$E$6:$E$13,$D9)>0,"Entrada",IF(COUNTIF('Config'!$G$6:$G$21,$D9)>0,"Saída","Verificar")))
G10: =IF($D10="","",IF(COUNTIF('Config'!$E$6:$E$13,$D10)>0,"Entrada",IF(COUNTIF('Config'!$G$6:$G$21,$D10)>0,"Saída","Verificar")))
G11: =IF($D11="","",IF(COUNTIF('Config'!$E$6:$E$13,$D11)>0,"Entrada",IF(COUNTIF('Config'!$G$6:$G$21,$D11)>0,"Saída","Verificar")))
G12: =IF($D12="","",IF(COUNTIF('Config'!$E$6:$E$13,$D12)>0,"Entrada",IF(COUNTIF('Config'!$G$6:$G$21,$D12)>0,"Saída","Verificar")))
G13: =IF($D13="","",IF(COUNTIF('Config'!$E$6:$E$13,$D13)>0,"Entrada",IF(COUNTIF('Config'!$G$6:$G$21,$D13)>0,"Saída","Verificar")))
G14: =IF($D14="","",IF(COUNTIF('Config'!$E$6:$E$13,$D14)>0,"Entrada",IF(COUNTIF('Config'!$G$6:$G$21,$D14)>0,"Saída","Verificar")))
G15: =IF($D15="","",IF(COUNTIF('Config'!$E$6:$E$13,$D15)>0,"Entrada",IF(COUNTIF('Config'!$G$6:$G$21,$D15)>0,"Saída","Verificar")))
G16: =IF($D16="","",IF(COUNTIF('Config'!$E$6:$E$13,$D16)>0,"Entrada",IF(COUNTIF('Config'!$G$6:$G$21,$D16)>0,"Saída","Verificar")))
G17: =IF($D17="","",IF(COUNTIF('Config'!$E$6:$E$13,$D17)>0,"Entrada",IF(COUNTIF('Config'!$G$6:$G$21,$D17)>0,"Saída","Verificar")))
G18: =IF($D18="","",IF(COUNTIF('Config'!$E$6:$E$13,$D18)>0,"Entrada",IF(COUNTIF('Config'!$G$6:$G$21,$D18)>0,"Saída","Verificar")))
G19: =IF($D19="","",IF(COUNTIF('Config'!$E$6:$E$13,$D19)>0,"Entrada",IF(COUNTIF('Config'!$G$6:$G$21,$D19)>0,"Saída","Verificar")))
G20: =IF($D20="","",IF(COUNTIF('Config'!$E$6:$E$13,$D20)>0,"Entrada",IF(COUNTIF('Config'!$G$6:$G$21,$D20)>0,"Saída","Verificar")))
... G1508: =IF($D1508="","",IF(COUNTIF('Config'!$E$6:$E$13,$D1508)>0,"Entrada",IF(COUNTIF('Config'!$G$6:$G$21,$D1508)>0,"Saída","Verificar")))

Sheet Orçamento
B1: 🏠 Início | C1: 📊 Painel | D1: 📝 Lançamentos | E1: 💳 Orçamento | F1: 📅 Resumo Anual | G1: 🎯 Metas | H1: ⚙ Config
B3: 💳 Orçamento mensal — planejado × realizado
B4: Defina quanto pretende gastar em cada categoria. O 'realizado' vem dos lançamentos do mês escolhido.
B5: 📅 Mês de análise: | C5: =INDEX('Config'!$K$6:$K$17,MAX(1,'Dados'!$C$8)) -> Outubro | D5: ← escolha o mês no menu suspenso. Os valores planejados (amarelo) valem para todos os meses.
B7: Categoria | C7: Planejado (mês) | D7: Realizado | E7: Diferença | F7: % usado | G7: Progresso | H7: Situação
B8: Renda do mês (entradas) | C8: 0 | D8: =INDEX('Resumo Anual'!$C$16:$N$16,'Dados'!$C$7) -> 0 | E8: =D8-C8 -> 0 | F8: =IF(C8>0,D8/C8,"") | G8: =IF(F8="","",REPT("█",MIN(22,ROUND(F8*20,0)))) | H8: =IF(C8=0,"—",IF(D8>=C8,"✓ Meta batida",IF(D8>=C8*0.8,"⚠ Quase lá","✖ Abaixo"))) -> —
B9: DESPESAS POR CATEGORIA
B10: =IF('Config'!$G$6="","",'Config'!$G$6) -> Moradia | C10: 0 | D10: =IF(B10="",0,INDEX('Resumo Anual'!$C$18:$N$18,'Dados'!$C$7)) -> 0 | E10: =C10-D10 -> 0 | F10: =IF(C10>0,D10/C10,"") | G10: =IF(F10="","",REPT("█",MIN(22,ROUND(F10*20,0)))) | H10: =IF(C10=0,IF(D10>0,"Sem orçamento","—"),IF(D10>C10,"✖ Estourou",IF(D10>=C10*0.8,"⚠ Atenção","✓ OK"))) -> —
B11: =IF('Config'!$G$7="","",'Config'!$G$7) -> Contas da casa | C11: 0 | D11: =IF(B11="",0,INDEX('Resumo Anual'!$C$19:$N$19,'Dados'!$C$7)) -> 0 | E11: =C11-D11 -> 0 | F11: =IF(C11>0,D11/C11,"") | G11: =IF(F11="","",REPT("█",MIN(22,ROUND(F11*20,0)))) | H11: =IF(C11=0,IF(D11>0,"Sem orçamento","—"),IF(D11>C11,"✖ Estourou",IF(D11>=C11*0.8,"⚠ Atenção","✓ OK"))) -> —
B12: =IF('Config'!$G$8="","",'Config'!$G$8) -> Alimentação | C12: 0 | D12: =IF(B12="",0,INDEX('Resumo Anual'!$C$20:$N$20,'Dados'!$C$7)) -> 0 | E12: =C12-D12 -> 0 | F12: =IF(C12>0,D12/C12,"") | G12: =IF(F12="","",REPT("█",MIN(22,ROUND(F12*20,0)))) | H12: =IF(C12=0,IF(D12>0,"Sem orçamento","—"),IF(D12>C12,"✖ Estourou",IF(D12>=C12*0.8,"⚠ Atenção","✓ OK"))) -> —
B13: =IF('Config'!$G$9="","",'Config'!$G$9) -> Transporte | C13: 0 | D13: =IF(B13="",0,INDEX('Resumo Anual'!$C$21:$N$21,'Dados'!$C$7)) -> 0 | E13: =C13-D13 -> 0 | F13: =IF(C13>0,D13/C13,"") | G13: =IF(F13="","",REPT("█",MIN(22,ROUND(F13*20,0)))) | H13: =IF(C13=0,IF(D13>0,"Sem orçamento","—"),IF(D13>C13,"✖ Estourou",IF(D13>=C13*0.8,"⚠ Atenção","✓ OK"))) -> —
B14: =IF('Config'!$G$10="","",'Config'!$G$10) -> Saúde | C14: 0 | D14: =IF(B14="",0,INDEX('Resumo Anual'!$C$22:$N$22,'Dados'!$C$7)) -> 0 | E14: =C14-D14 -> 0 | F14: =IF(C14>0,D14/C14,"") | G14: =IF(F14="","",REPT("█",MIN(22,ROUND(F14*20,0)))) | H14: =IF(C14=0,IF(D14>0,"Sem orçamento","—"),IF(D14>C14,"✖ Estourou",IF(D14>=C14*0.8,"⚠ Atenção","✓ OK"))) -> —
B15: =IF('Config'!$G$11="","",'Config'!$G$11) -> Educação | C15: 0 | D15: =IF(B15="",0,INDEX('Resumo Anual'!$C$23:$N$23,'Dados'!$C$7)) -> 0 | E15: =C15-D15 -> 0 | F15: =IF(C15>0,D15/C15,"") | G15: =IF(F15="","",REPT("█",MIN(22,ROUND(F15*20,0)))) | H15: =IF(C15=0,IF(D15>0,"Sem orçamento","—"),IF(D15>C15,"✖ Estourou",IF(D15>=C15*0.8,"⚠ Atenção","✓ OK"))) -> —
B16: =IF('Config'!$G$12="","",'Config'!$G$12) -> Lazer | C16: 0 | D16: =IF(B16="",0,INDEX('Resumo Anual'!$C$24:$N$24,'Dados'!$C$7)) -> 0 | E16: =C16-D16 -> 0 | F16: =IF(C16>0,D16/C16,"") | G16: =IF(F16="","",REPT("█",MIN(22,ROUND(F16*20,0)))) | H16: =IF(C16=0,IF(D16>0,"Sem orçamento","—"),IF(D16>C16,"✖ Estourou",IF(D16>=C16*0.8,"⚠ Atenção","✓ OK"))) -> —
B17: =IF('Config'!$G$13="","",'Config'!$G$13) -> Vestuário | C17: 0 | D17: =IF(B17="",0,INDEX('Resumo Anual'!$C$25:$N$25,'Dados'!$C$7)) -> 0 | E17: =C17-D17 -> 0 | F17: =IF(C17>0,D17/C17,"") | G17: =IF(F17="","",REPT("█",MIN(22,ROUND(F17*20,0)))) | H17: =IF(C17=0,IF(D17>0,"Sem orçamento","—"),IF(D17>C17,"✖ Estourou",IF(D17>=C17*0.8,"⚠ Atenção","✓ OK"))) -> —
B18: =IF('Config'!$G$14="","",'Config'!$G$14) -> Assinaturas | C18: 0 | D18: =IF(B18="",0,INDEX('Resumo Anual'!$C$26:$N$26,'Dados'!$C$7)) -> 0 | E18: =C18-D18 -> 0 | F18: =IF(C18>0,D18/C18,"") | G18: =IF(F18="","",REPT("█",MIN(22,ROUND(F18*20,0)))) | H18: =IF(C18=0,IF(D18>0,"Sem orçamento","—"),IF(D18>C18,"✖ Estourou",IF(D18>=C18*0.8,"⚠ Atenção","✓ OK"))) -> —
B19: =IF('Config'!$G$15="","",'Config'!$G$15) -> Cuidados pessoais | C19: 0 | D19: =IF(B19="",0,INDEX('Resumo Anual'!$C$27:$N$27,'Dados'!$C$7)) -> 0 | E19: =C19-D19 -> 0 | F19: =IF(C19>0,D19/C19,"") | G19: =IF(F19="","",REPT("█",MIN(22,ROUND(F19*20,0)))) | H19: =IF(C19=0,IF(D19>0,"Sem orçamento","—"),IF(D19>C19,"✖ Estourou",IF(D19>=C19*0.8,"⚠ Atenção","✓ OK"))) -> —
B20: =IF('Config'!$G$16="","",'Config'!$G$16) -> Pets | C20: 0 | D20: =IF(B20="",0,INDEX('Resumo Anual'!$C$28:$N$28,'Dados'!$C$7)) -> 0 | E20: =C20-D20 -> 0 | F20: =IF(C20>0,D20/C20,"") | G20: =IF(F20="","",REPT("█",MIN(22,ROUND(F20*20,0)))) | H20: =IF(C20=0,IF(D20>0,"Sem orçamento","—"),IF(D20>C20,"✖ Estourou",IF(D20>=C20*0.8,"⚠ Atenção","✓ OK"))) -> —
B21: =IF('Config'!$G$17="","",'Config'!$G$17) -> Presentes e doações | C21: 0 | D21: =IF(B21="",0,INDEX('Resumo Anual'!$C$29:$N$29,'Dados'!$C$7)) -> 0 | E21: =C21-D21 -> 0 | F21: =IF(C21>0,D21/C21,"") | G21: =IF(F21="","",REPT("█",MIN(22,ROUND(F21*20,0)))) | H21: =IF(C21=0,IF(D21>0,"Sem orçamento","—"),IF(D21>C21,"✖ Estourou",IF(D21>=C21*0.8,"⚠ Atenção","✓ OK"))) -> —
B22: =IF('Config'!$G$18="","",'Config'!$G$18) -> Dívidas e financiamentos | C22: 0 | D22: =IF(B22="",0,INDEX('Resumo Anual'!$C$30:$N$30,'Dados'!$C$7)) -> 0 | E22: =C22-D22 -> 0 | F22: =IF(C22>0,D22/C22,"") | G22: =IF(F22="","",REPT("█",MIN(22,ROUND(F22*20,0)))) | H22: =IF(C22=0,IF(D22>0,"Sem orçamento","—"),IF(D22>C22,"✖ Estourou",IF(D22>=C22*0.8,"⚠ Atenção","✓ OK"))) -> —
B23: =IF('Config'!$G$19="","",'Config'!$G$19) -> Reserva e Metas | C23: 0 | D23: =IF(B23="",0,INDEX('Resumo Anual'!$C$31:$N$31,'Dados'!$C$7)) -> 0 | E23: =D23-C23 -> 0 | F23: =IF(C23>0,D23/C23,"") | G23: =IF(F23="","",REPT("█",MIN(22,ROUND(F23*20,0)))) | H23: =IF(C23=0,"—",IF(D23>=C23,"✓ Meta batida",IF(D23>=C23*0.8,"⚠ Quase lá","✖ Abaixo"))) -> —
B24: =IF('Config'!$G$20="","",'Config'!$G$20) -> Impostos pessoais | C24: 0 | D24: =IF(B24="",0,INDEX('Resumo Anual'!$C$32:$N$32,'Dados'!$C$7)) -> 0 | E24: =C24-D24 -> 0 | F24: =IF(C24>0,D24/C24,"") | G24: =IF(F24="","",REPT("█",MIN(22,ROUND(F24*20,0)))) | H24: =IF(C24=0,IF(D24>0,"Sem orçamento","—"),IF(D24>C24,"✖ Estourou",IF(D24>=C24*0.8,"⚠ Atenção","✓ OK"))) -> —
B25: =IF('Config'!$G$21="","",'Config'!$G$21) -> Outros | C25: 0 | D25: =IF(B25="",0,INDEX('Resumo Anual'!$C$33:$N$33,'Dados'!$C$7)) -> 0 | E25: =C25-D25 -> 0 | F25: =IF(C25>0,D25/C25,"") | G25: =IF(F25="","",REPT("█",MIN(22,ROUND(F25*20,0)))) | H25: =IF(C25=0,IF(D25>0,"Sem orçamento","—"),IF(D25>C25,"✖ Estourou",IF(D25>=C25*0.8,"⚠ Atenção","✓ OK"))) -> —
B26: TOTAL DAS DESPESAS | C26: =SUM(C10:C25) -> 0 | D26: =SUM(D10:D25) -> 0 | E26: =C26-D26 -> 0 | F26: =IF(C26>0,D26/C26,"") | G26: =IF(F26="","",REPT("█",MIN(22,ROUND(F26*20,0)))) | H26: =IF(C26=0,"—",IF(D26>C26,"✖ Estourou",IF(D26>=C26*0.8,"⚠ Atenção","✓ OK"))) -> —
B27: SALDO (renda − despesas) | C27: =C8-C26 -> 0 | D27: =D8-D26 -> 0 | E27: =D27-C27 -> 0

Sheet Resumo Anual
B1: 🏠 Início | C1: 📊 Painel | E1: 📝 Lançamentos | H1: 💳 Orçamento | K1: 📅 Resumo Anual | N1: 🎯 Metas | P1: ⚙ Config
B3: 📅 Resumo anual — entradas e saídas por mês
B4: Totalizado automaticamente a partir da aba de lançamentos. Cores destacam saldos positivos e negativos.
C5: =DATE('Config'!$C$6,1,1) -> 46023 | D5: =DATE('Config'!$C$6,2,1) -> 46054 | E5: =DATE('Config'!$C$6,3,1) -> 46082 | F5: =DATE('Config'!$C$6,4,1) -> 46113 | G5: =DATE('Config'!$C$6,5,1) -> 46143 | H5: =DATE('Config'!$C$6,6,1) -> 46174 | I5: =DATE('Config'!$C$6,7,1) -> 46204 | J5: =DATE('Config'!$C$6,8,1) -> 46235 | K5: =DATE('Config'!$C$6,9,1) -> 46266 | L5: =DATE('Config'!$C$6,10,1) -> 46296 | M5: =DATE('Config'!$C$6,11,1) -> 46327 | N5: =DATE('Config'!$C$6,12,1) -> 46357
B6: Categoria | C6: =INDEX('Config'!$L$6:$L$17,1) -> Jan | D6: =INDEX('Config'!$L$6:$L$17,2) -> Fev | E6: =INDEX('Config'!$L$6:$L$17,3) -> Mar | F6: =INDEX('Config'!$L$6:$L$17,4) -> Abr | G6: =INDEX('Config'!$L$6:$L$17,5) -> Mai | H6: =INDEX('Config'!$L$6:$L$17,6) -> Jun | I6: =INDEX('Config'!$L$6:$L$17,7) -> Jul | J6: =INDEX('Config'!$L$6:$L$17,8) -> Ago | K6: =INDEX('Config'!$L$6:$L$17,9) -> Set | L6: =INDEX('Config'!$L$6:$L$17,10) -> Out | M6: =INDEX('Config'!$L$6:$L$17,11) -> Nov | N6: =INDEX('Config'!$L$6:$L$17,12) -> Dez | O6: Total | P6: Média/mês | Q6: % das saídas
B7: ▲ ENTRADAS
B8: =IF('Config'!$E$6="","",'Config'!$E$6) -> Salário | C8: =IF($B8="",0,SUMIFS('Lançamentos'!$F$9:$F$1508,'Lançamentos'!$D$9:$D$1508,$B8,'Lançamentos'!$B$9:$B$1508,">="&C$5,'Lançamentos'!$B$9:$B$1508,"<"&EDATE(C$5,1))) -> 0 | D8: =IF($B8="",0,SUMIFS('Lançamentos'!$F$9:$F$1508,'Lançamentos'!$D$9:$D$1508,$B8,'Lançamentos'!$B$9:$B$1508,">="&D$5,'Lançamentos'!$B$9:$B$1508,"<"&EDATE(D$5,1))) -> 0 | E8: =IF($B8="",0,SUMIFS('Lançamentos'!$F$9:$F$1508,'Lançamentos'!$D$9:$D$1508,$B8,'Lançamentos'!$B$9:$B$1508,">="&E$5,'Lançamentos'!$B$9:$B$1508,"<"&EDATE(E$5,1))) -> 0 | F8: =IF($B8="",0,SUMIFS('Lançamentos'!$F$9:$F$1508,'Lançamentos'!$D$9:$D$1508,$B8,'Lançamentos'!$B$9:$B$1508,">="&F$5,'Lançamentos'!$B$9:$B$1508,"<"&EDATE(F$5,1))) -> 0 | G8: =IF($B8="",0,SUMIFS('Lançamentos'!$F$9:$F$1508,'Lançamentos'!$D$9:$D$1508,$B8,'Lançamentos'!$B$9:$B$1508,">="&G$5,'Lançamentos'!$B$9:$B$1508,"<"&EDATE(G$5,1))) -> 0 | H8: =IF($B8="",0,SUMIFS('Lançamentos'!$F$9:$F$1508,'Lançamentos'!$D$9:$D$1508,$B8,'Lançamentos'!$B$9:$B$1508,">="&H$5,'Lançamentos'!$B$9:$B$1508,"<"&EDATE(H$5,1))) -> 0 | I8: =IF($B8="",0,SUMIFS('Lançamentos'!$F$9:$F$1508,'Lançamentos'!$D$9:$D$1508,$B8,'Lançamentos'!$B$9:$B$1508,">="&I$5,'Lançamentos'!$B$9:$B$1508,"<"&EDATE(I$5,1))) -> 0 | J8: =IF($B8="",0,SUMIFS('Lançamentos'!$F$9:$F$1508,'Lançamentos'!$D$9:$D$1508,$B8,'Lançamentos'!$B$9:$B$1508,">="&J$5,'Lançamentos'!$B$9:$B$1508,"<"&EDATE(J$5,1))) -> 0 | ... N8: =IF($B8="",0,SUMIFS('Lançamentos'!$F$9:$F$1508,'Lançamentos'!$D$9:$D$1508,$B8,'Lançamentos'!$B$9:$B$1508,">="&N$5,'Lançamentos'!$B$9:$B$1508,"<"&EDATE(N$5,1))) -> 0 | O8: =SUM(C8:N8) -> 0 | P8: =IFERROR(O8/'Dados'!$C$9,0) -> 0
B9: =IF('Config'!$E$7="","",'Config'!$E$7) -> Renda extra | C9: =IF($B9="",0,SUMIFS('Lançamentos'!$F$9:$F$1508,'Lançamentos'!$D$9:$D$1508,$B9,'Lançamentos'!$B$9:$B$1508,">="&C$5,'Lançamentos'!$B$9:$B$1508,"<"&EDATE(C$5,1))) -> 0 | D9: =IF($B9="",0,SUMIFS('Lançamentos'!$F$9:$F$1508,'Lançamentos'!$D$9:$D$1508,$B9,'Lançamentos'!$B$9:$B$1508,">="&D$5,'Lançamentos'!$B$9:$B$1508,"<"&EDATE(D$5,1))) -> 0 | E9: =IF($B9="",0,SUMIFS('Lançamentos'!$F$9:$F$1508,'Lançamentos'!$D$9:$D$1508,$B9,'Lançamentos'!$B$9:$B$1508,">="&E$5,'Lançamentos'!$B$9:$B$1508,"<"&EDATE(E$5,1))) -> 0 | F9: =IF($B9="",0,SUMIFS('Lançamentos'!$F$9:$F$1508,'Lançamentos'!$D$9:$D$1508,$B9,'Lançamentos'!$B$9:$B$1508,">="&F$5,'Lançamentos'!$B$9:$B$1508,"<"&EDATE(F$5,1))) -> 0 | G9: =IF($B9="",0,SUMIFS('Lançamentos'!$F$9:$F$1508,'Lançamentos'!$D$9:$D$1508,$B9,'Lançamentos'!$B$9:$B$1508,">="&G$5,'Lançamentos'!$B$9:$B$1508,"<"&EDATE(G$5,1))) -> 0 | H9: =IF($B9="",0,SUMIFS('Lançamentos'!$F$9:$F$1508,'Lançamentos'!$D$9:$D$1508,$B9,'Lançamentos'!$B$9:$B$1508,">="&H$5,'Lançamentos'!$B$9:$B$1508,"<"&EDATE(H$5,1))) -> 0 | I9: =IF($B9="",0,SUMIFS('Lançamentos'!$F$9:$F$1508,'Lançamentos'!$D$9:$D$1508,$B9,'Lançamentos'!$B$9:$B$1508,">="&I$5,'Lançamentos'!$B$9:$B$1508,"<"&EDATE(I$5,1))) -> 0 | J9: =IF($B9="",0,SUMIFS('Lançamentos'!$F$9:$F$1508,'Lançamentos'!$D$9:$D$1508,$B9,'Lançamentos'!$B$9:$B$1508,">="&J$5,'Lançamentos'!$B$9:$B$1508,"<"&EDATE(J$5,1))) -> 0 | ... N9: =IF($B9="",0,SUMIFS('Lançamentos'!$F$9:$F$1508,'Lançamentos'!$D$9:$D$1508,$B9,'Lançamentos'!$B$9:$B$1508,">="&N$5,'Lançamentos'!$B$9:$B$1508,"<"&EDATE(N$5,1))) -> 0 | O9: =SUM(C9:N9) -> 0 | P9: =IFERROR(O9/'Dados'!$C$9,0) -> 0
B10: =IF('Config'!$E$8="","",'Config'!$E$8) -> Rendimentos de investimentos | C10: =IF($B10="",0,SUMIFS('Lançamentos'!$F$9:$F$1508,'Lançamentos'!$D$9:$D$1508,$B10,'Lançamentos'!$B$9:$B$1508,">="&C$5,'Lançamentos'!$B$9:$B$1508,"<"&EDATE(C$5,1))) -> 0 | D10: =IF($B10="",0,SUMIFS('Lançamentos'!$F$9:$F$1508,'Lançamentos'!$D$9:$D$1508,$B10,'Lançamentos'!$B$9:$B$1508,">="&D$5,'Lançamentos'!$B$9:$B$1508,"<"&EDATE(D$5,1))) -> 0 | E10: =IF($B10="",0,SUMIFS('Lançamentos'!$F$9:$F$1508,'Lançamentos'!$D$9:$D$1508,$B10,'Lançamentos'!$B$9:$B$1508,">="&E$5,'Lançamentos'!$B$9:$B$1508,"<"&EDATE(E$5,1))) -> 0 | F10: =IF($B10="",0,SUMIFS('Lançamentos'!$F$9:$F$1508,'Lançamentos'!$D$9:$D$1508,$B10,'Lançamentos'!$B$9:$B$1508,">="&F$5,'Lançamentos'!$B$9:$B$1508,"<"&EDATE(F$5,1))) -> 0 | G10: =IF($B10="",0,SUMIFS('Lançamentos'!$F$9:$F$1508,'Lançamentos'!$D$9:$D$1508,$B10,'Lançamentos'!$B$9:$B$1508,">="&G$5,'Lançamentos'!$B$9:$B$1508,"<"&EDATE(G$5,1))) -> 0 | H10: =IF($B10="",0,SUMIFS('Lançamentos'!$F$9:$F$1508,'Lançamentos'!$D$9:$D$1508,$B10,'Lançamentos'!$B$9:$B$1508,">="&H$5,'Lançamentos'!$B$9:$B$1508,"<"&EDATE(H$5,1))) -> 0 | I10: =IF($B10="",0,SUMIFS('Lançamentos'!$F$9:$F$1508,'Lançamentos'!$D$9:$D$1508,$B10,'Lançamentos'!$B$9:$B$1508,">="&I$5,'Lançamentos'!$B$9:$B$1508,"<"&EDATE(I$5,1))) -> 0 | J10: =IF($B10="",0,SUMIFS('Lançamentos'!$F$9:$F$1508,'Lançamentos'!$D$9:$D$1508,$B10,'Lançamentos'!$B$9:$B$1508,">="&J$5,'Lançamentos'!$B$9:$B$1508,"<"&EDATE(J$5,1))) -> 0 | ... N10: =IF($B10="",0,SUMIFS('Lançamentos'!$F$9:$F$1508,'Lançamentos'!$D$9:$D$1508,$B10,'Lançamentos'!$B$9:$B$1508,">="&N$5,'Lançamentos'!$B$9:$B$1508,"<"&EDATE(N$5,1))) -> 0 | O10: =SUM(C10:N10) -> 0 | P10: =IFERROR(O10/'Dados'!$C$9,0) -> 0
B11: =IF('Config'!$E$9="","",'Config'!$E$9) -> 13º e bônus | C11: =IF($B11="",0,SUMIFS('Lançamentos'!$F$9:$F$1508,'Lançamentos'!$D$9:$D$1508,$B11,'Lançamentos'!$B$9:$B$1508,">="&C$5,'Lançamentos'!$B$9:$B$1508,"<"&EDATE(C$5,1))) -> 0 | D11: =IF($B11="",0,SUMIFS('Lançamentos'!$F$9:$F$1508,'Lançamentos'!$D$9:$D$1508,$B11,'Lançamentos'!$B$9:$B$1508,">="&D$5,'Lançamentos'!$B$9:$B$1508,"<"&EDATE(D$5,1))) -> 0 | E11: =IF($B11="",0,SUMIFS('Lançamentos'!$F$9:$F$1508,'Lançamentos'!$D$9:$D$1508,$B11,'Lançamentos'!$B$9:$B$1508,">="&E$5,'Lançamentos'!$B$9:$B$1508,"<"&EDATE(E$5,1))) -> 0 | F11: =IF($B11="",0,SUMIFS('Lançamentos'!$F$9:$F$1508,'Lançamentos'!$D$9:$D$1508,$B11,'Lançamentos'!$B$9:$B$1508,">="&F$5,'Lançamentos'!$B$9:$B$1508,"<"&EDATE(F$5,1))) -> 0 | G11: =IF($B11="",0,SUMIFS('Lançamentos'!$F$9:$F$1508,'Lançamentos'!$D$9:$D$1508,$B11,'Lançamentos'!$B$9:$B$1508,">="&G$5,'Lançamentos'!$B$9:$B$1508,"<"&EDATE(G$5,1))) -> 0 | H11: =IF($B11="",0,SUMIFS('Lançamentos'!$F$9:$F$1508,'Lançamentos'!$D$9:$D$1508,$B11,'Lançamentos'!$B$9:$B$1508,">="&H$5,'Lançamentos'!$B$9:$B$1508,"<"&EDATE(H$5,1))) -> 0 | I11: =IF($B11="",0,SUMIFS('Lançamentos'!$F$9:$F$1508,'Lançamentos'!$D$9:$D$1508,$B11,'Lançamentos'!$B$9:$B$1508,">="&I$5,'Lançamentos'!$B$9:$B$1508,"<"&EDATE(I$5,1))) -> 0 | J11: =IF($B11="",0,SUMIFS('Lançamentos'!$F$9:$F$1508,'Lançamentos'!$D$9:$D$1508,$B11,'Lançamentos'!$B$9:$B$1508,">="&J$5,'Lançamentos'!$B$9:$B$1508,"<"&EDATE(J$5,1))) -> 0 | ... N11: =IF($B11="",0,SUMIFS('Lançamentos'!$F$9:$F$1508,'Lançamentos'!$D$9:$D$1508,$B11,'Lançamentos'!$B$9:$B$1508,">="&N$5,'Lançamentos'!$B$9:$B$1508,"<"&EDATE(N$5,1))) -> 0 | O11: =SUM(C11:N11) -> 0 | P11: =IFERROR(O11/'Dados'!$C$9,0) -> 0
B12: =IF('Config'!$E$10="","",'Config'!$E$10) -> Reembolsos | C12: =IF($B12="",0,SUMIFS('Lançamentos'!$F$9:$F$1508,'Lançamentos'!$D$9:$D$1508,$B12,'Lançamentos'!$B$9:$B$1508,">="&C$5,'Lançamentos'!$B$9:$B$1508,"<"&EDATE(C$5,1))) -> 0 | D12: =IF($B12="",0,SUMIFS('Lançamentos'!$F$9:$F$1508,'Lançamentos'!$D$9:$D$1508,$B12,'Lançamentos'!$B$9:$B$1508,">="&D$5,'Lançamentos'!$B$9:$B$1508,"<"&EDATE(D$5,1))) -> 0 | E12: =IF($B12="",0,SUMIFS('Lançamentos'!$F$9:$F$1508,'Lançamentos'!$D$9:$D$1508,$B12,'Lançamentos'!$B$9:$B$1508,">="&E$5,'Lançamentos'!$B$9:$B$1508,"<"&EDATE(E$5,1))) -> 0 | F12: =IF($B12="",0,SUMIFS('Lançamentos'!$F$9:$F$1508,'Lançamentos'!$D$9:$D$1508,$B12,'Lançamentos'!$B$9:$B$1508,">="&F$5,'Lançamentos'!$B$9:$B$1508,"<"&EDATE(F$5,1))) -> 0 | G12: =IF($B12="",0,SUMIFS('Lançamentos'!$F$9:$F$1508,'Lançamentos'!$D$9:$D$1508,$B12,'Lançamentos'!$B$9:$B$1508,">="&G$5,'Lançamentos'!$B$9:$B$1508,"<"&EDATE(G$5,1))) -> 0 | H12: =IF($B12="",0,SUMIFS('Lançamentos'!$F$9:$F$1508,'Lançamentos'!$D$9:$D$1508,$B12,'Lançamentos'!$B$9:$B$1508,">="&H$5,'Lançamentos'!$B$9:$B$1508,"<"&EDATE(H$5,1))) -> 0 | I12: =IF($B12="",0,SUMIFS('Lançamentos'!$F$9:$F$1508,'Lançamentos'!$D$9:$D$1508,$B12,'Lançamentos'!$B$9:$B$1508,">="&I$5,'Lançamentos'!$B$9:$B$1508,"<"&EDATE(I$5,1))) -> 0 | J12: =IF($B12="",0,SUMIFS('Lançamentos'!$F$9:$F$1508,'Lançamentos'!$D$9:$D$1508,$B12,'Lançamentos'!$B$9:$B$1508,">="&J$5,'Lançamentos'!$B$9:$B$1508,"<"&EDATE(J$5,1))) -> 0 | ... N12: =IF($B12="",0,SUMIFS('Lançamentos'!$F$9:$F$1508,'Lançamentos'!$D$9:$D$1508,$B12,'Lançamentos'!$B$9:$B$1508,">="&N$5,'Lançamentos'!$B$9:$B$1508,"<"&EDATE(N$5,1))) -> 0 | O12: =SUM(C12:N12) -> 0 | P12: =IFERROR(O12/'Dados'!$C$9,0) -> 0
B13: =IF('Config'!$E$11="","",'Config'!$E$11) -> Aluguéis recebidos | C13: =IF($B13="",0,SUMIFS('Lançamentos'!$F$9:$F$1508,'Lançamentos'!$D$9:$D$1508,$B13,'Lançamentos'!$B$9:$B$1508,">="&C$5,'Lançamentos'!$B$9:$B$1508,"<"&EDATE(C$5,1))) -> 0 | D13: =IF($B13="",0,SUMIFS('Lançamentos'!$F$9:$F$1508,'Lançamentos'!$D$9:$D$1508,$B13,'Lançamentos'!$B$9:$B$1508,">="&D$5,'Lançamentos'!$B$9:$B$1508,"<"&EDATE(D$5,1))) -> 0 | E13: =IF($B13="",0,SUMIFS('Lançamentos'!$F$9:$F$1508,'Lançamentos'!$D$9:$D$1508,$B13,'Lançamentos'!$B$9:$B$1508,">="&E$5,'Lançamentos'!$B$9:$B$1508,"<"&EDATE(E$5,1))) -> 0 | F13: =IF($B13="",0,SUMIFS('Lançamentos'!$F$9:$F$1508,'Lançamentos'!$D$9:$D$1508,$B13,'Lançamentos'!$B$9:$B$1508,">="&F$5,'Lançamentos'!$B$9:$B$1508,"<"&EDATE(F$5,1))) -> 0 | G13: =IF($B13="",0,SUMIFS('Lançamentos'!$F$9:$F$1508,'Lançamentos'!$D$9:$D$1508,$B13,'Lançamentos'!$B$9:$B$1508,">="&G$5,'Lançamentos'!$B$9:$B$1508,"<"&EDATE(G$5,1))) -> 0 | H13: =IF($B13="",0,SUMIFS('Lançamentos'!$F$9:$F$1508,'Lançamentos'!$D$9:$D$1508,$B13,'Lançamentos'!$B$9:$B$1508,">="&H$5,'Lançamentos'!$B$9:$B$1508,"<"&EDATE(H$5,1))) -> 0 | I13: =IF($B13="",0,SUMIFS('Lançamentos'!$F$9:$F$1508,'Lançamentos'!$D$9:$D$1508,$B13,'Lançamentos'!$B$9:$B$1508,">="&I$5,'Lançamentos'!$B$9:$B$1508,"<"&EDATE(I$5,1))) -> 0 | J13: =IF($B13="",0,SUMIFS('Lançamentos'!$F$9:$F$1508,'Lançamentos'!$D$9:$D$1508,$B13,'Lançamentos'!$B$9:$B$1508,">="&J$5,'Lançamentos'!$B$9:$B$1508,"<"&EDATE(J$5,1))) -> 0 | ... N13: =IF($B13="",0,SUMIFS('Lançamentos'!$F$9:$F$1508,'Lançamentos'!$D$9:$D$1508,$B13,'Lançamentos'!$B$9:$B$1508,">="&N$5,'Lançamentos'!$B$9:$B$1508,"<"&EDATE(N$5,1))) -> 0 | O13: =SUM(C13:N13) -> 0 | P13: =IFERROR(O13/'Dados'!$C$9,0) -> 0
B14: =IF('Config'!$E$12="","",'Config'!$E$12) -> Presentes recebidos | C14: =IF($B14="",0,SUMIFS('Lançamentos'!$F$9:$F$1508,'Lançamentos'!$D$9:$D$1508,$B14,'Lançamentos'!$B$9:$B$1508,">="&C$5,'Lançamentos'!$B$9:$B$1508,"<"&EDATE(C$5,1))) -> 0 | D14: =IF($B14="",0,SUMIFS('Lançamentos'!$F$9:$F$1508,'Lançamentos'!$D$9:$D$1508,$B14,'Lançamentos'!$B$9:$B$1508,">="&D$5,'Lançamentos'!$B$9:$B$1508,"<"&EDATE(D$5,1))) -> 0 | E14: =IF($B14="",0,SUMIFS('Lançamentos'!$F$9:$F$1508,'Lançamentos'!$D$9:$D$1508,$B14,'Lançamentos'!$B$9:$B$1508,">="&E$5,'Lançamentos'!$B$9:$B$1508,"<"&EDATE(E$5,1))) -> 0 | F14: =IF($B14="",0,SUMIFS('Lançamentos'!$F$9:$F$1508,'Lançamentos'!$D$9:$D$1508,$B14,'Lançamentos'!$B$9:$B$1508,">="&F$5,'Lançamentos'!$B$9:$B$1508,"<"&EDATE(F$5,1))) -> 0 | G14: =IF($B14="",0,SUMIFS('Lançamentos'!$F$9:$F$1508,'Lançamentos'!$D$9:$D$1508,$B14,'Lançamentos'!$B$9:$B$1508,">="&G$5,'Lançamentos'!$B$9:$B$1508,"<"&EDATE(G$5,1))) -> 0 | H14: =IF($B14="",0,SUMIFS('Lançamentos'!$F$9:$F$1508,'Lançamentos'!$D$9:$D$1508,$B14,'Lançamentos'!$B$9:$B$1508,">="&H$5,'Lançamentos'!$B$9:$B$1508,"<"&EDATE(H$5,1))) -> 0 | I14: =IF($B14="",0,SUMIFS('Lançamentos'!$F$9:$F$1508,'Lançamentos'!$D$9:$D$1508,$B14,'Lançamentos'!$B$9:$B$1508,">="&I$5,'Lançamentos'!$B$9:$B$1508,"<"&EDATE(I$5,1))) -> 0 | J14: =IF($B14="",0,SUMIFS('Lançamentos'!$F$9:$F$1508,'Lançamentos'!$D$9:$D$1508,$B14,'Lançamentos'!$B$9:$B$1508,">="&J$5,'Lançamentos'!$B$9:$B$1508,"<"&EDATE(J$5,1))) -> 0 | ... N14: =IF($B14="",0,SUMIFS('Lançamentos'!$F$9:$F$1508,'Lançamentos'!$D$9:$D$1508,$B14,'Lançamentos'!$B$9:$B$1508,">="&N$5,'Lançamentos'!$B$9:$B$1508,"<"&EDATE(N$5,1))) -> 0 | O14: =SUM(C14:N14) -> 0 | P14: =IFERROR(O14/'Dados'!$C$9,0) -> 0
B15: =IF('Config'!$E$13="","",'Config'!$E$13) -> Outras entradas | C15: =IF($B15="",0,SUMIFS('Lançamentos'!$F$9:$F$1508,'Lançamentos'!$D$9:$D$1508,$B15,'Lançamentos'!$B$9:$B$1508,">="&C$5,'Lançamentos'!$B$9:$B$1508,"<"&EDATE(C$5,1))) -> 0 | D15: =IF($B15="",0,SUMIFS('Lançamentos'!$F$9:$F$1508,'Lançamentos'!$D$9:$D$1508,$B15,'Lançamentos'!$B$9:$B$1508,">="&D$5,'Lançamentos'!$B$9:$B$1508,"<"&EDATE(D$5,1))) -> 0 | E15: =IF($B15="",0,SUMIFS('Lançamentos'!$F$9:$F$1508,'Lançamentos'!$D$9:$D$1508,$B15,'Lançamentos'!$B$9:$B$1508,">="&E$5,'Lançamentos'!$B$9:$B$1508,"<"&EDATE(E$5,1))) -> 0 | F15: =IF($B15="",0,SUMIFS('Lançamentos'!$F$9:$F$1508,'Lançamentos'!$D$9:$D$1508,$B15,'Lançamentos'!$B$9:$B$1508,">="&F$5,'Lançamentos'!$B$9:$B$1508,"<"&EDATE(F$5,1))) -> 0 | G15: =IF($B15="",0,SUMIFS('Lançamentos'!$F$9:$F$1508,'Lançamentos'!$D$9:$D$1508,$B15,'Lançamentos'!$B$9:$B$1508,">="&G$5,'Lançamentos'!$B$9:$B$1508,"<"&EDATE(G$5,1))) -> 0 | H15: =IF($B15="",0,SUMIFS('Lançamentos'!$F$9:$F$1508,'Lançamentos'!$D$9:$D$1508,$B15,'Lançamentos'!$B$9:$B$1508,">="&H$5,'Lançamentos'!$B$9:$B$1508,"<"&EDATE(H$5,1))) -> 0 | I15: =IF($B15="",0,SUMIFS('Lançamentos'!$F$9:$F$1508,'Lançamentos'!$D$9:$D$1508,$B15,'Lançamentos'!$B$9:$B$1508,">="&I$5,'Lançamentos'!$B$9:$B$1508,"<"&EDATE(I$5,1))) -> 0 | J15: =IF($B15="",0,SUMIFS('Lançamentos'!$F$9:$F$1508,'Lançamentos'!$D$9:$D$1508,$B15,'Lançamentos'!$B$9:$B$1508,">="&J$5,'Lançamentos'!$B$9:$B$1508,"<"&EDATE(J$5,1))) -> 0 | ... N15: =IF($B15="",0,SUMIFS('Lançamentos'!$F$9:$F$1508,'Lançamentos'!$D$9:$D$1508,$B15,'Lançamentos'!$B$9:$B$1508,">="&N$5,'Lançamentos'!$B$9:$B$1508,"<"&EDATE(N$5,1))) -> 0 | O15: =SUM(C15:N15) -> 0 | P15: =IFERROR(O15/'Dados'!$C$9,0) -> 0
B16: Total de entradas | C16: =SUM(C8:C15) -> 0 | D16: =SUM(D8:D15) -> 0 | E16: =SUM(E8:E15) -> 0 | F16: =SUM(F8:F15) -> 0 | G16: =SUM(G8:G15) -> 0 | H16: =SUM(H8:H15) -> 0 | I16: =SUM(I8:I15) -> 0 | J16: =SUM(J8:J15) -> 0 | ... P16: =SUM(P8:P15) -> 0
B17: ▼ SAÍDAS
B18: =IF('Config'!$G$6="","",'Config'!$G$6) -> Moradia | C18: =IF($B18="",0,SUMIFS('Lançamentos'!$F$9:$F$1508,'Lançamentos'!$D$9:$D$1508,$B18,'Lançamentos'!$B$9:$B$1508,">="&C$5,'Lançamentos'!$B$9:$B$1508,"<"&EDATE(C$5,1))) -> 0 | D18: =IF($B18="",0,SUMIFS('Lançamentos'!$F$9:$F$1508,'Lançamentos'!$D$9:$D$1508,$B18,'Lançamentos'!$B$9:$B$1508,">="&D$5,'Lançamentos'!$B$9:$B$1508,"<"&EDATE(D$5,1))) -> 0 | E18: =IF($B18="",0,SUMIFS('Lançamentos'!$F$9:$F$1508,'Lançamentos'!$D$9:$D$1508,$B18,'Lançamentos'!$B$9:$B$1508,">="&E$5,'Lançamentos'!$B$9:$B$1508,"<"&EDATE(E$5,1))) -> 0 | F18: =IF($B18="",0,SUMIFS('Lançamentos'!$F$9:$F$1508,'Lançamentos'!$D$9:$D$1508,$B18,'Lançamentos'!$B$9:$B$1508,">="&F$5,'Lançamentos'!$B$9:$B$1508,"<"&EDATE(F$5,1))) -> 0 | G18: =IF($B18="",0,SUMIFS('Lançamentos'!$F$9:$F$1508,'Lançamentos'!$D$9:$D$1508,$B18,'Lançamentos'!$B$9:$B$1508,">="&G$5,'Lançamentos'!$B$9:$B$1508,"<"&EDATE(G$5,1))) -> 0 | H18: =IF($B18="",0,SUMIFS('Lançamentos'!$F$9:$F$1508,'Lançamentos'!$D$9:$D$1508,$B18,'Lançamentos'!$B$9:$B$1508,">="&H$5,'Lançamentos'!$B$9:$B$1508,"<"&EDATE(H$5,1))) -> 0 | I18: =IF($B18="",0,SUMIFS('Lançamentos'!$F$9:$F$1508,'Lançamentos'!$D$9:$D$1508,$B18,'Lançamentos'!$B$9:$B$1508,">="&I$5,'Lançamentos'!$B$9:$B$1508,"<"&EDATE(I$5,1))) -> 0 | J18: =IF($B18="",0,SUMIFS('Lançamentos'!$F$9:$F$1508,'Lançamentos'!$D$9:$D$1508,$B18,'Lançamentos'!$B$9:$B$1508,">="&J$5,'Lançamentos'!$B$9:$B$1508,"<"&EDATE(J$5,1))) -> 0 | ... N18: =IF($B18="",0,SUMIFS('Lançamentos'!$F$9:$F$1508,'Lançamentos'!$D$9:$D$1508,$B18,'Lançamentos'!$B$9:$B$1508,">="&N$5,'Lançamentos'!$B$9:$B$1508,"<"&EDATE(N$5,1))) -> 0 | O18: =SUM(C18:N18) -> 0 | P18: =IFERROR(O18/'Dados'!$C$9,0) -> 0 | Q18: =IFERROR(O18/$O$34,0) -> 0
B19: =IF('Config'!$G$7="","",'Config'!$G$7) -> Contas da casa | C19: =IF($B19="",0,SUMIFS('Lançamentos'!$F$9:$F$1508,'Lançamentos'!$D$9:$D$1508,$B19,'Lançamentos'!$B$9:$B$1508,">="&C$5,'Lançamentos'!$B$9:$B$1508,"<"&EDATE(C$5,1))) -> 0 | D19: =IF($B19="",0,SUMIFS('Lançamentos'!$F$9:$F$1508,'Lançamentos'!$D$9:$D$1508,$B19,'Lançamentos'!$B$9:$B$1508,">="&D$5,'Lançamentos'!$B$9:$B$1508,"<"&EDATE(D$5,1))) -> 0 | E19: =IF($B19="",0,SUMIFS('Lançamentos'!$F$9:$F$1508,'Lançamentos'!$D$9:$D$1508,$B19,'Lançamentos'!$B$9:$B$1508,">="&E$5,'Lançamentos'!$B$9:$B$1508,"<"&EDATE(E$5,1))) -> 0 | F19: =IF($B19="",0,SUMIFS('Lançamentos'!$F$9:$F$1508,'Lançamentos'!$D$9:$D$1508,$B19,'Lançamentos'!$B$9:$B$1508,">="&F$5,'Lançamentos'!$B$9:$B$1508,"<"&EDATE(F$5,1))) -> 0 | G19: =IF($B19="",0,SUMIFS('Lançamentos'!$F$9:$F$1508,'Lançamentos'!$D$9:$D$1508,$B19,'Lançamentos'!$B$9:$B$1508,">="&G$5,'Lançamentos'!$B$9:$B$1508,"<"&EDATE(G$5,1))) -> 0 | H19: =IF($B19="",0,SUMIFS('Lançamentos'!$F$9:$F$1508,'Lançamentos'!$D$9:$D$1508,$B19,'Lançamentos'!$B$9:$B$1508,">="&H$5,'Lançamentos'!$B$9:$B$1508,"<"&EDATE(H$5,1))) -> 0 | I19: =IF($B19="",0,SUMIFS('Lançamentos'!$F$9:$F$1508,'Lançamentos'!$D$9:$D$1508,$B19,'Lançamentos'!$B$9:$B$1508,">="&I$5,'Lançamentos'!$B$9:$B$1508,"<"&EDATE(I$5,1))) -> 0 | J19: =IF($B19="",0,SUMIFS('Lançamentos'!$F$9:$F$1508,'Lançamentos'!$D$9:$D$1508,$B19,'Lançamentos'!$B$9:$B$1508,">="&J$5,'Lançamentos'!$B$9:$B$1508,"<"&EDATE(J$5,1))) -> 0 | ... N19: =IF($B19="",0,SUMIFS('Lançamentos'!$F$9:$F$1508,'Lançamentos'!$D$9:$D$1508,$B19,'Lançamentos'!$B$9:$B$1508,">="&N$5,'Lançamentos'!$B$9:$B$1508,"<"&EDATE(N$5,1))) -> 0 | O19: =SUM(C19:N19) -> 0 | P19: =IFERROR(O19/'Dados'!$C$9,0) -> 0 | Q19: =IFERROR(O19/$O$34,0) -> 0
B20: =IF('Config'!$G$8="","",'Config'!$G$8) -> Alimentação | C20: =IF($B20="",0,SUMIFS('Lançamentos'!$F$9:$F$1508,'Lançamentos'!$D$9:$D$1508,$B20,'Lançamentos'!$B$9:$B$1508,">="&C$5,'Lançamentos'!$B$9:$B$1508,"<"&EDATE(C$5,1))) -> 0 | D20: =IF($B20="",0,SUMIFS('Lançamentos'!$F$9:$F$1508,'Lançamentos'!$D$9:$D$1508,$B20,'Lançamentos'!$B$9:$B$1508,">="&D$5,'Lançamentos'!$B$9:$B$1508,"<"&EDATE(D$5,1))) -> 0 | E20: =IF($B20="",0,SUMIFS('Lançamentos'!$F$9:$F$1508,'Lançamentos'!$D$9:$D$1508,$B20,'Lançamentos'!$B$9:$B$1508,">="&E$5,'Lançamentos'!$B$9:$B$1508,"<"&EDATE(E$5,1))) -> 0 | F20: =IF($B20="",0,SUMIFS('Lançamentos'!$F$9:$F$1508,'Lançamentos'!$D$9:$D$1508,$B20,'Lançamentos'!$B$9:$B$1508,">="&F$5,'Lançamentos'!$B$9:$B$1508,"<"&EDATE(F$5,1))) -> 0 | G20: =IF($B20="",0,SUMIFS('Lançamentos'!$F$9:$F$1508,'Lançamentos'!$D$9:$D$1508,$B20,'Lançamentos'!$B$9:$B$1508,">="&G$5,'Lançamentos'!$B$9:$B$1508,"<"&EDATE(G$5,1))) -> 0 | H20: =IF($B20="",0,SUMIFS('Lançamentos'!$F$9:$F$1508,'Lançamentos'!$D$9:$D$1508,$B20,'Lançamentos'!$B$9:$B$1508,">="&H$5,'Lançamentos'!$B$9:$B$1508,"<"&EDATE(H$5,1))) -> 0 | I20: =IF($B20="",0,SUMIFS('Lançamentos'!$F$9:$F$1508,'Lançamentos'!$D$9:$D$1508,$B20,'Lançamentos'!$B$9:$B$1508,">="&I$5,'Lançamentos'!$B$9:$B$1508,"<"&EDATE(I$5,1))) -> 0 | J20: =IF($B20="",0,SUMIFS('Lançamentos'!$F$9:$F$1508,'Lançamentos'!$D$9:$D$1508,$B20,'Lançamentos'!$B$9:$B$1508,">="&J$5,'Lançamentos'!$B$9:$B$1508,"<"&EDATE(J$5,1))) -> 0 | ... N20: =IF($B20="",0,SUMIFS('Lançamentos'!$F$9:$F$1508,'Lançamentos'!$D$9:$D$1508,$B20,'Lançamentos'!$B$9:$B$1508,">="&N$5,'Lançamentos'!$B$9:$B$1508,"<"&EDATE(N$5,1))) -> 0 | O20: =SUM(C20:N20) -> 0 | P20: =IFERROR(O20/'Dados'!$C$9,0) -> 0 | Q20: =IFERROR(O20/$O$34,0) -> 0
B21: =IF('Config'!$G$9="","",'Config'!$G$9) -> Transporte | C21: =IF($B21="",0,SUMIFS('Lançamentos'!$F$9:$F$1508,'Lançamentos'!$D$9:$D$1508,$B21,'Lançamentos'!$B$9:$B$1508,">="&C$5,'Lançamentos'!$B$9:$B$1508,"<"&EDATE(C$5,1))) -> 0 | D21: =IF($B21="",0,SUMIFS('Lançamentos'!$F$9:$F$1508,'Lançamentos'!$D$9:$D$1508,$B21,'Lançamentos'!$B$9:$B$1508,">="&D$5,'Lançamentos'!$B$9:$B$1508,"<"&EDATE(D$5,1))) -> 0 | E21: =IF($B21="",0,SUMIFS('Lançamentos'!$F$9:$F$1508,'Lançamentos'!$D$9:$D$1508,$B21,'Lançamentos'!$B$9:$B$1508,">="&E$5,'Lançamentos'!$B$9:$B$1508,"<"&EDATE(E$5,1))) -> 0 | F21: =IF($B21="",0,SUMIFS('Lançamentos'!$F$9:$F$1508,'Lançamentos'!$D$9:$D$1508,$B21,'Lançamentos'!$B$9:$B$1508,">="&F$5,'Lançamentos'!$B$9:$B$1508,"<"&EDATE(F$5,1))) -> 0 | G21: =IF($B21="",0,SUMIFS('Lançamentos'!$F$9:$F$1508,'Lançamentos'!$D$9:$D$1508,$B21,'Lançamentos'!$B$9:$B$1508,">="&G$5,'Lançamentos'!$B$9:$B$1508,"<"&EDATE(G$5,1))) -> 0 | H21: =IF($B21="",0,SUMIFS('Lançamentos'!$F$9:$F$1508,'Lançamentos'!$D$9:$D$1508,$B21,'Lançamentos'!$B$9:$B$1508,">="&H$5,'Lançamentos'!$B$9:$B$1508,"<"&EDATE(H$5,1))) -> 0 | I21: =IF($B21="",0,SUMIFS('Lançamentos'!$F$9:$F$1508,'Lançamentos'!$D$9:$D$1508,$B21,'Lançamentos'!$B$9:$B$1508,">="&I$5,'Lançamentos'!$B$9:$B$1508,"<"&EDATE(I$5,1))) -> 0 | J21: =IF($B21="",0,SUMIFS('Lançamentos'!$F$9:$F$1508,'Lançamentos'!$D$9:$D$1508,$B21,'Lançamentos'!$B$9:$B$1508,">="&J$5,'Lançamentos'!$B$9:$B$1508,"<"&EDATE(J$5,1))) -> 0 | ... N21: =IF($B21="",0,SUMIFS('Lançamentos'!$F$9:$F$1508,'Lançamentos'!$D$9:$D$1508,$B21,'Lançamentos'!$B$9:$B$1508,">="&N$5,'Lançamentos'!$B$9:$B$1508,"<"&EDATE(N$5,1))) -> 0 | O21: =SUM(C21:N21) -> 0 | P21: =IFERROR(O21/'Dados'!$C$9,0) -> 0 | Q21: =IFERROR(O21/$O$34,0) -> 0
B22: =IF('Config'!$G$10="","",'Config'!$G$10) -> Saúde | C22: =IF($B22="",0,SUMIFS('Lançamentos'!$F$9:$F$1508,'Lançamentos'!$D$9:$D$1508,$B22,'Lançamentos'!$B$9:$B$1508,">="&C$5,'Lançamentos'!$B$9:$B$1508,"<"&EDATE(C$5,1))) -> 0 | D22: =IF($B22="",0,SUMIFS('Lançamentos'!$F$9:$F$1508,'Lançamentos'!$D$9:$D$1508,$B22,'Lançamentos'!$B$9:$B$1508,">="&D$5,'Lançamentos'!$B$9:$B$1508,"<"&EDATE(D$5,1))) -> 0 | E22: =IF($B22="",0,SUMIFS('Lançamentos'!$F$9:$F$1508,'Lançamentos'!$D$9:$D$1508,$B22,'Lançamentos'!$B$9:$B$1508,">="&E$5,'Lançamentos'!$B$9:$B$1508,"<"&EDATE(E$5,1))) -> 0 | F22: =IF($B22="",0,SUMIFS('Lançamentos'!$F$9:$F$1508,'Lançamentos'!$D$9:$D$1508,$B22,'Lançamentos'!$B$9:$B$1508,">="&F$5,'Lançamentos'!$B$9:$B$1508,"<"&EDATE(F$5,1))) -> 0 | G22: =IF($B22="",0,SUMIFS('Lançamentos'!$F$9:$F$1508,'Lançamentos'!$D$9:$D$1508,$B22,'Lançamentos'!$B$9:$B$1508,">="&G$5,'Lançamentos'!$B$9:$B$1508,"<"&EDATE(G$5,1))) -> 0 | H22: =IF($B22="",0,SUMIFS('Lançamentos'!$F$9:$F$1508,'Lançamentos'!$D$9:$D$1508,$B22,'Lançamentos'!$B$9:$B$1508,">="&H$5,'Lançamentos'!$B$9:$B$1508,"<"&EDATE(H$5,1))) -> 0 | I22: =IF($B22="",0,SUMIFS('Lançamentos'!$F$9:$F$1508,'Lançamentos'!$D$9:$D$1508,$B22,'Lançamentos'!$B$9:$B$1508,">="&I$5,'Lançamentos'!$B$9:$B$1508,"<"&EDATE(I$5,1))) -> 0 | J22: =IF($B22="",0,SUMIFS('Lançamentos'!$F$9:$F$1508,'Lançamentos'!$D$9:$D$1508,$B22,'Lançamentos'!$B$9:$B$1508,">="&J$5,'Lançamentos'!$B$9:$B$1508,"<"&EDATE(J$5,1))) -> 0 | ... N22: =IF($B22="",0,SUMIFS('Lançamentos'!$F$9:$F$1508,'Lançamentos'!$D$9:$D$1508,$B22,'Lançamentos'!$B$9:$B$1508,">="&N$5,'Lançamentos'!$B$9:$B$1508,"<"&EDATE(N$5,1))) -> 0 | O22: =SUM(C22:N22) -> 0 | P22: =IFERROR(O22/'Dados'!$C$9,0) -> 0 | Q22: =IFERROR(O22/$O$34,0) -> 0
B23: =IF('Config'!$G$11="","",'Config'!$G$11) -> Educação | C23: =IF($B23="",0,SUMIFS('Lançamentos'!$F$9:$F$1508,'Lançamentos'!$D$9:$D$1508,$B23,'Lançamentos'!$B$9:$B$1508,">="&C$5,'Lançamentos'!$B$9:$B$1508,"<"&EDATE(C$5,1))) -> 0 | D23: =IF($B23="",0,SUMIFS('Lançamentos'!$F$9:$F$1508,'Lançamentos'!$D$9:$D$1508,$B23,'Lançamentos'!$B$9:$B$1508,">="&D$5,'Lançamentos'!$B$9:$B$1508,"<"&EDATE(D$5,1))) -> 0 | E23: =IF($B23="",0,SUMIFS('Lançamentos'!$F$9:$F$1508,'Lançamentos'!$D$9:$D$1508,$B23,'Lançamentos'!$B$9:$B$1508,">="&E$5,'Lançamentos'!$B$9:$B$1508,"<"&EDATE(E$5,1))) -> 0 | F23: =IF($B23="",0,SUMIFS('Lançamentos'!$F$9:$F$1508,'Lançamentos'!$D$9:$D$1508,$B23,'Lançamentos'!$B$9:$B$1508,">="&F$5,'Lançamentos'!$B$9:$B$1508,"<"&EDATE(F$5,1))) -> 0 | G23: =IF($B23="",0,SUMIFS('Lançamentos'!$F$9:$F$1508,'Lançamentos'!$D$9:$D$1508,$B23,'Lançamentos'!$B$9:$B$1508,">="&G$5,'Lançamentos'!$B$9:$B$1508,"<"&EDATE(G$5,1))) -> 0 | H23: =IF($B23="",0,SUMIFS('Lançamentos'!$F$9:$F$1508,'Lançamentos'!$D$9:$D$1508,$B23,'Lançamentos'!$B$9:$B$1508,">="&H$5,'Lançamentos'!$B$9:$B$1508,"<"&EDATE(H$5,1))) -> 0 | I23: =IF($B23="",0,SUMIFS('Lançamentos'!$F$9:$F$1508,'Lançamentos'!$D$9:$D$1508,$B23,'Lançamentos'!$B$9:$B$1508,">="&I$5,'Lançamentos'!$B$9:$B$1508,"<"&EDATE(I$5,1))) -> 0 | J23: =IF($B23="",0,SUMIFS('Lançamentos'!$F$9:$F$1508,'Lançamentos'!$D$9:$D$1508,$B23,'Lançamentos'!$B$9:$B$1508,">="&J$5,'Lançamentos'!$B$9:$B$1508,"<"&EDATE(J$5,1))) -> 0 | ... N23: =IF($B23="",0,SUMIFS('Lançamentos'!$F$9:$F$1508,'Lançamentos'!$D$9:$D$1508,$B23,'Lançamentos'!$B$9:$B$1508,">="&N$5,'Lançamentos'!$B$9:$B$1508,"<"&EDATE(N$5,1))) -> 0 | O23: =SUM(C23:N23) -> 0 | P23: =IFERROR(O23/'Dados'!$C$9,0) -> 0 | Q23: =IFERROR(O23/$O$34,0) -> 0
B24: =IF('Config'!$G$12="","",'Config'!$G$12) -> Lazer | C24: =IF($B24="",0,SUMIFS('Lançamentos'!$F$9:$F$1508,'Lançamentos'!$D$9:$D$1508,$B24,'Lançamentos'!$B$9:$B$1508,">="&C$5,'Lançamentos'!$B$9:$B$1508,"<"&EDATE(C$5,1))) -> 0 | D24: =IF($B24="",0,SUMIFS('Lançamentos'!$F$9:$F$1508,'Lançamentos'!$D$9:$D$1508,$B24,'Lançamentos'!$B$9:$B$1508,">="&D$5,'Lançamentos'!$B$9:$B$1508,"<"&EDATE(D$5,1))) -> 0 | E24: =IF($B24="",0,SUMIFS('Lançamentos'!$F$9:$F$1508,'Lançamentos'!$D$9:$D$1508,$B24,'Lançamentos'!$B$9:$B$1508,">="&E$5,'Lançamentos'!$B$9:$B$1508,"<"&EDATE(E$5,1))) -> 0 | F24: =IF($B24="",0,SUMIFS('Lançamentos'!$F$9:$F$1508,'Lançamentos'!$D$9:$D$1508,$B24,'Lançamentos'!$B$9:$B$1508,">="&F$5,'Lançamentos'!$B$9:$B$1508,"<"&EDATE(F$5,1))) -> 0 | G24: =IF($B24="",0,SUMIFS('Lançamentos'!$F$9:$F$1508,'Lançamentos'!$D$9:$D$1508,$B24,'Lançamentos'!$B$9:$B$1508,">="&G$5,'Lançamentos'!$B$9:$B$1508,"<"&EDATE(G$5,1))) -> 0 | H24: =IF($B24="",0,SUMIFS('Lançamentos'!$F$9:$F$1508,'Lançamentos'!$D$9:$D$1508,$B24,'Lançamentos'!$B$9:$B$1508,">="&H$5,'Lançamentos'!$B$9:$B$1508,"<"&EDATE(H$5,1))) -> 0 | I24: =IF($B24="",0,SUMIFS('Lançamentos'!$F$9:$F$1508,'Lançamentos'!$D$9:$D$1508,$B24,'Lançamentos'!$B$9:$B$1508,">="&I$5,'Lançamentos'!$B$9:$B$1508,"<"&EDATE(I$5,1))) -> 0 | J24: =IF($B24="",0,SUMIFS('Lançamentos'!$F$9:$F$1508,'Lançamentos'!$D$9:$D$1508,$B24,'Lançamentos'!$B$9:$B$1508,">="&J$5,'Lançamentos'!$B$9:$B$1508,"<"&EDATE(J$5,1))) -> 0 | ... N24: =IF($B24="",0,SUMIFS('Lançamentos'!$F$9:$F$1508,'Lançamentos'!$D$9:$D$1508,$B24,'Lançamentos'!$B$9:$B$1508,">="&N$5,'Lançamentos'!$B$9:$B$1508,"<"&EDATE(N$5,1))) -> 0 | O24: =SUM(C24:N24) -> 0 | P24: =IFERROR(O24/'Dados'!$C$9,0) -> 0 | Q24: =IFERROR(O24/$O$34,0) -> 0
B25: =IF('Config'!$G$13="","",'Config'!$G$13) -> Vestuário | C25: =IF($B25="",0,SUMIFS('Lançamentos'!$F$9:$F$1508,'Lançamentos'!$D$9:$D$1508,$B25,'Lançamentos'!$B$9:$B$1508,">="&C$5,'Lançamentos'!$B$9:$B$1508,"<"&EDATE(C$5,1))) -> 0 | D25: =IF($B25="",0,SUMIFS('Lançamentos'!$F$9:$F$1508,'Lançamentos'!$D$9:$D$1508,$B25,'Lançamentos'!$B$9:$B$1508,">="&D$5,'Lançamentos'!$B$9:$B$1508,"<"&EDATE(D$5,1))) -> 0 | E25: =IF($B25="",0,SUMIFS('Lançamentos'!$F$9:$F$1508,'Lançamentos'!$D$9:$D$1508,$B25,'Lançamentos'!$B$9:$B$1508,">="&E$5,'Lançamentos'!$B$9:$B$1508,"<"&EDATE(E$5,1))) -> 0 | F25: =IF($B25="",0,SUMIFS('Lançamentos'!$F$9:$F$1508,'Lançamentos'!$D$9:$D$1508,$B25,'Lançamentos'!$B$9:$B$1508,">="&F$5,'Lançamentos'!$B$9:$B$1508,"<"&EDATE(F$5,1))) -> 0 | G25: =IF($B25="",0,SUMIFS('Lançamentos'!$F$9:$F$1508,'Lançamentos'!$D$9:$D$1508,$B25,'Lançamentos'!$B$9:$B$1508,">="&G$5,'Lançamentos'!$B$9:$B$1508,"<"&EDATE(G$5,1))) -> 0 | H25: =IF($B25="",0,SUMIFS('Lançamentos'!$F$9:$F$1508,'Lançamentos'!$D$9:$D$1508,$B25,'Lançamentos'!$B$9:$B$1508,">="&H$5,'Lançamentos'!$B$9:$B$1508,"<"&EDATE(H$5,1))) -> 0 | I25: =IF($B25="",0,SUMIFS('Lançamentos'!$F$9:$F$1508,'Lançamentos'!$D$9:$D$1508,$B25,'Lançamentos'!$B$9:$B$1508,">="&I$5,'Lançamentos'!$B$9:$B$1508,"<"&EDATE(I$5,1))) -> 0 | J25: =IF($B25="",0,SUMIFS('Lançamentos'!$F$9:$F$1508,'Lançamentos'!$D$9:$D$1508,$B25,'Lançamentos'!$B$9:$B$1508,">="&J$5,'Lançamentos'!$B$9:$B$1508,"<"&EDATE(J$5,1))) -> 0 | ... N25: =IF($B25="",0,SUMIFS('Lançamentos'!$F$9:$F$1508,'Lançamentos'!$D$9:$D$1508,$B25,'Lançamentos'!$B$9:$B$1508,">="&N$5,'Lançamentos'!$B$9:$B$1508,"<"&EDATE(N$5,1))) -> 0 | O25: =SUM(C25:N25) -> 0 | P25: =IFERROR(O25/'Dados'!$C$9,0) -> 0 | Q25: =IFERROR(O25/$O$34,0) -> 0
B26: =IF('Config'!$G$14="","",'Config'!$G$14) -> Assinaturas | C26: =IF($B26="",0,SUMIFS('Lançamentos'!$F$9:$F$1508,'Lançamentos'!$D$9:$D$1508,$B26,'Lançamentos'!$B$9:$B$1508,">="&C$5,'Lançamentos'!$B$9:$B$1508,"<"&EDATE(C$5,1))) -> 0 | D26: =IF($B26="",0,SUMIFS('Lançamentos'!$F$9:$F$1508,'Lançamentos'!$D$9:$D$1508,$B26,'Lançamentos'!$B$9:$B$1508,">="&D$5,'Lançamentos'!$B$9:$B$1508,"<"&EDATE(D$5,1))) -> 0 | E26: =IF($B26="",0,SUMIFS('Lançamentos'!$F$9:$F$1508,'Lançamentos'!$D$9:$D$1508,$B26,'Lançamentos'!$B$9:$B$1508,">="&E$5,'Lançamentos'!$B$9:$B$1508,"<"&EDATE(E$5,1))) -> 0 | F26: =IF($B26="",0,SUMIFS('Lançamentos'!$F$9:$F$1508,'Lançamentos'!$D$9:$D$1508,$B26,'Lançamentos'!$B$9:$B$1508,">="&F$5,'Lançamentos'!$B$9:$B$1508,"<"&EDATE(F$5,1))) -> 0 | G26: =IF($B26="",0,SUMIFS('Lançamentos'!$F$9:$F$1508,'Lançamentos'!$D$9:$D$1508,$B26,'Lançamentos'!$B$9:$B$1508,">="&G$5,'Lançamentos'!$B$9:$B$1508,"<"&EDATE(G$5,1))) -> 0 | H26: =IF($B26="",0,SUMIFS('Lançamentos'!$F$9:$F$1508,'Lançamentos'!$D$9:$D$1508,$B26,'Lançamentos'!$B$9:$B$1508,">="&H$5,'Lançamentos'!$B$9:$B$1508,"<"&EDATE(H$5,1))) -> 0 | I26: =IF($B26="",0,SUMIFS('Lançamentos'!$F$9:$F$1508,'Lançamentos'!$D$9:$D$1508,$B26,'Lançamentos'!$B$9:$B$1508,">="&I$5,'Lançamentos'!$B$9:$B$1508,"<"&EDATE(I$5,1))) -> 0 | J26: =IF($B26="",0,SUMIFS('Lançamentos'!$F$9:$F$1508,'Lançamentos'!$D$9:$D$1508,$B26,'Lançamentos'!$B$9:$B$1508,">="&J$5,'Lançamentos'!$B$9:$B$1508,"<"&EDATE(J$5,1))) -> 0 | ... N26: =IF($B26="",0,SUMIFS('Lançamentos'!$F$9:$F$1508,'Lançamentos'!$D$9:$D$1508,$B26,'Lançamentos'!$B$9:$B$1508,">="&N$5,'Lançamentos'!$B$9:$B$1508,"<"&EDATE(N$5,1))) -> 0 | O26: =SUM(C26:N26) -> 0 | P26: =IFERROR(O26/'Dados'!$C$9,0) -> 0 | Q26: =IFERROR(O26/$O$34,0) -> 0
B27: =IF('Config'!$G$15="","",'Config'!$G$15) -> Cuidados pessoais | C27: =IF($B27="",0,SUMIFS('Lançamentos'!$F$9:$F$1508,'Lançamentos'!$D$9:$D$1508,$B27,'Lançamentos'!$B$9:$B$1508,">="&C$5,'Lançamentos'!$B$9:$B$1508,"<"&EDATE(C$5,1))) -> 0 | D27: =IF($B27="",0,SUMIFS('Lançamentos'!$F$9:$F$1508,'Lançamentos'!$D$9:$D$1508,$B27,'Lançamentos'!$B$9:$B$1508,">="&D$5,'Lançamentos'!$B$9:$B$1508,"<"&EDATE(D$5,1))) -> 0 | E27: =IF($B27="",0,SUMIFS('Lançamentos'!$F$9:$F$1508,'Lançamentos'!$D$9:$D$1508,$B27,'Lançamentos'!$B$9:$B$1508,">="&E$5,'Lançamentos'!$B$9:$B$1508,"<"&EDATE(E$5,1))) -> 0 | F27: =IF($B27="",0,SUMIFS('Lançamentos'!$F$9:$F$1508,'Lançamentos'!$D$9:$D$1508,$B27,'Lançamentos'!$B$9:$B$1508,">="&F$5,'Lançamentos'!$B$9:$B$1508,"<"&EDATE(F$5,1))) -> 0 | G27: =IF($B27="",0,SUMIFS('Lançamentos'!$F$9:$F$1508,'Lançamentos'!$D$9:$D$1508,$B27,'Lançamentos'!$B$9:$B$1508,">="&G$5,'Lançamentos'!$B$9:$B$1508,"<"&EDATE(G$5,1))) -> 0 | H27: =IF($B27="",0,SUMIFS('Lançamentos'!$F$9:$F$1508,'Lançamentos'!$D$9:$D$1508,$B27,'Lançamentos'!$B$9:$B$1508,">="&H$5,'Lançamentos'!$B$9:$B$1508,"<"&EDATE(H$5,1))) -> 0 | I27: =IF($B27="",0,SUMIFS('Lançamentos'!$F$9:$F$1508,'Lançamentos'!$D$9:$D$1508,$B27,'Lançamentos'!$B$9:$B$1508,">="&I$5,'Lançamentos'!$B$9:$B$1508,"<"&EDATE(I$5,1))) -> 0 | J27: =IF($B27="",0,SUMIFS('Lançamentos'!$F$9:$F$1508,'Lançamentos'!$D$9:$D$1508,$B27,'Lançamentos'!$B$9:$B$1508,">="&J$5,'Lançamentos'!$B$9:$B$1508,"<"&EDATE(J$5,1))) -> 0 | ... N27: =IF($B27="",0,SUMIFS('Lançamentos'!$F$9:$F$1508,'Lançamentos'!$D$9:$D$1508,$B27,'Lançamentos'!$B$9:$B$1508,">="&N$5,'Lançamentos'!$B$9:$B$1508,"<"&EDATE(N$5,1))) -> 0 | O27: =SUM(C27:N27) -> 0 | P27: =IFERROR(O27/'Dados'!$C$9,0) -> 0 | Q27: =IFERROR(O27/$O$34,0) -> 0
B28: =IF('Config'!$G$16="","",'Config'!$G$16) -> Pets | C28: =IF($B28="",0,SUMIFS('Lançamentos'!$F$9:$F$1508,'Lançamentos'!$D$9:$D$1508,$B28,'Lançamentos'!$B$9:$B$1508,">="&C$5,'Lançamentos'!$B$9:$B$1508,"<"&EDATE(C$5,1))) -> 0 | D28: =IF($B28="",0,SUMIFS('Lançamentos'!$F$9:$F$1508,'Lançamentos'!$D$9:$D$1508,$B28,'Lançamentos'!$B$9:$B$1508,">="&D$5,'Lançamentos'!$B$9:$B$1508,"<"&EDATE(D$5,1))) -> 0 | E28: =IF($B28="",0,SUMIFS('Lançamentos'!$F$9:$F$1508,'Lançamentos'!$D$9:$D$1508,$B28,'Lançamentos'!$B$9:$B$1508,">="&E$5,'Lançamentos'!$B$9:$B$1508,"<"&EDATE(E$5,1))) -> 0 | F28: =IF($B28="",0,SUMIFS('Lançamentos'!$F$9:$F$1508,'Lançamentos'!$D$9:$D$1508,$B28,'Lançamentos'!$B$9:$B$1508,">="&F$5,'Lançamentos'!$B$9:$B$1508,"<"&EDATE(F$5,1))) -> 0 | G28: =IF($B28="",0,SUMIFS('Lançamentos'!$F$9:$F$1508,'Lançamentos'!$D$9:$D$1508,$B28,'Lançamentos'!$B$9:$B$1508,">="&G$5,'Lançamentos'!$B$9:$B$1508,"<"&EDATE(G$5,1))) -> 0 | H28: =IF($B28="",0,SUMIFS('Lançamentos'!$F$9:$F$1508,'Lançamentos'!$D$9:$D$1508,$B28,'Lançamentos'!$B$9:$B$1508,">="&H$5,'Lançamentos'!$B$9:$B$1508,"<"&EDATE(H$5,1))) -> 0 | I28: =IF($B28="",0,SUMIFS('Lançamentos'!$F$9:$F$1508,'Lançamentos'!$D$9:$D$1508,$B28,'Lançamentos'!$B$9:$B$1508,">="&I$5,'Lançamentos'!$B$9:$B$1508,"<"&EDATE(I$5,1))) -> 0 | J28: =IF($B28="",0,SUMIFS('Lançamentos'!$F$9:$F$1508,'Lançamentos'!$D$9:$D$1508,$B28,'Lançamentos'!$B$9:$B$1508,">="&J$5,'Lançamentos'!$B$9:$B$1508,"<"&EDATE(J$5,1))) -> 0 | ... N28: =IF($B28="",0,SUMIFS('Lançamentos'!$F$9:$F$1508,'Lançamentos'!$D$9:$D$1508,$B28,'Lançamentos'!$B$9:$B$1508,">="&N$5,'Lançamentos'!$B$9:$B$1508,"<"&EDATE(N$5,1))) -> 0 | O28: =SUM(C28:N28) -> 0 | P28: =IFERROR(O28/'Dados'!$C$9,0) -> 0 | Q28: =IFERROR(O28/$O$34,0) -> 0
B29: =IF('Config'!$G$17="","",'Config'!$G$17) -> Presentes e doações | C29: =IF($B29="",0,SUMIFS('Lançamentos'!$F$9:$F$1508,'Lançamentos'!$D$9:$D$1508,$B29,'Lançamentos'!$B$9:$B$1508,">="&C$5,'Lançamentos'!$B$9:$B$1508,"<"&EDATE(C$5,1))) -> 0 | D29: =IF($B29="",0,SUMIFS('Lançamentos'!$F$9:$F$1508,'Lançamentos'!$D$9:$D$1508,$B29,'Lançamentos'!$B$9:$B$1508,">="&D$5,'Lançamentos'!$B$9:$B$1508,"<"&EDATE(D$5,1))) -> 0 | E29: =IF($B29="",0,SUMIFS('Lançamentos'!$F$9:$F$1508,'Lançamentos'!$D$9:$D$1508,$B29,'Lançamentos'!$B$9:$B$1508,">="&E$5,'Lançamentos'!$B$9:$B$1508,"<"&EDATE(E$5,1))) -> 0 | F29: =IF($B29="",0,SUMIFS('Lançamentos'!$F$9:$F$1508,'Lançamentos'!$D$9:$D$1508,$B29,'Lançamentos'!$B$9:$B$1508,">="&F$5,'Lançamentos'!$B$9:$B$1508,"<"&EDATE(F$5,1))) -> 0 | G29: =IF($B29="",0,SUMIFS('Lançamentos'!$F$9:$F$1508,'Lançamentos'!$D$9:$D$1508,$B29,'Lançamentos'!$B$9:$B$1508,">="&G$5,'Lançamentos'!$B$9:$B$1508,"<"&EDATE(G$5,1))) -> 0 | H29: =IF($B29="",0,SUMIFS('Lançamentos'!$F$9:$F$1508,'Lançamentos'!$D$9:$D$1508,$B29,'Lançamentos'!$B$9:$B$1508,">="&H$5,'Lançamentos'!$B$9:$B$1508,"<"&EDATE(H$5,1))) -> 0 | I29: =IF($B29="",0,SUMIFS('Lançamentos'!$F$9:$F$1508,'Lançamentos'!$D$9:$D$1508,$B29,'Lançamentos'!$B$9:$B$1508,">="&I$5,'Lançamentos'!$B$9:$B$1508,"<"&EDATE(I$5,1))) -> 0 | J29: =IF($B29="",0,SUMIFS('Lançamentos'!$F$9:$F$1508,'Lançamentos'!$D$9:$D$1508,$B29,'Lançamentos'!$B$9:$B$1508,">="&J$5,'Lançamentos'!$B$9:$B$1508,"<"&EDATE(J$5,1))) -> 0 | ... N29: =IF($B29="",0,SUMIFS('Lançamentos'!$F$9:$F$1508,'Lançamentos'!$D$9:$D$1508,$B29,'Lançamentos'!$B$9:$B$1508,">="&N$5,'Lançamentos'!$B$9:$B$1508,"<"&EDATE(N$5,1))) -> 0 | O29: =SUM(C29:N29) -> 0 | P29: =IFERROR(O29/'Dados'!$C$9,0) -> 0 | Q29: =IFERROR(O29/$O$34,0) -> 0
B30: =IF('Config'!$G$18="","",'Config'!$G$18) -> Dívidas e financiamentos | C30: =IF($B30="",0,SUMIFS('Lançamentos'!$F$9:$F$1508,'Lançamentos'!$D$9:$D$1508,$B30,'Lançamentos'!$B$9:$B$1508,">="&C$5,'Lançamentos'!$B$9:$B$1508,"<"&EDATE(C$5,1))) -> 0 | D30: =IF($B30="",0,SUMIFS('Lançamentos'!$F$9:$F$1508,'Lançamentos'!$D$9:$D$1508,$B30,'Lançamentos'!$B$9:$B$1508,">="&D$5,'Lançamentos'!$B$9:$B$1508,"<"&EDATE(D$5,1))) -> 0 | E30: =IF($B30="",0,SUMIFS('Lançamentos'!$F$9:$F$1508,'Lançamentos'!$D$9:$D$1508,$B30,'Lançamentos'!$B$9:$B$1508,">="&E$5,'Lançamentos'!$B$9:$B$1508,"<"&EDATE(E$5,1))) -> 0 | F30: =IF($B30="",0,SUMIFS('Lançamentos'!$F$9:$F$1508,'Lançamentos'!$D$9:$D$1508,$B30,'Lançamentos'!$B$9:$B$1508,">="&F$5,'Lançamentos'!$B$9:$B$1508,"<"&EDATE(F$5,1))) -> 0 | G30: =IF($B30="",0,SUMIFS('Lançamentos'!$F$9:$F$1508,'Lançamentos'!$D$9:$D$1508,$B30,'Lançamentos'!$B$9:$B$1508,">="&G$5,'Lançamentos'!$B$9:$B$1508,"<"&EDATE(G$5,1))) -> 0 | H30: =IF($B30="",0,SUMIFS('Lançamentos'!$F$9:$F$1508,'Lançamentos'!$D$9:$D$1508,$B30,'Lançamentos'!$B$9:$B$1508,">="&H$5,'Lançamentos'!$B$9:$B$1508,"<"&EDATE(H$5,1))) -> 0 | I30: =IF($B30="",0,SUMIFS('Lançamentos'!$F$9:$F$1508,'Lançamentos'!$D$9:$D$1508,$B30,'Lançamentos'!$B$9:$B$1508,">="&I$5,'Lançamentos'!$B$9:$B$1508,"<"&EDATE(I$5,1))) -> 0 | J30: =IF($B30="",0,SUMIFS('Lançamentos'!$F$9:$F$1508,'Lançamentos'!$D$9:$D$1508,$B30,'Lançamentos'!$B$9:$B$1508,">="&J$5,'Lançamentos'!$B$9:$B$1508,"<"&EDATE(J$5,1))) -> 0 | ... N30: =IF($B30="",0,SUMIFS('Lançamentos'!$F$9:$F$1508,'Lançamentos'!$D$9:$D$1508,$B30,'Lançamentos'!$B$9:$B$1508,">="&N$5,'Lançamentos'!$B$9:$B$1508,"<"&EDATE(N$5,1))) -> 0 | O30: =SUM(C30:N30) -> 0 | P30: =IFERROR(O30/'Dados'!$C$9,0) -> 0 | Q30: =IFERROR(O30/$O$34,0) -> 0
B31: =IF('Config'!$G$19="","",'Config'!$G$19) -> Reserva e Metas | C31: =IF($B31="",0,SUMIFS('Lançamentos'!$F$9:$F$1508,'Lançamentos'!$D$9:$D$1508,$B31,'Lançamentos'!$B$9:$B$1508,">="&C$5,'Lançamentos'!$B$9:$B$1508,"<"&EDATE(C$5,1))) -> 0 | D31: =IF($B31="",0,SUMIFS('Lançamentos'!$F$9:$F$1508,'Lançamentos'!$D$9:$D$1508,$B31,'Lançamentos'!$B$9:$B$1508,">="&D$5,'Lançamentos'!$B$9:$B$1508,"<"&EDATE(D$5,1))) -> 0 | E31: =IF($B31="",0,SUMIFS('Lançamentos'!$F$9:$F$1508,'Lançamentos'!$D$9:$D$1508,$B31,'Lançamentos'!$B$9:$B$1508,">="&E$5,'Lançamentos'!$B$9:$B$1508,"<"&EDATE(E$5,1))) -> 0 | F31: =IF($B31="",0,SUMIFS('Lançamentos'!$F$9:$F$1508,'Lançamentos'!$D$9:$D$1508,$B31,'Lançamentos'!$B$9:$B$1508,">="&F$5,'Lançamentos'!$B$9:$B$1508,"<"&EDATE(F$5,1))) -> 0 | G31: =IF($B31="",0,SUMIFS('Lançamentos'!$F$9:$F$1508,'Lançamentos'!$D$9:$D$1508,$B31,'Lançamentos'!$B$9:$B$1508,">="&G$5,'Lançamentos'!$B$9:$B$1508,"<"&EDATE(G$5,1))) -> 0 | H31: =IF($B31="",0,SUMIFS('Lançamentos'!$F$9:$F$1508,'Lançamentos'!$D$9:$D$1508,$B31,'Lançamentos'!$B$9:$B$1508,">="&H$5,'Lançamentos'!$B$9:$B$1508,"<"&EDATE(H$5,1))) -> 0 | I31: =IF($B31="",0,SUMIFS('Lançamentos'!$F$9:$F$1508,'Lançamentos'!$D$9:$D$1508,$B31,'Lançamentos'!$B$9:$B$1508,">="&I$5,'Lançamentos'!$B$9:$B$1508,"<"&EDATE(I$5,1))) -> 0 | J31: =IF($B31="",0,SUMIFS('Lançamentos'!$F$9:$F$1508,'Lançamentos'!$D$9:$D$1508,$B31,'Lançamentos'!$B$9:$B$1508,">="&J$5,'Lançamentos'!$B$9:$B$1508,"<"&EDATE(J$5,1))) -> 0 | ... N31: =IF($B31="",0,SUMIFS('Lançamentos'!$F$9:$F$1508,'Lançamentos'!$D$9:$D$1508,$B31,'Lançamentos'!$B$9:$B$1508,">="&N$5,'Lançamentos'!$B$9:$B$1508,"<"&EDATE(N$5,1))) -> 0 | O31: =SUM(C31:N31) -> 0 | P31: =IFERROR(O31/'Dados'!$C$9,0) -> 0 | Q31: =IFERROR(O31/$O$34,0) -> 0
B32: =IF('Config'!$G$20="","",'Config'!$G$20) -> Impostos pessoais | C32: =IF($B32="",0,SUMIFS('Lançamentos'!$F$9:$F$1508,'Lançamentos'!$D$9:$D$1508,$B32,'Lançamentos'!$B$9:$B$1508,">="&C$5,'Lançamentos'!$B$9:$B$1508,"<"&EDATE(C$5,1))) -> 0 | D32: =IF($B32="",0,SUMIFS('Lançamentos'!$F$9:$F$1508,'Lançamentos'!$D$9:$D$1508,$B32,'Lançamentos'!$B$9:$B$1508,">="&D$5,'Lançamentos'!$B$9:$B$1508,"<"&EDATE(D$5,1))) -> 0 | E32: =IF($B32="",0,SUMIFS('Lançamentos'!$F$9:$F$1508,'Lançamentos'!$D$9:$D$1508,$B32,'Lançamentos'!$B$9:$B$1508,">="&E$5,'Lançamentos'!$B$9:$B$1508,"<"&EDATE(E$5,1))) -> 0 | F32: =IF($B32="",0,SUMIFS('Lançamentos'!$F$9:$F$1508,'Lançamentos'!$D$9:$D$1508,$B32,'Lançamentos'!$B$9:$B$1508,">="&F$5,'Lançamentos'!$B$9:$B$1508,"<"&EDATE(F$5,1))) -> 0 | G32: =IF($B32="",0,SUMIFS('Lançamentos'!$F$9:$F$1508,'Lançamentos'!$D$9:$D$1508,$B32,'Lançamentos'!$B$9:$B$1508,">="&G$5,'Lançamentos'!$B$9:$B$1508,"<"&EDATE(G$5,1))) -> 0 | H32: =IF($B32="",0,SUMIFS('Lançamentos'!$F$9:$F$1508,'Lançamentos'!$D$9:$D$1508,$B32,'Lançamentos'!$B$9:$B$1508,">="&H$5,'Lançamentos'!$B$9:$B$1508,"<"&EDATE(H$5,1))) -> 0 | I32: =IF($B32="",0,SUMIFS('Lançamentos'!$F$9:$F$1508,'Lançamentos'!$D$9:$D$1508,$B32,'Lançamentos'!$B$9:$B$1508,">="&I$5,'Lançamentos'!$B$9:$B$1508,"<"&EDATE(I$5,1))) -> 0 | J32: =IF($B32="",0,SUMIFS('Lançamentos'!$F$9:$F$1508,'Lançamentos'!$D$9:$D$1508,$B32,'Lançamentos'!$B$9:$B$1508,">="&J$5,'Lançamentos'!$B$9:$B$1508,"<"&EDATE(J$5,1))) -> 0 | ... N32: =IF($B32="",0,SUMIFS('Lançamentos'!$F$9:$F$1508,'Lançamentos'!$D$9:$D$1508,$B32,'Lançamentos'!$B$9:$B$1508,">="&N$5,'Lançamentos'!$B$9:$B$1508,"<"&EDATE(N$5,1))) -> 0 | O32: =SUM(C32:N32) -> 0 | P32: =IFERROR(O32/'Dados'!$C$9,0) -> 0 | Q32: =IFERROR(O32/$O$34,0) -> 0
B33: =IF('Config'!$G$21="","",'Config'!$G$21) -> Outros | C33: =IF($B33="",0,SUMIFS('Lançamentos'!$F$9:$F$1508,'Lançamentos'!$D$9:$D$1508,$B33,'Lançamentos'!$B$9:$B$1508,">="&C$5,'Lançamentos'!$B$9:$B$1508,"<"&EDATE(C$5,1))) -> 0 | D33: =IF($B33="",0,SUMIFS('Lançamentos'!$F$9:$F$1508,'Lançamentos'!$D$9:$D$1508,$B33,'Lançamentos'!$B$9:$B$1508,">="&D$5,'Lançamentos'!$B$9:$B$1508,"<"&EDATE(D$5,1))) -> 0 | E33: =IF($B33="",0,SUMIFS('Lançamentos'!$F$9:$F$1508,'Lançamentos'!$D$9:$D$1508,$B33,'Lançamentos'!$B$9:$B$1508,">="&E$5,'Lançamentos'!$B$9:$B$1508,"<"&EDATE(E$5,1))) -> 0 | F33: =IF($B33="",0,SUMIFS('Lançamentos'!$F$9:$F$1508,'Lançamentos'!$D$9:$D$1508,$B33,'Lançamentos'!$B$9:$B$1508,">="&F$5,'Lançamentos'!$B$9:$B$1508,"<"&EDATE(F$5,1))) -> 0 | G33: =IF($B33="",0,SUMIFS('Lançamentos'!$F$9:$F$1508,'Lançamentos'!$D$9:$D$1508,$B33,'Lançamentos'!$B$9:$B$1508,">="&G$5,'Lançamentos'!$B$9:$B$1508,"<"&EDATE(G$5,1))) -> 0 | H33: =IF($B33="",0,SUMIFS('Lançamentos'!$F$9:$F$1508,'Lançamentos'!$D$9:$D$1508,$B33,'Lançamentos'!$B$9:$B$1508,">="&H$5,'Lançamentos'!$B$9:$B$1508,"<"&EDATE(H$5,1))) -> 0 | I33: =IF($B33="",0,SUMIFS('Lançamentos'!$F$9:$F$1508,'Lançamentos'!$D$9:$D$1508,$B33,'Lançamentos'!$B$9:$B$1508,">="&I$5,'Lançamentos'!$B$9:$B$1508,"<"&EDATE(I$5,1))) -> 0 | J33: =IF($B33="",0,SUMIFS('Lançamentos'!$F$9:$F$1508,'Lançamentos'!$D$9:$D$1508,$B33,'Lançamentos'!$B$9:$B$1508,">="&J$5,'Lançamentos'!$B$9:$B$1508,"<"&EDATE(J$5,1))) -> 0 | ... N33: =IF($B33="",0,SUMIFS('Lançamentos'!$F$9:$F$1508,'Lançamentos'!$D$9:$D$1508,$B33,'Lançamentos'!$B$9:$B$1508,">="&N$5,'Lançamentos'!$B$9:$B$1508,"<"&EDATE(N$5,1))) -> 0 | O33: =SUM(C33:N33) -> 0 | P33: =IFERROR(O33/'Dados'!$C$9,0) -> 0 | Q33: =IFERROR(O33/$O$34,0) -> 0
B34: Total de saídas | C34: =SUM(C18:C33) -> 0 | D34: =SUM(D18:D33) -> 0 | E34: =SUM(E18:E33) -> 0 | F34: =SUM(F18:F33) -> 0 | G34: =SUM(G18:G33) -> 0 | H34: =SUM(H18:H33) -> 0 | I34: =SUM(I18:I33) -> 0 | J34: =SUM(J18:J33) -> 0 | ... P34: =SUM(P18:P33) -> 0
B35: 💰 Saldo do mês (entradas − saídas) | C35: =C16-C34 -> 0 | D35: =D16-D34 -> 0 | E35: =E16-E34 -> 0 | F35: =F16-F34 -> 0 | G35: =G16-G34 -> 0 | H35: =H16-H34 -> 0 | I35: =I16-I34 -> 0 | J35: =J16-J34 -> 0 | ... O35: =O16-O34 -> 0
B36: 📈 Saldo acumulado (inclui saldo inicial) | C36: ='Config'!$C$10+C35 -> 0 | D36: =C36+D35 -> 0 | E36: =D36+E35 -> 0 | F36: =E36+F35 -> 0 | G36: =F36+G35 -> 0 | H36: =G36+H35 -> 0 | I36: =H36+I35 -> 0 | J36: =I36+J35 -> 0 | K36: =J36+K35 -> 0 | ... N36: =M36+N35 -> 0 | O36: =N36 -> 0
B37: 🏦 Taxa de poupança | C37: =IF(C16=0,"",(C35+C31)/C16) | D37: =IF(D16=0,"",(D35+D31)/D16) | E37: =IF(E16=0,"",(E35+E31)/E16) | F37: =IF(F16=0,"",(F35+F31)/F16) | G37: =IF(G16=0,"",(G35+G31)/G16) | H37: =IF(H16=0,"",(H35+H31)/H16) | I37: =IF(I16=0,"",(I35+I31)/I16) | J37: =IF(J16=0,"",(J35+J31)/J16) | ... O37: =IF(O16=0,"",(O35+O31)/O16)
B39: Taxa de poupança: o que sobrou + o que foi para 'Reserva e Metas' (14ª categoria de saída, tratada como poupança, não como gasto). Verde = meta atingida (Config); amarelo = abaixo da meta; vermelho = negativa.

Sheet Metas
B1: 🏠 Início | C1: 📊 Painel | E1: 📝 Lançamentos | G1: 💳 Orçamento | I1: 📅 Resumo Anual | J1: 🎯 Metas | L1: ⚙ Config
B3: 🎯 Metas de economia
B4: Cadastre seus objetivos. Para registrar um aporte, lance uma SAÍDA na aba de lançamentos e escolha a meta na última coluna (um resgate é uma ENTRADA com a meta escolhida).
B5: Meta | C5: Valor alvo | D5: Já guardado (antes) | E5: Prazo | F5: Aportes lançados | G5: Total guardado | H5: % concl. | I5: Progresso | J5: Falta | K5: Meses restantes | L5: Aporte mensal necessário | M5: Situação
F6: =IF($B6="","",SUMIFS('Lançamentos'!$F$9:$F$1508,'Lançamentos'!$H$9:$H$1508,$B6,'Lançamentos'!$G$9:$G$1508,"Saída")-SUMIFS('Lançamentos'!$F$9:$F$1508,'Lançamentos'!$H$9:$H$1508,$B6,'Lançamentos'!$G$9:$G$1508,"Entrada")) | G6: =IF($B6="","",N(D6)+F6) | H6: =IF(OR($B6="",N(C6)=0),"",G6/C6) | I6: =IF(H6="","",REPT("█",MIN(24,ROUND(H6*20,0)))) | J6: =IF(H6="","",MAX(0,C6-G6)) | K6: =IF(OR($B6="",E6=""),"",MAX(0,(YEAR(E6)-YEAR('Config'!$C$7))*12+MONTH(E6)-MONTH('Config'!$C$7))) | L6: =IF(OR(J6="",K6=""),"",IF(J6=0,0,IF(K6=0,J6,J6/K6))) | M6: =IF($B6="","",IF(N(C6)=0,"—",IF(G6>=C6,"✓ Concluída",IF(E6="","Em andamento",IF('Config'!$C$7>E6,"✖ Atrasada","● No prazo")))))
F7: =IF($B7="","",SUMIFS('Lançamentos'!$F$9:$F$1508,'Lançamentos'!$H$9:$H$1508,$B7,'Lançamentos'!$G$9:$G$1508,"Saída")-SUMIFS('Lançamentos'!$F$9:$F$1508,'Lançamentos'!$H$9:$H$1508,$B7,'Lançamentos'!$G$9:$G$1508,"Entrada")) | G7: =IF($B7="","",N(D7)+F7) | H7: =IF(OR($B7="",N(C7)=0),"",G7/C7) | I7: =IF(H7="","",REPT("█",MIN(24,ROUND(H7*20,0)))) | J7: =IF(H7="","",MAX(0,C7-G7)) | K7: =IF(OR($B7="",E7=""),"",MAX(0,(YEAR(E7)-YEAR('Config'!$C$7))*12+MONTH(E7)-MONTH('Config'!$C$7))) | L7: =IF(OR(J7="",K7=""),"",IF(J7=0,0,IF(K7=0,J7,J7/K7))) | M7: =IF($B7="","",IF(N(C7)=0,"—",IF(G7>=C7,"✓ Concluída",IF(E7="","Em andamento",IF('Config'!$C$7>E7,"✖ Atrasada","● No prazo")))))
F8: =IF($B8="","",SUMIFS('Lançamentos'!$F$9:$F$1508,'Lançamentos'!$H$9:$H$1508,$B8,'Lançamentos'!$G$9:$G$1508,"Saída")-SUMIFS('Lançamentos'!$F$9:$F$1508,'Lançamentos'!$H$9:$H$1508,$B8,'Lançamentos'!$G$9:$G$1508,"Entrada")) | G8: =IF($B8="","",N(D8)+F8) | H8: =IF(OR($B8="",N(C8)=0),"",G8/C8) | I8: =IF(H8="","",REPT("█",MIN(24,ROUND(H8*20,0)))) | J8: =IF(H8="","",MAX(0,C8-G8)) | K8: =IF(OR($B8="",E8=""),"",MAX(0,(YEAR(E8)-YEAR('Config'!$C$7))*12+MONTH(E8)-MONTH('Config'!$C$7))) | L8: =IF(OR(J8="",K8=""),"",IF(J8=0,0,IF(K8=0,J8,J8/K8))) | M8: =IF($B8="","",IF(N(C8)=0,"—",IF(G8>=C8,"✓ Concluída",IF(E8="","Em andamento",IF('Config'!$C$7>E8,"✖ Atrasada","● No prazo")))))
F9: =IF($B9="","",SUMIFS('Lançamentos'!$F$9:$F$1508,'Lançamentos'!$H$9:$H$1508,$B9,'Lançamentos'!$G$9:$G$1508,"Saída")-SUMIFS('Lançamentos'!$F$9:$F$1508,'Lançamentos'!$H$9:$H$1508,$B9,'Lançamentos'!$G$9:$G$1508,"Entrada")) | G9: =IF($B9="","",N(D9)+F9) | H9: =IF(OR($B9="",N(C9)=0),"",G9/C9) | I9: =IF(H9="","",REPT("█",MIN(24,ROUND(H9*20,0)))) | J9: =IF(H9="","",MAX(0,C9-G9)) | K9: =IF(OR($B9="",E9=""),"",MAX(0,(YEAR(E9)-YEAR('Config'!$C$7))*12+MONTH(E9)-MONTH('Config'!$C$7))) | L9: =IF(OR(J9="",K9=""),"",IF(J9=0,0,IF(K9=0,J9,J9/K9))) | M9: =IF($B9="","",IF(N(C9)=0,"—",IF(G9>=C9,"✓ Concluída",IF(E9="","Em andamento",IF('Config'!$C$7>E9,"✖ Atrasada","● No prazo")))))
F10: =IF($B10="","",SUMIFS('Lançamentos'!$F$9:$F$1508,'Lançamentos'!$H$9:$H$1508,$B10,'Lançamentos'!$G$9:$G$1508,"Saída")-SUMIFS('Lançamentos'!$F$9:$F$1508,'Lançamentos'!$H$9:$H$1508,$B10,'Lançamentos'!$G$9:$G$1508,"Entrada")) | G10: =IF($B10="","",N(D10)+F10) | H10: =IF(OR($B10="",N(C10)=0),"",G10/C10) | I10: =IF(H10="","",REPT("█",MIN(24,ROUND(H10*20,0)))) | J10: =IF(H10="","",MAX(0,C10-G10)) | K10: =IF(OR($B10="",E10=""),"",MAX(0,(YEAR(E10)-YEAR('Config'!$C$7))*12+MONTH(E10)-MONTH('Config'!$C$7))) | L10: =IF(OR(J10="",K10=""),"",IF(J10=0,0,IF(K10=0,J10,J10/K10))) | M10: =IF($B10="","",IF(N(C10)=0,"—",IF(G10>=C10,"✓ Concluída",IF(E10="","Em andamento",IF('Config'!$C$7>E10,"✖ Atrasada","● No prazo")))))
F11: =IF($B11="","",SUMIFS('Lançamentos'!$F$9:$F$1508,'Lançamentos'!$H$9:$H$1508,$B11,'Lançamentos'!$G$9:$G$1508,"Saída")-SUMIFS('Lançamentos'!$F$9:$F$1508,'Lançamentos'!$H$9:$H$1508,$B11,'Lançamentos'!$G$9:$G$1508,"Entrada")) | G11: =IF($B11="","",N(D11)+F11) | H11: =IF(OR($B11="",N(C11)=0),"",G11/C11) | I11: =IF(H11="","",REPT("█",MIN(24,ROUND(H11*20,0)))) | J11: =IF(H11="","",MAX(0,C11-G11)) | K11: =IF(OR($B11="",E11=""),"",MAX(0,(YEAR(E11)-YEAR('Config'!$C$7))*12+MONTH(E11)-MONTH('Config'!$C$7))) | L11: =IF(OR(J11="",K11=""),"",IF(J11=0,0,IF(K11=0,J11,J11/K11))) | M11: =IF($B11="","",IF(N(C11)=0,"—",IF(G11>=C11,"✓ Concluída",IF(E11="","Em andamento",IF('Config'!$C$7>E11,"✖ Atrasada","● No prazo")))))
F12: =IF($B12="","",SUMIFS('Lançamentos'!$F$9:$F$1508,'Lançamentos'!$H$9:$H$1508,$B12,'Lançamentos'!$G$9:$G$1508,"Saída")-SUMIFS('Lançamentos'!$F$9:$F$1508,'Lançamentos'!$H$9:$H$1508,$B12,'Lançamentos'!$G$9:$G$1508,"Entrada")) | G12: =IF($B12="","",N(D12)+F12) | H12: =IF(OR($B12="",N(C12)=0),"",G12/C12) | I12: =IF(H12="","",REPT("█",MIN(24,ROUND(H12*20,0)))) | J12: =IF(H12="","",MAX(0,C12-G12)) | K12: =IF(OR($B12="",E12=""),"",MAX(0,(YEAR(E12)-YEAR('Config'!$C$7))*12+MONTH(E12)-MONTH('Config'!$C$7))) | L12: =IF(OR(J12="",K12=""),"",IF(J12=0,0,IF(K12=0,J12,J12/K12))) | M12: =IF($B12="","",IF(N(C12)=0,"—",IF(G12>=C12,"✓ Concluída",IF(E12="","Em andamento",IF('Config'!$C$7>E12,"✖ Atrasada","● No prazo")))))
F13: =IF($B13="","",SUMIFS('Lançamentos'!$F$9:$F$1508,'Lançamentos'!$H$9:$H$1508,$B13,'Lançamentos'!$G$9:$G$1508,"Saída")-SUMIFS('Lançamentos'!$F$9:$F$1508,'Lançamentos'!$H$9:$H$1508,$B13,'Lançamentos'!$G$9:$G$1508,"Entrada")) | G13: =IF($B13="","",N(D13)+F13) | H13: =IF(OR($B13="",N(C13)=0),"",G13/C13) | I13: =IF(H13="","",REPT("█",MIN(24,ROUND(H13*20,0)))) | J13: =IF(H13="","",MAX(0,C13-G13)) | K13: =IF(OR($B13="",E13=""),"",MAX(0,(YEAR(E13)-YEAR('Config'!$C$7))*12+MONTH(E13)-MONTH('Config'!$C$7))) | L13: =IF(OR(J13="",K13=""),"",IF(J13=0,0,IF(K13=0,J13,J13/K13))) | M13: =IF($B13="","",IF(N(C13)=0,"—",IF(G13>=C13,"✓ Concluída",IF(E13="","Em andamento",IF('Config'!$C$7>E13,"✖ Atrasada","● No prazo")))))
B15: 🛟 RESERVA DE EMERGÊNCIA IDEAL
B16: Meses de cobertura desejados | D16: 6
B17: Média mensal de saídas | D17: =IFERROR('Resumo Anual'!$O$34/'Dados'!$C$9,0) -> 0
B18: Reserva ideal (meses × média) | D18: =D16*D17 -> 0
B19: Total guardado nas suas metas | D19: =SUM(G6:G13) -> 0
B21: A regra de bolso: entre 3 e 6 meses do seu custo de vida (6 a 12 para autônomos e renda variável).

Sheet Config
B1: 🏠 Início | C1: 📊 Painel | E1: 📝 Lançamentos | F1: 💳 Orçamento | H1: 📅 Resumo Anual | J1: 🎯 Metas | L1: ⚙ Config
B3: ⚙ Configurações
B4: Personalize categorias, ano e parâmetros — tudo nas células amarelas. As mudanças se refletem em todas as abas.
B5: PARÂMETROS GERAIS | E5: CATEGORIAS DE ENTRADA | G5: CATEGORIAS DE SAÍDA | I5: FORMAS DE PAGAMENTO | K5: MÊS | L5: ABREV.
B6: Ano de referência | C6: 2026 | E6: Salário | G6: Moradia | I6: Pix | K6: Janeiro | L6: Jan
B7: Data de hoje (referência) | C7: =TODAY() -> 46299 | E7: Renda extra | G7: Contas da casa | I7: Cartão de débito | K7: Fevereiro | L7: Fev
B8: Seu nome / título nos painéis | C8: Minhas Finanças | E8: Rendimentos de investimentos | G8: Alimentação | I8: Cartão de crédito | K8: Março | L8: Mar
B9: Meta de taxa de poupança | C9: 0.2 | E9: 13º e bônus | G9: Transporte | I9: Dinheiro | K9: Abril | L9: Abr
B10: Saldo pessoal em 1º de janeiro | C10: 0 | E10: Reembolsos | G10: Saúde | I10: Boleto | K10: Maio | L10: Mai
B11: 💡 Células AMARELAS são suas: edite à vontade. A data de hoje usa =HOJE(); se quiser congelar uma data (por exemplo para estudar um mês passado), digite-a. 💡 Renomeie as categorias ao lado como preferir — os painéis acompanham. Evite deixar vazio e evite nomes repetidos. 💡 A 14ª categoria de SAÍDA ('Reserva e Metas') é tratada como poupança, não como gasto, no cálculo da taxa de poupança. ⚠ Renomeie as categorias ANTES de começar a lançar. Se renomear depois, use Localizar e Substituir na coluna Categoria dos lançamentos (senão eles ficam como 'Verificar'). | E11: Aluguéis recebidos | G11: Educação | I11: Transferência | K11: Junho | L11: Jun
E12: Presentes recebidos | G12: Lazer | I12: Débito automático | K12: Julho | L12: Jul
E13: Outras entradas | G13: Vestuário | I13: Outro | K13: Agosto | L13: Ago
G14: Assinaturas | K14: Setembro | L14: Set
G15: Cuidados pessoais | K15: Outubro | L15: Out
G16: Pets | K16: Novembro | L16: Nov
G17: Presentes e doações | K17: Dezembro | L17: Dez
G18: Dívidas e financiamentos
G19: Reserva e Metas
G20: Impostos pessoais
G21: Outros

Sheet Dados
B1: 🏠 Início | C1: 📊 Painel | F1: 📝 Lançamentos | J1: 💳 Orçamento | L1: 📅 Resumo Anual | O1: 🎯 Metas | R1: ⚙ Config
B3: 🧮 Dados auxiliares
B4: Cálculos que alimentam os gráficos e painéis. Não edite esta aba.
B5: PARÂMETROS CALCULADOS | Q5: LISTA COMBINADA (pessoal)
B6: Mês selecionado – Painel (1-12) | C6: =IFERROR(MATCH('Painel'!$D$5,'Config'!$K$6:$K$17,0),1) -> 10 | Q6: =IF('Config'!$E$6="","",'Config'!$E$6) -> Salário
B7: Mês selecionado – Orçamento (1-12) | C7: =IFERROR(MATCH('Orçamento'!$C$5,'Config'!$K$6:$K$17,0),1) -> 10 | Q7: =IF('Config'!$E$7="","",'Config'!$E$7) -> Renda extra
B8: Meses decorridos no ano (pela data de hoje) | C8: =IF(YEAR('Config'!$C$7)<'Config'!$C$6,0,IF(YEAR('Config'!$C$7)>'Config'!$C$6,12,MONTH('Config'!$C$7))) -> 10 | Q8: =IF('Config'!$E$8="","",'Config'!$E$8) -> Rendimentos de investimentos
B9: Meses com movimento (pessoal) | C9: =MAX(1,SUMPRODUCT(--(('Resumo Anual'!$C$16:$N$16+'Resumo Anual'!$C$34:$N$34)>0))) -> 1 | Q9: =IF('Config'!$E$9="","",'Config'!$E$9) -> 13º e bônus
B10: Total de saídas no mês do Painel | C10: =INDEX('Resumo Anual'!$C$34:$N$34,$C$6) -> 0 | Q10: =IF('Config'!$E$10="","",'Config'!$E$10) -> Reembolsos
B11: Categorias acima do orçamento (mês do Painel) | C11: =SUM($F$16:$F$31) -> 0 | Q11: =IF('Config'!$E$11="","",'Config'!$E$11) -> Aluguéis recebidos
B12: Título do gráfico de rosca | C12: ="Para onde foi o dinheiro — "&INDEX('Config'!$K$6:$K$17,$C$6) -> Para onde foi o dinheiro — Outubro | Q12: =IF('Config'!$E$12="","",'Config'!$E$12) -> Presentes recebidos
Q13: =IF('Config'!$E$13="","",'Config'!$E$13) -> Outras entradas
Q14: =IF('Config'!$G$6="","",'Config'!$G$6) -> Moradia
B15: Categoria de saída | C15: Valor no mês | D15: Planejado | E15: Chave (aux) | F15: Acima? | H15: # | I15: Posição na lista | J15: Categoria | K15: Realizado | L15: Planejado | M15: Rosca – categoria | N15: Valor | Q15: =IF('Config'!$G$7="","",'Config'!$G$7) -> Contas da casa
B16: =IF('Config'!$G$6="","",'Config'!$G$6) -> Moradia | C16: =IF(B16="",0,INDEX('Resumo Anual'!$C$18:$N$18,$C$6)) -> 0 | D16: =IF(B16="",0,'Orçamento'!$C$10) -> 0 | E16: =IF(C16>0,C16+ROW()/1000000,0) -> 0 | F16: =IF(AND(D16>0,C16>D16),1,0) -> 0 | H16: 1 | I16: =IF(LARGE($E$16:$E$31,1)>0,MATCH(LARGE($E$16:$E$31,1),$E$16:$E$31,0),0) -> 0 | J16: =IF(I16>0,INDEX($B$16:$B$31,I16),"—") -> — | K16: =IF(I16>0,INDEX($C$16:$C$31,I16),0) -> 0 | L16: =IF(I16>0,INDEX($D$16:$D$31,I16),0) -> 0 | M16: =J16 -> — | N16: =K16 -> 0 | Q16: =IF('Config'!$G$8="","",'Config'!$G$8) -> Alimentação
B17: =IF('Config'!$G$7="","",'Config'!$G$7) -> Contas da casa | C17: =IF(B17="",0,INDEX('Resumo Anual'!$C$19:$N$19,$C$6)) -> 0 | D17: =IF(B17="",0,'Orçamento'!$C$11) -> 0 | E17: =IF(C17>0,C17+ROW()/1000000,0) -> 0 | F17: =IF(AND(D17>0,C17>D17),1,0) -> 0 | H17: 2 | I17: =IF(LARGE($E$16:$E$31,2)>0,MATCH(LARGE($E$16:$E$31,2),$E$16:$E$31,0),0) -> 0 | J17: =IF(I17>0,INDEX($B$16:$B$31,I17),"—") -> — | K17: =IF(I17>0,INDEX($C$16:$C$31,I17),0) -> 0 | L17: =IF(I17>0,INDEX($D$16:$D$31,I17),0) -> 0 | M17: =J17 -> — | N17: =K17 -> 0 | Q17: =IF('Config'!$G$9="","",'Config'!$G$9) -> Transporte
B18: =IF('Config'!$G$8="","",'Config'!$G$8) -> Alimentação | C18: =IF(B18="",0,INDEX('Resumo Anual'!$C$20:$N$20,$C$6)) -> 0 | D18: =IF(B18="",0,'Orçamento'!$C$12) -> 0 | E18: =IF(C18>0,C18+ROW()/1000000,0) -> 0 | F18: =IF(AND(D18>0,C18>D18),1,0) -> 0 | H18: 3 | I18: =IF(LARGE($E$16:$E$31,3)>0,MATCH(LARGE($E$16:$E$31,3),$E$16:$E$31,0),0) -> 0 | J18: =IF(I18>0,INDEX($B$16:$B$31,I18),"—") -> — | K18: =IF(I18>0,INDEX($C$16:$C$31,I18),0) -> 0 | L18: =IF(I18>0,INDEX($D$16:$D$31,I18),0) -> 0 | M18: =J18 -> — | N18: =K18 -> 0 | Q18: =IF('Config'!$G$10="","",'Config'!$G$10) -> Saúde
B19: =IF('Config'!$G$9="","",'Config'!$G$9) -> Transporte | C19: =IF(B19="",0,INDEX('Resumo Anual'!$C$21:$N$21,$C$6)) -> 0 | D19: =IF(B19="",0,'Orçamento'!$C$13) -> 0 | E19: =IF(C19>0,C19+ROW()/1000000,0) -> 0 | F19: =IF(AND(D19>0,C19>D19),1,0) -> 0 | H19: 4 | I19: =IF(LARGE($E$16:$E$31,4)>0,MATCH(LARGE($E$16:$E$31,4),$E$16:$E$31,0),0) -> 0 | J19: =IF(I19>0,INDEX($B$16:$B$31,I19),"—") -> — | K19: =IF(I19>0,INDEX($C$16:$C$31,I19),0) -> 0 | L19: =IF(I19>0,INDEX($D$16:$D$31,I19),0) -> 0 | M19: =J19 -> — | N19: =K19 -> 0 | Q19: =IF('Config'!$G$11="","",'Config'!$G$11) -> Educação
B20: =IF('Config'!$G$10="","",'Config'!$G$10) -> Saúde | C20: =IF(B20="",0,INDEX('Resumo Anual'!$C$22:$N$22,$C$6)) -> 0 | D20: =IF(B20="",0,'Orçamento'!$C$14) -> 0 | E20: =IF(C20>0,C20+ROW()/1000000,0) -> 0 | F20: =IF(AND(D20>0,C20>D20),1,0) -> 0 | H20: 5 | I20: =IF(LARGE($E$16:$E$31,5)>0,MATCH(LARGE($E$16:$E$31,5),$E$16:$E$31,0),0) -> 0 | J20: =IF(I20>0,INDEX($B$16:$B$31,I20),"—") -> — | K20: =IF(I20>0,INDEX($C$16:$C$31,I20),0) -> 0 | L20: =IF(I20>0,INDEX($D$16:$D$31,I20),0) -> 0 | M20: =J20 -> — | N20: =K20 -> 0 | Q20: =IF('Config'!$G$12="","",'Config'!$G$12) -> Lazer
B21: =IF('Config'!$G$11="","",'Config'!$G$11) -> Educação | C21: =IF(B21="",0,INDEX('Resumo Anual'!$C$23:$N$23,$C$6)) -> 0 | D21: =IF(B21="",0,'Orçamento'!$C$15) -> 0 | E21: =IF(C21>0,C21+ROW()/1000000,0) -> 0 | F21: =IF(AND(D21>0,C21>D21),1,0) -> 0 | H21: 6 | I21: =IF(LARGE($E$16:$E$31,6)>0,MATCH(LARGE($E$16:$E$31,6),$E$16:$E$31,0),0) -> 0 | J21: =IF(I21>0,INDEX($B$16:$B$31,I21),"—") -> — | K21: =IF(I21>0,INDEX($C$16:$C$31,I21),0) -> 0 | L21: =IF(I21>0,INDEX($D$16:$D$31,I21),0) -> 0 | M21: =J21 -> — | N21: =K21 -> 0 | Q21: =IF('Config'!$G$13="","",'Config'!$G$13) -> Vestuário
B22: =IF('Config'!$G$12="","",'Config'!$G$12) -> Lazer | C22: =IF(B22="",0,INDEX('Resumo Anual'!$C$24:$N$24,$C$6)) -> 0 | D22: =IF(B22="",0,'Orçamento'!$C$16) -> 0 | E22: =IF(C22>0,C22+ROW()/1000000,0) -> 0 | F22: =IF(AND(D22>0,C22>D22),1,0) -> 0 | H22: 7 | I22: =IF(LARGE($E$16:$E$31,7)>0,MATCH(LARGE($E$16:$E$31,7),$E$16:$E$31,0),0) -> 0 | J22: =IF(I22>0,INDEX($B$16:$B$31,I22),"—") -> — | K22: =IF(I22>0,INDEX($C$16:$C$31,I22),0) -> 0 | L22: =IF(I22>0,INDEX($D$16:$D$31,I22),0) -> 0 | M22: =J22 -> — | N22: =K22 -> 0 | Q22: =IF('Config'!$G$14="","",'Config'!$G$14) -> Assinaturas
B23: =IF('Config'!$G$13="","",'Config'!$G$13) -> Vestuário | C23: =IF(B23="",0,INDEX('Resumo Anual'!$C$25:$N$25,$C$6)) -> 0 | D23: =IF(B23="",0,'Orçamento'!$C$17) -> 0 | E23: =IF(C23>0,C23+ROW()/1000000,0) -> 0 | F23: =IF(AND(D23>0,C23>D23),1,0) -> 0 | H23: 8 | I23: =IF(LARGE($E$16:$E$31,8)>0,MATCH(LARGE($E$16:$E$31,8),$E$16:$E$31,0),0) -> 0 | J23: =IF(I23>0,INDEX($B$16:$B$31,I23),"—") -> — | K23: =IF(I23>0,INDEX($C$16:$C$31,I23),0) -> 0 | L23: =IF(I23>0,INDEX($D$16:$D$31,I23),0) -> 0 | M23: Outras categorias | N23: =MAX(0,$C$10-SUM(N16:N22)) -> 0 | Q23: =IF('Config'!$G$15="","",'Config'!$G$15) -> Cuidados pessoais
B24: =IF('Config'!$G$14="","",'Config'!$G$14) -> Assinaturas | C24: =IF(B24="",0,INDEX('Resumo Anual'!$C$26:$N$26,$C$6)) -> 0 | D24: =IF(B24="",0,'Orçamento'!$C$18) -> 0 | E24: =IF(C24>0,C24+ROW()/1000000,0) -> 0 | F24: =IF(AND(D24>0,C24>D24),1,0) -> 0 | Q24: =IF('Config'!$G$16="","",'Config'!$G$16) -> Pets
B25: =IF('Config'!$G$15="","",'Config'!$G$15) -> Cuidados pessoais | C25: =IF(B25="",0,INDEX('Resumo Anual'!$C$27:$N$27,$C$6)) -> 0 | D25: =IF(B25="",0,'Orçamento'!$C$19) -> 0 | E25: =IF(C25>0,C25+ROW()/1000000,0) -> 0 | F25: =IF(AND(D25>0,C25>D25),1,0) -> 0 | Q25: =IF('Config'!$G$17="","",'Config'!$G$17) -> Presentes e doações
B26: =IF('Config'!$G$16="","",'Config'!$G$16) -> Pets | C26: =IF(B26="",0,INDEX('Resumo Anual'!$C$28:$N$28,$C$6)) -> 0 | D26: =IF(B26="",0,'Orçamento'!$C$20) -> 0 | E26: =IF(C26>0,C26+ROW()/1000000,0) -> 0 | F26: =IF(AND(D26>0,C26>D26),1,0) -> 0 | Q26: =IF('Config'!$G$18="","",'Config'!$G$18) -> Dívidas e financiamentos
B27: =IF('Config'!$G$17="","",'Config'!$G$17) -> Presentes e doações | C27: =IF(B27="",0,INDEX('Resumo Anual'!$C$29:$N$29,$C$6)) -> 0 | D27: =IF(B27="",0,'Orçamento'!$C$21) -> 0 | E27: =IF(C27>0,C27+ROW()/1000000,0) -> 0 | F27: =IF(AND(D27>0,C27>D27),1,0) -> 0 | Q27: =IF('Config'!$G$19="","",'Config'!$G$19) -> Reserva e Metas
B28: =IF('Config'!$G$18="","",'Config'!$G$18) -> Dívidas e financiamentos | C28: =IF(B28="",0,INDEX('Resumo Anual'!$C$30:$N$30,$C$6)) -> 0 | D28: =IF(B28="",0,'Orçamento'!$C$22) -> 0 | E28: =IF(C28>0,C28+ROW()/1000000,0) -> 0 | F28: =IF(AND(D28>0,C28>D28),1,0) -> 0 | Q28: =IF('Config'!$G$20="","",'Config'!$G$20) -> Impostos pessoais
B29: =IF('Config'!$G$19="","",'Config'!$G$19) -> Reserva e Metas | C29: =IF(B29="",0,INDEX('Resumo Anual'!$C$31:$N$31,$C$6)) -> 0 | D29: =IF(B29="",0,'Orçamento'!$C$23) -> 0 | E29: =IF(C29>0,C29+ROW()/1000000,0) -> 0 | F29: =0 -> 0 | Q29: =IF('Config'!$G$21="","",'Config'!$G$21) -> Outros
B30: =IF('Config'!$G$20="","",'Config'!$G$20) -> Impostos pessoais | C30: =IF(B30="",0,INDEX('Resumo Anual'!$C$32:$N$32,$C$6)) -> 0 | D30: =IF(B30="",0,'Orçamento'!$C$24) -> 0 | E30: =IF(C30>0,C30+ROW()/1000000,0) -> 0 | F30: =IF(AND(D30>0,C30>D30),1,0) -> 0
B31: =IF('Config'!$G$21="","",'Config'!$G$21) -> Outros | C31: =IF(B31="",0,INDEX('Resumo Anual'!$C$33:$N$33,$C$6)) -> 0 | D31: =IF(B31="",0,'Orçamento'!$C$25) -> 0 | E31: =IF(C31>0,C31+ROW()/1000000,0) -> 0 | F31: =IF(AND(D31>0,C31>D31),1,0) -> 0
